Workbook
Name cfg_AboveOptimumRatio: _CONFIG_Model_Settings!$B$24
Name cfg_CrisisHighCut: _CONFIG_Model_Settings!$B$17
Name cfg_CrisisMedCut: _CONFIG_Model_Settings!$B$18
Name cfg_IndPriorityHigh: _CONFIG_Model_Settings!$B$19
Name cfg_IndPriorityLow: _CONFIG_Model_Settings!$B$20
Name cfg_RiskFitScale: _CONFIG_Model_Settings!$B$26
Name cfg_RiskSecondaryWeight: _CONFIG_Model_Settings!$B$25
Name cfg_ScenarioFitScale: _CONFIG_Model_Settings!$B$27
Name cfg_TimelineBucket1: _CONFIG_Model_Settings!$B$21
Name cfg_TimelineBucket2: _CONFIG_Model_Settings!$B$22
Name cfg_TimelineBucket3: _CONFIG_Model_Settings!$B$23
Name CTX_Rules: _REF_Context_Relevance!$A$1:$K$25
Name DV_ASSESSMENT_CADENCE: _REF_Dropdowns!$K$3:$K$7
Name DV_ASSESSOR_CONFIDENCE: _REF_Dropdowns!$L$3:$L$5
Name DV_BUSINESS_MODEL: _REF_Dropdowns!$M$3:$M$10
Name DV_CASH_RUNWAY_BAND: _REF_Dropdowns!$N$3:$N$7
Name DV_CHANGE_CAPACITY_BAND: _REF_Dropdowns!$O$3:$O$13
Name DV_CLOUD_MODEL: _REF_Dropdowns!$P$3:$P$11
Name DV_COMPANY_SIZE_BAND: _REF_Dropdowns!$Q$3:$Q$7
Name DV_CONCENTRATION_BAND: _REF_Dropdowns!$R$3:$R$8
Name DV_CONFIDENCE_LEVEL: _REF_Dropdowns!$S$3:$S$5
Name DV_CONTINUITY_OPTION: _REF_Dropdowns!$T$3:$T$7
Name DV_CORE_SYSTEM_FAMILY: _REF_Dropdowns!$U$3:$U$22
Name DV_COUNTRY: _REF_Dropdowns!$V$3:$V$20
Name DV_CRISIS_HISTORY_IMPACT: _REF_Dropdowns!$W$3:$W$8
Name DV_CRITICAL_PEOPLE_DEPENDENCY: _REF_Dropdowns!$X$3:$X$6
Name DV_CRITICAL_PROCESS_FAMILY: _REF_Dropdowns!$Y$3:$Y$14
Name DV_CRITICAL_PRODUCT_SERVICE_TYPE: _REF_Dropdowns!$Z$3:$Z$12
Name DV_DATA_CRITICALITY: _REF_Dropdowns!$AA$3:$AA$6
Name DV_DEBT_LOAD: _REF_Dropdowns!$AB$3:$AB$7
Name DV_DIGITAL_DEPENDENCY: _REF_Dropdowns!$AC$3:$AC$6
Name DV_DISRUPTION_IMPACT: _REF_Dropdowns!$AD$3:$AD$7
Name DV_EVIDENCE_CONFIDENCE: _REF_Dropdowns!$AE$3:$AE$5
Name DV_FX_EXPOSURE_BAND: _REF_Dropdowns!$AF$3:$AF$7
Name DV_GEOGRAPHIC_FOOTPRINT: _REF_Dropdowns!$AG$3:$AG$7
Name DV_ICP_SEGMENT: _REF_Dropdowns!$AH$3:$AH$11
Name DV_INDUSTRY_ALIAS: _REF_Dropdowns!$AI$3:$AI$14
Name DV_INDUSTRY_CANONICAL: _REF_Dropdowns!$AJ$3:$AJ$11
Name DV_INDUSTRY_TEMPLATE_LEGACY: _REF_Dropdowns!$AK$3:$AK$11
Name DV_LEGAL_ENTITY_COMPLEXITY: _REF_Dropdowns!$AL$3:$AL$8
Name DV_LOCATION_CRITICALITY: _REF_Dropdowns!$AM$3:$AM$7
Name DV_MARKET_CONCENTRATION: _REF_Dropdowns!$AN$3:$AN$8
Name DV_MATURITY_TARGET: _REF_Dropdowns!$AO$3:$AO$8
Name DV_MOBILITY_SUPPORT: _REF_Dropdowns!$AP$3:$AP$8
Name DV_OPERATING_MODEL: _REF_Dropdowns!$AQ$3:$AQ$12
Name DV_OWNERSHIP_TYPE: _REF_Dropdowns!$AR$3:$AR$10
Name DV_PHYSICAL_FOOTPRINT_INTENSITY: _REF_Dropdowns!$AS$3:$AS$7
Name DV_REGULATION_FAMILY: _REF_Dropdowns!$AT$3:$AT$14
Name DV_REGULATORY_INTENSITY: _REF_Dropdowns!$AU$3:$AU$7
Name DV_REMOTE_WORK_READINESS: _REF_Dropdowns!$AV$3:$AV$8
Name DV_REVENUE_BAND: _REF_Dropdowns!$AW$3:$AW$7
Name DV_REVENUE_MODEL: _REF_Dropdowns!$AX$3:$AX$13
Name DV_REVENUE_RECURRENCE: _REF_Dropdowns!$AY$3:$AY$9
Name DV_RISK_APPETITE: _REF_Dropdowns!$AZ$3:$AZ$5
Name DV_SALES_MOTION: _REF_Dropdowns!$BA$3:$BA$11
Name DV_SUB_INDUSTRY_BY_INDUSTRY: _REF_Dropdowns!$BB$3:$BB$22
Name DV_SUPPLIER_SUBSTITUTABILITY: _REF_Dropdowns!$BC$3:$BC$9
Name DV_TRANSFORMATION_EXPERIENCE: _REF_Dropdowns!$BD$3:$BD$6
Name DV_YES_NO_PLANNED_UNKNOWN: _REF_Dropdowns!$BE$3:$BE$6
Name IW_Canonical_Industry: _REF_Industry_Wording!$C$2:$C$70

Sheet Guidelines
A1: RR Framework — Guidelines
A2: Consolidated user guide, methodology, model calibration, workbook map, and change history for the RR-framework Excel tool.
A4: Workbook status
A5: Workbook version | B5: v3.0 | C5: Static audit fixes: hardened visible crisis fallback, cleaned initiative QIDs, aligned risk→initiative coverage, normalized dropdown registry.
A6: Build ID | B6: ="RR-FRAMEWORK-"&$B$5&"-20260624" -> RR-FRAMEWORK-v3.0-20260624 | C6: Build ID derives from Guidelines!B5 so the current version is maintained in one place.
A7: Recommended audience | B7: CEO / COO / CTO / CIO / CFO / CHRO / Consultant / Analyst | C7: Business users should focus on visible workflow sheets; model owners may use calibration/config sheets.
A8: Monte Carlo mode | B8: =_CONFIG_Model_Settings!B178 -> Frozen | C8: Default should be Frozen for public templates and formal reports.
A9: Live seed / Frozen seed | C9: Change mc_live_seed only for intentional reruns; copy to mc_frozen_seed when freezing a scenario.
A11: 0. Quick navigation
A12: Section | B12: Action | C12: Purpose | D12: Internal link
A13: How to use this file | B13: Go to section 1 | C13: Step-by-step workflow from company profile to roadmap. | D13: #Guidelines!A18 | F13: Quick menu | G13: Select a topic | H13: Use the table links or Excel outline +/- controls to expand/collapse sections.
A14: Methodology & calculations | B14: Go to section 2 | C14: Scoring, risk engine, crisis simulation, MC VaR/CVaR, WSJF. | D14: #Guidelines!A39
A15: Calibration & weights | B15: Go to section 3 | C15: Which parameters can be tuned and where they live. | D15: #Guidelines!A70
A16: Workbook tabs | B16: Go to section 4 | C16: Visible, hidden, and veryHidden sheets with edit policy. | D16: #Guidelines!A98
A17: Change history | B17: Go to section 5 | C17: Release notes from v2.0 to current release. | D17: #Guidelines!A140
A18: 1. How to use this file
A19: Step | B19: What to do | C19: Description | D19: Primary sheet
A20: 1 | B20: Start with Company Profile | C20: Enter company size, industry, geography, revenue model, location criticality, crisis exposure, concentration risks, and operational context. | D20: Company Profile
A21: 2 | B21: Complete the assessment | C21: Use Assessment Questions / AS-IS Assessment to evaluate digitalization, process maturity, organizational resilience, crisis readiness, and domain capabilities. | D21: Assessment Questions; AS-IS Assessment
A22: 3 | B22: Review AS-IS diagnostics | C22: Check maturity gaps, weak domains, scoring distribution, and management-level interpretation before moving to risk and strategy. | D22: AS-IS Assessment
A23: 4 | B23: Run risk and crisis scenario review | C23: Use Resilience & Risk Scenario to review risk exposure, crisis amplification, Indexed VaR/CVaR, and top areas of vulnerability. | D23: Resilience & Risk Scenario
A24: 5 | B24: Build action plan and roadmap | C24: Review prioritized initiatives, WSJF, strategic alignment, risk pressure, financial value, and roadmap waves. | D24: Action Plan & Roadmap
A25: 6 | B25: Calibrate only when needed | C25: Consultants/model owners can adjust weights and assumptions in config sheets. Always document changes and rerun QA checks. | D25: Guidelines + hidden config sheets
A27: Operating principles
A28: Principle | B28: Guidance
A29: Client-facing use | B29: Use the six visible workflow sheets. Hidden/veryHidden sheets are calculation and configuration layers.
A30: Public template mode | B30: Public templates should ship with Monte Carlo in Frozen mode and with one visible documentation hub: Guidelines.
A31: Formal report mode | B31: Record selected crisis scenario, mc_mode, active seed, date/time of run, and any calibration changes.
A32: Excel limitation | B32: The RR-framework Excel file is a calculation/model prototype. The future web-app should implement governed backend calculation, audit logs, and deterministic simulation runs.
A39: 2. Methodology & calculations
A40: Logic block | B40: How it works | C40: Important note
A41: Assessment scoring | B41: Question-level scores are aggregated into maturity, process, digitalization and resilience views. | C41: Input: Assessment Questions. Output: _DATA_Assessment_Model / dashboard facts.
A42: Profile Vector | B42: Company Profile values are normalized into canonical model fields such as Canonical Industry, Org Type, cloud dependency, data criticality, supplier dependency, physical footprint and selected crisis. | C42: Downstream logic should consume PV_* named outputs, not raw profile cells.
A43: Relevance Engine | B43: Applicability gates, context multipliers and crisis dominance determine whether a capability/risk/initiative is relevant for the company. | C43: Hard exclusions must be applied before ranking; they are not merely low weights.
A44: Capability Bridge | B44: Broad domains and subdomains are mapped to Capability_ID so SaaS, Banking, Retail and Manufacturing can share the same engine without misleading labels. | C44: Use Capability_ID for ranking and wording; do not rely on text labels alone.
A45: Risk engine | B45: Assessment gaps and scenario pressure become capability-adjusted risk exposure and prioritized risk items. | C45: Risk ontology sheets document the canonical output schema.
A46: Treatment Library | B46: Current maturity band selects the appropriate action style: establish, standardize, integrate, optimize or stress-test. | C46: High maturity companies should receive evidence/proof/stress-test treatments, not beginner recommendations.
A47: Industry Wording | B47: The same capability receives different risk/recommendation wording by industry. | C47: Prevents MES/WMS/TMS wording for SaaS/Banking and core banking wording for Manufacturing.
A48: Crisis simulation | B48: Selected crisis and severity apply dominance multipliers and cascade logic. | C48: Ransomware should prioritize cyber/DR/data/legal/system themes; cloud outage should prioritize platform/cloud/SRE/customer communication.
A49: Monte Carlo / indexed exposure | B49: Deterministic seed-based Monte Carlo and analytic VaR/CVaR remain directional indexed outputs unless calibrated with financial loss data. | C49: Keep Frozen mode for formal reports.
A51: Model chain — from company context to roadmap (current v3.0)
A52: Order | B52: Layer | C52: Output | D52: Source of truth / control
A53: 1 | B53: Company Profile inputs | C53: Structured company context, selected crisis, operating model and controlled dropdown values | D53: Company Profile + _REF_Dropdowns
A54: 2 | B54: Profile Vector | C54: Canonical industry, org type, dependency, concentration, regulatory/data/physical context | D54: _ENGINE_Profile_Vector
A55: 3 | B55: Assessment answers | C55: Question-level maturity/evidence/confidence data | D55: Assessment Questions → _DATA_Assessment_Model
A56: 4 | B56: Relevance Engine | C56: Industry applicability, hard gates, context relevance and crisis dominance | D56: _ENGINE_Relevance + _REF_Applicability_Gates + _REF_Context_Relevance + _REF_Crisis_Dominance
A57: 5 | B57: Capability Bridge | C57: Domain/subdomain/initiative/risk mapped to Capability_ID | D57: _REF_Capability_Taxonomy + _REF_Capability_Bridge
A58: 6 | B58: Risk interpretation | C58: Capability-adjusted risk pressure, scenario effects and ontology-driven risk outputs | D58: _ENGINE_Risk + _REF_Risk_Ontology
A59: 7 | B59: Treatment / wording selection | C59: Maturity-aware recommendation pattern and industry-specific wording | D59: _REF_Treatment_Library + _REF_Industry_Wording
A60: 8 | B60: Initiative prioritization | C60: Capability/relevance-adjusted WSJF and roadmap wave assignment | D60: _ENGINE_Initiatives + _REF_Initiative_Ontology
A61: 9 | B61: Visible outputs / backend contract | C61: Dashboards, roadmap, lineage, data dictionary and import contract | D61: _REF_Output_Reconciliation + _LINT (consolidated) + _REF_Backend_*
A70: 3. Calibration & weights
A71: Profile normalization | B71: _REF_Industry_Aliases; _ENGINE_Profile_Vector | C71: Maintain aliases, canonical industry keys and derived profile factors before tuning downstream logic. | D71: Model owner
A72: Dropdown / controlled inputs | B72: _REF_Dropdowns; Company Profile validations | C72: Add new user-facing categories here before using them in relevance or backend mapping. | D72: Product/model owner
A73: Applicability / hard gates | B73: _REF_Applicability_Gates; _ENGINE_Relevance | C73: Use hard gates for impossible/irrelevant capability combinations, not just weak weights. | D73: Model owner
A74: Context relevance | B74: _REF_Context_Relevance; _ENGINE_Profile_Vector | C74: Tune how cloud, physical footprint, data, regulatory, supplier/customer concentration and workforce factors affect relevance. | D74: Consultant/model owner
A75: Crisis dominance | B75: _REF_Crisis_Dominance | C75: Tune scenario-specific dominance rules and ensure top-N sanity checks remain valid. | D75: Scenario owner
A76: Capability taxonomy / bridge | B76: _REF_Capability_Taxonomy; _REF_Capability_Bridge | C76: Map domains, subdomains, risks and initiatives to Capability_ID. Avoid text-label-only rules. | D76: Product/model owner
A77: Treatment / maturity bands | B77: _REF_Treatment_Library | C77: Tune action language and KPI/evidence by capability, industry and maturity score band. | D77: Consultant/model owner
A78: Industry wording | B78: _REF_Industry_Wording | C78: Maintain preferred/forbidden terms and industry-specific examples. | D78: Content owner
A79: Backend import contract | B79: _REF_Backend_*; _API_Import_Contract | C79: Keep entity/field mappings aligned with future web/backend model. | D79: Backend/product owner
A81: Calibration governance checklist
A82: Control point | B82: Required action
A83: Before changing weights | B83: Define reason, affected domain, client/industry assumption, and expected direction of change.
A84: When changing assumptions | B84: Change config/data sheets, not formulas in engine sheets, unless doing advanced model development.
A85: After changing mappings | B85: Check invalid IDs, missing IDs, duplicate IDs, and coverage of risk questions.
A86: After Monte Carlo rerun | B86: Record mc_mode, active seed, scenario, date, and freeze the seed for reports.
A87: Before sharing externally | B87: Keep public templates in Frozen mode, hide legacy/internal sheets, and validate that no formula error tokens are present.
A98: 4. Workbook tabs and edit policy
A99: Sheet | B99: Visibility / role | C99: Purpose | D99: Edit policy
A100: Guidelines | B100: Visible | C100: Consolidated guide, methodology, calibration guide, workbook map, change history. | D100: Edit content only; do not place calculations here.
A101: Company Profile | B101: Visible | C101: Company context, segmentation inputs, crisis exposure, operational profile. | D101: Client/consultant editable.
A102: Assessment Questions | B102: Visible | C102: Questionnaire and scoring input layer for domain assessment. | D102: Client/consultant editable where input fields are provided.
A103: AS-IS Assessment | B103: Visible | C103: Dashboard-like diagnostic output for current maturity/resilience state. | D103: Review only; formulas should be protected.
A104: Resilience & Risk Scenario | B104: Visible | C104: Risk scenario, crisis stress test, Indexed VaR/CVaR, exposure matrix, fuzzy posture radar and risk visualization. | D104: Review scenario outputs; use configuration sheets for deep calibration.
A105: Action Plan & Roadmap | B105: Visible | C105: Prioritized initiatives, WSJF, roadmap waves, action planning matrix and portfolio visualization. | D105: Review/edit action planning fields where designed.
A106: _DATA_Assessment_Model | B106: Hidden | C106: Assessment model, question metadata, score logic data. | D106: Model owner only.
A107: _DATA_Dashboard_Facts | B107: Hidden | C107: Dashboard staging and computed facts. | D107: Do not manually edit formulas.
A108: _ENGINE_Initiatives | B108: VeryHidden | C108: Initiative value, risk pressure, WSJF and roadmap logic. | D108: Engine layer; advanced model owner only.
A109: _DATA_Mappings | B109: Hidden | C109: Recommendation mapping table. | D109: Model owner only.
A110: _ENGINE_Risk | B110: VeryHidden | C110: Risk scoring, control weakness, evidence, standards, crisis tags and risk distribution logic. | D110: Engine layer; advanced model owner only.
... A119: _DATA_RiskInitiativeMap | B119: Hidden | C119: Question/risk-to-initiative coverage mapping. | D119: Model owner only.
A140: 5. Change history
A141: Version | B141: Theme | C141: What changed
A142: v2.0 | B142: Clean architecture baseline | C142: Layered workbook structure, visible workflow sheets, hidden data/config, veryHidden engine layers, clearer assessment-to-roadmap flow.
A143: v2.4 | B143: Quantitative risk layer | C143: Added risk table, simulation layer, Monte Carlo logic, Indexed VaR/CVaR outputs, and crisis/risk quantification.
A144: v2.5 candidate | B144: Risk-initiative mapping & coverage governance | C144: Separated risk-initiative mapping, restored standards/evidence/crisis tags, fixed mapping integrity, added coverage governance.
A145: v2.9.30 candidate | B145: Monte Carlo freeze / deterministic simulation | C145: Removed volatile RAND(); added Frozen/Live mode, mc_live_seed/mc_frozen_seed, and reproducible non-volatile Monte Carlo simulation.
A146: v2.5.2 candidate | B146: Consolidated Guidelines | C146: Merged START HERE, Release & QA, Methodology & Controls, and Model Calibration into one visible Guidelines tab; initially kept old pages hidden for traceability.
A147: v2.5.3 candidate | B147: Guidelines cleanup / legacy sheet deletion | C147: Physically deleted four old documentation sheets after confirming they had no calculation-critical dependencies; redirected seven navigation hyperlinks to Guidelines.
A148: v2.5.4 candidate | B148: AS-IS visual dashboard | C148: Added AgileTPI-inspired AS-IS maturity matrix, current-vs-target radar and bar chart.
A149: v2.5.5 candidate | B149: Risk & Roadmap visual dashboards | C149: Added scenario exposure matrix, fuzzy posture radar, domain exposure bar chart, roadmap wave matrix, WSJF component radar and initiative bar chart.
A150: Recommended next backlog items
A151: Priority | B151: Item | C151: Description
A152: P0 | B152: Add automated QA counters to Guidelines | C152: Formula error count, invalid mapping IDs, missing risk coverage, duplicate IDs, MC mode/seed status.
A153: P0 | B153: Add report snapshot block | C153: Scenario, date, version, calibration ID, mc_mode, active seed, VaR/CVaR, top risk contributors.
A154: P1 | B154: Add sensitivity analysis | C154: Show which calibration factors most influence Indexed VaR/CVaR and roadmap prioritization.
A155: v2.9.4 | B155: Profile Vector layer | C155: Added canonical _ENGINE_Profile_Vector and industry alias normalization.
A156: v2.9.5 | B156: Consumer redirect | C156: Redirected downstream industry formulas to PV_Canonical_Industry and fixed selected-scenario reference B60→B6.
A157: v2.9.6 | B157: Relevance seed | C157: Added applicability gates, crisis dominance and _ENGINE_Relevance seed layer.
...

Sheet Company Profile
A1: Company Profile
A2: Fill controlled inputs once per organization. Duplicate summary fields are now formula-derived; Profile Vector preview shows canonical values used by engines.
A3: =HYPERLINK("#'Guidelines'!A1","⌂ Guidelines") -> ⌂ Guidelines | C3: ✎ Input: edit coloured dropdown cells only. Grey/formula rows are derived or compatibility-only.
A4: Profile field | B4: Value / input | C4: Guidance | D4: Used by | F4: How this sheet is used
A5: Organization name | C5: Legal or commercial name used in the assessment. | D5: Dashboard / executive summary | F5: 1. Define organization context and assessment boundaries. 2. Use Crisis Simulator for active scenario and severity. 3. Use Assessment date as the roadmap start date. 4. Use target scores to calibrate expected maturity level. 5. Keep LLM and financial analysis outside this workbook version.
A6: Assessment date | B6: =TODAY() -> 46197 | C6: Baseline date. Defaults to TODAY() and can be replaced by the actual assessment date. | D6: Gantt Roadmap
A7: Assessment owner | C7: Person responsible for coordinating the assessment. | D7: Quality Control
A8: Executive sponsor | C8: Senior owner who accepts priorities and crisis roadmap. | D8: Roadmap governance
A9: Industry | C9: Primary industry or sector. | D9: Strategy logic
A10: Sub-industry / segment | C10: More specific segment, e.g. manufacturing, SaaS, retail, healthcare. | D10: Strategy logic
A11: Headquarters country | C11: Country where the main legal or management entity is located. | D11: Risk context
A12: Operating countries / regions | C12: List countries, regions and key cities where the company operates. | D12: Geographical exposure
A13: Ownership type | C13: Private, public, state-owned, family-owned, PE-backed, NGO or other. | D13: Governance context
A14: Legal entities | C14: Main legal entities and subsidiaries. | D14: Legal / continuity context
A15: Employee count | C15: Total employees and contractors. | D15: HR / continuity logic
A16: Revenue size band (derived) | B16: =IF($B$108<>"",$B$108,"") | C16: Derived from Annual revenue band in Financial Anchors. Do not edit here. | D16: Derived summary / compatibility
A17: Operating model | C17: Centralized, decentralized, hub-and-spoke, remote-first, multi-site, franchise, hybrid. | D17: Crisis exposure
A18: Business model | C18: B2B, B2C, B2B2C, marketplace, subscription, project-based, manufacturing, distribution. | D18: GTM / resilience logic
A19: Critical products / services (derived) | B19: =IF($B$87<>"",$B$87&" | ","")&IF($B$88<>"",$B$88&" | ","")&IF($B$89<>"",$B$89&" | ","")&IF($B$90<>"",$B$90&" | ","")&IF($B$91<>"",$B$91&" | ","") | C19: Derived from structured Critical Product / Service List rows 87–91. Do not edit here. | D19: Continuity summary
A20: ICP / key customer segments | C20: Ideal customer profiles and most important customer groups. | D20: GTM / revenue resilience
A21: Top markets by revenue | C21: Countries, regions or customer segments with highest revenue share. | D21: Revenue concentration
A22: Customer concentration (derived) | B22: =IF(IF($B$54<>"","Top 1: "&$B$54,"")<>"",IF($B$54<>"","Top 1: "&$B$54,"")&" | ","")&IF(IF($B$55<>"","Top 5: "&$B$55,"")<>"",IF($B$55<>"","Top 5: "&$B$55,"")&" | ","")&IF(IF($B$56<>"","Top 10: "&$B$56,"")<>"",IF($B$56<>"","Top 10: "&$B$56,"")&" | ","") | C22: Derived from top 1 / top 5 / top 10 structured concentration bands. Do not edit here. | D22: Revenue concentration summary
A23: Critical sites / facilities (derived) | B23: =IF(IF($B$63<>"",$A$63&": "&$B$63,"")<>"",IF($B$63<>"",$A$63&": "&$B$63,"")&" | ","")&IF(IF($B$64<>"",$A$64&": "&$B$64,"")<>"",IF($B$64<>"",$A$64&": "&$B$64,"")&" | ","")&IF(IF($B$65<>"",$A$65&": "&$B$65,"")<>"",IF($B$65<>"",$A$65&": "&$B$65,"")&" | ","")&IF(IF($B$66<>"",$A$66&": "&$B$66,"")<>"",IF($B$66<>"",$A$66&": "&$B$66,"")&" | ","")&IF(IF($B$67<>"",$A$67&": "&$B$67,"")<>"",IF($B$67<>"",$A$67&": "&$B$67,"")&" | ","")&IF(IF($B$68<>"",$A$68&": "&$B$68,"")<>"",IF($B$68<>"",$A$68&": "&$B$68,"")&" | ","")&IF(IF($B$69<>"",$A$69&": "&$B$69,"")<>"",IF($B$69<>"",$A$69&": "&$B$69,"")&" | ","")&IF(IF($B$70<>"",$A$70&": "&$B$70,"")<>"",IF($B$70<>"",$A$70&": "&$B$70,"")&" | ","") | C23: Derived from Business Criticality of Locations table rows 63–70. Do not edit here. | D23: Physical footprint summary
A24: Critical people / roles | C24: Roles where loss of individuals creates continuity risk. | D24: Workforce resilience
A25: Regulatory exposure level | C25: Low, medium, high or critical regulatory exposure. | D25: Legal / compliance risk
A26: Main regulations / obligations | C26: Examples: GDPR, NIS2, HIPAA, SOX, ISO, industry licenses, customer audit obligations. | D26: Compliance context
A27: Core business systems | C27: ERP, CRM, MES, HRMS, BI, WMS, SCM, billing, support desk, data warehouse. | D27: Digital maturity
A28: Cloud and infrastructure model | C28: On-premise, public cloud, private cloud, hybrid, multi-cloud, SaaS-first. | D28: IT / DR strategy
A29: Primary crisis scenario to test | B29: ='Resilience & Risk Scenario'!$B$6 -> 0 | C29: Active scenario is selected in Crisis Simulator. | D29: Crisis Simulator
A30: Scenario severity 1-5 | B30: ='Resilience & Risk Scenario'!$B$7 -> 0 | C30: Active scenario severity is selected in Crisis Simulator. | D30: Crisis Simulator
A31: Target process maturity 0-5 | C31: Target level for process maturity. | D31: Gap analysis
A32: Target digitalization 0-5 | C32: Target level for implementation of digital technologies. | D32: Gap analysis
A33: Target resilience 0-5 | C33: Target level for resilience against relevant risks. | D33: Gap analysis
A34: Assessment cadence | C34: Quarterly, semi-annual, annual, or crisis-triggered review. | D34: Governance
A35: Risk appetite statement | C35: Closed choice: Low / Balanced / High. Low = risk-averse (targets tightened), High = more residual risk accepted (targets relaxed). Adjusts industry maturity targets across the model via _CONFIG_Model_Settings. | D35: Risk treatment
A36: Key assumptions / comments | C36: Context notes, assumptions, excluded scope or special assessment limitations. Leave blank until the real assessment is configured. | D36: All outputs
A38: Industry Template and Improved Scoring Logic
A39: Selected industry template | B39: =PV_Canonical_Industry -> 0 | C39: Derived from _ENGINE_Profile_Vector. Compatibility display only; not an active input.
A40: Default evidence confidence | B40: Medium | C40: Used when question-level evidence confidence is blank.
A41: Default assessor confidence | B41: Medium | C41: Used when question-level assessor confidence is blank.
A42: Template domains | B42: =COUNTIF(_REF_Model_Content!$A$1:$A$174,PV_Canonical_Industry) -> 0 | C42: Derived from PV_Canonical_Industry; should match template row count.
A43: Average target maturity | B43: =IFERROR(ROUND(AVERAGEIFS(_REF_Model_Content!$D$1:$D$174,_REF_Model_Content!$A$1:$A$174,PV_Canonical_Industry),2),"") | C43: Derived from PV_Canonical_Industry; legacy direct B9 reference retired.
A44: Average criticality multiplier | B44: =IFERROR(ROUND(AVERAGEIFS(_REF_Model_Content!$E$1:$E$174,_REF_Model_Content!$A$1:$A$174,PV_Canonical_Industry),2),"") | C44: Derived from PV_Canonical_Industry; legacy direct B9 reference retired.
A45: Critical systems | B45: =IFERROR(INDEX(_REF_Model_Content!$H$1:$H$157,MATCH(PV_Canonical_Industry,_REF_Model_Content!$A$1:$A$174,0)),"") | C45: Derived from PV_Canonical_Industry; legacy direct B9 reference retired.
A46: Red-line controls | B46: =IFERROR(INDEX(_REF_Model_Content!$I$1:$I$157,MATCH(PV_Canonical_Industry,_REF_Model_Content!$A$1:$A$174,0)),"") | C46: Derived from PV_Canonical_Industry; legacy direct B9 reference retired.
A47: Preferred strategy logic | B47: =IFERROR(INDEX(_REF_Model_Content!$L$1:$L$157,MATCH(PV_Canonical_Industry,_REF_Model_Content!$A$1:$A$174,0)),"") | C47: Derived from PV_Canonical_Industry; legacy direct B9 reference retired.
A48: Selected industry (_REF benchmark / weights) | B48: =PV_Canonical_Industry -> 0 | C48: Derived canonical industry used as compatibility bridge. Do not edit manually.
A49: Extended Company Context Inputs (closed answers only)
A50: Revenue model | C50: Primary revenue model used by the company. | D50: Risk, strategy and initiative logic
A51: Secondary revenue model | C51: Secondary or supporting monetization model. | D51: Revenue diversification logic
A52: Revenue recurrence | C52: Revenue stability profile. | D52: Crisis impact and revenue risk
A53: Primary sales motion | C53: Dominant sales motion. | D53: GTM and CRM strategy
A54: Customer concentration: top 1 client revenue share | C54: Estimated revenue share of the largest customer. | D54: Customer concentration risk
A55: Customer concentration: top 5 clients revenue share | C55: Estimated revenue share of top 5 customers. | D55: Customer concentration risk
A56: Customer concentration: top 10 clients revenue share | C56: Estimated revenue share of top 10 customers. | D56: Revenue diversification risk
A57: Supplier concentration: top 1 supplier dependency | C57: Estimated dependency on largest supplier/vendor/input. | D57: Supplier risk
A58: Supplier concentration: top 5 supplier dependency | C58: Estimated dependency on top 5 suppliers/vendors/inputs. | D58: Supply chain risk
A59: Critical supplier substitutability | C59: Availability of alternatives for critical suppliers. | D59: Supply chain resilience
A61: Business Criticality of Locations
A62: Location type | B62: Business criticality | C62: Disruption impact | D62: Continuity option | E62: Used by
A63: HQ | E63: Location and physical resilience logic
A64: Production site | E64: Location and physical resilience logic
A65: Warehouse | E65: Location and physical resilience logic
A66: Data center / core cloud region | E66: Location and physical resilience logic
A67: Call center / customer support center | E67: Location and physical resilience logic
A68: R&D / engineering center | E68: Location and physical resilience logic
A69: Sales office | E69: Location and physical resilience logic
A70: Retail / service branch | E70: Location and physical resilience logic
A72: Workforce Distribution
A73: Countries with workforce | C73: Workforce country footprint. | D73: Workforce/geographic concentration
A74: Largest country workforce share | C74: Estimated share of workforce in largest country. | D74: Workforce concentration risk
A75: Largest city/location workforce share | C75: Estimated share of workforce in largest city/site. | D75: Location concentration risk
A76: Remote work readiness | C76: Ability to continue work remotely. | D76: Pandemic/war/infrastructure resilience
A77: Cross-border mobility / relocation support | C77: Ability to relocate or support distributed workforce during crisis. | D77: Workforce continuity
A79: Critical Process List (select top processes)
A80: Critical process #1 | C80: Select one of the most business-critical processes. | D80: Risk, continuity and roadmap logic
A81: Critical process #2 | C81: Select one of the most business-critical processes. | D81: Risk, continuity and roadmap logic
A82: Critical process #3 | C82: Select one of the most business-critical processes. | D82: Risk, continuity and roadmap logic
A83: Critical process #4 | C83: Select one of the most business-critical processes. | D83: Risk, continuity and roadmap logic
A84: Critical process #5 | C84: Select one of the most business-critical processes. | D84: Risk, continuity and roadmap logic
A86: Critical Product / Service List (select top items)
A87: Critical product/service #1 | C87: Select one of the most critical products or services. | D87: Revenue and continuity logic
A88: Critical product/service #2 | C88: Select one of the most critical products or services. | D88: Revenue and continuity logic
A89: Critical product/service #3 | C89: Select one of the most critical products or services. | D89: Revenue and continuity logic
A90: Critical product/service #4 | C90: Select one of the most critical products or services. | D90: Revenue and continuity logic
A91: Critical product/service #5 | C91: Select one of the most critical products or services. | D91: Revenue and continuity logic
A93: Crisis History
A94: Experienced crisis | B94: Impact level | C94: Guidance | D94: Used by
A95: Pandemic | C95: Select a crisis the organization has already experienced and its observed impact. | D95: Calibration of scenario logic
A96: War / geopolitical escalation | C96: Select a crisis the organization has already experienced and its observed impact. | D96: Calibration of scenario logic
A97: Cyberattack / ransomware | C97: Select a crisis the organization has already experienced and its observed impact. | D97: Calibration of scenario logic
A98: Supply chain disruption | C98: Select a crisis the organization has already experienced and its observed impact. | D98: Calibration of scenario logic
A99: None experienced | C99: Select a crisis the organization has already experienced and its observed impact. | D99: Calibration of scenario logic
A101: Change Capacity and Brownfield
A102: Monthly change capacity (complexity points) | C102: Sum of initiative complexity points the organization can absorb per month. Rule of thumb: ~3 points per dedicated change FTE; adjust by transformation experience. Used as the overload threshold in Gantt Roadmap. | D102: Gantt Roadmap
A103: Transformation experience | C103: Low = few successful change programs (reduce capacity); High = mature PMO and delivery track record. | D103: Capacity guidance
A104: Brownfield note | C104: Mark initiatives already underway or completed on the Initiative Status sheet. Done / Not applicable items are excluded from rankings and the roadmap; In progress items keep consuming capacity.
A105: Company size band | C105: Peer benchmarks are size-adjusted. Eurostat DII shows ~1-level digital maturity gap between SMEs and large enterprises. | D105: Benchmark View
A107: Financial Anchors (hard data)
A108: Annual revenue band | C108: Pick the closest band. Used to monetize risks (cost of inaction) and size revenue-at-risk. | D108: Financial Resilience / Cost of inaction
...

Sheet Assessment Questions
A1: Assessment Questions
A2: Main assessment surface with all 424 questions. Use green/input columns for answers, evidence confidence, coverage, owners and comments.
A3: =HYPERLINK("#'Guidelines'!A1","⌂ Guidelines") -> ⌂ Guidelines | C3: ✎ Input: edit answer / confidence / comment columns only — the rest is formula-driven.
A4: Domain | B4: Source sheet | C4: Source row | D4: ID | E4: Subdomain | F4: Question | G4: Crisis relevance / why it matters | H4: Standards / frameworks | I4: Evidence to request | J4: Weight 1-5 | K4: Score 0-5 (auto from answer) | L4: Weighted score | M4: Max score | N4: Gap | O4: Risk level | P4: Score 0 criteria | Q4: Score 1 criteria | R4: Score 2 criteria | S4: Score 3 criteria | T4: Score 4 criteria | U4: Score 5 criteria | V4: Crisis scenario tags | W4: Owner / SME | X4: Comments / findings | Y4: Recommended action | Z4: Digitalization relevance 0-5 | AA4: Resilience relevance 0-5 | AB4: Process maturity relevance 0-5 | AC4: Answer (0–5) — select stage | AD4: Subarea | AE4: Questions | AF4: Avg score 0-5 | AG4: Maturity % | AH4: Critical/High | AI4: Gap to 5 | AJ4: Answered | AK4: Evidence confidence | AL4: Assessor confidence | AM4: Evidence factor | AN4: Assessor factor | AO4: Confidence-adjusted score 0-5 | AP4: Normalized score 0-100 | AQ4: Industry target 0-5 | AR4: Gap to industry target | AS4: Industry criticality multiplier | AT4: Industry-adjusted gap priority | AU4: Improved scoring note | AV4: v2 conf-adj score | AW4: v2 conf factor | AX4: Coverage (how widely deployed) | AY4: Coverage factor
A5: Company Geography | B5: Company Geography | C5: 5 | D5: COMP-001 | E5: Company profile | F5: How mature is the organization in managing legal entity structure, ownership, subsidiaries and operating countries, including ownership, evidence, metrics, fallback procedures and crisis stress testing? | G5: This topic affects exposure to Geopolitical risk; Physical site loss; Regulatory/legal shock. It helps identify how disruption may impact operations, people, revenue, systems, legal exposure or recovery time. | H5: ISO 22301; ISO 31000; ISO 9001; ISO 37000; PESTLE; Business Model Canvas | I5: Policy/SOP; owner/RACI; system report; dashboard; contracts; test records; incident history; interview evidence related to legal entity structure, ownership, subsidiaries and operating countries. | J5: 3 | K5: =_DATA_Assessment_Model!H5 -> 0 | L5: =_DATA_Assessment_Model!I5 -> 0 | M5: =_DATA_Assessment_Model!J5 -> 3 | N5: =_DATA_Assessment_Model!K5 -> 3 | O5: =_DATA_Assessment_Model!L5 -> Critical | P5: No reliable evidence that legal entity structure, ownership, subsidiaries and operating countries is defined, owned or managed. | Q5: Legal entity structure, ownership, subsidiaries and operating countries is handled informally and depends on individual knowledge or heroic effort. | R5: Legal entity structure, ownership, subsidiaries and operating countries is partially documented or implemented, but coverage is inconsistent and not crisis-tested. | S5: Legal entity structure, ownership, subsidiaries and operating countries is documented, owned, used in normal operations and supported by basic evidence or metrics. | T5: Legal entity structure, ownership, subsidiaries and operating countries is measured, periodically reviewed, integrated with related processes and tested against relevant disruption scenarios. | U5: Legal entity structure, ownership, subsidiaries and operating countries is optimized, continuously improved, automated where practical and demonstrably supports crisis resilience. | V5: Geopolitical risk; Physical site loss; Regulatory/legal shock | Y5: Use the recommended action generated by the model; validate with domain owner during real assessment. | Z5: 4 | AA5: 5 | AB5: 5 | AD5: Company profile | AE5: =_DATA_Assessment_Model!AB5 -> 7 | AF5: =_DATA_Assessment_Model!AC5 -> 0 | AG5: =_DATA_Assessment_Model!AD5 -> 0 | AH5: =_DATA_Assessment_Model!AE5 -> 7 | AI5: =_DATA_Assessment_Model!AF5 -> 5 | AJ5: =_DATA_Assessment_Model!AG5 -> 7 | AM5: =_DATA_Assessment_Model!AJ5 -> 0.9 | AN5: =_DATA_Assessment_Model!AK5 -> 0.9 | AO5: =_DATA_Assessment_Model!AL5 -> 0 | AP5: =_DATA_Assessment_Model!AM5 -> 0 | AQ5: =_DATA_Assessment_Model!AN5 -> 0 | AR5: =_DATA_Assessment_Model!AO5 -> 0 | AS5: =_DATA_Assessment_Model!AP5 -> 0 | AT5: =_DATA_Assessment_Model!AQ5 -> 0 | ... AW5: =_DATA_Assessment_Model!AT5 -> 0.9 | AY5: =_DATA_Assessment_Model!AV5 -> 0.9
A6: Company Geography | B6: Company Geography | C6: 6 | D6: COMP-002 | E6: Company profile | F6: How mature is the organization in managing business model, value proposition, revenue streams and cost drivers, including ownership, evidence, metrics, fallback procedures and crisis stress testing? | G6: This topic affects exposure to Geopolitical risk; Physical site loss; Regulatory/legal shock. It helps identify how disruption may impact operations, people, revenue, systems, legal exposure or recovery time. | H6: ISO 22301; ISO 31000; ISO 9001; ISO 37000; PESTLE; Business Model Canvas | I6: Policy/SOP; owner/RACI; system report; dashboard; contracts; test records; incident history; interview evidence related to business model, value proposition, revenue streams and cost drivers. | J6: 5 | K6: =_DATA_Assessment_Model!H6 -> 0 | L6: =_DATA_Assessment_Model!I6 -> 0 | M6: =_DATA_Assessment_Model!J6 -> 5 | N6: =_DATA_Assessment_Model!K6 -> 5 | O6: =_DATA_Assessment_Model!L6 -> Critical | P6: Does not exist; no owner, no documentation, no practice. | Q6: Ad hoc; depends entirely on specific individuals. | R6: Partially documented or implemented; coverage inconsistent; never tested under stress. | S6: Documented, owned, executed consistently; basic evidence and metrics exist. | T6: Measured and periodically tested/audited; integrated with adjacent processes. | U6: Optimized and automated where practical; stress-tested; benchmarked externally. | V6: Geopolitical risk; Physical site loss; Regulatory/legal shock | Y6: Use the recommended action generated by the model; validate with domain owner during real assessment. | Z6: 4 | AA6: 5 | AB6: 5 | AD6: Geographical distribution | AE6: =_DATA_Assessment_Model!AB6 -> 7 | AF6: =_DATA_Assessment_Model!AC6 -> 0 | AG6: =_DATA_Assessment_Model!AD6 -> 0 | AH6: =_DATA_Assessment_Model!AE6 -> 7 | AI6: =_DATA_Assessment_Model!AF6 -> 5 | AJ6: =_DATA_Assessment_Model!AG6 -> 7 | AM6: =_DATA_Assessment_Model!AJ6 -> 0.9 | AN6: =_DATA_Assessment_Model!AK6 -> 0.9 | AO6: =_DATA_Assessment_Model!AL6 -> 0 | AP6: =_DATA_Assessment_Model!AM6 -> 0 | AQ6: =_DATA_Assessment_Model!AN6 -> 0 | AR6: =_DATA_Assessment_Model!AO6 -> 0 | AS6: =_DATA_Assessment_Model!AP6 -> 0 | AT6: =_DATA_Assessment_Model!AQ6 -> 0 | ... AW6: =_DATA_Assessment_Model!AT6 -> 0.9 | AY6: =_DATA_Assessment_Model!AV6 -> 0.9
A7: Company Geography | B7: Company Geography | C7: 7 | D7: COMP-003 | E7: Company profile | F7: How mature is the organization in managing critical products and services ranked by revenue, margin and continuity priority, including ownership, evidence, metrics, fallback procedures and crisis stress testing? | G7: This topic affects exposure to Geopolitical risk; Physical site loss; Regulatory/legal shock. It helps identify how disruption may impact operations, people, revenue, systems, legal exposure or recovery time. | H7: ISO 22301; ISO 31000; ISO 9001; ISO 37000; PESTLE; Business Model Canvas | I7: Policy/SOP; owner/RACI; system report; dashboard; contracts; test records; incident history; interview evidence related to critical products and services ranked by revenue, margin and continuity priority. | J7: 5 | K7: =_DATA_Assessment_Model!H7 -> 0 | L7: =_DATA_Assessment_Model!I7 -> 0 | M7: =_DATA_Assessment_Model!J7 -> 5 | N7: =_DATA_Assessment_Model!K7 -> 5 | O7: =_DATA_Assessment_Model!L7 -> Critical | P7: Does not exist; no owner, no documentation, no practice. | Q7: Ad hoc; depends entirely on specific individuals. | R7: Partially documented or implemented; coverage inconsistent; never tested under stress. | S7: Documented, owned, executed consistently; basic evidence and metrics exist. | T7: Measured and periodically tested/audited; integrated with adjacent processes. | U7: Optimized and automated where practical; stress-tested; benchmarked externally. | V7: Geopolitical risk; Physical site loss; Regulatory/legal shock | Y7: Use the recommended action generated by the model; validate with domain owner during real assessment. | Z7: 4 | AA7: 5 | AB7: 5 | AD7: Context and dependencies | AE7: =_DATA_Assessment_Model!AB7 -> 5 | AF7: =_DATA_Assessment_Model!AC7 -> 0 | AG7: =_DATA_Assessment_Model!AD7 -> 0 | AH7: =_DATA_Assessment_Model!AE7 -> 5 | AI7: =_DATA_Assessment_Model!AF7 -> 5 | AJ7: =_DATA_Assessment_Model!AG7 -> 5 | AM7: =_DATA_Assessment_Model!AJ7 -> 0.9 | AN7: =_DATA_Assessment_Model!AK7 -> 0.9 | AO7: =_DATA_Assessment_Model!AL7 -> 0 | AP7: =_DATA_Assessment_Model!AM7 -> 0 | AQ7: =_DATA_Assessment_Model!AN7 -> 0 | AR7: =_DATA_Assessment_Model!AO7 -> 0 | AS7: =_DATA_Assessment_Model!AP7 -> 0 | AT7: =_DATA_Assessment_Model!AQ7 -> 0 | ... AW7: =_DATA_Assessment_Model!AT7 -> 0.9 | AY7: =_DATA_Assessment_Model!AV7 -> 0.9
A8: Company Geography | B8: Company Geography | C8: 8 | D8: COMP-004 | E8: Company profile | F8: How mature is the organization in managing operating model: centralized, distributed, outsourced, remote or hybrid, including ownership, evidence, metrics, fallback procedures and crisis stress testing? | G8: This topic affects exposure to Geopolitical risk; Physical site loss; Regulatory/legal shock. It helps identify how disruption may impact operations, people, revenue, systems, legal exposure or recovery time. | H8: ISO 22301; ISO 31000; ISO 9001; ISO 37000; PESTLE; Business Model Canvas | I8: Policy/SOP; owner/RACI; system report; dashboard; contracts; test records; incident history; interview evidence related to operating model: centralized, distributed, outsourced, remote or hybrid. | J8: 4 | K8: =_DATA_Assessment_Model!H8 -> 0 | L8: =_DATA_Assessment_Model!I8 -> 0 | M8: =_DATA_Assessment_Model!J8 -> 4 | N8: =_DATA_Assessment_Model!K8 -> 4 | O8: =_DATA_Assessment_Model!L8 -> Critical | P8: No reliable evidence that operating model: centralized, distributed, outsourced, remote or hybrid is defined, owned or managed. | Q8: Operating model: centralized, distributed, outsourced, remote or hybrid is handled informally and depends on individual knowledge or heroic effort. | R8: Operating model: centralized, distributed, outsourced, remote or hybrid is partially documented or implemented, but coverage is inconsistent and not crisis-tested. | S8: Operating model: centralized, distributed, outsourced, remote or hybrid is documented, owned, used in normal operations and supported by basic evidence or metrics. | T8: Operating model: centralized, distributed, outsourced, remote or hybrid is measured, periodically reviewed, integrated with related processes and tested against relevant disruption scenarios. | U8: Operating model: centralized, distributed, outsourced, remote or hybrid is optimized, continuously improved, automated where practical and demonstrably supports crisis resilience. | V8: Geopolitical risk; Physical site loss; Regulatory/legal shock | Y8: Use the recommended action generated by the model; validate with domain owner during real assessment. | Z8: 4 | AA8: 5 | AB8: 5 | AM8: =_DATA_Assessment_Model!AJ8 -> 0.9 | AN8: =_DATA_Assessment_Model!AK8 -> 0.9 | AO8: =_DATA_Assessment_Model!AL8 -> 0 | AP8: =_DATA_Assessment_Model!AM8 -> 0 | AQ8: =_DATA_Assessment_Model!AN8 -> 0 | AR8: =_DATA_Assessment_Model!AO8 -> 0 | AS8: =_DATA_Assessment_Model!AP8 -> 0 | AT8: =_DATA_Assessment_Model!AQ8 -> 0 | ... AW8: =_DATA_Assessment_Model!AT8 -> 0.9 | AY8: =_DATA_Assessment_Model!AV8 -> 0.9
A9: Company Geography | B9: Company Geography | C9: 9 | D9: COMP-005 | E9: Company profile | F9: How mature is the organization in managing critical assets: people, facilities, systems, data, equipment and intellectual property, including ownership, evidence, metrics, fallback procedures and crisis stress testing? | G9: This topic affects exposure to Geopolitical risk; Physical site loss; Regulatory/legal shock. It helps identify how disruption may impact operations, people, revenue, systems, legal exposure or recovery time. | H9: ISO 22301; ISO 31000; ISO 9001; ISO 37000; PESTLE; Business Model Canvas | I9: Policy/SOP; owner/RACI; system report; dashboard; contracts; test records; incident history; interview evidence related to critical assets: people, facilities, systems, data, equipment and intellectual property. | J9: 5 | K9: =_DATA_Assessment_Model!H9 -> 0 | L9: =_DATA_Assessment_Model!I9 -> 0 | M9: =_DATA_Assessment_Model!J9 -> 5 | N9: =_DATA_Assessment_Model!K9 -> 5 | O9: =_DATA_Assessment_Model!L9 -> Critical | P9: Does not exist; no owner, no documentation, no practice. | Q9: Ad hoc; depends entirely on specific individuals. | R9: Partially documented or implemented; coverage inconsistent; never tested under stress. | S9: Documented, owned, executed consistently; basic evidence and metrics exist. | T9: Measured and periodically tested/audited; integrated with adjacent processes. | U9: Optimized and automated where practical; stress-tested; benchmarked externally. | V9: Geopolitical risk; Physical site loss; Regulatory/legal shock | Y9: Use the recommended action generated by the model; validate with domain owner during real assessment. | Z9: 5 | AA9: 5 | AB9: 5 | AM9: =_DATA_Assessment_Model!AJ9 -> 0.9 | AN9: =_DATA_Assessment_Model!AK9 -> 0.9 | AO9: =_DATA_Assessment_Model!AL9 -> 0 | AP9: =_DATA_Assessment_Model!AM9 -> 0 | AQ9: =_DATA_Assessment_Model!AN9 -> 0 | AR9: =_DATA_Assessment_Model!AO9 -> 0 | AS9: =_DATA_Assessment_Model!AP9 -> 0 | AT9: =_DATA_Assessment_Model!AQ9 -> 0 | ... AW9: =_DATA_Assessment_Model!AT9 -> 0.9 | AY9: =_DATA_Assessment_Model!AV9 -> 0.9
A10: Company Geography | B10: Company Geography | C10: 10 | D10: COMP-006 | E10: Company profile | F10: How mature is the organization in managing regulatory exposure by country, market, product and customer type, including ownership, evidence, metrics, fallback procedures and crisis stress testing? | G10: This topic affects exposure to Geopolitical risk; Physical site loss; Regulatory/legal shock. It helps identify how disruption may impact operations, people, revenue, systems, legal exposure or recovery time. | H10: ISO 22301; ISO 31000; ISO 9001; ISO 37000; PESTLE; Business Model Canvas | I10: Policy/SOP; owner/RACI; system report; dashboard; contracts; test records; incident history; interview evidence related to regulatory exposure by country, market, product and customer type. | J10: 4 | K10: =_DATA_Assessment_Model!H10 -> 0 | L10: =_DATA_Assessment_Model!I10 -> 0 | M10: =_DATA_Assessment_Model!J10 -> 4 | N10: =_DATA_Assessment_Model!K10 -> 4 | O10: =_DATA_Assessment_Model!L10 -> Critical | P10: No reliable evidence that regulatory exposure by country, market, product and customer type is defined, owned or managed. | Q10: Regulatory exposure by country, market, product and customer type is handled informally and depends on individual knowledge or heroic effort. | R10: Regulatory exposure by country, market, product and customer type is partially documented or implemented, but coverage is inconsistent and not crisis-tested. | S10: Regulatory exposure by country, market, product and customer type is documented, owned, used in normal operations and supported by basic evidence or metrics. | T10: Regulatory exposure by country, market, product and customer type is measured, periodically reviewed, integrated with related processes and tested against relevant disruption scenarios. | U10: Regulatory exposure by country, market, product and customer type is optimized, continuously improved, automated where practical and demonstrably supports crisis resilience. | V10: Geopolitical risk; Physical site loss; Regulatory/legal shock | Y10: Use the recommended action generated by the model; validate with domain owner during real assessment. | Z10: 4 | AA10: 5 | AB10: 5 | AM10: =_DATA_Assessment_Model!AJ10 -> 0.9 | AN10: =_DATA_Assessment_Model!AK10 -> 0.9 | AO10: =_DATA_Assessment_Model!AL10 -> 0 | AP10: =_DATA_Assessment_Model!AM10 -> 0 | AQ10: =_DATA_Assessment_Model!AN10 -> 0 | AR10: =_DATA_Assessment_Model!AO10 -> 0 | AS10: =_DATA_Assessment_Model!AP10 -> 0 | AT10: =_DATA_Assessment_Model!AQ10 -> 0 | ... AW10: =_DATA_Assessment_Model!AT10 -> 0.9 | AY10: =_DATA_Assessment_Model!AV10 -> 0.9
A11: Company Geography | B11: Company Geography | C11: 11 | D11: COMP-007 | E11: Company profile | F11: How mature is the organization in managing insurance coverage for business interruption, cyber, liability, property and key assets, including ownership, evidence, metrics, fallback procedures and crisis stress testing? | G11: This topic affects exposure to Geopolitical risk; Physical site loss; Regulatory/legal shock. It helps identify how disruption may impact operations, people, revenue, systems, legal exposure or recovery time. | H11: ISO 22301; ISO 31000; ISO 9001; ISO 37000; PESTLE; Business Model Canvas | I11: Policy/SOP; owner/RACI; system report; dashboard; contracts; test records; incident history; interview evidence related to insurance coverage for business interruption, cyber, liability, property and key assets. | J11: 5 | K11: =_DATA_Assessment_Model!H11 -> 0 | L11: =_DATA_Assessment_Model!I11 -> 0 | M11: =_DATA_Assessment_Model!J11 -> 5 | N11: =_DATA_Assessment_Model!K11 -> 5 | O11: =_DATA_Assessment_Model!L11 -> Critical | P11: Does not exist; no owner, no documentation, no practice. | Q11: Ad hoc; depends entirely on specific individuals. | R11: Partially documented or implemented; coverage inconsistent; never tested under stress. | S11: Documented, owned, executed consistently; basic evidence and metrics exist. | T11: Measured and periodically tested/audited; integrated with adjacent processes. | U11: Optimized and automated where practical; stress-tested; benchmarked externally. | V11: Geopolitical risk; Physical site loss; Regulatory/legal shock | Y11: Use the recommended action generated by the model; validate with domain owner during real assessment. | Z11: 5 | AA11: 5 | AB11: 5 | AM11: =_DATA_Assessment_Model!AJ11 -> 0.9 | AN11: =_DATA_Assessment_Model!AK11 -> 0.9 | AO11: =_DATA_Assessment_Model!AL11 -> 0 | AP11: =_DATA_Assessment_Model!AM11 -> 0 | AQ11: =_DATA_Assessment_Model!AN11 -> 0 | AR11: =_DATA_Assessment_Model!AO11 -> 0 | AS11: =_DATA_Assessment_Model!AP11 -> 0 | AT11: =_DATA_Assessment_Model!AQ11 -> 0 | ... AW11: =_DATA_Assessment_Model!AT11 -> 0.9 | AY11: =_DATA_Assessment_Model!AV11 -> 0.9
A12: Company Geography | B12: Company Geography | C12: 12 | D12: COMP-008 | E12: Geographical distribution | F12: How mature is the organization in managing workforce distribution by country, city, function, contract type and criticality, including ownership, evidence, metrics, fallback procedures and crisis stress testing? | G12: This topic affects exposure to Geopolitical risk; Physical site loss; Regulatory/legal shock. It helps identify how disruption may impact operations, people, revenue, systems, legal exposure or recovery time. | H12: ISO 22301; ISO 31000; ISO 9001; ISO 37000; PESTLE; Business Model Canvas | I12: Policy/SOP; owner/RACI; system report; dashboard; contracts; test records; incident history; interview evidence related to workforce distribution by country, city, function, contract type and criticality. | J12: 5 | K12: =_DATA_Assessment_Model!H12 -> 0 | L12: =_DATA_Assessment_Model!I12 -> 0 | M12: =_DATA_Assessment_Model!J12 -> 5 | N12: =_DATA_Assessment_Model!K12 -> 5 | O12: =_DATA_Assessment_Model!L12 -> Critical | P12: Does not exist; no owner, no documentation, no practice. | Q12: Ad hoc; depends entirely on specific individuals. | R12: Partially documented or implemented; coverage inconsistent; never tested under stress. | S12: Documented, owned, executed consistently; basic evidence and metrics exist. | T12: Measured and periodically tested/audited; integrated with adjacent processes. | U12: Optimized and automated where practical; stress-tested; benchmarked externally. | V12: Geopolitical risk; Physical site loss; Regulatory/legal shock | Y12: Use the recommended action generated by the model; validate with domain owner during real assessment. | Z12: 4 | AA12: 5 | AB12: 5 | AM12: =_DATA_Assessment_Model!AJ12 -> 0.9 | AN12: =_DATA_Assessment_Model!AK12 -> 0.9 | AO12: =_DATA_Assessment_Model!AL12 -> 0 | AP12: =_DATA_Assessment_Model!AM12 -> 0 | AQ12: =_DATA_Assessment_Model!AN12 -> 0 | AR12: =_DATA_Assessment_Model!AO12 -> 0 | AS12: =_DATA_Assessment_Model!AP12 -> 0 | AT12: =_DATA_Assessment_Model!AQ12 -> 0 | ... AW12: =_DATA_Assessment_Model!AT12 -> 0.9 | AY12: =_DATA_Assessment_Model!AV12 -> 0.9
A13: Company Geography | B13: Company Geography | C13: 13 | D13: COMP-009 | E13: Geographical distribution | F13: How mature is the organization in managing site distribution across offices, plants, warehouses, stores, labs and data centers, including ownership, evidence, metrics, fallback procedures and crisis stress testing? | G13: This topic affects exposure to Geopolitical risk; Physical site loss; Regulatory/legal shock. It helps identify how disruption may impact operations, people, revenue, systems, legal exposure or recovery time. | H13: ISO 22301; ISO 31000; ISO 9001; ISO 37000; PESTLE; Business Model Canvas | I13: Policy/SOP; owner/RACI; system report; dashboard; contracts; test records; incident history; interview evidence related to site distribution across offices, plants, warehouses, stores, labs and data centers. | J13: 5 | K13: =_DATA_Assessment_Model!H13 -> 0 | L13: =_DATA_Assessment_Model!I13 -> 0 | M13: =_DATA_Assessment_Model!J13 -> 5 | N13: =_DATA_Assessment_Model!K13 -> 5 | O13: =_DATA_Assessment_Model!L13 -> Critical | P13: No plan or procedure exists. | Q13: Knowledge lives with individuals; nothing usable is written down. | R13: Drafted but outdated, not approved, or unknown to the people who must use it. | S13: Approved and current; owners assigned; affected staff know it exists and where to find it. | T13: Tested against realistic scenarios; updated after each test or real incident. | U13: Exercised regularly including external parties; readiness measured; continuously improved. | V13: Geopolitical risk; Physical site loss; Regulatory/legal shock | Y13: Use the recommended action generated by the model; validate with domain owner during real assessment. | Z13: 5 | AA13: 5 | AB13: 5 | AM13: =_DATA_Assessment_Model!AJ13 -> 0.9 | AN13: =_DATA_Assessment_Model!AK13 -> 0.9 | AO13: =_DATA_Assessment_Model!AL13 -> 0 | AP13: =_DATA_Assessment_Model!AM13 -> 0 | AQ13: =_DATA_Assessment_Model!AN13 -> 0 | AR13: =_DATA_Assessment_Model!AO13 -> 0 | AS13: =_DATA_Assessment_Model!AP13 -> 0 | AT13: =_DATA_Assessment_Model!AQ13 -> 0 | ... AW13: =_DATA_Assessment_Model!AT13 -> 0.9 | AY13: =_DATA_Assessment_Model!AV13 -> 0.9
A14: Company Geography | B14: Company Geography | C14: 14 | D14: COMP-010 | E14: Geographical distribution | F14: How mature is the organization in managing revenue distribution by country, currency, customer geography and market exposure, including ownership, evidence, metrics, fallback procedures and crisis stress testing? | G14: This topic affects exposure to Geopolitical risk; Physical site loss; Regulatory/legal shock. It helps identify how disruption may impact operations, people, revenue, systems, legal exposure or recovery time. | H14: ISO 22301; ISO 31000; ISO 9001; ISO 37000; PESTLE; Business Model Canvas | I14: Policy/SOP; owner/RACI; system report; dashboard; contracts; test records; incident history; interview evidence related to revenue distribution by country, currency, customer geography and market exposure. | J14: 4 | K14: =_DATA_Assessment_Model!H14 -> 0 | L14: =_DATA_Assessment_Model!I14 -> 0 | M14: =_DATA_Assessment_Model!J14 -> 4 | N14: =_DATA_Assessment_Model!K14 -> 4 | O14: =_DATA_Assessment_Model!L14 -> Critical | P14: No reliable evidence that revenue distribution by country, currency, customer geography and market exposure is defined, owned or managed. | Q14: Revenue distribution by country, currency, customer geography and market exposure is handled informally and depends on individual knowledge or heroic effort. | R14: Revenue distribution by country, currency, customer geography and market exposure is partially documented or implemented, but coverage is inconsistent and not crisis-tested. | S14: Revenue distribution by country, currency, customer geography and market exposure is documented, owned, used in normal operations and supported by basic evidence or metrics. | T14: Revenue distribution by country, currency, customer geography and market exposure is measured, periodically reviewed, integrated with related processes and tested against relevant disruption scenarios. | U14: Revenue distribution by country, currency, customer geography and market exposure is optimized, continuously improved, automated where practical and demonstrably supports crisis resilience. | V14: Geopolitical risk; Physical site loss; Regulatory/legal shock | Y14: Use the recommended action generated by the model; validate with domain owner during real assessment. | Z14: 4 | AA14: 5 | AB14: 5 | AM14: =_DATA_Assessment_Model!AJ14 -> 0.9 | AN14: =_DATA_Assessment_Model!AK14 -> 0.9 | AO14: =_DATA_Assessment_Model!AL14 -> 0 | AP14: =_DATA_Assessment_Model!AM14 -> 0 | AQ14: =_DATA_Assessment_Model!AN14 -> 0 | AR14: =_DATA_Assessment_Model!AO14 -> 0 | AS14: =_DATA_Assessment_Model!AP14 -> 0 | AT14: =_DATA_Assessment_Model!AQ14 -> 0 | ... AW14: =_DATA_Assessment_Model!AT14 -> 0.9 | AY14: =_DATA_Assessment_Model!AV14 -> 0.9
A15: Company Geography | B15: Company Geography | C15: 15 | D15: COMP-011 | E15: Geographical distribution | F15: How mature is the organization in managing supplier distribution by country, tier, criticality and replacement options, including ownership, evidence, metrics, fallback procedures and crisis stress testing? | G15: This topic affects exposure to Geopolitical risk; Physical site loss; Regulatory/legal shock. It helps identify how disruption may impact operations, people, revenue, systems, legal exposure or recovery time. | H15: ISO 22301; ISO 31000; ISO 9001; ISO 37000; PESTLE; Business Model Canvas | I15: Policy/SOP; owner/RACI; system report; dashboard; contracts; test records; incident history; interview evidence related to supplier distribution by country, tier, criticality and replacement options. | J15: 5 | K15: =_DATA_Assessment_Model!H15 -> 0 | L15: =_DATA_Assessment_Model!I15 -> 0 | M15: =_DATA_Assessment_Model!J15 -> 5 | N15: =_DATA_Assessment_Model!K15 -> 5 | O15: =_DATA_Assessment_Model!L15 -> Critical | P15: Does not exist; no owner, no documentation, no practice. | Q15: Ad hoc; depends entirely on specific individuals. | R15: Partially documented or implemented; coverage inconsistent; never tested under stress. | S15: Documented, owned, executed consistently; basic evidence and metrics exist. | T15: Measured and periodically tested/audited; integrated with adjacent processes. | U15: Optimized and automated where practical; stress-tested; benchmarked externally. | V15: Geopolitical risk; Physical site loss; Regulatory/legal shock | Y15: Use the recommended action generated by the model; validate with domain owner during real assessment. | Z15: 4 | AA15: 5 | AB15: 5 | AM15: =_DATA_Assessment_Model!AJ15 -> 0.9 | AN15: =_DATA_Assessment_Model!AK15 -> 0.9 | AO15: =_DATA_Assessment_Model!AL15 -> 0 | AP15: =_DATA_Assessment_Model!AM15 -> 0 | AQ15: =_DATA_Assessment_Model!AN15 -> 0 | AR15: =_DATA_Assessment_Model!AO15 -> 0 | AS15: =_DATA_Assessment_Model!AP15 -> 0 | AT15: =_DATA_Assessment_Model!AQ15 -> 0 | ... AW15: =_DATA_Assessment_Model!AT15 -> 0.9 | AY15: =_DATA_Assessment_Model!AV15 -> 0.9
A16: Company Geography | B16: Company Geography | C16: 16 | D16: COMP-012 | E16: Geographical distribution | F16: How mature is the organization in managing customer distribution by geography, industry, contract and crisis sensitivity, including ownership, evidence, metrics, fallback procedures and crisis stress testing? | G16: This topic affects exposure to Geopolitical risk; Physical site loss; Regulatory/legal shock. It helps identify how disruption may impact operations, people, revenue, systems, legal exposure or recovery time. | H16: ISO 22301; ISO 31000; ISO 9001; ISO 37000; PESTLE; Business Model Canvas | I16: Policy/SOP; owner/RACI; system report; dashboard; contracts; test records; incident history; interview evidence related to customer distribution by geography, industry, contract and crisis sensitivity. | J16: 5 | K16: =_DATA_Assessment_Model!H16 -> 0 | L16: =_DATA_Assessment_Model!I16 -> 0 | M16: =_DATA_Assessment_Model!J16 -> 5 | N16: =_DATA_Assessment_Model!K16 -> 5 | O16: =_DATA_Assessment_Model!L16 -> Critical | P16: Does not exist; no owner, no documentation, no practice. | Q16: Ad hoc; depends entirely on specific individuals. | R16: Partially documented or implemented; coverage inconsistent; never tested under stress. | S16: Documented, owned, executed consistently; basic evidence and metrics exist. | T16: Measured and periodically tested/audited; integrated with adjacent processes. | U16: Optimized and automated where practical; stress-tested; benchmarked externally. | V16: Geopolitical risk; Physical site loss; Regulatory/legal shock | Y16: Use the recommended action generated by the model; validate with domain owner during real assessment. | Z16: 4 | AA16: 5 | AB16: 5 | AM16: =_DATA_Assessment_Model!AJ16 -> 0.9 | AN16: =_DATA_Assessment_Model!AK16 -> 0.9 | AO16: =_DATA_Assessment_Model!AL16 -> 0 | AP16: =_DATA_Assessment_Model!AM16 -> 0 | AQ16: =_DATA_Assessment_Model!AN16 -> 0 | AR16: =_DATA_Assessment_Model!AO16 -> 0 | AS16: =_DATA_Assessment_Model!AP16 -> 0 | AT16: =_DATA_Assessment_Model!AQ16 -> 0 | ... AW16: =_DATA_Assessment_Model!AT16 -> 0.9 | AY16: =_DATA_Assessment_Model!AV16 -> 0.9
A17: Company Geography | B17: Company Geography | C17: 17 | D17: COMP-013 | E17: Geographical distribution | F17: How mature is the organization in managing country risk monitoring for war, sanctions, political instability, natural disaster and energy risks, including ownership, evidence, metrics, fallback procedures and crisis stress testing? | G17: This topic affects exposure to Geopolitical risk; Physical site loss; Regulatory/legal shock. It helps identify how disruption may impact operations, people, revenue, systems, legal exposure or recovery time. | H17: ISO 22301; ISO 31000; ISO 9001; ISO 37000; PESTLE; Business Model Canvas | I17: Policy/SOP; owner/RACI; system report; dashboard; contracts; test records; incident history; interview evidence related to country risk monitoring for war, sanctions, political instability, natural disaster and energy risks. | J17: 4 | K17: =_DATA_Assessment_Model!H17 -> 0 | L17: =_DATA_Assessment_Model!I17 -> 0 | M17: =_DATA_Assessment_Model!J17 -> 4 | N17: =_DATA_Assessment_Model!K17 -> 4 | O17: =_DATA_Assessment_Model!L17 -> Critical | P17: No reliable evidence that country risk monitoring for war, sanctions, political instability, natural disaster and energy risks is defined, owned or managed. | Q17: Country risk monitoring for war, sanctions, political instability, natural disaster and energy risks is handled informally and depends on individual knowledge or heroic effort. | R17: Country risk monitoring for war, sanctions, political instability, natural disaster and energy risks is partially documented or implemented, but coverage is inconsistent and not crisis-tested. | S17: Country risk monitoring for war, sanctions, political instability, natural disaster and energy risks is documented, owned, used in normal operations and supported by basic evidence or metrics. | T17: Country risk monitoring for war, sanctions, political instability, natural disaster and energy risks is measured, periodically reviewed, integrated with related processes and tested against relevant disruption scenarios. | U17: Country risk monitoring for war, sanctions, political instability, natural disaster and energy risks is optimized, continuously improved, automated where practical and demonstrably supports crisis resilience. | V17: Geopolitical risk; Physical site loss; Regulatory/legal shock | Y17: Use the recommended action generated by the model; validate with domain owner during real assessment. | Z17: 4 | AA17: 5 | AB17: 5 | AM17: =_DATA_Assessment_Model!AJ17 -> 0.9 | AN17: =_DATA_Assessment_Model!AK17 -> 0.9 | AO17: =_DATA_Assessment_Model!AL17 -> 0 | AP17: =_DATA_Assessment_Model!AM17 -> 0 | AQ17: =_DATA_Assessment_Model!AN17 -> 0 | AR17: =_DATA_Assessment_Model!AO17 -> 0 | AS17: =_DATA_Assessment_Model!AP17 -> 0 | AT17: =_DATA_Assessment_Model!AQ17 -> 0 | ... AW17: =_DATA_Assessment_Model!AT17 -> 0.9 | AY17: =_DATA_Assessment_Model!AV17 -> 0.9
A18: Company Geography | B18: Company Geography | C18: 18 | D18: COMP-014 | E18: Geographical distribution | F18: How mature is the organization in managing relocation and alternative location options for critical teams and operations, including ownership, evidence, metrics, fallback procedures and crisis stress testing? | G18: This topic affects exposure to Geopolitical risk; Physical site loss; Regulatory/legal shock. It helps identify how disruption may impact operations, people, revenue, systems, legal exposure or recovery time. | H18: ISO 22301; ISO 31000; ISO 9001; ISO 37000; PESTLE; Business Model Canvas | I18: Policy/SOP; owner/RACI; system report; dashboard; contracts; test records; incident history; interview evidence related to relocation and alternative location options for critical teams and operations. | J18: 5 | K18: =_DATA_Assessment_Model!H18 -> 0 | L18: =_DATA_Assessment_Model!I18 -> 0 | M18: =_DATA_Assessment_Model!J18 -> 5 | N18: =_DATA_Assessment_Model!K18 -> 5 | O18: =_DATA_Assessment_Model!L18 -> Critical | P18: Does not exist; no owner, no documentation, no practice. | Q18: Ad hoc; depends entirely on specific individuals. | R18: Partially documented or implemented; coverage inconsistent; never tested under stress. | S18: Documented, owned, executed consistently; basic evidence and metrics exist. | T18: Measured and periodically tested/audited; integrated with adjacent processes. | U18: Optimized and automated where practical; stress-tested; benchmarked externally. | V18: Geopolitical risk; Physical site loss; Regulatory/legal shock | Y18: Use the recommended action generated by the model; validate with domain owner during real assessment. | Z18: 4 | AA18: 5 | AB18: 5 | AM18: =_DATA_Assessment_Model!AJ18 -> 0.9 | AN18: =_DATA_Assessment_Model!AK18 -> 0.9 | AO18: =_DATA_Assessment_Model!AL18 -> 0 | AP18: =_DATA_Assessment_Model!AM18 -> 0 | AQ18: =_DATA_Assessment_Model!AN18 -> 0 | AR18: =_DATA_Assessment_Model!AO18 -> 0 | AS18: =_DATA_Assessment_Model!AP18 -> 0 | AT18: =_DATA_Assessment_Model!AQ18 -> 0 | ... AW18: =_DATA_Assessment_Model!AT18 -> 0.9 | AY18: =_DATA_Assessment_Model!AV18 -> 0.9
A19: Company Geography | B19: Company Geography | C19: 19 | D19: COMP-016 | E19: Context and dependencies | F19: How mature is the organization in managing single-country, single-site and single-provider concentration risks, including ownership, evidence, metrics, fallback procedures and crisis stress testing? | G19: This topic affects exposure to Geopolitical risk; Physical site loss; Regulatory/legal shock. It helps identify how disruption may impact operations, people, revenue, systems, legal exposure or recovery time. | H19: ISO 22301; ISO 31000; ISO 9001; ISO 37000; PESTLE; Business Model Canvas | I19: Policy/SOP; owner/RACI; system report; dashboard; contracts; test records; incident history; interview evidence related to single-country, single-site and single-provider concentration risks. | J19: 5 | K19: =_DATA_Assessment_Model!H19 -> 0 | L19: =_DATA_Assessment_Model!I19 -> 0 | M19: =_DATA_Assessment_Model!J19 -> 5 | N19: =_DATA_Assessment_Model!K19 -> 5 | O19: =_DATA_Assessment_Model!L19 -> Critical | P19: Does not exist; no owner, no documentation, no practice. | Q19: Ad hoc; depends entirely on specific individuals. | R19: Partially documented or implemented; coverage inconsistent; never tested under stress. | S19: Documented, owned, executed consistently; basic evidence and metrics exist. | T19: Measured and periodically tested/audited; integrated with adjacent processes. | U19: Optimized and automated where practical; stress-tested; benchmarked externally. | V19: Geopolitical risk; Physical site loss; Regulatory/legal shock | Y19: Use the recommended action generated by the model; validate with domain owner during real assessment. | Z19: 4 | AA19: 5 | AB19: 5 | AM19: =_DATA_Assessment_Model!AJ19 -> 0.9 | AN19: =_DATA_Assessment_Model!AK19 -> 0.9 | AO19: =_DATA_Assessment_Model!AL19 -> 0 | AP19: =_DATA_Assessment_Model!AM19 -> 0 | AQ19: =_DATA_Assessment_Model!AN19 -> 0 | AR19: =_DATA_Assessment_Model!AO19 -> 0 | AS19: =_DATA_Assessment_Model!AP19 -> 0 | AT19: =_DATA_Assessment_Model!AQ19 -> 0 | ... AW19: =_DATA_Assessment_Model!AT19 -> 0.9 | AY19: =_DATA_Assessment_Model!AV19 -> 0.9
... A23: Company Geography | B23: Company Geography | C23: 23 | D23: COMP-021 | E23: Context and dependencies | F23: How mature is the organization in managing critical infrastructure status and government emergency obligations across operating geographies, including ownership, evidence, metrics, fallback procedures and crisis stress testing? | G23: This topic affects exposure to War/security crisis; Energy/utilities outage; Regulatory/legal shock. It helps identify how disruption may impact operations, people, revenue, systems, legal exposure or recovery time. | H23: ISO 22301; NIS2; national critical infrastructure regulation | I23: Policy/SOP; owner/RACI; system report; dashboard; contracts; test records; incident history; interview evidence | J23: 3 | K23: =_DATA_Assessment_Model!H23 -> 0 | L23: =_DATA_Assessment_Model!I23 -> 0 | M23: =_DATA_Assessment_Model!J23 -> 3 | N23: =_DATA_Assessment_Model!K23 -> 3 | O23: =_DATA_Assessment_Model!L23 -> Critical | P23: No reliable evidence that critical infrastructure status and government emergency obligations across operating geographies is defined, owned or managed. | Q23: Critical infrastructure status and government emergency obligations across operating geographies is handled informally and depends on individual knowledge or heroic effort. | R23: Critical infrastructure status and government emergency obligations across operating geographies is partially documented or implemented, but coverage is inconsistent and not crisis-tested. | S23: Critical infrastructure status and government emergency obligations across operating geographies is documented, owned, used in normal operations and supported by basic evidence or metrics. | T23: Critical infrastructure status and government emergency obligations across operating geographies is measured, periodically reviewed, integrated with related processes and tested against relevant disruption scenarios. | U23: Critical infrastructure status and government emergency obligations across operating geographies is optimized, continuously improved, automated where practical and demonstrably supports crisis resilience. | V23: War/security crisis; Energy/utilities outage; Regulatory/legal shock | Y23: Use the recommended action generated by the model; validate with domain owner during real assessment. | Z23: 2 | AA23: 4 | AB23: 4 | AM23: =_DATA_Assessment_Model!AJ23 -> 0.9 | AN23: =_DATA_Assessment_Model!AK23 -> 0.9 | AO23: =_DATA_Assessment_Model!AL23 -> 0 | AP23: =_DATA_Assessment_Model!AM23 -> 0 | AQ23: =_DATA_Assessment_Model!AN23 -> 0 | AR23: =_DATA_Assessment_Model!AO23 -> 0 | AS23: =_DATA_Assessment_Model!AP23 -> 0 | AT23: =_DATA_Assessment_Model!AQ23 -> 0 | ... AW23: =_DATA_Assessment_Model!AT23 -> 0.9 | AY23: =_DATA_Assessment_Model!AV23 -> 0.9
A24: Strategy GTM | B24: Strategy GTM | C24: 5 | D24: STRA-001 | E24: Corporate strategy | F24: How mature is the organization in managing documented strategy translated into objectives, KPIs, budgets and accountable owners, including ownership, evidence, metrics, fallback procedures and crisis stress testing? | G24: This topic affects exposure to Demand shock; Financial / liquidity shock; Reputation crisis. It helps identify how disruption may impact operations, people, revenue, systems, legal exposure or recovery time. | H24: ISO 9001; ISO 31000; ISO 37000; McKinsey 7S; OHI; Bain Elements of Value; Jobs-to-be-Done; Porter Five Forces; OKR | I24: Policy/SOP; owner/RACI; system report; dashboard; contracts; test records; incident history; interview evidence related to documented strategy translated into objectives, KPIs, budgets and accountable owners. | J24: 4 | K24: =_DATA_Assessment_Model!H24 -> 0 | L24: =_DATA_Assessment_Model!I24 -> 0 | M24: =_DATA_Assessment_Model!J24 -> 4 | N24: =_DATA_Assessment_Model!K24 -> 4 | O24: =_DATA_Assessment_Model!L24 -> Critical | P24: No reliable evidence that documented strategy translated into objectives, kpis, budgets and accountable owners is defined, owned or managed. | Q24: Documented strategy translated into objectives, KPIs, budgets and accountable owners is handled informally and depends on individual knowledge or heroic effort. | R24: Documented strategy translated into objectives, KPIs, budgets and accountable owners is partially documented or implemented, but coverage is inconsistent and not crisis-tested. | S24: Documented strategy translated into objectives, KPIs, budgets and accountable owners is documented, owned, used in normal operations and supported by basic evidence or metrics. | T24: Documented strategy translated into objectives, KPIs, budgets and accountable owners is measured, periodically reviewed, integrated with related processes and tested against relevant disruption scenarios. | U24: Documented strategy translated into objectives, KPIs, budgets and accountable owners is optimized, continuously improved, automated where practical and demonstrably supports crisis resilience. | V24: Demand shock; Financial / liquidity shock; Reputation crisis | Y24: Use the recommended action generated by the model; validate with domain owner during real assessment. | Z24: 4 | AA24: 5 | AB24: 5 | AD24: Corporate strategy | AE24: =_DATA_Assessment_Model!AB24 -> 6 | AF24: =_DATA_Assessment_Model!AC24 -> 0 | AG24: =_DATA_Assessment_Model!AD24 -> 0 | AH24: =_DATA_Assessment_Model!AE24 -> 6 | AI24: =_DATA_Assessment_Model!AF24 -> 5 | AJ24: =_DATA_Assessment_Model!AG24 -> 6 | AM24: =_DATA_Assessment_Model!AJ24 -> 0.9 | AN24: =_DATA_Assessment_Model!AK24 -> 0.9 | AO24: =_DATA_Assessment_Model!AL24 -> 0 | AP24: =_DATA_Assessment_Model!AM24 -> 0 | AQ24: =_DATA_Assessment_Model!AN24 -> 0 | AR24: =_DATA_Assessment_Model!AO24 -> 0 | AS24: =_DATA_Assessment_Model!AP24 -> 0 | AT24: =_DATA_Assessment_Model!AQ24 -> 0 | ... AW24: =_DATA_Assessment_Model!AT24 -> 0.9 | AY24: =_DATA_Assessment_Model!AV24 -> 0.9
A25: Strategy GTM | B25: Strategy GTM | C25: 6 | D25: STRA-002 | E25: Corporate strategy | F25: How mature is the organization in managing explicit strategic assumptions and periodic challenge of those assumptions, including ownership, evidence, metrics, fallback procedures and crisis stress testing? | G25: This topic affects exposure to Demand shock; Financial / liquidity shock; Reputation crisis. It helps identify how disruption may impact operations, people, revenue, systems, legal exposure or recovery time. | H25: ISO 9001; ISO 31000; ISO 37000; McKinsey 7S; OHI; Bain Elements of Value; Jobs-to-be-Done; Porter Five Forces; OKR | I25: Policy/SOP; owner/RACI; system report; dashboard; contracts; test records; incident history; interview evidence related to explicit strategic assumptions and periodic challenge of those assumptions. | J25: 3 | K25: =_DATA_Assessment_Model!H25 -> 0 | L25: =_DATA_Assessment_Model!I25 -> 0 | M25: =_DATA_Assessment_Model!J25 -> 3 | N25: =_DATA_Assessment_Model!K25 -> 3 | O25: =_DATA_Assessment_Model!L25 -> Critical | P25: No reliable evidence that explicit strategic assumptions and periodic challenge of those assumptions is defined, owned or managed. | Q25: Explicit strategic assumptions and periodic challenge of those assumptions is handled informally and depends on individual knowledge or heroic effort. | R25: Explicit strategic assumptions and periodic challenge of those assumptions is partially documented or implemented, but coverage is inconsistent and not crisis-tested. | S25: Explicit strategic assumptions and periodic challenge of those assumptions is documented, owned, used in normal operations and supported by basic evidence or metrics. | T25: Explicit strategic assumptions and periodic challenge of those assumptions is measured, periodically reviewed, integrated with related processes and tested against relevant disruption scenarios. | U25: Explicit strategic assumptions and periodic challenge of those assumptions is optimized, continuously improved, automated where practical and demonstrably supports crisis resilience. | V25: Demand shock; Financial / liquidity shock; Reputation crisis | Y25: Use the recommended action generated by the model; validate with domain owner during real assessment. | Z25: 4 | AA25: 5 | AB25: 5 | AD25: Market and ICP | AE25: =_DATA_Assessment_Model!AB25 -> 6 | AF25: =_DATA_Assessment_Model!AC25 -> 0 | AG25: =_DATA_Assessment_Model!AD25 -> 0 | AH25: =_DATA_Assessment_Model!AE25 -> 6 | AI25: =_DATA_Assessment_Model!AF25 -> 5 | AJ25: =_DATA_Assessment_Model!AG25 -> 6 | AM25: =_DATA_Assessment_Model!AJ25 -> 0.9 | AN25: =_DATA_Assessment_Model!AK25 -> 0.9 | AO25: =_DATA_Assessment_Model!AL25 -> 0 | AP25: =_DATA_Assessment_Model!AM25 -> 0 | AQ25: =_DATA_Assessment_Model!AN25 -> 0 | AR25: =_DATA_Assessment_Model!AO25 -> 0 | AS25: =_DATA_Assessment_Model!AP25 -> 0 | AT25: =_DATA_Assessment_Model!AQ25 -> 0 | ... AW25: =_DATA_Assessment_Model!AT25 -> 0.9 | AY25: =_DATA_Assessment_Model!AV25 -> 0.9
A26: Strategy GTM | B26: Strategy GTM | C26: 7 | D26: STRA-003 | E26: Corporate strategy | F26: How mature is the organization in managing crisis-resilient strategy including adaptation, continuity, digital enablement and recovery options, including ownership, evidence, metrics, fallback procedures and crisis stress testing? | G26: This topic affects exposure to Demand shock; Financial / liquidity shock; Reputation crisis. It helps identify how disruption may impact operations, people, revenue, systems, legal exposure or recovery time. | H26: ISO 9001; ISO 31000; ISO 37000; McKinsey 7S; OHI; Bain Elements of Value; Jobs-to-be-Done; Porter Five Forces; OKR | I26: Policy/SOP; owner/RACI; system report; dashboard; contracts; test records; incident history; interview evidence related to crisis-resilient strategy including adaptation, continuity, digital enablement and recovery options. | J26: 5 | K26: =_DATA_Assessment_Model!H26 -> 0 | L26: =_DATA_Assessment_Model!I26 -> 0 | M26: =_DATA_Assessment_Model!J26 -> 5 | N26: =_DATA_Assessment_Model!K26 -> 5 | O26: =_DATA_Assessment_Model!L26 -> Critical | P26: Does not exist; no owner, no documentation, no practice. | Q26: Ad hoc; depends entirely on specific individuals. | R26: Partially documented or implemented; coverage inconsistent; never tested under stress. | S26: Documented, owned, executed consistently; basic evidence and metrics exist. | T26: Measured and periodically tested/audited; integrated with adjacent processes. | U26: Optimized and automated where practical; stress-tested; benchmarked externally. | V26: Demand shock; Financial / liquidity shock; Reputation crisis | Y26: Use the recommended action generated by the model; validate with domain owner during real assessment. | Z26: 4 | AA26: 5 | AB26: 5 | AD26: Offering and positioning | AE26: =_DATA_Assessment_Model!AB26 -> 6 | AF26: =_DATA_Assessment_Model!AC26 -> 0 | AG26: =_DATA_Assessment_Model!AD26 -> 0 | AH26: =_DATA_Assessment_Model!AE26 -> 6 | AI26: =_DATA_Assessment_Model!AF26 -> 5 | AJ26: =_DATA_Assessment_Model!AG26 -> 6 | AM26: =_DATA_Assessment_Model!AJ26 -> 0.9 | AN26: =_DATA_Assessment_Model!AK26 -> 0.9 | AO26: =_DATA_Assessment_Model!AL26 -> 0 | AP26: =_DATA_Assessment_Model!AM26 -> 0 | AQ26: =_DATA_Assessment_Model!AN26 -> 0 | AR26: =_DATA_Assessment_Model!AO26 -> 0 | AS26: =_DATA_Assessment_Model!AP26 -> 0 | AT26: =_DATA_Assessment_Model!AQ26 -> 0 | ... AW26: =_DATA_Assessment_Model!AT26 -> 0.9 | AY26: =_DATA_Assessment_Model!AV26 -> 0.9
A27: Strategy GTM | B27: Strategy GTM | C27: 8 | D27: STRA-004 | E27: Corporate strategy | F27: How mature is the organization in managing strategic priorities ranked by business value, urgency, risk and resource constraints, including ownership, evidence, metrics, fallback procedures and crisis stress testing? | G27: This topic affects exposure to Demand shock; Financial / liquidity shock; Reputation crisis. It helps identify how disruption may impact operations, people, revenue, systems, legal exposure or recovery time. | H27: ISO 9001; ISO 31000; ISO 37000; McKinsey 7S; OHI; Bain Elements of Value; Jobs-to-be-Done; Porter Five Forces; OKR | I27: Policy/SOP; owner/RACI; system report; dashboard; contracts; test records; incident history; interview evidence related to strategic priorities ranked by business value, urgency, risk and resource constraints. | J27: 4 | K27: =_DATA_Assessment_Model!H27 -> 0 | L27: =_DATA_Assessment_Model!I27 -> 0 | M27: =_DATA_Assessment_Model!J27 -> 4 | N27: =_DATA_Assessment_Model!K27 -> 4 | O27: =_DATA_Assessment_Model!L27 -> Critical | P27: No reliable evidence that strategic priorities ranked by business value, urgency, risk and resource constraints is defined, owned or managed. | Q27: Strategic priorities ranked by business value, urgency, risk and resource constraints is handled informally and depends on individual knowledge or heroic effort. | R27: Strategic priorities ranked by business value, urgency, risk and resource constraints is partially documented or implemented, but coverage is inconsistent and not crisis-tested. | S27: Strategic priorities ranked by business value, urgency, risk and resource constraints is documented, owned, used in normal operations and supported by basic evidence or metrics. | T27: Strategic priorities ranked by business value, urgency, risk and resource constraints is measured, periodically reviewed, integrated with related processes and tested against relevant disruption scenarios. | U27: Strategic priorities ranked by business value, urgency, risk and resource constraints is optimized, continuously improved, automated where practical and demonstrably supports crisis resilience. | V27: Demand shock; Financial / liquidity shock; Reputation crisis | Y27: Use the recommended action generated by the model; validate with domain owner during real assessment. | Z27: 4 | AA27: 5 | AB27: 5 | AD27: GTM execution | AE27: =_DATA_Assessment_Model!AB27 -> 5 | AF27: =_DATA_Assessment_Model!AC27 -> 0 | AG27: =_DATA_Assessment_Model!AD27 -> 0 | AH27: =_DATA_Assessment_Model!AE27 -> 5 | AI27: =_DATA_Assessment_Model!AF27 -> 5 | AJ27: =_DATA_Assessment_Model!AG27 -> 5 | AM27: =_DATA_Assessment_Model!AJ27 -> 0.9 | AN27: =_DATA_Assessment_Model!AK27 -> 0.9 | AO27: =_DATA_Assessment_Model!AL27 -> 0 | AP27: =_DATA_Assessment_Model!AM27 -> 0 | AQ27: =_DATA_Assessment_Model!AN27 -> 0 | AR27: =_DATA_Assessment_Model!AO27 -> 0 | AS27: =_DATA_Assessment_Model!AP27 -> 0 | AT27: =_DATA_Assessment_Model!AQ27 -> 0 | ... AW27: =_DATA_Assessment_Model!AT27 -> 0.9 | AY27: =_DATA_Assessment_Model!AV27 -> 0.9
A28: Strategy GTM | B28: Strategy GTM | C28: 9 | D28: STRA-005 | E28: Corporate strategy | F28: How mature is the organization in managing strategic options for pivoting under demand shock, war, regulation, supply or liquidity crisis, including ownership, evidence, metrics, fallback procedures and crisis stress testing? | G28: This topic affects exposure to Demand shock; Financial / liquidity shock; Reputation crisis. It helps identify how disruption may impact operations, people, revenue, systems, legal exposure or recovery time. | H28: ISO 9001; ISO 31000; ISO 37000; McKinsey 7S; OHI; Bain Elements of Value; Jobs-to-be-Done; Porter Five Forces; OKR | I28: Policy/SOP; owner/RACI; system report; dashboard; contracts; test records; incident history; interview evidence related to strategic options for pivoting under demand shock, war, regulation, supply or liquidity crisis. | J28: 5 | K28: =_DATA_Assessment_Model!H28 -> 0 | L28: =_DATA_Assessment_Model!I28 -> 0 | M28: =_DATA_Assessment_Model!J28 -> 5 | N28: =_DATA_Assessment_Model!K28 -> 5 | O28: =_DATA_Assessment_Model!L28 -> Critical | P28: Does not exist; no owner, no documentation, no practice. | Q28: Ad hoc; depends entirely on specific individuals. | R28: Partially documented or implemented; coverage inconsistent; never tested under stress. | S28: Documented, owned, executed consistently; basic evidence and metrics exist. | T28: Measured and periodically tested/audited; integrated with adjacent processes. | U28: Optimized and automated where practical; stress-tested; benchmarked externally. | V28: Demand shock; Financial / liquidity shock; Reputation crisis | Y28: Use the recommended action generated by the model; validate with domain owner during real assessment. | Z28: 4 | AA28: 5 | AB28: 5 | AD28: External relations and partnerships | AE28: =_DATA_Assessment_Model!AB28 -> 3 | AF28: =_DATA_Assessment_Model!AC28 -> 0 | AG28: =_DATA_Assessment_Model!AD28 -> 0 | AH28: =_DATA_Assessment_Model!AE28 -> 3 | AI28: =_DATA_Assessment_Model!AF28 -> 5 | AJ28: =_DATA_Assessment_Model!AG28 -> 3 | AM28: =_DATA_Assessment_Model!AJ28 -> 0.9 | AN28: =_DATA_Assessment_Model!AK28 -> 0.9 | AO28: =_DATA_Assessment_Model!AL28 -> 0 | AP28: =_DATA_Assessment_Model!AM28 -> 0 | AQ28: =_DATA_Assessment_Model!AN28 -> 0 | AR28: =_DATA_Assessment_Model!AO28 -> 0 | AS28: =_DATA_Assessment_Model!AP28 -> 0 | AT28: =_DATA_Assessment_Model!AQ28 -> 0 | ... AW28: =_DATA_Assessment_Model!AT28 -> 0.9 | AY28: =_DATA_Assessment_Model!AV28 -> 0.9
A29: Strategy GTM | B29: Strategy GTM | C29: 10 | D29: STRA-006 | E29: Corporate strategy | F29: How mature is the organization in managing alignment between strategy, structure, systems, skills, staff, leadership style and culture, including ownership, evidence, metrics, fallback procedures and crisis stress testing? | G29: This topic affects exposure to Demand shock; Financial / liquidity shock; Reputation crisis. It helps identify how disruption may impact operations, people, revenue, systems, legal exposure or recovery time. | H29: ISO 9001; ISO 31000; ISO 37000; McKinsey 7S; OHI; Bain Elements of Value; Jobs-to-be-Done; Porter Five Forces; OKR | I29: Policy/SOP; owner/RACI; system report; dashboard; contracts; test records; incident history; interview evidence related to alignment between strategy, structure, systems, skills, staff, leadership style and culture. | J29: 4 | K29: =_DATA_Assessment_Model!H29 -> 0 | L29: =_DATA_Assessment_Model!I29 -> 0 | M29: =_DATA_Assessment_Model!J29 -> 4 | N29: =_DATA_Assessment_Model!K29 -> 4 | O29: =_DATA_Assessment_Model!L29 -> Critical | P29: No reliable evidence that alignment between strategy, structure, systems, skills, staff, leadership style and culture is defined, owned or managed. | Q29: Alignment between strategy, structure, systems, skills, staff, leadership style and culture is handled informally and depends on individual knowledge or heroic effort. | R29: Alignment between strategy, structure, systems, skills, staff, leadership style and culture is partially documented or implemented, but coverage is inconsistent and not crisis-tested. | S29: Alignment between strategy, structure, systems, skills, staff, leadership style and culture is documented, owned, used in normal operations and supported by basic evidence or metrics. | T29: Alignment between strategy, structure, systems, skills, staff, leadership style and culture is measured, periodically reviewed, integrated with related processes and tested against relevant disruption scenarios. | U29: Alignment between strategy, structure, systems, skills, staff, leadership style and culture is optimized, continuously improved, automated where practical and demonstrably supports crisis resilience. | V29: Demand shock; Financial / liquidity shock; Reputation crisis | Y29: Use the recommended action generated by the model; validate with domain owner during real assessment. | Z29: 4 | AA29: 5 | AB29: 5 | AM29: =_DATA_Assessment_Model!AJ29 -> 0.9 | AN29: =_DATA_Assessment_Model!AK29 -> 0.9 | AO29: =_DATA_Assessment_Model!AL29 -> 0 | AP29: =_DATA_Assessment_Model!AM29 -> 0 | AQ29: =_DATA_Assessment_Model!AN29 -> 0 | AR29: =_DATA_Assessment_Model!AO29 -> 0 | AS29: =_DATA_Assessment_Model!AP29 -> 0 | AT29: =_DATA_Assessment_Model!AQ29 -> 0 | ... AW29: =_DATA_Assessment_Model!AT29 -> 0.9 | AY29: =_DATA_Assessment_Model!AV29 -> 0.9
A30: Strategy GTM | B30: Strategy GTM | C30: 11 | D30: STRA-007 | E30: Market and ICP | F30: How mature is the organization in managing ideal customer profile by segment, geography, industry, company size, pain, budget and buying trigger, including ownership, evidence, metrics, fallback procedures and crisis stress testing? | G30: This topic affects exposure to Demand shock; Financial / liquidity shock; Reputation crisis. It helps identify how disruption may impact operations, people, revenue, systems, legal exposure or recovery time. | H30: ISO 9001; ISO 31000; ISO 37000; McKinsey 7S; OHI; Bain Elements of Value; Jobs-to-be-Done; Porter Five Forces; OKR | I30: Policy/SOP; owner/RACI; system report; dashboard; contracts; test records; incident history; interview evidence related to ideal customer profile by segment, geography, industry, company size, pain, budget and buying trigger. | J30: 4 | K30: =_DATA_Assessment_Model!H30 -> 0 | L30: =_DATA_Assessment_Model!I30 -> 0 | M30: =_DATA_Assessment_Model!J30 -> 4 | N30: =_DATA_Assessment_Model!K30 -> 4 | O30: =_DATA_Assessment_Model!L30 -> Critical | P30: No reliable evidence that ideal customer profile by segment, geography, industry, company size, pain, budget and buying trigger is defined, owned or managed. | Q30: Ideal customer profile by segment, geography, industry, company size, pain, budget and buying trigger is handled informally and depends on individual knowledge or heroic effort. | R30: Ideal customer profile by segment, geography, industry, company size, pain, budget and buying trigger is partially documented or implemented, but coverage is inconsistent and not crisis-tested. | S30: Ideal customer profile by segment, geography, industry, company size, pain, budget and buying trigger is documented, owned, used in normal operations and supported by basic evidence or metrics. | T30: Ideal customer profile by segment, geography, industry, company size, pain, budget and buying trigger is measured, periodically reviewed, integrated with related processes and tested against relevant disruption scenarios. | U30: Ideal customer profile by segment, geography, industry, company size, pain, budget and buying trigger is optimized, continuously improved, automated where practical and demonstrably supports crisis resilience. | V30: Demand shock; Financial / liquidity shock; Reputation crisis | Y30: Use the recommended action generated by the model; validate with domain owner during real assessment. | Z30: 4 | AA30: 5 | AB30: 5 | AM30: =_DATA_Assessment_Model!AJ30 -> 0.9 | AN30: =_DATA_Assessment_Model!AK30 -> 0.9 | AO30: =_DATA_Assessment_Model!AL30 -> 0 | AP30: =_DATA_Assessment_Model!AM30 -> 0 | AQ30: =_DATA_Assessment_Model!AN30 -> 0 | AR30: =_DATA_Assessment_Model!AO30 -> 0 | AS30: =_DATA_Assessment_Model!AP30 -> 0 | AT30: =_DATA_Assessment_Model!AQ30 -> 0 | ... AW30: =_DATA_Assessment_Model!AT30 -> 0.9 | AY30: =_DATA_Assessment_Model!AV30 -> 0.9
A31: Strategy GTM | B31: Strategy GTM | C31: 12 | D31: STRA-008 | E31: Market and ICP | F31: How mature is the organization in managing buyer personas covering economic buyer, technical buyer, user, influencer and blocker, including ownership, evidence, metrics, fallback procedures and crisis stress testing? | G31: This topic affects exposure to Demand shock; Financial / liquidity shock; Reputation crisis. It helps identify how disruption may impact operations, people, revenue, systems, legal exposure or recovery time. | H31: ISO 9001; ISO 31000; ISO 37000; McKinsey 7S; OHI; Bain Elements of Value; Jobs-to-be-Done; Porter Five Forces; OKR | I31: Policy/SOP; owner/RACI; system report; dashboard; contracts; test records; incident history; interview evidence related to buyer personas covering economic buyer, technical buyer, user, influencer and blocker. | J31: 3 | K31: =_DATA_Assessment_Model!H31 -> 0 | L31: =_DATA_Assessment_Model!I31 -> 0 | M31: =_DATA_Assessment_Model!J31 -> 3 | N31: =_DATA_Assessment_Model!K31 -> 3 | O31: =_DATA_Assessment_Model!L31 -> Critical | P31: No reliable evidence that buyer personas covering economic buyer, technical buyer, user, influencer and blocker is defined, owned or managed. | Q31: Buyer personas covering economic buyer, technical buyer, user, influencer and blocker is handled informally and depends on individual knowledge or heroic effort. | R31: Buyer personas covering economic buyer, technical buyer, user, influencer and blocker is partially documented or implemented, but coverage is inconsistent and not crisis-tested. | S31: Buyer personas covering economic buyer, technical buyer, user, influencer and blocker is documented, owned, used in normal operations and supported by basic evidence or metrics. | T31: Buyer personas covering economic buyer, technical buyer, user, influencer and blocker is measured, periodically reviewed, integrated with related processes and tested against relevant disruption scenarios. | U31: Buyer personas covering economic buyer, technical buyer, user, influencer and blocker is optimized, continuously improved, automated where practical and demonstrably supports crisis resilience. | V31: Demand shock; Financial / liquidity shock; Reputation crisis | Y31: Use the recommended action generated by the model; validate with domain owner during real assessment. | Z31: 4 | AA31: 5 | AB31: 5 | AM31: =_DATA_Assessment_Model!AJ31 -> 0.9 | AN31: =_DATA_Assessment_Model!AK31 -> 0.9 | AO31: =_DATA_Assessment_Model!AL31 -> 0 | AP31: =_DATA_Assessment_Model!AM31 -> 0 | AQ31: =_DATA_Assessment_Model!AN31 -> 0 | AR31: =_DATA_Assessment_Model!AO31 -> 0 | AS31: =_DATA_Assessment_Model!AP31 -> 0 | AT31: =_DATA_Assessment_Model!AQ31 -> 0 | ... AW31: =_DATA_Assessment_Model!AT31 -> 0.9 | AY31: =_DATA_Assessment_Model!AV31 -> 0.9
A32: Strategy GTM | B32: Strategy GTM | C32: 13 | D32: STRA-009 | E32: Market and ICP | F32: How mature is the organization in managing validated customer problems, jobs-to-be-done, urgency triggers and willingness to pay, including ownership, evidence, metrics, fallback procedures and crisis stress testing? | G32: This topic affects exposure to Demand shock; Financial / liquidity shock; Reputation crisis. It helps identify how disruption may impact operations, people, revenue, systems, legal exposure or recovery time. | H32: ISO 9001; ISO 31000; ISO 37000; McKinsey 7S; OHI; Bain Elements of Value; Jobs-to-be-Done; Porter Five Forces; OKR | I32: Policy/SOP; owner/RACI; system report; dashboard; contracts; test records; incident history; interview evidence related to validated customer problems, jobs-to-be-done, urgency triggers and willingness to pay. | J32: 4 | K32: =_DATA_Assessment_Model!H32 -> 0 | L32: =_DATA_Assessment_Model!I32 -> 0 | M32: =_DATA_Assessment_Model!J32 -> 4 | N32: =_DATA_Assessment_Model!K32 -> 4 | O32: =_DATA_Assessment_Model!L32 -> Critical | P32: No reliable evidence that validated customer problems, jobs-to-be-done, urgency triggers and willingness to pay is defined, owned or managed. | Q32: Validated customer problems, jobs-to-be-done, urgency triggers and willingness to pay is handled informally and depends on individual knowledge or heroic effort. | R32: Validated customer problems, jobs-to-be-done, urgency triggers and willingness to pay is partially documented or implemented, but coverage is inconsistent and not crisis-tested. | S32: Validated customer problems, jobs-to-be-done, urgency triggers and willingness to pay is documented, owned, used in normal operations and supported by basic evidence or metrics. | T32: Validated customer problems, jobs-to-be-done, urgency triggers and willingness to pay is measured, periodically reviewed, integrated with related processes and tested against relevant disruption scenarios. | U32: Validated customer problems, jobs-to-be-done, urgency triggers and willingness to pay is optimized, continuously improved, automated where practical and demonstrably supports crisis resilience. | V32: Demand shock; Financial / liquidity shock; Reputation crisis | Y32: Use the recommended action generated by the model; validate with domain owner during real assessment. | Z32: 4 | AA32: 5 | AB32: 5 | AM32: =_DATA_Assessment_Model!AJ32 -> 0.9 | AN32: =_DATA_Assessment_Model!AK32 -> 0.9 | AO32: =_DATA_Assessment_Model!AL32 -> 0 | AP32: =_DATA_Assessment_Model!AM32 -> 0 | AQ32: =_DATA_Assessment_Model!AN32 -> 0 | AR32: =_DATA_Assessment_Model!AO32 -> 0 | AS32: =_DATA_Assessment_Model!AP32 -> 0 | AT32: =_DATA_Assessment_Model!AQ32 -> 0 | ... AW32: =_DATA_Assessment_Model!AT32 -> 0.9 | AY32: =_DATA_Assessment_Model!AV32 -> 0.9
A33: Strategy GTM | B33: Strategy GTM | C33: 14 | D33: STRA-010 | E33: Market and ICP | F33: How mature is the organization in managing market segmentation by attractiveness, accessibility, profitability and crisis sensitivity, including ownership, evidence, metrics, fallback procedures and crisis stress testing? | G33: This topic affects exposure to Demand shock; Financial / liquidity shock; Reputation crisis. It helps identify how disruption may impact operations, people, revenue, systems, legal exposure or recovery time. | H33: ISO 9001; ISO 31000; ISO 37000; McKinsey 7S; OHI; Bain Elements of Value; Jobs-to-be-Done; Porter Five Forces; OKR | I33: Policy/SOP; owner/RACI; system report; dashboard; contracts; test records; incident history; interview evidence related to market segmentation by attractiveness, accessibility, profitability and crisis sensitivity. | J33: 5 | K33: =_DATA_Assessment_Model!H33 -> 0 | L33: =_DATA_Assessment_Model!I33 -> 0 | M33: =_DATA_Assessment_Model!J33 -> 5 | N33: =_DATA_Assessment_Model!K33 -> 5 | O33: =_DATA_Assessment_Model!L33 -> Critical | P33: Does not exist; no owner, no documentation, no practice. | Q33: Ad hoc; depends entirely on specific individuals. | R33: Partially documented or implemented; coverage inconsistent; never tested under stress. | S33: Documented, owned, executed consistently; basic evidence and metrics exist. | T33: Measured and periodically tested/audited; integrated with adjacent processes. | U33: Optimized and automated where practical; stress-tested; benchmarked externally. | V33: Demand shock; Financial / liquidity shock; Reputation crisis | Y33: Use the recommended action generated by the model; validate with domain owner during real assessment. | Z33: 4 | AA33: 5 | AB33: 5 | AM33: =_DATA_Assessment_Model!AJ33 -> 0.9 | AN33: =_DATA_Assessment_Model!AK33 -> 0.9 | AO33: =_DATA_Assessment_Model!AL33 -> 0 | AP33: =_DATA_Assessment_Model!AM33 -> 0 | AQ33: =_DATA_Assessment_Model!AN33 -> 0 | AR33: =_DATA_Assessment_Model!AO33 -> 0 | AS33: =_DATA_Assessment_Model!AP33 -> 0 | AT33: =_DATA_Assessment_Model!AQ33 -> 0 | ... AW33: =_DATA_Assessment_Model!AT33 -> 0.9 | AY33: =_DATA_Assessment_Model!AV33 -> 0.9
A34: Strategy GTM | B34: Strategy GTM | C34: 15 | D34: STRA-011 | E34: Market and ICP | F34: How mature is the organization in managing market size and growth assumptions with explicit evidence and uncertainty level, including ownership, evidence, metrics, fallback procedures and crisis stress testing? | G34: This topic affects exposure to Demand shock; Financial / liquidity shock; Reputation crisis. It helps identify how disruption may impact operations, people, revenue, systems, legal exposure or recovery time. | H34: ISO 9001; ISO 31000; ISO 37000; McKinsey 7S; OHI; Bain Elements of Value; Jobs-to-be-Done; Porter Five Forces; OKR | I34: Policy/SOP; owner/RACI; system report; dashboard; contracts; test records; incident history; interview evidence related to market size and growth assumptions with explicit evidence and uncertainty level. | J34: 3 | K34: =_DATA_Assessment_Model!H34 -> 0 | L34: =_DATA_Assessment_Model!I34 -> 0 | M34: =_DATA_Assessment_Model!J34 -> 3 | N34: =_DATA_Assessment_Model!K34 -> 3 | O34: =_DATA_Assessment_Model!L34 -> Critical | P34: No reliable evidence that market size and growth assumptions with explicit evidence and uncertainty level is defined, owned or managed. | Q34: Market size and growth assumptions with explicit evidence and uncertainty level is handled informally and depends on individual knowledge or heroic effort. | R34: Market size and growth assumptions with explicit evidence and uncertainty level is partially documented or implemented, but coverage is inconsistent and not crisis-tested. | S34: Market size and growth assumptions with explicit evidence and uncertainty level is documented, owned, used in normal operations and supported by basic evidence or metrics. | T34: Market size and growth assumptions with explicit evidence and uncertainty level is measured, periodically reviewed, integrated with related processes and tested against relevant disruption scenarios. | U34: Market size and growth assumptions with explicit evidence and uncertainty level is optimized, continuously improved, automated where practical and demonstrably supports crisis resilience. | V34: Demand shock; Financial / liquidity shock; Reputation crisis | Y34: Use the recommended action generated by the model; validate with domain owner during real assessment. | Z34: 4 | AA34: 5 | AB34: 5 | AM34: =_DATA_Assessment_Model!AJ34 -> 0.9 | AN34: =_DATA_Assessment_Model!AK34 -> 0.9 | AO34: =_DATA_Assessment_Model!AL34 -> 0 | AP34: =_DATA_Assessment_Model!AM34 -> 0 | AQ34: =_DATA_Assessment_Model!AN34 -> 0 | AR34: =_DATA_Assessment_Model!AO34 -> 0 | AS34: =_DATA_Assessment_Model!AP34 -> 0 | AT34: =_DATA_Assessment_Model!AQ34 -> 0 | ... AW34: =_DATA_Assessment_Model!AT34 -> 0.9 | AY34: =_DATA_Assessment_Model!AV34 -> 0.9
A35: Strategy GTM | B35: Strategy GTM | C35: 16 | D35: STRA-012 | E35: Market and ICP | F35: How mature is the organization in managing customer concentration and exposure to specific industries, geographies or budget cycles, including ownership, evidence, metrics, fallback procedures and crisis stress testing? | G35: This topic affects exposure to Demand shock; Financial / liquidity shock; Reputation crisis. It helps identify how disruption may impact operations, people, revenue, systems, legal exposure or recovery time. | H35: ISO 9001; ISO 31000; ISO 37000; McKinsey 7S; OHI; Bain Elements of Value; Jobs-to-be-Done; Porter Five Forces; OKR | I35: Policy/SOP; owner/RACI; system report; dashboard; contracts; test records; incident history; interview evidence related to customer concentration and exposure to specific industries, geographies or budget cycles. | J35: 4 | K35: =_DATA_Assessment_Model!H35 -> 0 | L35: =_DATA_Assessment_Model!I35 -> 0 | M35: =_DATA_Assessment_Model!J35 -> 4 | N35: =_DATA_Assessment_Model!K35 -> 4 | O35: =_DATA_Assessment_Model!L35 -> Critical | P35: No reliable evidence that customer concentration and exposure to specific industries, geographies or budget cycles is defined, owned or managed. | Q35: Customer concentration and exposure to specific industries, geographies or budget cycles is handled informally and depends on individual knowledge or heroic effort. | R35: Customer concentration and exposure to specific industries, geographies or budget cycles is partially documented or implemented, but coverage is inconsistent and not crisis-tested. | S35: Customer concentration and exposure to specific industries, geographies or budget cycles is documented, owned, used in normal operations and supported by basic evidence or metrics. | T35: Customer concentration and exposure to specific industries, geographies or budget cycles is measured, periodically reviewed, integrated with related processes and tested against relevant disruption scenarios. | U35: Customer concentration and exposure to specific industries, geographies or budget cycles is optimized, continuously improved, automated where practical and demonstrably supports crisis resilience. | V35: Demand shock; Financial / liquidity shock; Reputation crisis | Y35: Use the recommended action generated by the model; validate with domain owner during real assessment. | Z35: 4 | AA35: 5 | AB35: 5 | AM35: =_DATA_Assessment_Model!AJ35 -> 0.9 | AN35: =_DATA_Assessment_Model!AK35 -> 0.9 | AO35: =_DATA_Assessment_Model!AL35 -> 0 | AP35: =_DATA_Assessment_Model!AM35 -> 0 | AQ35: =_DATA_Assessment_Model!AN35 -> 0 | AR35: =_DATA_Assessment_Model!AO35 -> 0 | AS35: =_DATA_Assessment_Model!AP35 -> 0 | AT35: =_DATA_Assessment_Model!AQ35 -> 0 | ... AW35: =_DATA_Assessment_Model!AT35 -> 0.9 | AY35: =_DATA_Assessment_Model!AV35 -> 0.9
A36: Strategy GTM | B36: Strategy GTM | C36: 17 | D36: STRA-013 | E36: Offering and positioning | F36: How mature is the organization in managing structured offering catalog with packages, scope, outcomes, assumptions and delivery requirements, including ownership, evidence, metrics, fallback procedures and crisis stress testing? | G36: This topic affects exposure to Demand shock; Financial / liquidity shock; Reputation crisis. It helps identify how disruption may impact operations, people, revenue, systems, legal exposure or recovery time. | H36: ISO 9001; ISO 31000; ISO 37000; McKinsey 7S; OHI; Bain Elements of Value; Jobs-to-be-Done; Porter Five Forces; OKR | I36: Policy/SOP; owner/RACI; system report; dashboard; contracts; test records; incident history; interview evidence related to structured offering catalog with packages, scope, outcomes, assumptions and delivery requirements. | J36: 5 | K36: =_DATA_Assessment_Model!H36 -> 0 | L36: =_DATA_Assessment_Model!I36 -> 0 | M36: =_DATA_Assessment_Model!J36 -> 5 | N36: =_DATA_Assessment_Model!K36 -> 5 | O36: =_DATA_Assessment_Model!L36 -> Critical | P36: No inventory/register exists. | Q36: Partial lists live in individuals' heads or personal files. | R36: A register exists but is incomplete or outdated (>1 year) and has no owner. | S36: Owned, documented, updated on a defined schedule, covers the main scope. | T36: Complete and periodically reviewed; integrated with related processes; completeness measured. | U36: Maintained automatically or synced with systems; drives decisions; audited. | V36: Demand shock; Financial / liquidity shock; Reputation crisis | Y36: Use the recommended action generated by the model; validate with domain owner during real assessment. | Z36: 4 | AA36: 5 | AB36: 5 | AM36: =_DATA_Assessment_Model!AJ36 -> 0.9 | AN36: =_DATA_Assessment_Model!AK36 -> 0.9 | AO36: =_DATA_Assessment_Model!AL36 -> 0 | AP36: =_DATA_Assessment_Model!AM36 -> 0 | AQ36: =_DATA_Assessment_Model!AN36 -> 0 | AR36: =_DATA_Assessment_Model!AO36 -> 0 | AS36: =_DATA_Assessment_Model!AP36 -> 0 | AT36: =_DATA_Assessment_Model!AQ36 -> 0 | ... AW36: =_DATA_Assessment_Model!AT36 -> 0.9 | AY36: =_DATA_Assessment_Model!AV36 -> 0.9
A37: Strategy GTM | B37: Strategy GTM | C37: 18 | D37: STRA-014 | E37: Offering and positioning | F37: How mature is the organization in managing clear differentiation against direct competitors, substitutes and in-house alternatives, including ownership, evidence, metrics, fallback procedures and crisis stress testing? | G37: This topic affects exposure to Demand shock; Financial / liquidity shock; Reputation crisis. It helps identify how disruption may impact operations, people, revenue, systems, legal exposure or recovery time. | H37: ISO 9001; ISO 31000; ISO 37000; McKinsey 7S; OHI; Bain Elements of Value; Jobs-to-be-Done; Porter Five Forces; OKR | I37: Policy/SOP; owner/RACI; system report; dashboard; contracts; test records; incident history; interview evidence related to clear differentiation against direct competitors, substitutes and in-house alternatives. | J37: 3 | K37: =_DATA_Assessment_Model!H37 -> 0 | L37: =_DATA_Assessment_Model!I37 -> 0 | M37: =_DATA_Assessment_Model!J37 -> 3 | N37: =_DATA_Assessment_Model!K37 -> 3 | O37: =_DATA_Assessment_Model!L37 -> Critical | P37: No reliable evidence that clear differentiation against direct competitors, substitutes and in-house alternatives is defined, owned or managed. | Q37: Clear differentiation against direct competitors, substitutes and in-house alternatives is handled informally and depends on individual knowledge or heroic effort. | R37: Clear differentiation against direct competitors, substitutes and in-house alternatives is partially documented or implemented, but coverage is inconsistent and not crisis-tested. | S37: Clear differentiation against direct competitors, substitutes and in-house alternatives is documented, owned, used in normal operations and supported by basic evidence or metrics. | T37: Clear differentiation against direct competitors, substitutes and in-house alternatives is measured, periodically reviewed, integrated with related processes and tested against relevant disruption scenarios. | U37: Clear differentiation against direct competitors, substitutes and in-house alternatives is optimized, continuously improved, automated where practical and demonstrably supports crisis resilience. | V37: Demand shock; Financial / liquidity shock; Reputation crisis | Y37: Use the recommended action generated by the model; validate with domain owner during real assessment. | Z37: 4 | AA37: 5 | AB37: 5 | AM37: =_DATA_Assessment_Model!AJ37 -> 0.9 | AN37: =_DATA_Assessment_Model!AK37 -> 0.9 | AO37: =_DATA_Assessment_Model!AL37 -> 0 | AP37: =_DATA_Assessment_Model!AM37 -> 0 | AQ37: =_DATA_Assessment_Model!AN37 -> 0 | AR37: =_DATA_Assessment_Model!AO37 -> 0 | AS37: =_DATA_Assessment_Model!AP37 -> 0 | AT37: =_DATA_Assessment_Model!AQ37 -> 0 | ... AW37: =_DATA_Assessment_Model!AT37 -> 0.9 | AY37: =_DATA_Assessment_Model!AV37 -> 0.9
A38: Strategy GTM | B38: Strategy GTM | C38: 19 | D38: STRA-015 | E38: Offering and positioning | F38: How mature is the organization in managing value proposition linked to measurable customer economic value, risk reduction or continuity impact, including ownership, evidence, metrics, fallback procedures and crisis stress testing? | G38: This topic affects exposure to Demand shock; Financial / liquidity shock; Reputation crisis. It helps identify how disruption may impact operations, people, revenue, systems, legal exposure or recovery time. | H38: ISO 9001; ISO 31000; ISO 37000; McKinsey 7S; OHI; Bain Elements of Value; Jobs-to-be-Done; Porter Five Forces; OKR | I38: Policy/SOP; owner/RACI; system report; dashboard; contracts; test records; incident history; interview evidence related to value proposition linked to measurable customer economic value, risk reduction or continuity impact. | J38: 5 | K38: =_DATA_Assessment_Model!H38 -> 0 | L38: =_DATA_Assessment_Model!I38 -> 0 | M38: =_DATA_Assessment_Model!J38 -> 5 | N38: =_DATA_Assessment_Model!K38 -> 5 | O38: =_DATA_Assessment_Model!L38 -> Critical | P38: Nothing is monitored or measured. | Q38: Occasional manual checks by individuals. | R38: Some metrics exist but are not reviewed regularly and trigger no action. | S38: Defined metrics with an owner, reviewed on a set cadence. | T38: Thresholds and alerts in place; deviations trigger documented action; trends analyzed. | U38: Automated monitoring with leading indicators, integrated into management decisions. | V38: Demand shock; Financial / liquidity shock; Reputation crisis | Y38: Use the recommended action generated by the model; validate with domain owner during real assessment. | Z38: 4 | AA38: 5 | AB38: 5 | AM38: =_DATA_Assessment_Model!AJ38 -> 0.9 | AN38: =_DATA_Assessment_Model!AK38 -> 0.9 | AO38: =_DATA_Assessment_Model!AL38 -> 0 | AP38: =_DATA_Assessment_Model!AM38 -> 0 | AQ38: =_DATA_Assessment_Model!AN38 -> 0 | AR38: =_DATA_Assessment_Model!AO38 -> 0 | AS38: =_DATA_Assessment_Model!AP38 -> 0 | AT38: =_DATA_Assessment_Model!AQ38 -> 0 | ... AW38: =_DATA_Assessment_Model!AT38 -> 0.9 | AY38: =_DATA_Assessment_Model!AV38 -> 0.9
A39: Strategy GTM | B39: Strategy GTM | C39: 20 | D39: STRA-016 | E39: Offering and positioning | F39: How mature is the organization in managing pricing strategy with margin thresholds, discount governance and crisis boundaries, including ownership, evidence, metrics, fallback procedures and crisis stress testing? | G39: This topic affects exposure to Demand shock; Financial / liquidity shock; Reputation crisis. It helps identify how disruption may impact operations, people, revenue, systems, legal exposure or recovery time. | H39: ISO 9001; ISO 31000; ISO 37000; McKinsey 7S; OHI; Bain Elements of Value; Jobs-to-be-Done; Porter Five Forces; OKR | I39: Policy/SOP; owner/RACI; system report; dashboard; contracts; test records; incident history; interview evidence related to pricing strategy with margin thresholds, discount governance and crisis boundaries. | J39: 5 | K39: =_DATA_Assessment_Model!H39 -> 0 | L39: =_DATA_Assessment_Model!I39 -> 0 | M39: =_DATA_Assessment_Model!J39 -> 5 | N39: =_DATA_Assessment_Model!K39 -> 5 | O39: =_DATA_Assessment_Model!L39 -> Critical | P39: Does not exist; no owner, no documentation, no practice. | Q39: Ad hoc; depends entirely on specific individuals. | R39: Partially documented or implemented; coverage inconsistent; never tested under stress. | S39: Documented, owned, executed consistently; basic evidence and metrics exist. | T39: Measured and periodically tested/audited; integrated with adjacent processes. | U39: Optimized and automated where practical; stress-tested; benchmarked externally. | V39: Demand shock; Financial / liquidity shock; Reputation crisis | Y39: Use the recommended action generated by the model; validate with domain owner during real assessment. | Z39: 4 | AA39: 5 | AB39: 5 | AM39: =_DATA_Assessment_Model!AJ39 -> 0.9 | AN39: =_DATA_Assessment_Model!AK39 -> 0.9 | AO39: =_DATA_Assessment_Model!AL39 -> 0 | AP39: =_DATA_Assessment_Model!AM39 -> 0 | AQ39: =_DATA_Assessment_Model!AN39 -> 0 | AR39: =_DATA_Assessment_Model!AO39 -> 0 | AS39: =_DATA_Assessment_Model!AP39 -> 0 | AT39: =_DATA_Assessment_Model!AQ39 -> 0 | ... AW39: =_DATA_Assessment_Model!AT39 -> 0.9 | AY39: =_DATA_Assessment_Model!AV39 -> 0.9
A40: Strategy GTM | B40: Strategy GTM | C40: 21 | D40: STRA-017 | E40: Offering and positioning | F40: How mature is the organization in managing proof assets such as case studies, references, certifications, security evidence and continuity commitments, including ownership, evidence, metrics, fallback procedures and crisis stress testing? | G40: This topic affects exposure to Demand shock; Financial / liquidity shock; Reputation crisis. It helps identify how disruption may impact operations, people, revenue, systems, legal exposure or recovery time. | H40: ISO 9001; ISO 31000; ISO 37000; McKinsey 7S; OHI; Bain Elements of Value; Jobs-to-be-Done; Porter Five Forces; OKR | I40: Policy/SOP; owner/RACI; system report; dashboard; contracts; test records; incident history; interview evidence related to proof assets such as case studies, references, certifications, security evidence and continuity commitments. | J40: 5 | K40: =_DATA_Assessment_Model!H40 -> 0 | L40: =_DATA_Assessment_Model!I40 -> 0 | M40: =_DATA_Assessment_Model!J40 -> 5 | N40: =_DATA_Assessment_Model!K40 -> 5 | O40: =_DATA_Assessment_Model!L40 -> Critical | P40: Does not exist; no owner, no documentation, no practice. | Q40: Ad hoc; depends entirely on specific individuals. | R40: Partially documented or implemented; coverage inconsistent; never tested under stress. | S40: Documented, owned, executed consistently; basic evidence and metrics exist. | T40: Measured and periodically tested/audited; integrated with adjacent processes. | U40: Optimized and automated where practical; stress-tested; benchmarked externally. | V40: Demand shock; Financial / liquidity shock; Reputation crisis | Y40: Use the recommended action generated by the model; validate with domain owner during real assessment. | Z40: 4 | AA40: 5 | AB40: 5 | AM40: =_DATA_Assessment_Model!AJ40 -> 0.9 | AN40: =_DATA_Assessment_Model!AK40 -> 0.9 | AO40: =_DATA_Assessment_Model!AL40 -> 0 | AP40: =_DATA_Assessment_Model!AM40 -> 0 | AQ40: =_DATA_Assessment_Model!AN40 -> 0 | AR40: =_DATA_Assessment_Model!AO40 -> 0 | AS40: =_DATA_Assessment_Model!AP40 -> 0 | AT40: =_DATA_Assessment_Model!AQ40 -> 0 | ... AW40: =_DATA_Assessment_Model!AT40 -> 0.9 | AY40: =_DATA_Assessment_Model!AV40 -> 0.9
... A49: Strategy GTM | B49: Strategy GTM | C49: 30 | D49: STRA-028 | E49: External relations and partnerships | F49: How mature is the organization in managing owner, investor and lender communication discipline including bad-news protocols and crisis updates, including ownership, evidence, metrics, fallback procedures and crisis stress testing? | G49: This topic affects exposure to Financial/liquidity crisis; Reputation crisis. It helps identify how disruption may impact operations, people, revenue, systems, legal exposure or recovery time. | H49: APQC PCF 12.2; ISO 37000; COSO | I49: Policy/SOP; owner/RACI; system report; dashboard; contracts; test records; incident history; interview evidence related to documented strategy translated into objectives, KPIs, budgets and accountable owners. | J49: 4 | K49: =_DATA_Assessment_Model!H49 -> 0 | L49: =_DATA_Assessment_Model!I49 -> 0 | M49: =_DATA_Assessment_Model!J49 -> 4 | N49: =_DATA_Assessment_Model!K49 -> 4 | O49: =_DATA_Assessment_Model!L49 -> Critical | P49: No reliable evidence that owner, investor and lender communication discipline including bad-news protocols and crisis updates is defined, owned or managed. | Q49: Owner, investor and lender communication discipline including bad-news protocols and crisis updates is handled informally and depends on individual knowledge or heroic effort. | R49: Owner, investor and lender communication discipline including bad-news protocols and crisis updates is partially documented or implemented, but coverage is inconsistent and not crisis-tested. | S49: Owner, investor and lender communication discipline including bad-news protocols and crisis updates is documented, owned, used in normal operations and supported by basic evidence or metrics. | T49: Owner, investor and lender communication discipline including bad-news protocols and crisis updates is measured, periodically reviewed, integrated with related processes and tested against relevant disruption scenarios. | U49: Owner, investor and lender communication discipline including bad-news protocols and crisis updates is optimized, continuously improved, automated where practical and demonstrably supports crisis resilience. | V49: Financial/liquidity crisis; Reputation crisis | Y49: Use the recommended action generated by the model; validate with domain owner during real assessment. | Z49: 2 | AA49: 4 | AB49: 4 | AM49: =_DATA_Assessment_Model!AJ49 -> 0.9 | AN49: =_DATA_Assessment_Model!AK49 -> 0.9 | AO49: =_DATA_Assessment_Model!AL49 -> 0 | AP49: =_DATA_Assessment_Model!AM49 -> 0 | AQ49: =_DATA_Assessment_Model!AN49 -> 0 | AR49: =_DATA_Assessment_Model!AO49 -> 0 | AS49: =_DATA_Assessment_Model!AP49 -> 0 | AT49: =_DATA_Assessment_Model!AQ49 -> 0 | ... AW49: =_DATA_Assessment_Model!AT49 -> 0.9 | AY49: =_DATA_Assessment_Model!AV49 -> 0.9
A50: Governance Crisis | B50: Governance Crisis | C50: 5 | D50: GOVE-001 | E50: Crisis governance | F50: How mature is the organization in managing formal crisis management structure with named roles, deputies, escalation paths and decision authority, including ownership, evidence, metrics, fallback procedures and crisis stress testing? | G50: This topic affects exposure to All crisis types. It helps identify how disruption may impact operations, people, revenue, systems, legal exposure or recovery time. | H50: ISO 22301; ISO 22320; ISO 31000; ISO 37000; NIST SP 800-34; BCI Good Practice Guidelines; Bain RAPID | I50: Policy/SOP; owner/RACI; system report; dashboard; contracts; test records; incident history; interview evidence related to formal crisis management structure with named roles, deputies, escalation paths and decision authority. | J50: 5 | K50: =_DATA_Assessment_Model!H50 -> 0 | L50: =_DATA_Assessment_Model!I50 -> 0 | M50: =_DATA_Assessment_Model!J50 -> 5 | N50: =_DATA_Assessment_Model!K50 -> 5 | O50: =_DATA_Assessment_Model!L50 -> Critical | P50: Does not exist; no owner, no documentation, no practice. | Q50: Ad hoc; depends entirely on specific individuals. | R50: Partially documented or implemented; coverage inconsistent; never tested under stress. | S50: Documented, owned, executed consistently; basic evidence and metrics exist. | T50: Measured and periodically tested/audited; integrated with adjacent processes. | U50: Optimized and automated where practical; stress-tested; benchmarked externally. | V50: All crisis types | Y50: Use the recommended action generated by the model; validate with domain owner during real assessment. | Z50: 4 | AA50: 5 | AB50: 5 | AD50: Crisis governance | AE50: =_DATA_Assessment_Model!AB50 -> 7 | AF50: =_DATA_Assessment_Model!AC50 -> 0 | AG50: =_DATA_Assessment_Model!AD50 -> 0 | AH50: =_DATA_Assessment_Model!AE50 -> 7 | AI50: =_DATA_Assessment_Model!AF50 -> 5 | AJ50: =_DATA_Assessment_Model!AG50 -> 7 | AM50: =_DATA_Assessment_Model!AJ50 -> 0.9 | AN50: =_DATA_Assessment_Model!AK50 -> 0.9 | AO50: =_DATA_Assessment_Model!AL50 -> 0 | AP50: =_DATA_Assessment_Model!AM50 -> 0 | AQ50: =_DATA_Assessment_Model!AN50 -> 0 | AR50: =_DATA_Assessment_Model!AO50 -> 0 | AS50: =_DATA_Assessment_Model!AP50 -> 0 | AT50: =_DATA_Assessment_Model!AQ50 -> 0 | ... AW50: =_DATA_Assessment_Model!AT50 -> 0.9 | AY50: =_DATA_Assessment_Model!AV50 -> 0.9
A51: Governance Crisis | B51: Governance Crisis | C51: 6 | D51: GOVE-002 | E51: Crisis governance | F51: How mature is the organization in managing executive crisis team trained for cross-functional crisis response, including ownership, evidence, metrics, fallback procedures and crisis stress testing? | G51: This topic affects exposure to All crisis types. It helps identify how disruption may impact operations, people, revenue, systems, legal exposure or recovery time. | H51: ISO 22301; ISO 22320; ISO 31000; ISO 37000; NIST SP 800-34; BCI Good Practice Guidelines; Bain RAPID | I51: Policy/SOP; owner/RACI; system report; dashboard; contracts; test records; incident history; interview evidence related to executive crisis team trained for cross-functional crisis response. | J51: 5 | K51: =_DATA_Assessment_Model!H51 -> 0 | L51: =_DATA_Assessment_Model!I51 -> 0 | M51: =_DATA_Assessment_Model!J51 -> 5 | N51: =_DATA_Assessment_Model!K51 -> 5 | O51: =_DATA_Assessment_Model!L51 -> Critical | P51: Does not exist; no owner, no documentation, no practice. | Q51: Ad hoc; depends entirely on specific individuals. | R51: Partially documented or implemented; coverage inconsistent; never tested under stress. | S51: Documented, owned, executed consistently; basic evidence and metrics exist. | T51: Measured and periodically tested/audited; integrated with adjacent processes. | U51: Optimized and automated where practical; stress-tested; benchmarked externally. | V51: All crisis types | Y51: Use the recommended action generated by the model; validate with domain owner during real assessment. | Z51: 4 | AA51: 5 | AB51: 5 | AD51: Risk and continuity | AE51: =_DATA_Assessment_Model!AB51 -> 9 | AF51: =_DATA_Assessment_Model!AC51 -> 0 | AG51: =_DATA_Assessment_Model!AD51 -> 0 | AH51: =_DATA_Assessment_Model!AE51 -> 9 | AI51: =_DATA_Assessment_Model!AF51 -> 5 | AJ51: =_DATA_Assessment_Model!AG51 -> 9 | AM51: =_DATA_Assessment_Model!AJ51 -> 0.9 | AN51: =_DATA_Assessment_Model!AK51 -> 0.9 | AO51: =_DATA_Assessment_Model!AL51 -> 0 | AP51: =_DATA_Assessment_Model!AM51 -> 0 | AQ51: =_DATA_Assessment_Model!AN51 -> 0 | AR51: =_DATA_Assessment_Model!AO51 -> 0 | AS51: =_DATA_Assessment_Model!AP51 -> 0 | AT51: =_DATA_Assessment_Model!AQ51 -> 0 | ... AW51: =_DATA_Assessment_Model!AT51 -> 0.9 | AY51: =_DATA_Assessment_Model!AV51 -> 0.9
A52: Governance Crisis | B52: Governance Crisis | C52: 7 | D52: GOVE-003 | E52: Crisis governance | F52: How mature is the organization in managing clear crisis decision rights for finance, people, operations, IT, legal, safety and communications, including ownership, evidence, metrics, fallback procedures and crisis stress testing? | G52: This topic affects exposure to All crisis types. It helps identify how disruption may impact operations, people, revenue, systems, legal exposure or recovery time. | H52: ISO 22301; ISO 22320; ISO 31000; ISO 37000; NIST SP 800-34; BCI Good Practice Guidelines; Bain RAPID | I52: Policy/SOP; owner/RACI; system report; dashboard; contracts; test records; incident history; interview evidence related to clear crisis decision rights for finance, people, operations, IT, legal, safety and communications. | J52: 5 | K52: =_DATA_Assessment_Model!H52 -> 0 | L52: =_DATA_Assessment_Model!I52 -> 0 | M52: =_DATA_Assessment_Model!J52 -> 5 | N52: =_DATA_Assessment_Model!K52 -> 5 | O52: =_DATA_Assessment_Model!L52 -> Critical | P52: Does not exist; no owner, no documentation, no practice. | Q52: Ad hoc; depends entirely on specific individuals. | R52: Partially documented or implemented; coverage inconsistent; never tested under stress. | S52: Documented, owned, executed consistently; basic evidence and metrics exist. | T52: Measured and periodically tested/audited; integrated with adjacent processes. | U52: Optimized and automated where practical; stress-tested; benchmarked externally. | V52: All crisis types | Y52: Use the recommended action generated by the model; validate with domain owner during real assessment. | Z52: 4 | AA52: 5 | AB52: 5 | AD52: Incident management | AE52: =_DATA_Assessment_Model!AB52 -> 6 | AF52: =_DATA_Assessment_Model!AC52 -> 0 | AG52: =_DATA_Assessment_Model!AD52 -> 0 | AH52: =_DATA_Assessment_Model!AE52 -> 6 | AI52: =_DATA_Assessment_Model!AF52 -> 5 | AJ52: =_DATA_Assessment_Model!AG52 -> 6 | AM52: =_DATA_Assessment_Model!AJ52 -> 0.9 | AN52: =_DATA_Assessment_Model!AK52 -> 0.9 | AO52: =_DATA_Assessment_Model!AL52 -> 0 | AP52: =_DATA_Assessment_Model!AM52 -> 0 | AQ52: =_DATA_Assessment_Model!AN52 -> 0 | AR52: =_DATA_Assessment_Model!AO52 -> 0 | AS52: =_DATA_Assessment_Model!AP52 -> 0 | AT52: =_DATA_Assessment_Model!AQ52 -> 0 | ... AW52: =_DATA_Assessment_Model!AT52 -> 0.9 | AY52: =_DATA_Assessment_Model!AV52 -> 0.9
A53: Governance Crisis | B53: Governance Crisis | C53: 8 | D53: GOVE-004 | E53: Crisis governance | F53: How mature is the organization in managing crisis cadence for situation reports, decisions, action owners, deadlines and follow-up, including ownership, evidence, metrics, fallback procedures and crisis stress testing? | G53: This topic affects exposure to All crisis types. It helps identify how disruption may impact operations, people, revenue, systems, legal exposure or recovery time. | H53: ISO 22301; ISO 22320; ISO 31000; ISO 37000; NIST SP 800-34; BCI Good Practice Guidelines; Bain RAPID | I53: Policy/SOP; owner/RACI; system report; dashboard; contracts; test records; incident history; interview evidence related to crisis cadence for situation reports, decisions, action owners, deadlines and follow-up. | J53: 5 | K53: =_DATA_Assessment_Model!H53 -> 0 | L53: =_DATA_Assessment_Model!I53 -> 0 | M53: =_DATA_Assessment_Model!J53 -> 5 | N53: =_DATA_Assessment_Model!K53 -> 5 | O53: =_DATA_Assessment_Model!L53 -> Critical | P53: Does not exist; no owner, no documentation, no practice. | Q53: Ad hoc; depends entirely on specific individuals. | R53: Partially documented or implemented; coverage inconsistent; never tested under stress. | S53: Documented, owned, executed consistently; basic evidence and metrics exist. | T53: Measured and periodically tested/audited; integrated with adjacent processes. | U53: Optimized and automated where practical; stress-tested; benchmarked externally. | V53: All crisis types | Y53: Use the recommended action generated by the model; validate with domain owner during real assessment. | Z53: 4 | AA53: 5 | AB53: 5 | AM53: =_DATA_Assessment_Model!AJ53 -> 0.9 | AN53: =_DATA_Assessment_Model!AK53 -> 0.9 | AO53: =_DATA_Assessment_Model!AL53 -> 0 | AP53: =_DATA_Assessment_Model!AM53 -> 0 | AQ53: =_DATA_Assessment_Model!AN53 -> 0 | AR53: =_DATA_Assessment_Model!AO53 -> 0 | AS53: =_DATA_Assessment_Model!AP53 -> 0 | AT53: =_DATA_Assessment_Model!AQ53 -> 0 | ... AW53: =_DATA_Assessment_Model!AT53 -> 0.9 | AY53: =_DATA_Assessment_Model!AV53 -> 0.9
A54: Governance Crisis | B54: Governance Crisis | C54: 9 | D54: GOVE-005 | E54: Crisis governance | F54: How mature is the organization in managing board or owner-level oversight of resilience, continuity and enterprise risk, including ownership, evidence, metrics, fallback procedures and crisis stress testing? | G54: This topic affects exposure to All crisis types. It helps identify how disruption may impact operations, people, revenue, systems, legal exposure or recovery time. | H54: ISO 22301; ISO 22320; ISO 31000; ISO 37000; NIST SP 800-34; BCI Good Practice Guidelines; Bain RAPID | I54: Policy/SOP; owner/RACI; system report; dashboard; contracts; test records; incident history; interview evidence related to board or owner-level oversight of resilience, continuity and enterprise risk. | J54: 5 | K54: =_DATA_Assessment_Model!H54 -> 0 | L54: =_DATA_Assessment_Model!I54 -> 0 | M54: =_DATA_Assessment_Model!J54 -> 5 | N54: =_DATA_Assessment_Model!K54 -> 5 | O54: =_DATA_Assessment_Model!L54 -> Critical | P54: Does not exist; no owner, no documentation, no practice. | Q54: Ad hoc; depends entirely on specific individuals. | R54: Partially documented or implemented; coverage inconsistent; never tested under stress. | S54: Documented, owned, executed consistently; basic evidence and metrics exist. | T54: Measured and periodically tested/audited; integrated with adjacent processes. | U54: Optimized and automated where practical; stress-tested; benchmarked externally. | V54: All crisis types | Y54: Use the recommended action generated by the model; validate with domain owner during real assessment. | Z54: 4 | AA54: 5 | AB54: 5 | AM54: =_DATA_Assessment_Model!AJ54 -> 0.9 | AN54: =_DATA_Assessment_Model!AK54 -> 0.9 | AO54: =_DATA_Assessment_Model!AL54 -> 0 | AP54: =_DATA_Assessment_Model!AM54 -> 0 | AQ54: =_DATA_Assessment_Model!AN54 -> 0 | AR54: =_DATA_Assessment_Model!AO54 -> 0 | AS54: =_DATA_Assessment_Model!AP54 -> 0 | AT54: =_DATA_Assessment_Model!AQ54 -> 0 | ... AW54: =_DATA_Assessment_Model!AT54 -> 0.9 | AY54: =_DATA_Assessment_Model!AV54 -> 0.9
A55: Governance Crisis | B55: Governance Crisis | C55: 10 | D55: GOVE-006 | E55: Crisis governance | F55: How mature is the organization in managing emergency spending authority and budget release rules, including ownership, evidence, metrics, fallback procedures and crisis stress testing? | G55: This topic affects exposure to All crisis types. It helps identify how disruption may impact operations, people, revenue, systems, legal exposure or recovery time. | H55: ISO 22301; ISO 22320; ISO 31000; ISO 37000; NIST SP 800-34; BCI Good Practice Guidelines; Bain RAPID | I55: Policy/SOP; owner/RACI; system report; dashboard; contracts; test records; incident history; interview evidence related to emergency spending authority and budget release rules. | J55: 3 | K55: =_DATA_Assessment_Model!H55 -> 0 | L55: =_DATA_Assessment_Model!I55 -> 0 | M55: =_DATA_Assessment_Model!J55 -> 3 | N55: =_DATA_Assessment_Model!K55 -> 3 | O55: =_DATA_Assessment_Model!L55 -> Critical | P55: No reliable evidence that emergency spending authority and budget release rules is defined, owned or managed. | Q55: Emergency spending authority and budget release rules is handled informally and depends on individual knowledge or heroic effort. | R55: Emergency spending authority and budget release rules is partially documented or implemented, but coverage is inconsistent and not crisis-tested. | S55: Emergency spending authority and budget release rules is documented, owned, used in normal operations and supported by basic evidence or metrics. | T55: Emergency spending authority and budget release rules is measured, periodically reviewed, integrated with related processes and tested against relevant disruption scenarios. | U55: Emergency spending authority and budget release rules is optimized, continuously improved, automated where practical and demonstrably supports crisis resilience. | V55: All crisis types | Y55: Use the recommended action generated by the model; validate with domain owner during real assessment. | Z55: 4 | AA55: 5 | AB55: 5 | AM55: =_DATA_Assessment_Model!AJ55 -> 0.9 | AN55: =_DATA_Assessment_Model!AK55 -> 0.9 | AO55: =_DATA_Assessment_Model!AL55 -> 0 | AP55: =_DATA_Assessment_Model!AM55 -> 0 | AQ55: =_DATA_Assessment_Model!AN55 -> 0 | AR55: =_DATA_Assessment_Model!AO55 -> 0 | AS55: =_DATA_Assessment_Model!AP55 -> 0 | AT55: =_DATA_Assessment_Model!AQ55 -> 0 | ... AW55: =_DATA_Assessment_Model!AT55 -> 0.9 | AY55: =_DATA_Assessment_Model!AV55 -> 0.9
A56: Governance Crisis | B56: Governance Crisis | C56: 11 | D56: GOVE-007 | E56: Risk and continuity | F56: How mature is the organization in managing enterprise risk register with owners, likelihood, impact, controls, triggers and residual risk, including ownership, evidence, metrics, fallback procedures and crisis stress testing? | G56: This topic affects exposure to All crisis types. It helps identify how disruption may impact operations, people, revenue, systems, legal exposure or recovery time. | H56: ISO 22301; ISO 22320; ISO 31000; ISO 37000; NIST SP 800-34; BCI Good Practice Guidelines; Bain RAPID | I56: Policy/SOP; owner/RACI; system report; dashboard; contracts; test records; incident history; interview evidence related to enterprise risk register with owners, likelihood, impact, controls, triggers and residual risk. | J56: 5 | K56: =_DATA_Assessment_Model!H56 -> 0 | L56: =_DATA_Assessment_Model!I56 -> 0 | M56: =_DATA_Assessment_Model!J56 -> 5 | N56: =_DATA_Assessment_Model!K56 -> 5 | O56: =_DATA_Assessment_Model!L56 -> Critical | P56: No inventory/register exists. | Q56: Partial lists live in individuals' heads or personal files. | R56: A register exists but is incomplete or outdated (>1 year) and has no owner. | S56: Owned, documented, updated on a defined schedule, covers the main scope. | T56: Complete and periodically reviewed; integrated with related processes; completeness measured. | U56: Maintained automatically or synced with systems; drives decisions; audited. | V56: All crisis types | Y56: Use the recommended action generated by the model; validate with domain owner during real assessment. | Z56: 4 | AA56: 5 | AB56: 5 | AM56: =_DATA_Assessment_Model!AJ56 -> 0.9 | AN56: =_DATA_Assessment_Model!AK56 -> 0.9 | AO56: =_DATA_Assessment_Model!AL56 -> 0 | AP56: =_DATA_Assessment_Model!AM56 -> 0 | AQ56: =_DATA_Assessment_Model!AN56 -> 0 | AR56: =_DATA_Assessment_Model!AO56 -> 0 | AS56: =_DATA_Assessment_Model!AP56 -> 0 | AT56: =_DATA_Assessment_Model!AQ56 -> 0 | ... AW56: =_DATA_Assessment_Model!AT56 -> 0.9 | AY56: =_DATA_Assessment_Model!AV56 -> 0.9
A57: Governance Crisis | B57: Governance Crisis | C57: 12 | D57: GOVE-008 | E57: Risk and continuity | F57: How mature is the organization in managing risk appetite for safety, cash, cyber, delivery, compliance, reputation and operational continuity, including ownership, evidence, metrics, fallback procedures and crisis stress testing? | G57: This topic affects exposure to All crisis types. It helps identify how disruption may impact operations, people, revenue, systems, legal exposure or recovery time. | H57: ISO 22301; ISO 22320; ISO 31000; ISO 37000; NIST SP 800-34; BCI Good Practice Guidelines; Bain RAPID | I57: Policy/SOP; owner/RACI; system report; dashboard; contracts; test records; incident history; interview evidence related to risk appetite for safety, cash, cyber, delivery, compliance, reputation and operational continuity. | J57: 5 | K57: =_DATA_Assessment_Model!H57 -> 0 | L57: =_DATA_Assessment_Model!I57 -> 0 | M57: =_DATA_Assessment_Model!J57 -> 5 | N57: =_DATA_Assessment_Model!K57 -> 5 | O57: =_DATA_Assessment_Model!L57 -> Critical | P57: Does not exist; no owner, no documentation, no practice. | Q57: Ad hoc; depends entirely on specific individuals. | R57: Partially documented or implemented; coverage inconsistent; never tested under stress. | S57: Documented, owned, executed consistently; basic evidence and metrics exist. | T57: Measured and periodically tested/audited; integrated with adjacent processes. | U57: Optimized and automated where practical; stress-tested; benchmarked externally. | V57: All crisis types | Y57: Use the recommended action generated by the model; validate with domain owner during real assessment. | Z57: 5 | AA57: 5 | AB57: 5 | AM57: =_DATA_Assessment_Model!AJ57 -> 0.9 | AN57: =_DATA_Assessment_Model!AK57 -> 0.9 | AO57: =_DATA_Assessment_Model!AL57 -> 0 | AP57: =_DATA_Assessment_Model!AM57 -> 0 | AQ57: =_DATA_Assessment_Model!AN57 -> 0 | AR57: =_DATA_Assessment_Model!AO57 -> 0 | AS57: =_DATA_Assessment_Model!AP57 -> 0 | AT57: =_DATA_Assessment_Model!AQ57 -> 0 | ... AW57: =_DATA_Assessment_Model!AT57 -> 0.9 | AY57: =_DATA_Assessment_Model!AV57 -> 0.9
A58: Governance Crisis | B58: Governance Crisis | C58: 13 | D58: GOVE-009 | E58: Risk and continuity | F58: How mature is the organization in managing early warning indicators for major crisis types and objective crisis activation triggers, including ownership, evidence, metrics, fallback procedures and crisis stress testing? | G58: This topic affects exposure to All crisis types. It helps identify how disruption may impact operations, people, revenue, systems, legal exposure or recovery time. | H58: ISO 22301; ISO 22320; ISO 31000; ISO 37000; NIST SP 800-34; BCI Good Practice Guidelines; Bain RAPID | I58: Policy/SOP; owner/RACI; system report; dashboard; contracts; test records; incident history; interview evidence related to early warning indicators for major crisis types and objective crisis activation triggers. | J58: 5 | K58: =_DATA_Assessment_Model!H58 -> 0 | L58: =_DATA_Assessment_Model!I58 -> 0 | M58: =_DATA_Assessment_Model!J58 -> 5 | N58: =_DATA_Assessment_Model!K58 -> 5 | O58: =_DATA_Assessment_Model!L58 -> Critical | P58: Nothing is monitored or measured. | Q58: Occasional manual checks by individuals. | R58: Some metrics exist but are not reviewed regularly and trigger no action. | S58: Defined metrics with an owner, reviewed on a set cadence. | T58: Thresholds and alerts in place; deviations trigger documented action; trends analyzed. | U58: Automated monitoring with leading indicators, integrated into management decisions. | V58: All crisis types | Y58: Use the recommended action generated by the model; validate with domain owner during real assessment. | Z58: 4 | AA58: 5 | AB58: 5 | AM58: =_DATA_Assessment_Model!AJ58 -> 0.9 | AN58: =_DATA_Assessment_Model!AK58 -> 0.9 | AO58: =_DATA_Assessment_Model!AL58 -> 0 | AP58: =_DATA_Assessment_Model!AM58 -> 0 | AQ58: =_DATA_Assessment_Model!AN58 -> 0 | AR58: =_DATA_Assessment_Model!AO58 -> 0 | AS58: =_DATA_Assessment_Model!AP58 -> 0 | AT58: =_DATA_Assessment_Model!AQ58 -> 0 | ... AW58: =_DATA_Assessment_Model!AT58 -> 0.9 | AY58: =_DATA_Assessment_Model!AV58 -> 0.9
A59: Governance Crisis | B59: Governance Crisis | C59: 14 | D59: GOVE-010 | E59: Risk and continuity | F59: How mature is the organization in managing business impact analysis across functions, sites, systems, people and suppliers, including ownership, evidence, metrics, fallback procedures and crisis stress testing? | G59: This topic affects exposure to All crisis types. It helps identify how disruption may impact operations, people, revenue, systems, legal exposure or recovery time. | H59: ISO 22301; ISO 22320; ISO 31000; ISO 37000; NIST SP 800-34; BCI Good Practice Guidelines; Bain RAPID | I59: Policy/SOP; owner/RACI; system report; dashboard; contracts; test records; incident history; interview evidence related to business impact analysis across functions, sites, systems, people and suppliers. | J59: 5 | K59: =_DATA_Assessment_Model!H59 -> 0 | L59: =_DATA_Assessment_Model!I59 -> 0 | M59: =_DATA_Assessment_Model!J59 -> 5 | N59: =_DATA_Assessment_Model!K59 -> 5 | O59: =_DATA_Assessment_Model!L59 -> Critical | P59: Does not exist; no owner, no documentation, no practice. | Q59: Ad hoc; depends entirely on specific individuals. | R59: Partially documented or implemented; coverage inconsistent; never tested under stress. | S59: Documented, owned, executed consistently; basic evidence and metrics exist. | T59: Measured and periodically tested/audited; integrated with adjacent processes. | U59: Optimized and automated where practical; stress-tested; benchmarked externally. | V59: All crisis types | Y59: Use the recommended action generated by the model; validate with domain owner during real assessment. | Z59: 4 | AA59: 5 | AB59: 5 | AM59: =_DATA_Assessment_Model!AJ59 -> 0.9 | AN59: =_DATA_Assessment_Model!AK59 -> 0.9 | AO59: =_DATA_Assessment_Model!AL59 -> 0 | AP59: =_DATA_Assessment_Model!AM59 -> 0 | AQ59: =_DATA_Assessment_Model!AN59 -> 0 | AR59: =_DATA_Assessment_Model!AO59 -> 0 | AS59: =_DATA_Assessment_Model!AP59 -> 0 | AT59: =_DATA_Assessment_Model!AQ59 -> 0 | ... AW59: =_DATA_Assessment_Model!AT59 -> 0.9 | AY59: =_DATA_Assessment_Model!AV59 -> 0.9
A60: Governance Crisis | B60: Governance Crisis | C60: 15 | D60: GOVE-011 | E60: Risk and continuity | F60: How mature is the organization in managing business continuity plans covering critical processes, people, systems, sites, suppliers and communication, including ownership, evidence, metrics, fallback procedures and crisis stress testing? | G60: This topic affects exposure to All crisis types. It helps identify how disruption may impact operations, people, revenue, systems, legal exposure or recovery time. | H60: ISO 22301; ISO 22320; ISO 31000; ISO 37000; NIST SP 800-34; BCI Good Practice Guidelines; Bain RAPID | I60: Policy/SOP; owner/RACI; system report; dashboard; contracts; test records; incident history; interview evidence related to business continuity plans covering critical processes, people, systems, sites, suppliers and communication. | J60: 5 | K60: =_DATA_Assessment_Model!H60 -> 0 | L60: =_DATA_Assessment_Model!I60 -> 0 | M60: =_DATA_Assessment_Model!J60 -> 5 | N60: =_DATA_Assessment_Model!K60 -> 5 | O60: =_DATA_Assessment_Model!L60 -> Critical | P60: No plan or procedure exists. | Q60: Knowledge lives with individuals; nothing usable is written down. | R60: Drafted but outdated, not approved, or unknown to the people who must use it. | S60: Approved and current; owners assigned; affected staff know it exists and where to find it. | T60: Tested against realistic scenarios; updated after each test or real incident. | U60: Exercised regularly including external parties; readiness measured; continuously improved. | V60: All crisis types | Y60: Use the recommended action generated by the model; validate with domain owner during real assessment. | Z60: 4 | AA60: 5 | AB60: 5 | AM60: =_DATA_Assessment_Model!AJ60 -> 0.9 | AN60: =_DATA_Assessment_Model!AK60 -> 0.9 | AO60: =_DATA_Assessment_Model!AL60 -> 0 | AP60: =_DATA_Assessment_Model!AM60 -> 0 | AQ60: =_DATA_Assessment_Model!AN60 -> 0 | AR60: =_DATA_Assessment_Model!AO60 -> 0 | AS60: =_DATA_Assessment_Model!AP60 -> 0 | AT60: =_DATA_Assessment_Model!AQ60 -> 0 | ... AW60: =_DATA_Assessment_Model!AT60 -> 0.9 | AY60: =_DATA_Assessment_Model!AV60 -> 0.9
A61: Governance Crisis | B61: Governance Crisis | C61: 16 | D61: GOVE-012 | E61: Risk and continuity | F61: How mature is the organization in managing scenario library covering cyberattack, war/security, site loss, supplier disruption, cloud outage, pandemic, demand shock and liquidity crisis, including ownership, evidence, metrics, fallback procedures and crisis stress testing? | G61: This topic affects exposure to All crisis types. It helps identify how disruption may impact operations, people, revenue, systems, legal exposure or recovery time. | H61: ISO 22301; ISO 22320; ISO 31000; ISO 37000; NIST SP 800-34; BCI Good Practice Guidelines; Bain RAPID | I61: Policy/SOP; owner/RACI; system report; dashboard; contracts; test records; incident history; interview evidence related to scenario library covering cyberattack, war/security, site loss, supplier disruption, cloud outage, pandemic, demand shock and liquidity crisis. | J61: 5 | K61: =_DATA_Assessment_Model!H61 -> 0 | L61: =_DATA_Assessment_Model!I61 -> 0 | M61: =_DATA_Assessment_Model!J61 -> 5 | N61: =_DATA_Assessment_Model!K61 -> 5 | O61: =_DATA_Assessment_Model!L61 -> Critical | P61: Does not exist; no owner, no documentation, no practice. | Q61: Ad hoc; depends entirely on specific individuals. | R61: Partially documented or implemented; coverage inconsistent; never tested under stress. | S61: Documented, owned, executed consistently; basic evidence and metrics exist. | T61: Measured and periodically tested/audited; integrated with adjacent processes. | U61: Optimized and automated where practical; stress-tested; benchmarked externally. | V61: All crisis types | Y61: Use the recommended action generated by the model; validate with domain owner during real assessment. | Z61: 5 | AA61: 5 | AB61: 5 | AM61: =_DATA_Assessment_Model!AJ61 -> 0.9 | AN61: =_DATA_Assessment_Model!AK61 -> 0.9 | AO61: =_DATA_Assessment_Model!AL61 -> 0 | AP61: =_DATA_Assessment_Model!AM61 -> 0 | AQ61: =_DATA_Assessment_Model!AN61 -> 0 | AR61: =_DATA_Assessment_Model!AO61 -> 0 | AS61: =_DATA_Assessment_Model!AP61 -> 0 | AT61: =_DATA_Assessment_Model!AQ61 -> 0 | ... AW61: =_DATA_Assessment_Model!AT61 -> 0.9 | AY61: =_DATA_Assessment_Model!AV61 -> 0.9
A62: Governance Crisis | B62: Governance Crisis | C62: 17 | D62: GOVE-013 | E62: Risk and continuity | F62: How mature is the organization in managing continuity testing through tabletop exercises, simulations and real incident reviews, including ownership, evidence, metrics, fallback procedures and crisis stress testing? | G62: This topic affects exposure to All crisis types. It helps identify how disruption may impact operations, people, revenue, systems, legal exposure or recovery time. | H62: ISO 22301; ISO 22320; ISO 31000; ISO 37000; NIST SP 800-34; BCI Good Practice Guidelines; Bain RAPID | I62: Policy/SOP; owner/RACI; system report; dashboard; contracts; test records; incident history; interview evidence related to continuity testing through tabletop exercises, simulations and real incident reviews. | J62: 5 | K62: =_DATA_Assessment_Model!H62 -> 0 | L62: =_DATA_Assessment_Model!I62 -> 0 | M62: =_DATA_Assessment_Model!J62 -> 5 | N62: =_DATA_Assessment_Model!K62 -> 5 | O62: =_DATA_Assessment_Model!L62 -> Critical | P62: Never done; no records exist. | Q62: Done once long ago or only after an incident; no schedule, no records. | R62: Done irregularly; results are not documented and findings are not tracked. | S62: Done on a defined schedule (at least annually); results documented, owner assigned. | T62: Done quarterly/semi-annually; findings tracked to closure, effectiveness measured against targets. | U62: Continuous or automated where possible; results drive improvements and are validated externally (audit/customer). | V62: All crisis types | Y62: Use the recommended action generated by the model; validate with domain owner during real assessment. | Z62: 4 | AA62: 5 | AB62: 5 | AM62: =_DATA_Assessment_Model!AJ62 -> 0.9 | AN62: =_DATA_Assessment_Model!AK62 -> 0.9 | AO62: =_DATA_Assessment_Model!AL62 -> 0 | AP62: =_DATA_Assessment_Model!AM62 -> 0 | AQ62: =_DATA_Assessment_Model!AN62 -> 0 | AR62: =_DATA_Assessment_Model!AO62 -> 0 | AS62: =_DATA_Assessment_Model!AP62 -> 0 | AT62: =_DATA_Assessment_Model!AQ62 -> 0 | ... AW62: =_DATA_Assessment_Model!AT62 -> 0.9 | AY62: =_DATA_Assessment_Model!AV62 -> 0.9
A63: Governance Crisis | B63: Governance Crisis | C63: 18 | D63: GOVE-014 | E63: Incident management | F63: How mature is the organization in managing common incident classification model for severity, impact, escalation and communication, including ownership, evidence, metrics, fallback procedures and crisis stress testing? | G63: This topic affects exposure to All crisis types. It helps identify how disruption may impact operations, people, revenue, systems, legal exposure or recovery time. | H63: ISO 22301; ISO 22320; ISO 31000; ISO 37000; NIST SP 800-34; BCI Good Practice Guidelines; Bain RAPID | I63: Policy/SOP; owner/RACI; system report; dashboard; contracts; test records; incident history; interview evidence related to common incident classification model for severity, impact, escalation and communication. | J63: 5 | K63: =_DATA_Assessment_Model!H63 -> 0 | L63: =_DATA_Assessment_Model!I63 -> 0 | M63: =_DATA_Assessment_Model!J63 -> 5 | N63: =_DATA_Assessment_Model!K63 -> 5 | O63: =_DATA_Assessment_Model!L63 -> Critical | P63: Does not exist; no owner, no documentation, no practice. | Q63: Ad hoc; depends entirely on specific individuals. | R63: Partially documented or implemented; coverage inconsistent; never tested under stress. | S63: Documented, owned, executed consistently; basic evidence and metrics exist. | T63: Measured and periodically tested/audited; integrated with adjacent processes. | U63: Optimized and automated where practical; stress-tested; benchmarked externally. | V63: All crisis types | Y63: Use the recommended action generated by the model; validate with domain owner during real assessment. | Z63: 4 | AA63: 5 | AB63: 5 | AM63: =_DATA_Assessment_Model!AJ63 -> 0.9 | AN63: =_DATA_Assessment_Model!AK63 -> 0.9 | AO63: =_DATA_Assessment_Model!AL63 -> 0 | AP63: =_DATA_Assessment_Model!AM63 -> 0 | AQ63: =_DATA_Assessment_Model!AN63 -> 0 | AR63: =_DATA_Assessment_Model!AO63 -> 0 | AS63: =_DATA_Assessment_Model!AP63 -> 0 | AT63: =_DATA_Assessment_Model!AQ63 -> 0 | ... AW63: =_DATA_Assessment_Model!AT63 -> 0.9 | AY63: =_DATA_Assessment_Model!AV63 -> 0.9
A64: Governance Crisis | B64: Governance Crisis | C64: 19 | D64: GOVE-015 | E64: Incident management | F64: How mature is the organization in managing post-incident review process that converts incidents into corrective and preventive actions, including ownership, evidence, metrics, fallback procedures and crisis stress testing? | G64: This topic affects exposure to All crisis types. It helps identify how disruption may impact operations, people, revenue, systems, legal exposure or recovery time. | H64: ISO 22301; ISO 22320; ISO 31000; ISO 37000; NIST SP 800-34; BCI Good Practice Guidelines; Bain RAPID | I64: Policy/SOP; owner/RACI; system report; dashboard; contracts; test records; incident history; interview evidence related to post-incident review process that converts incidents into corrective and preventive actions. | J64: 5 | K64: =_DATA_Assessment_Model!H64 -> 0 | L64: =_DATA_Assessment_Model!I64 -> 0 | M64: =_DATA_Assessment_Model!J64 -> 5 | N64: =_DATA_Assessment_Model!K64 -> 5 | O64: =_DATA_Assessment_Model!L64 -> Critical | P64: Does not exist; no owner, no documentation, no practice. | Q64: Ad hoc; depends entirely on specific individuals. | R64: Partially documented or implemented; coverage inconsistent; never tested under stress. | S64: Documented, owned, executed consistently; basic evidence and metrics exist. | T64: Measured and periodically tested/audited; integrated with adjacent processes. | U64: Optimized and automated where practical; stress-tested; benchmarked externally. | V64: All crisis types | Y64: Use the recommended action generated by the model; validate with domain owner during real assessment. | Z64: 4 | AA64: 5 | AB64: 5 | AM64: =_DATA_Assessment_Model!AJ64 -> 0.9 | AN64: =_DATA_Assessment_Model!AK64 -> 0.9 | AO64: =_DATA_Assessment_Model!AL64 -> 0 | AP64: =_DATA_Assessment_Model!AM64 -> 0 | AQ64: =_DATA_Assessment_Model!AN64 -> 0 | AR64: =_DATA_Assessment_Model!AO64 -> 0 | AS64: =_DATA_Assessment_Model!AP64 -> 0 | AT64: =_DATA_Assessment_Model!AQ64 -> 0 | ... AW64: =_DATA_Assessment_Model!AT64 -> 0.9 | AY64: =_DATA_Assessment_Model!AV64 -> 0.9
... A71: Governance Crisis | B71: Governance Crisis | C71: 26 | D71: GOVE-022 | E71: Risk and continuity | F71: How mature is the organization in managing joint crisis exercises with critical suppliers, customers, authorities and insurers, including ownership, evidence, metrics, fallback procedures and crisis stress testing? | G71: This topic affects exposure to Supplier/logistics disruption; War/security crisis; Cyberattack/ransomware. It helps identify how disruption may impact operations, people, revenue, systems, legal exposure or recovery time. | H71: ISO 22301; ISO 22398 | I71: Policy/SOP; owner/RACI; system report; dashboard; contracts; test records; incident history; interview evidence | J71: 3 | K71: =_DATA_Assessment_Model!H71 -> 0 | L71: =_DATA_Assessment_Model!I71 -> 0 | M71: =_DATA_Assessment_Model!J71 -> 3 | N71: =_DATA_Assessment_Model!K71 -> 3 | O71: =_DATA_Assessment_Model!L71 -> Critical | P71: Never done; no records exist. | Q71: Done once long ago or only after an incident; no schedule, no records. | R71: Done irregularly; results are not documented and findings are not tracked. | S71: Done on a defined schedule (at least annually); results documented, owner assigned. | T71: Done quarterly/semi-annually; findings tracked to closure, effectiveness measured against targets. | U71: Continuous or automated where possible; results drive improvements and are validated externally (audit/customer). | V71: Supplier/logistics disruption; War/security crisis; Cyberattack/ransomware | Y71: Use the recommended action generated by the model; validate with domain owner during real assessment. | Z71: 2 | AA71: 5 | AB71: 3 | AM71: =_DATA_Assessment_Model!AJ71 -> 0.9 | AN71: =_DATA_Assessment_Model!AK71 -> 0.9 | AO71: =_DATA_Assessment_Model!AL71 -> 0 | AP71: =_DATA_Assessment_Model!AM71 -> 0 | AQ71: =_DATA_Assessment_Model!AN71 -> 0 | AR71: =_DATA_Assessment_Model!AO71 -> 0 | AS71: =_DATA_Assessment_Model!AP71 -> 0 | AT71: =_DATA_Assessment_Model!AQ71 -> 0 | ... AW71: =_DATA_Assessment_Model!AT71 -> 0.9 | AY71: =_DATA_Assessment_Model!AV71 -> 0.9
A72: HR Workforce | B72: HR Workforce | C72: 5 | D72: HRWO-001 | E72: Workforce visibility | F72: How mature is the organization in managing workforce inventory by role, location, manager, contract type, employment entity, skill and criticality, including ownership, evidence, metrics, fallback procedures and crisis stress testing? | G72: This topic affects exposure to Workforce disruption; Pandemic/health crisis; War/security crisis. It helps identify how disruption may impact operations, people, revenue, systems, legal exposure or recovery time. | H72: ISO 30414; ISO 30405; ISO 45001; ISO 22301; CIPD; SHRM | I72: Policy/SOP; owner/RACI; system report; dashboard; contracts; test records; incident history; interview evidence related to workforce inventory by role, location, manager, contract type, employment entity, skill and criticality. | J72: 5 | K72: =_DATA_Assessment_Model!H72 -> 0 | L72: =_DATA_Assessment_Model!I72 -> 0 | M72: =_DATA_Assessment_Model!J72 -> 5 | N72: =_DATA_Assessment_Model!K72 -> 5 | O72: =_DATA_Assessment_Model!L72 -> Critical | P72: No inventory/register exists. | Q72: Partial lists live in individuals' heads or personal files. | R72: A register exists but is incomplete or outdated (>1 year) and has no owner. | S72: Owned, documented, updated on a defined schedule, covers the main scope. | T72: Complete and periodically reviewed; integrated with related processes; completeness measured. | U72: Maintained automatically or synced with systems; drives decisions; audited. | V72: Workforce disruption; Pandemic/health crisis; War/security crisis | Y72: Use the recommended action generated by the model; validate with domain owner during real assessment. | Z72: 4 | AA72: 5 | AB72: 5 | AD72: Workforce visibility | AE72: =_DATA_Assessment_Model!AB72 -> 7 | AF72: =_DATA_Assessment_Model!AC72 -> 0 | AG72: =_DATA_Assessment_Model!AD72 -> 0 | AH72: =_DATA_Assessment_Model!AE72 -> 7 | AI72: =_DATA_Assessment_Model!AF72 -> 5 | AJ72: =_DATA_Assessment_Model!AG72 -> 7 | AM72: =_DATA_Assessment_Model!AJ72 -> 0.9 | AN72: =_DATA_Assessment_Model!AK72 -> 0.9 | AO72: =_DATA_Assessment_Model!AL72 -> 0 | AP72: =_DATA_Assessment_Model!AM72 -> 0 | AQ72: =_DATA_Assessment_Model!AN72 -> 0 | AR72: =_DATA_Assessment_Model!AO72 -> 0 | AS72: =_DATA_Assessment_Model!AP72 -> 0 | AT72: =_DATA_Assessment_Model!AQ72 -> 0 | ... AW72: =_DATA_Assessment_Model!AT72 -> 0.9 | AY72: =_DATA_Assessment_Model!AV72 -> 0.9
A73: HR Workforce | B73: HR Workforce | C73: 6 | D73: HRWO-002 | E73: Workforce visibility | F73: How mature is the organization in managing critical role mapping by process dependency, customer impact, system access and knowledge concentration, including ownership, evidence, metrics, fallback procedures and crisis stress testing? | G73: This topic affects exposure to Workforce disruption; Pandemic/health crisis; War/security crisis. It helps identify how disruption may impact operations, people, revenue, systems, legal exposure or recovery time. | H73: ISO 30414; ISO 30405; ISO 45001; ISO 22301; CIPD; SHRM | I73: Policy/SOP; owner/RACI; system report; dashboard; contracts; test records; incident history; interview evidence related to critical role mapping by process dependency, customer impact, system access and knowledge concentration. | J73: 5 | K73: =_DATA_Assessment_Model!H73 -> 0 | L73: =_DATA_Assessment_Model!I73 -> 0 | M73: =_DATA_Assessment_Model!J73 -> 5 | N73: =_DATA_Assessment_Model!K73 -> 5 | O73: =_DATA_Assessment_Model!L73 -> Critical | P73: No inventory/register exists. | Q73: Partial lists live in individuals' heads or personal files. | R73: A register exists but is incomplete or outdated (>1 year) and has no owner. | S73: Owned, documented, updated on a defined schedule, covers the main scope. | T73: Complete and periodically reviewed; integrated with related processes; completeness measured. | U73: Maintained automatically or synced with systems; drives decisions; audited. | V73: Workforce disruption; Pandemic/health crisis; War/security crisis | Y73: Use the recommended action generated by the model; validate with domain owner during real assessment. | Z73: 4 | AA73: 5 | AB73: 5 | AD73: Recruitment and retention | AE73: =_DATA_Assessment_Model!AB73 -> 6 | AF73: =_DATA_Assessment_Model!AC73 -> 0 | AG73: =_DATA_Assessment_Model!AD73 -> 0 | AH73: =_DATA_Assessment_Model!AE73 -> 6 | AI73: =_DATA_Assessment_Model!AF73 -> 5 | AJ73: =_DATA_Assessment_Model!AG73 -> 6 | AM73: =_DATA_Assessment_Model!AJ73 -> 0.9 | AN73: =_DATA_Assessment_Model!AK73 -> 0.9 | AO73: =_DATA_Assessment_Model!AL73 -> 0 | AP73: =_DATA_Assessment_Model!AM73 -> 0 | AQ73: =_DATA_Assessment_Model!AN73 -> 0 | AR73: =_DATA_Assessment_Model!AO73 -> 0 | AS73: =_DATA_Assessment_Model!AP73 -> 0 | AT73: =_DATA_Assessment_Model!AQ73 -> 0 | ... AW73: =_DATA_Assessment_Model!AT73 -> 0.9 | AY73: =_DATA_Assessment_Model!AV73 -> 0.9
A74: HR Workforce | B74: HR Workforce | C74: 7 | D74: HRWO-003 | E74: Workforce visibility | F74: How mature is the organization in managing key-person risk for executives, founders, architects, plant specialists, client owners and finance signatories, including ownership, evidence, metrics, fallback procedures and crisis stress testing? | G74: This topic affects exposure to Workforce disruption; Pandemic/health crisis; War/security crisis. It helps identify how disruption may impact operations, people, revenue, systems, legal exposure or recovery time. | H74: ISO 30414; ISO 30405; ISO 45001; ISO 22301; CIPD; SHRM | I74: Policy/SOP; owner/RACI; system report; dashboard; contracts; test records; incident history; interview evidence related to key-person risk for executives, founders, architects, plant specialists, client owners and finance signatories. | J74: 5 | K74: =_DATA_Assessment_Model!H74 -> 0 | L74: =_DATA_Assessment_Model!I74 -> 0 | M74: =_DATA_Assessment_Model!J74 -> 5 | N74: =_DATA_Assessment_Model!K74 -> 5 | O74: =_DATA_Assessment_Model!L74 -> Critical | P74: No plan or procedure exists. | Q74: Knowledge lives with individuals; nothing usable is written down. | R74: Drafted but outdated, not approved, or unknown to the people who must use it. | S74: Approved and current; owners assigned; affected staff know it exists and where to find it. | T74: Tested against realistic scenarios; updated after each test or real incident. | U74: Exercised regularly including external parties; readiness measured; continuously improved. | V74: Workforce disruption; Pandemic/health crisis; War/security crisis | Y74: Use the recommended action generated by the model; validate with domain owner during real assessment. | Z74: 4 | AA74: 5 | AB74: 5 | AD74: Continuity and wellbeing | AE74: =_DATA_Assessment_Model!AB74 -> 8 | AF74: =_DATA_Assessment_Model!AC74 -> 0 | AG74: =_DATA_Assessment_Model!AD74 -> 0 | AH74: =_DATA_Assessment_Model!AE74 -> 8 | AI74: =_DATA_Assessment_Model!AF74 -> 5 | AJ74: =_DATA_Assessment_Model!AG74 -> 8 | AM74: =_DATA_Assessment_Model!AJ74 -> 0.9 | AN74: =_DATA_Assessment_Model!AK74 -> 0.9 | AO74: =_DATA_Assessment_Model!AL74 -> 0 | AP74: =_DATA_Assessment_Model!AM74 -> 0 | AQ74: =_DATA_Assessment_Model!AN74 -> 0 | AR74: =_DATA_Assessment_Model!AO74 -> 0 | AS74: =_DATA_Assessment_Model!AP74 -> 0 | AT74: =_DATA_Assessment_Model!AQ74 -> 0 | ... AW74: =_DATA_Assessment_Model!AT74 -> 0.9 | AY74: =_DATA_Assessment_Model!AV74 -> 0.9
A75: HR Workforce | B75: HR Workforce | C75: 8 | D75: HRWO-004 | E75: Workforce visibility | F75: How mature is the organization in managing skills matrix linked to critical processes, systems, products, sites and backup coverage, including ownership, evidence, metrics, fallback procedures and crisis stress testing? | G75: This topic affects exposure to Workforce disruption; Pandemic/health crisis; War/security crisis. It helps identify how disruption may impact operations, people, revenue, systems, legal exposure or recovery time. | H75: ISO 30414; ISO 30405; ISO 45001; ISO 22301; CIPD; SHRM | I75: Policy/SOP; owner/RACI; system report; dashboard; contracts; test records; incident history; interview evidence related to skills matrix linked to critical processes, systems, products, sites and backup coverage. | J75: 5 | K75: =_DATA_Assessment_Model!H75 -> 0 | L75: =_DATA_Assessment_Model!I75 -> 0 | M75: =_DATA_Assessment_Model!J75 -> 5 | N75: =_DATA_Assessment_Model!K75 -> 5 | O75: =_DATA_Assessment_Model!L75 -> Critical | P75: No inventory/register exists. | Q75: Partial lists live in individuals' heads or personal files. | R75: A register exists but is incomplete or outdated (>1 year) and has no owner. | S75: Owned, documented, updated on a defined schedule, covers the main scope. | T75: Complete and periodically reviewed; integrated with related processes; completeness measured. | U75: Maintained automatically or synced with systems; drives decisions; audited. | V75: Workforce disruption; Pandemic/health crisis; War/security crisis | Y75: Use the recommended action generated by the model; validate with domain owner during real assessment. | Z75: 5 | AA75: 5 | AB75: 5 | AD75: HR systems and compliance | AE75: =_DATA_Assessment_Model!AB75 -> 5 | AF75: =_DATA_Assessment_Model!AC75 -> 0 | AG75: =_DATA_Assessment_Model!AD75 -> 0 | AH75: =_DATA_Assessment_Model!AE75 -> 5 | AI75: =_DATA_Assessment_Model!AF75 -> 5 | AJ75: =_DATA_Assessment_Model!AG75 -> 5 | AM75: =_DATA_Assessment_Model!AJ75 -> 0.9 | AN75: =_DATA_Assessment_Model!AK75 -> 0.9 | AO75: =_DATA_Assessment_Model!AL75 -> 0 | AP75: =_DATA_Assessment_Model!AM75 -> 0 | AQ75: =_DATA_Assessment_Model!AN75 -> 0 | AR75: =_DATA_Assessment_Model!AO75 -> 0 | AS75: =_DATA_Assessment_Model!AP75 -> 0 | AT75: =_DATA_Assessment_Model!AQ75 -> 0 | ... AW75: =_DATA_Assessment_Model!AT75 -> 0.9 | AY75: =_DATA_Assessment_Model!AV75 -> 0.9
A76: HR Workforce | B76: HR Workforce | C76: 9 | D76: HRWO-005 | E76: Workforce visibility | F76: How mature is the organization in managing minimum staffing levels for critical functions, shifts, production lines and customer support, including ownership, evidence, metrics, fallback procedures and crisis stress testing? | G76: This topic affects exposure to Workforce disruption; Pandemic/health crisis; War/security crisis. It helps identify how disruption may impact operations, people, revenue, systems, legal exposure or recovery time. | H76: ISO 30414; ISO 30405; ISO 45001; ISO 22301; CIPD; SHRM | I76: Policy/SOP; owner/RACI; system report; dashboard; contracts; test records; incident history; interview evidence related to minimum staffing levels for critical functions, shifts, production lines and customer support. | J76: 5 | K76: =_DATA_Assessment_Model!H76 -> 0 | L76: =_DATA_Assessment_Model!I76 -> 0 | M76: =_DATA_Assessment_Model!J76 -> 5 | N76: =_DATA_Assessment_Model!K76 -> 5 | O76: =_DATA_Assessment_Model!L76 -> Critical | P76: Does not exist; no owner, no documentation, no practice. | Q76: Ad hoc; depends entirely on specific individuals. | R76: Partially documented or implemented; coverage inconsistent; never tested under stress. | S76: Documented, owned, executed consistently; basic evidence and metrics exist. | T76: Measured and periodically tested/audited; integrated with adjacent processes. | U76: Optimized and automated where practical; stress-tested; benchmarked externally. | V76: Workforce disruption; Pandemic/health crisis; War/security crisis | Y76: Use the recommended action generated by the model; validate with domain owner during real assessment. | Z76: 4 | AA76: 5 | AB76: 5 | AM76: =_DATA_Assessment_Model!AJ76 -> 0.9 | AN76: =_DATA_Assessment_Model!AK76 -> 0.9 | AO76: =_DATA_Assessment_Model!AL76 -> 0 | AP76: =_DATA_Assessment_Model!AM76 -> 0 | AQ76: =_DATA_Assessment_Model!AN76 -> 0 | AR76: =_DATA_Assessment_Model!AO76 -> 0 | AS76: =_DATA_Assessment_Model!AP76 -> 0 | AT76: =_DATA_Assessment_Model!AQ76 -> 0 | ... AW76: =_DATA_Assessment_Model!AT76 -> 0.9 | AY76: =_DATA_Assessment_Model!AV76 -> 0.9
A77: HR Workforce | B77: HR Workforce | C77: 10 | D77: HRWO-006 | E77: Workforce visibility | F77: How mature is the organization in managing absence trends, sick leave spikes and workforce availability monitoring, including ownership, evidence, metrics, fallback procedures and crisis stress testing? | G77: This topic affects exposure to Workforce disruption; Pandemic/health crisis; War/security crisis. It helps identify how disruption may impact operations, people, revenue, systems, legal exposure or recovery time. | H77: ISO 30414; ISO 30405; ISO 45001; ISO 22301; CIPD; SHRM | I77: Policy/SOP; owner/RACI; system report; dashboard; contracts; test records; incident history; interview evidence related to absence trends, sick leave spikes and workforce availability monitoring. | J77: 3 | K77: =_DATA_Assessment_Model!H77 -> 0 | L77: =_DATA_Assessment_Model!I77 -> 0 | M77: =_DATA_Assessment_Model!J77 -> 3 | N77: =_DATA_Assessment_Model!K77 -> 3 | O77: =_DATA_Assessment_Model!L77 -> Critical | P77: No reliable evidence that absence trends, sick leave spikes and workforce availability monitoring is defined, owned or managed. | Q77: Absence trends, sick leave spikes and workforce availability monitoring is handled informally and depends on individual knowledge or heroic effort. | R77: Absence trends, sick leave spikes and workforce availability monitoring is partially documented or implemented, but coverage is inconsistent and not crisis-tested. | S77: Absence trends, sick leave spikes and workforce availability monitoring is documented, owned, used in normal operations and supported by basic evidence or metrics. | T77: Absence trends, sick leave spikes and workforce availability monitoring is measured, periodically reviewed, integrated with related processes and tested against relevant disruption scenarios. | U77: Absence trends, sick leave spikes and workforce availability monitoring is optimized, continuously improved, automated where practical and demonstrably supports crisis resilience. | V77: Workforce disruption; Pandemic/health crisis; War/security crisis | Y77: Use the recommended action generated by the model; validate with domain owner during real assessment. | Z77: 4 | AA77: 5 | AB77: 5 | AM77: =_DATA_Assessment_Model!AJ77 -> 0.9 | AN77: =_DATA_Assessment_Model!AK77 -> 0.9 | AO77: =_DATA_Assessment_Model!AL77 -> 0 | AP77: =_DATA_Assessment_Model!AM77 -> 0 | AQ77: =_DATA_Assessment_Model!AN77 -> 0 | AR77: =_DATA_Assessment_Model!AO77 -> 0 | AS77: =_DATA_Assessment_Model!AP77 -> 0 | AT77: =_DATA_Assessment_Model!AQ77 -> 0 | ... AW77: =_DATA_Assessment_Model!AT77 -> 0.9 | AY77: =_DATA_Assessment_Model!AV77 -> 0.9
A78: HR Workforce | B78: HR Workforce | C78: 11 | D78: HRWO-007 | E78: Recruitment and retention | F78: How mature is the organization in managing hiring pipeline resilience for critical roles under market shortage or geographic disruption, including ownership, evidence, metrics, fallback procedures and crisis stress testing? | G78: This topic affects exposure to Workforce disruption; Pandemic/health crisis; War/security crisis. It helps identify how disruption may impact operations, people, revenue, systems, legal exposure or recovery time. | H78: ISO 30414; ISO 30405; ISO 45001; ISO 22301; CIPD; SHRM | I78: Policy/SOP; owner/RACI; system report; dashboard; contracts; test records; incident history; interview evidence related to hiring pipeline resilience for critical roles under market shortage or geographic disruption. | J78: 5 | K78: =_DATA_Assessment_Model!H78 -> 0 | L78: =_DATA_Assessment_Model!I78 -> 0 | M78: =_DATA_Assessment_Model!J78 -> 5 | N78: =_DATA_Assessment_Model!K78 -> 5 | O78: =_DATA_Assessment_Model!L78 -> Critical | P78: Does not exist; no owner, no documentation, no practice. | Q78: Ad hoc; depends entirely on specific individuals. | R78: Partially documented or implemented; coverage inconsistent; never tested under stress. | S78: Documented, owned, executed consistently; basic evidence and metrics exist. | T78: Measured and periodically tested/audited; integrated with adjacent processes. | U78: Optimized and automated where practical; stress-tested; benchmarked externally. | V78: Workforce disruption; Pandemic/health crisis; War/security crisis | Y78: Use the recommended action generated by the model; validate with domain owner during real assessment. | Z78: 4 | AA78: 5 | AB78: 5 | AM78: =_DATA_Assessment_Model!AJ78 -> 0.9 | AN78: =_DATA_Assessment_Model!AK78 -> 0.9 | AO78: =_DATA_Assessment_Model!AL78 -> 0 | AP78: =_DATA_Assessment_Model!AM78 -> 0 | AQ78: =_DATA_Assessment_Model!AN78 -> 0 | AR78: =_DATA_Assessment_Model!AO78 -> 0 | AS78: =_DATA_Assessment_Model!AP78 -> 0 | AT78: =_DATA_Assessment_Model!AQ78 -> 0 | ... AW78: =_DATA_Assessment_Model!AT78 -> 0.9 | AY78: =_DATA_Assessment_Model!AV78 -> 0.9
A79: HR Workforce | B79: HR Workforce | C79: 12 | D79: HRWO-008 | E79: Recruitment and retention | F79: How mature is the organization in managing time-to-hire tracking by critical role, geography and seniority, including ownership, evidence, metrics, fallback procedures and crisis stress testing? | G79: This topic affects exposure to Workforce disruption; Pandemic/health crisis; War/security crisis. It helps identify how disruption may impact operations, people, revenue, systems, legal exposure or recovery time. | H79: ISO 30414; ISO 30405; ISO 45001; ISO 22301; CIPD; SHRM | I79: Policy/SOP; owner/RACI; system report; dashboard; contracts; test records; incident history; interview evidence related to time-to-hire tracking by critical role, geography and seniority. | J79: 5 | K79: =_DATA_Assessment_Model!H79 -> 0 | L79: =_DATA_Assessment_Model!I79 -> 0 | M79: =_DATA_Assessment_Model!J79 -> 5 | N79: =_DATA_Assessment_Model!K79 -> 5 | O79: =_DATA_Assessment_Model!L79 -> Critical | P79: Nothing is monitored or measured. | Q79: Occasional manual checks by individuals. | R79: Some metrics exist but are not reviewed regularly and trigger no action. | S79: Defined metrics with an owner, reviewed on a set cadence. | T79: Thresholds and alerts in place; deviations trigger documented action; trends analyzed. | U79: Automated monitoring with leading indicators, integrated into management decisions. | V79: Workforce disruption; Pandemic/health crisis; War/security crisis | Y79: Use the recommended action generated by the model; validate with domain owner during real assessment. | Z79: 4 | AA79: 5 | AB79: 5 | AM79: =_DATA_Assessment_Model!AJ79 -> 0.9 | AN79: =_DATA_Assessment_Model!AK79 -> 0.9 | AO79: =_DATA_Assessment_Model!AL79 -> 0 | AP79: =_DATA_Assessment_Model!AM79 -> 0 | AQ79: =_DATA_Assessment_Model!AN79 -> 0 | AR79: =_DATA_Assessment_Model!AO79 -> 0 | AS79: =_DATA_Assessment_Model!AP79 -> 0 | AT79: =_DATA_Assessment_Model!AQ79 -> 0 | ... AW79: =_DATA_Assessment_Model!AT79 -> 0.9 | AY79: =_DATA_Assessment_Model!AV79 -> 0.9
A80: HR Workforce | B80: HR Workforce | C80: 13 | D80: HRWO-009 | E80: Recruitment and retention | F80: How mature is the organization in managing alternative sourcing channels for critical roles, geographies and rare skills, including ownership, evidence, metrics, fallback procedures and crisis stress testing? | G80: This topic affects exposure to Workforce disruption; Pandemic/health crisis; War/security crisis. It helps identify how disruption may impact operations, people, revenue, systems, legal exposure or recovery time. | H80: ISO 30414; ISO 30405; ISO 45001; ISO 22301; CIPD; SHRM | I80: Policy/SOP; owner/RACI; system report; dashboard; contracts; test records; incident history; interview evidence related to alternative sourcing channels for critical roles, geographies and rare skills. | J80: 5 | K80: =_DATA_Assessment_Model!H80 -> 0 | L80: =_DATA_Assessment_Model!I80 -> 0 | M80: =_DATA_Assessment_Model!J80 -> 5 | N80: =_DATA_Assessment_Model!K80 -> 5 | O80: =_DATA_Assessment_Model!L80 -> Critical | P80: Does not exist; no owner, no documentation, no practice. | Q80: Ad hoc; depends entirely on specific individuals. | R80: Partially documented or implemented; coverage inconsistent; never tested under stress. | S80: Documented, owned, executed consistently; basic evidence and metrics exist. | T80: Measured and periodically tested/audited; integrated with adjacent processes. | U80: Optimized and automated where practical; stress-tested; benchmarked externally. | V80: Workforce disruption; Pandemic/health crisis; War/security crisis | Y80: Use the recommended action generated by the model; validate with domain owner during real assessment. | Z80: 4 | AA80: 5 | AB80: 5 | AM80: =_DATA_Assessment_Model!AJ80 -> 0.9 | AN80: =_DATA_Assessment_Model!AK80 -> 0.9 | AO80: =_DATA_Assessment_Model!AL80 -> 0 | AP80: =_DATA_Assessment_Model!AM80 -> 0 | AQ80: =_DATA_Assessment_Model!AN80 -> 0 | AR80: =_DATA_Assessment_Model!AO80 -> 0 | AS80: =_DATA_Assessment_Model!AP80 -> 0 | AT80: =_DATA_Assessment_Model!AQ80 -> 0 | ... AW80: =_DATA_Assessment_Model!AT80 -> 0.9 | AY80: =_DATA_Assessment_Model!AV80 -> 0.9
A81: HR Workforce | B81: HR Workforce | C81: 14 | D81: HRWO-010 | E81: Recruitment and retention | F81: How mature is the organization in managing retention risk monitoring for critical people, high performers and scarce-skill roles, including ownership, evidence, metrics, fallback procedures and crisis stress testing? | G81: This topic affects exposure to Workforce disruption; Pandemic/health crisis; War/security crisis. It helps identify how disruption may impact operations, people, revenue, systems, legal exposure or recovery time. | H81: ISO 30414; ISO 30405; ISO 45001; ISO 22301; CIPD; SHRM | I81: Policy/SOP; owner/RACI; system report; dashboard; contracts; test records; incident history; interview evidence related to retention risk monitoring for critical people, high performers and scarce-skill roles. | J81: 5 | K81: =_DATA_Assessment_Model!H81 -> 0 | L81: =_DATA_Assessment_Model!I81 -> 0 | M81: =_DATA_Assessment_Model!J81 -> 5 | N81: =_DATA_Assessment_Model!K81 -> 5 | O81: =_DATA_Assessment_Model!L81 -> Critical | P81: Nothing is monitored or measured. | Q81: Occasional manual checks by individuals. | R81: Some metrics exist but are not reviewed regularly and trigger no action. | S81: Defined metrics with an owner, reviewed on a set cadence. | T81: Thresholds and alerts in place; deviations trigger documented action; trends analyzed. | U81: Automated monitoring with leading indicators, integrated into management decisions. | V81: Workforce disruption; Pandemic/health crisis; War/security crisis | Y81: Use the recommended action generated by the model; validate with domain owner during real assessment. | Z81: 4 | AA81: 5 | AB81: 5 | AM81: =_DATA_Assessment_Model!AJ81 -> 0.9 | AN81: =_DATA_Assessment_Model!AK81 -> 0.9 | AO81: =_DATA_Assessment_Model!AL81 -> 0 | AP81: =_DATA_Assessment_Model!AM81 -> 0 | AQ81: =_DATA_Assessment_Model!AN81 -> 0 | AR81: =_DATA_Assessment_Model!AO81 -> 0 | AS81: =_DATA_Assessment_Model!AP81 -> 0 | AT81: =_DATA_Assessment_Model!AQ81 -> 0 | ... AW81: =_DATA_Assessment_Model!AT81 -> 0.9 | AY81: =_DATA_Assessment_Model!AV81 -> 0.9
A82: HR Workforce | B82: HR Workforce | C82: 15 | D82: HRWO-011 | E82: Recruitment and retention | F82: How mature is the organization in managing compensation and payroll continuity during banking, legal or system disruption, including ownership, evidence, metrics, fallback procedures and crisis stress testing? | G82: This topic affects exposure to Workforce disruption; Pandemic/health crisis; War/security crisis. It helps identify how disruption may impact operations, people, revenue, systems, legal exposure or recovery time. | H82: ISO 30414; ISO 30405; ISO 45001; ISO 22301; CIPD; SHRM | I82: Policy/SOP; owner/RACI; system report; dashboard; contracts; test records; incident history; interview evidence related to compensation and payroll continuity during banking, legal or system disruption. | J82: 5 | K82: =_DATA_Assessment_Model!H82 -> 0 | L82: =_DATA_Assessment_Model!I82 -> 0 | M82: =_DATA_Assessment_Model!J82 -> 5 | N82: =_DATA_Assessment_Model!K82 -> 5 | O82: =_DATA_Assessment_Model!L82 -> Critical | P82: Does not exist; no owner, no documentation, no practice. | Q82: Ad hoc; depends entirely on specific individuals. | R82: Partially documented or implemented; coverage inconsistent; never tested under stress. | S82: Documented, owned, executed consistently; basic evidence and metrics exist. | T82: Measured and periodically tested/audited; integrated with adjacent processes. | U82: Optimized and automated where practical; stress-tested; benchmarked externally. | V82: Workforce disruption; Pandemic/health crisis; War/security crisis | Y82: Use the recommended action generated by the model; validate with domain owner during real assessment. | Z82: 4 | AA82: 5 | AB82: 5 | AM82: =_DATA_Assessment_Model!AJ82 -> 0.9 | AN82: =_DATA_Assessment_Model!AK82 -> 0.9 | AO82: =_DATA_Assessment_Model!AL82 -> 0 | AP82: =_DATA_Assessment_Model!AM82 -> 0 | AQ82: =_DATA_Assessment_Model!AN82 -> 0 | AR82: =_DATA_Assessment_Model!AO82 -> 0 | AS82: =_DATA_Assessment_Model!AP82 -> 0 | AT82: =_DATA_Assessment_Model!AQ82 -> 0 | ... AW82: =_DATA_Assessment_Model!AT82 -> 0.9 | AY82: =_DATA_Assessment_Model!AV82 -> 0.9
A83: HR Workforce | B83: HR Workforce | C83: 16 | D83: HRWO-012 | E83: Recruitment and retention | F83: How mature is the organization in managing succession planning and deputies for all critical leadership and operational roles, including ownership, evidence, metrics, fallback procedures and crisis stress testing? | G83: This topic affects exposure to Workforce disruption; Pandemic/health crisis; War/security crisis. It helps identify how disruption may impact operations, people, revenue, systems, legal exposure or recovery time. | H83: ISO 30414; ISO 30405; ISO 45001; ISO 22301; CIPD; SHRM | I83: Policy/SOP; owner/RACI; system report; dashboard; contracts; test records; incident history; interview evidence related to succession planning and deputies for all critical leadership and operational roles. | J83: 5 | K83: =_DATA_Assessment_Model!H83 -> 0 | L83: =_DATA_Assessment_Model!I83 -> 0 | M83: =_DATA_Assessment_Model!J83 -> 5 | N83: =_DATA_Assessment_Model!K83 -> 5 | O83: =_DATA_Assessment_Model!L83 -> Critical | P83: No plan or procedure exists. | Q83: Knowledge lives with individuals; nothing usable is written down. | R83: Drafted but outdated, not approved, or unknown to the people who must use it. | S83: Approved and current; owners assigned; affected staff know it exists and where to find it. | T83: Tested against realistic scenarios; updated after each test or real incident. | U83: Exercised regularly including external parties; readiness measured; continuously improved. | V83: Workforce disruption; Pandemic/health crisis; War/security crisis | Y83: Use the recommended action generated by the model; validate with domain owner during real assessment. | Z83: 4 | AA83: 5 | AB83: 5 | AM83: =_DATA_Assessment_Model!AJ83 -> 0.9 | AN83: =_DATA_Assessment_Model!AK83 -> 0.9 | AO83: =_DATA_Assessment_Model!AL83 -> 0 | AP83: =_DATA_Assessment_Model!AM83 -> 0 | AQ83: =_DATA_Assessment_Model!AN83 -> 0 | AR83: =_DATA_Assessment_Model!AO83 -> 0 | AS83: =_DATA_Assessment_Model!AP83 -> 0 | AT83: =_DATA_Assessment_Model!AQ83 -> 0 | ... AW83: =_DATA_Assessment_Model!AT83 -> 0.9 | AY83: =_DATA_Assessment_Model!AV83 -> 0.9
A84: HR Workforce | B84: HR Workforce | C84: 17 | D84: HRWO-013 | E84: Continuity and wellbeing | F84: How mature is the organization in managing remote onboarding with secure access, equipment, training and manager support, including ownership, evidence, metrics, fallback procedures and crisis stress testing? | G84: This topic affects exposure to Workforce disruption; Pandemic/health crisis; War/security crisis. It helps identify how disruption may impact operations, people, revenue, systems, legal exposure or recovery time. | H84: ISO 30414; ISO 30405; ISO 45001; ISO 22301; CIPD; SHRM | I84: Policy/SOP; owner/RACI; system report; dashboard; contracts; test records; incident history; interview evidence related to remote onboarding with secure access, equipment, training and manager support. | J84: 4 | K84: =_DATA_Assessment_Model!H84 -> 0 | L84: =_DATA_Assessment_Model!I84 -> 0 | M84: =_DATA_Assessment_Model!J84 -> 4 | N84: =_DATA_Assessment_Model!K84 -> 4 | O84: =_DATA_Assessment_Model!L84 -> Critical | P84: Never done; no records exist. | Q84: Done once long ago or only after an incident; no schedule, no records. | R84: Done irregularly; results are not documented and findings are not tracked. | S84: Done on a defined schedule (at least annually); results documented, owner assigned. | T84: Done quarterly/semi-annually; findings tracked to closure, effectiveness measured against targets. | U84: Continuous or automated where possible; results drive improvements and are validated externally (audit/customer). | V84: Workforce disruption; Pandemic/health crisis; War/security crisis | Y84: Use the recommended action generated by the model; validate with domain owner during real assessment. | Z84: 4 | AA84: 5 | AB84: 5 | AM84: =_DATA_Assessment_Model!AJ84 -> 0.9 | AN84: =_DATA_Assessment_Model!AK84 -> 0.9 | AO84: =_DATA_Assessment_Model!AL84 -> 0 | AP84: =_DATA_Assessment_Model!AM84 -> 0 | AQ84: =_DATA_Assessment_Model!AN84 -> 0 | AR84: =_DATA_Assessment_Model!AO84 -> 0 | AS84: =_DATA_Assessment_Model!AP84 -> 0 | AT84: =_DATA_Assessment_Model!AQ84 -> 0 | ... AW84: =_DATA_Assessment_Model!AT84 -> 0.9 | AY84: =_DATA_Assessment_Model!AV84 -> 0.9
A85: HR Workforce | B85: HR Workforce | C85: 18 | D85: HRWO-014 | E85: Continuity and wellbeing | F85: How mature is the organization in managing remote work capability with secure access, connectivity, equipment and documented procedures, including ownership, evidence, metrics, fallback procedures and crisis stress testing? | G85: This topic affects exposure to Workforce disruption; Pandemic/health crisis; War/security crisis. It helps identify how disruption may impact operations, people, revenue, systems, legal exposure or recovery time. | H85: ISO 30414; ISO 30405; ISO 45001; ISO 22301; CIPD; SHRM | I85: Policy/SOP; owner/RACI; system report; dashboard; contracts; test records; incident history; interview evidence related to remote work capability with secure access, connectivity, equipment and documented procedures. | J85: 4 | K85: =_DATA_Assessment_Model!H85 -> 0 | L85: =_DATA_Assessment_Model!I85 -> 0 | M85: =_DATA_Assessment_Model!J85 -> 4 | N85: =_DATA_Assessment_Model!K85 -> 4 | O85: =_DATA_Assessment_Model!L85 -> Critical | P85: No reliable evidence that remote work capability with secure access, connectivity, equipment and documented procedures is defined, owned or managed. | Q85: Remote work capability with secure access, connectivity, equipment and documented procedures is handled informally and depends on individual knowledge or heroic effort. | R85: Remote work capability with secure access, connectivity, equipment and documented procedures is partially documented or implemented, but coverage is inconsistent and not crisis-tested. | S85: Remote work capability with secure access, connectivity, equipment and documented procedures is documented, owned, used in normal operations and supported by basic evidence or metrics. | T85: Remote work capability with secure access, connectivity, equipment and documented procedures is measured, periodically reviewed, integrated with related processes and tested against relevant disruption scenarios. | U85: Remote work capability with secure access, connectivity, equipment and documented procedures is optimized, continuously improved, automated where practical and demonstrably supports crisis resilience. | V85: Workforce disruption; Pandemic/health crisis; War/security crisis | Y85: Use the recommended action generated by the model; validate with domain owner during real assessment. | Z85: 4 | AA85: 5 | AB85: 5 | AM85: =_DATA_Assessment_Model!AJ85 -> 0.9 | AN85: =_DATA_Assessment_Model!AK85 -> 0.9 | AO85: =_DATA_Assessment_Model!AL85 -> 0 | AP85: =_DATA_Assessment_Model!AM85 -> 0 | AQ85: =_DATA_Assessment_Model!AN85 -> 0 | AR85: =_DATA_Assessment_Model!AO85 -> 0 | AS85: =_DATA_Assessment_Model!AP85 -> 0 | AT85: =_DATA_Assessment_Model!AQ85 -> 0 | ... AW85: =_DATA_Assessment_Model!AT85 -> 0.9 | AY85: =_DATA_Assessment_Model!AV85 -> 0.9
A86: HR Workforce | B86: HR Workforce | C86: 19 | D86: HRWO-015 | E86: Continuity and wellbeing | F86: How mature is the organization in managing backup connectivity options for critical staff and locations, including ownership, evidence, metrics, fallback procedures and crisis stress testing? | G86: This topic affects exposure to Workforce disruption; Pandemic/health crisis; War/security crisis. It helps identify how disruption may impact operations, people, revenue, systems, legal exposure or recovery time. | H86: ISO 30414; ISO 30405; ISO 45001; ISO 22301; CIPD; SHRM | I86: Policy/SOP; owner/RACI; system report; dashboard; contracts; test records; incident history; interview evidence related to backup connectivity options for critical staff and locations. | J86: 5 | K86: =_DATA_Assessment_Model!H86 -> 0 | L86: =_DATA_Assessment_Model!I86 -> 0 | M86: =_DATA_Assessment_Model!J86 -> 5 | N86: =_DATA_Assessment_Model!K86 -> 5 | O86: =_DATA_Assessment_Model!L86 -> Critical | P86: Does not exist; no owner, no documentation, no practice. | Q86: Ad hoc; depends entirely on specific individuals. | R86: Partially documented or implemented; coverage inconsistent; never tested under stress. | S86: Documented, owned, executed consistently; basic evidence and metrics exist. | T86: Measured and periodically tested/audited; integrated with adjacent processes. | U86: Optimized and automated where practical; stress-tested; benchmarked externally. | V86: Workforce disruption; Pandemic/health crisis; War/security crisis | Y86: Use the recommended action generated by the model; validate with domain owner during real assessment. | Z86: 5 | AA86: 5 | AB86: 5 | AM86: =_DATA_Assessment_Model!AJ86 -> 0.9 | AN86: =_DATA_Assessment_Model!AK86 -> 0.9 | AO86: =_DATA_Assessment_Model!AL86 -> 0 | AP86: =_DATA_Assessment_Model!AM86 -> 0 | AQ86: =_DATA_Assessment_Model!AN86 -> 0 | AR86: =_DATA_Assessment_Model!AO86 -> 0 | AS86: =_DATA_Assessment_Model!AP86 -> 0 | AT86: =_DATA_Assessment_Model!AQ86 -> 0 | ... AW86: =_DATA_Assessment_Model!AT86 -> 0.9 | AY86: =_DATA_Assessment_Model!AV86 -> 0.9
A87: HR Workforce | B87: HR Workforce | C87: 20 | D87: HRWO-016 | E87: Continuity and wellbeing | F87: How mature is the organization in managing employee location and safety check process during severe incidents, including ownership, evidence, metrics, fallback procedures and crisis stress testing? | G87: This topic affects exposure to Workforce disruption; Pandemic/health crisis; War/security crisis. It helps identify how disruption may impact operations, people, revenue, systems, legal exposure or recovery time. | H87: ISO 30414; ISO 30405; ISO 45001; ISO 22301; CIPD; SHRM | I87: Policy/SOP; owner/RACI; system report; dashboard; contracts; test records; incident history; interview evidence related to employee location and safety check process during severe incidents. | J87: 5 | K87: =_DATA_Assessment_Model!H87 -> 0 | L87: =_DATA_Assessment_Model!I87 -> 0 | M87: =_DATA_Assessment_Model!J87 -> 5 | N87: =_DATA_Assessment_Model!K87 -> 5 | O87: =_DATA_Assessment_Model!L87 -> Critical | P87: Does not exist; no owner, no documentation, no practice. | Q87: Ad hoc; depends entirely on specific individuals. | R87: Partially documented or implemented; coverage inconsistent; never tested under stress. | S87: Documented, owned, executed consistently; basic evidence and metrics exist. | T87: Measured and periodically tested/audited; integrated with adjacent processes. | U87: Optimized and automated where practical; stress-tested; benchmarked externally. | V87: Workforce disruption; Pandemic/health crisis; War/security crisis | Y87: Use the recommended action generated by the model; validate with domain owner during real assessment. | Z87: 4 | AA87: 5 | AB87: 5 | AM87: =_DATA_Assessment_Model!AJ87 -> 0.9 | AN87: =_DATA_Assessment_Model!AK87 -> 0.9 | AO87: =_DATA_Assessment_Model!AL87 -> 0 | AP87: =_DATA_Assessment_Model!AM87 -> 0 | AQ87: =_DATA_Assessment_Model!AN87 -> 0 | AR87: =_DATA_Assessment_Model!AO87 -> 0 | AS87: =_DATA_Assessment_Model!AP87 -> 0 | AT87: =_DATA_Assessment_Model!AQ87 -> 0 | ... AW87: =_DATA_Assessment_Model!AT87 -> 0.9 | AY87: =_DATA_Assessment_Model!AV87 -> 0.9
... A97: HR Workforce | B97: HR Workforce | C97: 30 | D97: HRWO-028 | E97: Workforce visibility | F97: How mature is the organization in managing workforce exposure to national emergency duties such as conscription, reservist service or civil mobilization, including exemption processes and continuity planning, including ownership, evidence, metrics, fallback procedures and crisis stress testing? | G97: This topic affects exposure to War/security crisis; Workforce disruption. It helps identify how disruption may impact operations, people, revenue, systems, legal exposure or recovery time. | H97: ISO 22301; national emergency and labor legislation; workforce planning | I97: Policy/SOP; owner/RACI; system report; dashboard; contracts; test records; incident history; interview evidence | J97: 4 | K97: =_DATA_Assessment_Model!H97 -> 0 | L97: =_DATA_Assessment_Model!I97 -> 0 | M97: =_DATA_Assessment_Model!J97 -> 4 | N97: =_DATA_Assessment_Model!K97 -> 4 | O97: =_DATA_Assessment_Model!L97 -> Critical | P97: No reliable evidence that workforce exposure to national emergency duties such as conscription, reservist service or civil mobilization, including exemption processes and continuity planning is defined, owned or managed. | Q97: Workforce exposure to national emergency duties such as conscription, reservist service or civil mobilization, including exemption processes and continuity planning is handled informally and depends on individual knowledge or heroic effort. | R97: Workforce exposure to national emergency duties such as conscription, reservist service or civil mobilization, including exemption processes and continuity planning is partially documented or implemented, but coverage is inconsistent and not crisis-tested. | S97: Workforce exposure to national emergency duties such as conscription, reservist service or civil mobilization, including exemption processes and continuity planning is documented, owned, used in normal operations and supported by basic evidence or metrics. | T97: Workforce exposure to national emergency duties such as conscription, reservist service or civil mobilization, including exemption processes and continuity planning is measured, periodically reviewed, integrated with related processes and tested against relevant disruption scenarios. | U97: Workforce exposure to national emergency duties such as conscription, reservist service or civil mobilization, including exemption processes and continuity planning is optimized, continuously improved, automated where practical and demonstrably supports crisis resilience. | V97: War/security crisis; Workforce disruption | Y97: Use the recommended action generated by the model; validate with domain owner during real assessment. | Z97: 2 | AA97: 5 | AB97: 4 | AM97: =_DATA_Assessment_Model!AJ97 -> 0.9 | AN97: =_DATA_Assessment_Model!AK97 -> 0.9 | AO97: =_DATA_Assessment_Model!AL97 -> 0 | AP97: =_DATA_Assessment_Model!AM97 -> 0 | AQ97: =_DATA_Assessment_Model!AN97 -> 0 | AR97: =_DATA_Assessment_Model!AO97 -> 0 | AS97: =_DATA_Assessment_Model!AP97 -> 0 | AT97: =_DATA_Assessment_Model!AQ97 -> 0 | ... AW97: =_DATA_Assessment_Model!AT97 -> 0.9 | AY97: =_DATA_Assessment_Model!AV97 -> 0.9
A98: Finance Procurement | B98: Finance Procurement | C98: 5 | D98: FINA-001 | E98: Financial resilience | F98: How mature is the organization in managing cash visibility by legal entity, bank, currency, restrictions and emergency access, including ownership, evidence, metrics, fallback procedures and crisis stress testing? | G98: This topic affects exposure to Financial / liquidity shock; Supplier disruption; Fraud risk. It helps identify how disruption may impact operations, people, revenue, systems, legal exposure or recovery time. | H98: COSO Internal Control; COSO ERM; IFRS; ISO 20400; ISO 37001; CIPS | I98: Policy/SOP; owner/RACI; system report; dashboard; contracts; test records; incident history; interview evidence related to cash visibility by legal entity, bank, currency, restrictions and emergency access. | J98: 5 | K98: =_DATA_Assessment_Model!H98 -> 0 | L98: =_DATA_Assessment_Model!I98 -> 0 | M98: =_DATA_Assessment_Model!J98 -> 5 | N98: =_DATA_Assessment_Model!K98 -> 5 | O98: =_DATA_Assessment_Model!L98 -> Critical | P98: Nothing is monitored or measured. | Q98: Occasional manual checks by individuals. | R98: Some metrics exist but are not reviewed regularly and trigger no action. | S98: Defined metrics with an owner, reviewed on a set cadence. | T98: Thresholds and alerts in place; deviations trigger documented action; trends analyzed. | U98: Automated monitoring with leading indicators, integrated into management decisions. | V98: Financial / liquidity shock; Supplier disruption; Fraud risk | Y98: Use the recommended action generated by the model; validate with domain owner during real assessment. | Z98: 4 | AA98: 5 | AB98: 5 | AD98: Financial resilience | AE98: =_DATA_Assessment_Model!AB98 -> 8 | AF98: =_DATA_Assessment_Model!AC98 -> 0 | AG98: =_DATA_Assessment_Model!AD98 -> 0 | AH98: =_DATA_Assessment_Model!AE98 -> 8 | AI98: =_DATA_Assessment_Model!AF98 -> 5 | AJ98: =_DATA_Assessment_Model!AG98 -> 8 | AM98: =_DATA_Assessment_Model!AJ98 -> 0.9 | AN98: =_DATA_Assessment_Model!AK98 -> 0.9 | AO98: =_DATA_Assessment_Model!AL98 -> 0 | AP98: =_DATA_Assessment_Model!AM98 -> 0 | AQ98: =_DATA_Assessment_Model!AN98 -> 0 | AR98: =_DATA_Assessment_Model!AO98 -> 0 | AS98: =_DATA_Assessment_Model!AP98 -> 0 | AT98: =_DATA_Assessment_Model!AQ98 -> 0 | ... AW98: =_DATA_Assessment_Model!AT98 -> 0.9 | AY98: =_DATA_Assessment_Model!AV98 -> 0.9
