Workbook
Name cfg_AboveOptimumRatio: _CONFIG_Model_Settings!$B$24
Name cfg_CrisisHighCut: _CONFIG_Model_Settings!$B$17
Name cfg_CrisisMedCut: _CONFIG_Model_Settings!$B$18
Name cfg_IndPriorityHigh: _CONFIG_Model_Settings!$B$19
Name cfg_IndPriorityLow: _CONFIG_Model_Settings!$B$20
Name cfg_RiskFitScale: _CONFIG_Model_Settings!$B$26
Name cfg_RiskSecondaryWeight: _CONFIG_Model_Settings!$B$25
Name cfg_ScenarioFitScale: _CONFIG_Model_Settings!$B$27
Name cfg_TimelineBucket1: _CONFIG_Model_Settings!$B$21
Name cfg_TimelineBucket2: _CONFIG_Model_Settings!$B$22
Name cfg_TimelineBucket3: _CONFIG_Model_Settings!$B$23
Name qn_AssessConf: _DATA_Assessment_Model!$AI$5:$AI$428
Name qn_Comments: _DATA_Assessment_Model!$U$5:$U$428
Name qn_Coverage: _DATA_Assessment_Model!$AU$5:$AU$428
Name qn_Domain: _DATA_Assessment_Model!$AW$5:$AW$428
Name qn_EvidConf: _DATA_Assessment_Model!$AH$5:$AH$428
Name qn_RiskLevel: _DATA_Assessment_Model!$L$5:$L$428
Name qn_Score: _DATA_Assessment_Model!$H$5:$H$428

Sheet ① START HERE
A1: RR-framework v1.992 — Logic Engine Template
A2: Clean workbook architecture: user inputs, consolidated outputs, engine/data layers and incremental safe staging cleanup. | B2: RR-framework v1.992 — crisis/fuzzy staging refactor; clean 20-sheet architecture for Excel logic prototype and future web app backend design.
A4: Recommended flow | B4: Sheet | C4: Purpose
A5: 1 | B5: Company Profile | C5: Enter company context: industry, size, geography, revenue model, critical dependencies.
A6: 2 | B6: Assessment Questions | C6: Complete 424-question assessment. This is the main input source for AS-IS and risk logic.
A7: 3 | B7: AS-IS Assessment | C7: Current state: maturity, diagnostics, gaps and domain-level view.
A8: 4 | B8: Resilience & Risk Scenario | C8: Scenario-adjusted state: crisis, fuzzy posture, resilience and risks.
A9: 5 | B9: Action Plan & Roadmap | C9: What to do next: recommendations, initiatives, P2 WSJF and roadmap waves.
A10: 6 | B10: Model Calibration | C10: Admin/consultant controls and parameter guidance.
A12: Visible sheets in v1.992 | B12: ① START HERE; Release & QA; Methodology, Controls & Std; Company Profile; Assessment Questions; AS-IS Assessment; Resilience & Risk Scenario; Action Plan & Roadmap; Model Calibration
A13: Legacy handling | B13: Legacy presentation/staging tabs have been removed. Consolidated visible workflow sheets now read from hidden data/engine/config layers.
A14: Architecture rule | B14: Visible layer = workflow. Hidden/veryHidden layers = source of truth, engines and configuration.
A18: Current architecture note | B18: v1.99 removes the redundant Executive Dashboard staging sheet. Consolidated visible sheets remain the workflow layer; hidden/veryHidden sheets hold data, config, staging and calculation engines.

Sheet Release & QA
A1: RR-framework v1.992 — Crisis/Fuzzy Staging Refactor
A2: Release status | B2: Clean template / calculation logic preserved / final crisis-fuzzy staging sheet removed
A3: Release status | B3: v1.992
A4: Build ID | B4: RR-FRAMEWORK-v1.992-CRISIS-FUZZY-STAGING-REFACTOR-20260619
A5: Current workbook architecture | B5: 20 sheets: 9 visible workflow sheets, 7 hidden data/config/helper sheets, 4 veryHidden engine sheets.
A6: Calculation policy | B6: Crisis scenario, fuzzy posture and crisis-domain multipliers now read from visible workflow inputs and engine/data layers; full recalculation on open is preserved.
A7: v1.992 refactor summary
A8: Change | B8: Status | C8: Notes
A9: Backlog | B9: Next architecture target: regression-test v1.992 against v1.81/v1.93 and consider optional final cleanup of any non-formula text references or unused hidden helper ranges. | C9: All legacy output/staging sheets have now been removed or absorbed into engine/data layers.
A10: Visible action layer switched to direct engine output | B10: Removed redundant scoring staging sheet; preserved AS-IS calculations through a hidden refactored scoring helper block in _DATA_Dashboard_Facts. | C10: Action Plan & Roadmap now owns initiative status input and reads initiative ranking directly from _ENGINE_Initiatives.
A11: Legacy roadmap staging removed | C11: No formulas, charts or workbook relationships reference Roadmap & Portfolio.
A12: Legacy AS-IS dashboard cleanup | C12: Executive Dashboard and AS-IS scoring staging removed. Crisis/Resilience/Fuzzy retained temporarily as calculation staging only.
A14: Backlog ID | B14: Backlog item | C14: Target release | D14: Acceptance criteria
A15: B-LEGACY-001 | B15: Completed: redundant Executive Dashboard removed after AS-IS Assessment was redirected to _DATA_Dashboard_Facts / engines. | C15: v1.99 done | D15: No formulas reference Executive Dashboard.
A16: B-LEGACY-002 | B16: Completed: Risk & Recommendations refactored into _ENGINE_Risk / _DATA_Mappings and removed. | C16: v1.97 done | D16: Risk-output, recommendation and strategy dependencies migrated before deletion.
A17: B-LEGACY-003 | B17: Completed: Roadmap & Portfolio removed after Action Plan & Roadmap took ownership of action/status workflow. | C17: v1.98 done | D17: Legacy sheet physically removed; Action Plan & Roadmap owns status/action workflow.
A18: B-ARCH-004 | B18: Migrate remaining crisis/resilience/fuzzy staging dependencies into engine/data layers; then move major backend tables to structured tables / ID-driven formulas. | C18: future | D18: Reduced row-offset risk and simpler web-app migration.
A20: QA check | B20: Expected result
A21: XLSX structure | B21: Valid workbook relationships and content types.
A22: Formula errors | B22: No #REF!, #DIV/0!, #VALUE!, #NAME? or #N/A tokens in formulas.
A23: Visible user flow | B23: 9 visible sheets; redundant Executive Dashboard removed; remaining staging tabs are hidden only because active formulas still depend on them.
A24: Recalculation | B24: Full recalculation on open preserved.

Sheet Methodology, Controls & Std
A1: Methodology, Controls & Standards — v1.992
A2: Current-state documentation for the consolidated logic prototype. This workbook is the calculation/methodology layer for the future web app; visual UX will be implemented in the web product. | B2: Current-state methodology for v1.992: 20-sheet architecture with crisis/fuzzy staging migrated into engine/data layers.
A3: Current calculation architecture | B3: AS-IS, crisis/fuzzy, risk, recommendation and roadmap logic now flow through consolidated visible workflow sheets and hidden engine/data layers without legacy presentation staging tabs.
A4: Layer | B4: Visible sheet / engine | C4: Purpose
A5: Risk engine | B5: _DATA_Assessment_Model, _DATA_Dashboard_Facts and _DATA_Mappings provide the normalized data layer for company profile, assessment and output facts. | C5: Capture company context and 424-question assessment data.
A6: Strategy engine | B6: _ENGINE_Risk, _ENGINE_Strategy and _ENGINE_Initiatives are the sources for risk outputs, strategy scoring, recommendations, initiative prioritization and roadmap logic. | C6: Combines executive summary and diagnostics into one current-state assessment layer.
A7: Scenario-adjusted state | B7: Resilience & Risk Scenario | C7: Combines crisis selection, resilience, fuzzy posture and risk exposure into one state interpretation layer.
A8: Action layer | B8: Action Plan & Roadmap | C8: Combines recommendations, initiatives, P2 WSJF and roadmap waves into one execution layer.
A9: Calibration | B9: Model Calibration; _CONFIG_Model_Settings; _CONFIG_Risk_Calibration | C9: Keeps visible controls separate from hidden source-of-truth parameters.
A10: Risk engine | B10: _ENGINE_Risk | C10: Calculates risk states, impact/probability, P1-adjusted risk score and now hosts the consolidated risk-output block used by visible scenario/action sheets.
A11: Initiative engine | B11: _ENGINE_Initiatives | C11: Calculates initiative value, risk reduction, P2 WSJF v3, rank and roadmap wave.
A12: Crisis/fuzzy engine | B12: _ENGINE_Crisis and _ENGINE_Fuzzy_Posture model crisis multipliers, cascade pressure, fuzzy membership and strategic posture. Scenario inputs are owned by Resilience & Risk Scenario. | C12: Models crisis multipliers, cascade pressure and fuzzy strategic posture.
A14: Fuzzy logic summary | B14: Fuzzy logic is an interpretation and prioritization-weighting layer. It converts maturity/risk pressure into membership across Fragile, Exposed, Adaptive, Resilient and Anti-fragile states. It does not overwrite baseline risk scores.
A15: Risk logic summary | B15: Baseline probability/impact are enhanced by P1 calibration: exposure, incident history, evidence uncertainty, dependency/cascade and red-line logic.
A16: WSJF logic summary | B16: P2 WSJF v3 uses fuzzy posture, client objective multipliers, financial value and risk-reduction pressure to prioritize initiatives.
A17: Governance rule | B17: One source of truth per parameter. Visible sheets may summarize or reference parameters, but hidden config/engine sheets own the calculation inputs.
A18: Legacy backlog rule | B18: Legacy deletion rule: physically remove staging sheets only after formulas are rewritten to engine/data layers and audit confirms zero remaining references.

Sheet Company Profile
A1: Company Profile — Assessment Context
A2: Fill this once per organization. This clean template contains no client/test profile data; profile answers drive targets, risk context, crisis interpretation and roadmap priorities.
A3: =HYPERLINK("#'① START HERE'!A1","⌂ START HERE") | C3: ✎ Input: edit coloured cells only — everything else is formula-driven.
A4: Profile field | B4: Value / input | C4: Guidance | D4: Used by | F4: How this sheet is used
A5: Organization name | C5: Legal or commercial name used in the assessment. | D5: Dashboard / executive summary | F5: 1. Define organization context and assessment boundaries. 2. Use Crisis Simulator for active scenario and severity. 3. Use Assessment date as the roadmap start date. 4. Use target scores to calibrate expected maturity level. 5. Keep LLM and financial analysis outside this workbook version.
A6: Assessment date | B6: =TODAY() | C6: Baseline date. Defaults to TODAY() and can be replaced by the actual assessment date. | D6: Gantt Roadmap
A7: Assessment owner | C7: Person responsible for coordinating the assessment. | D7: Quality Control
A8: Executive sponsor | C8: Senior owner who accepts priorities and crisis roadmap. | D8: Roadmap governance
A9: Industry | C9: Primary industry or sector. | D9: Strategy logic
A10: Sub-industry / segment | C10: More specific segment, e.g. manufacturing, SaaS, retail, healthcare. | D10: Strategy logic
A11: Headquarters country | C11: Country where the main legal or management entity is located. | D11: Risk context
A12: Operating countries / regions | C12: List countries, regions and key cities where the company operates. | D12: Geographical exposure
A13: Ownership type | C13: Private, public, state-owned, family-owned, PE-backed, NGO or other. | D13: Governance context
A14: Legal entities | C14: Main legal entities and subsidiaries. | D14: Legal / continuity context
A15: Employee count | C15: Total employees and contractors. | D15: HR / continuity logic
A16: Revenue size band | C16: Annual revenue band. | D16: Financial context, not calculation
A17: Operating model | C17: Centralized, decentralized, hub-and-spoke, remote-first, multi-site, franchise, hybrid. | D17: Crisis exposure
A18: Business model | C18: B2B, B2C, B2B2C, marketplace, subscription, project-based, manufacturing, distribution. | D18: GTM / resilience logic
... A28: Cloud and infrastructure model | C28: On-premise, public cloud, private cloud, hybrid, multi-cloud, SaaS-first. | D28: IT / DR strategy
A29: Primary crisis scenario to test | B29: ='Resilience & Risk Scenario'!$B$6 | C29: Active scenario is selected in Crisis Simulator. | D29: Crisis Simulator
A30: Scenario severity 1-5 | B30: ='Resilience & Risk Scenario'!$B$7 | C30: Active scenario severity is selected in Crisis Simulator. | D30: Crisis Simulator
A31: Target process maturity 0-5 | C31: Target level for process maturity. | D31: Gap analysis
A32: Target digitalization 0-5 | C32: Target level for implementation of digital technologies. | D32: Gap analysis
A33: Target resilience 0-5 | C33: Target level for resilience against relevant risks. | D33: Gap analysis
A34: Assessment cadence | C34: Quarterly, semi-annual, annual, or crisis-triggered review. | D34: Governance
A35: Risk appetite statement | C35: Closed choice: Low / Balanced / High. Low = risk-averse (targets tightened), High = more residual risk accepted (targets relaxed). Adjusts industry maturity targets across the model via _CONFIG_Model_Settings. | D35: Risk treatment
A36: Key assumptions / comments | C36: Context notes, assumptions, excluded scope or special assessment limitations. Leave blank until the real assessment is configured. | D36: All outputs
A38: Industry Template and Improved Scoring Logic
A39: Selected industry template | B39: =B9 | C39: Used as lookup key for domain weights, targets, criticality and recommendations.
A40: Default evidence confidence | B40: Medium | C40: Used when question-level evidence confidence is blank.
A41: Default assessor confidence | B41: Medium | C41: Used when question-level assessor confidence is blank.
A42: Template domains | B42: =COUNTIF(_REF_Model_Content!$A$1:$A$157,$B$9) | C42: Should equal 17 for a valid industry template.
A43: Average target maturity | B43: =IFERROR(ROUND(AVERAGEIFS(_REF_Model_Content!$D$1:$D$157,_REF_Model_Content!$A$1:$A$157,$B$9),2),"") | C43: Average expected maturity for selected industry.
A44: Average criticality multiplier | B44: =IFERROR(ROUND(AVERAGEIFS(_REF_Model_Content!$E$1:$E$157,_REF_Model_Content!$A$1:$A$157,$B$9),2),"") | C44: Higher value means industry makes weaknesses more material.
A45: Critical systems | B45: =IFERROR(INDEX(_REF_Model_Content!$H$1:$H$157,MATCH($B$9,_REF_Model_Content!$A$1:$A$157,0)),"") | C45: Typical systems that should be treated as critical for this industry.
A46: Red-line controls | B46: =IFERROR(INDEX(_REF_Model_Content!$I$1:$I$157,MATCH($B$9,_REF_Model_Content!$A$1:$A$157,0)),"") | C46: Minimum controls that should not be missing even if average maturity looks acceptable.
A47: Preferred strategy logic | B47: =IFERROR(INDEX(_REF_Model_Content!$L$1:$L$157,MATCH($B$9,_REF_Model_Content!$A$1:$A$157,0)),"") | C47: Strategies that receive extra relevance for this industry.
A49: Extended Company Context Inputs (closed answers only)
A50: Revenue model | C50: Primary revenue model used by the company. | D50: Risk, strategy and initiative logic
A51: Secondary revenue model | C51: Secondary or supporting monetization model. | D51: Revenue diversification logic
A52: Revenue recurrence | C52: Revenue stability profile. | D52: Crisis impact and revenue risk
A53: Primary sales motion | C53: Dominant sales motion. | D53: GTM and CRM strategy
A54: Customer concentration: top 1 client revenue share | C54: Estimated revenue share of the largest customer. | D54: Customer concentration risk
A55: Customer concentration: top 5 clients revenue share | C55: Estimated revenue share of top 5 customers. | D55: Customer concentration risk
A56: Customer concentration: top 10 clients revenue share | C56: Estimated revenue share of top 10 customers. | D56: Revenue diversification risk
A57: Supplier concentration: top 1 supplier dependency | C57: Estimated dependency on largest supplier/vendor/input. | D57: Supplier risk
A58: Supplier concentration: top 5 supplier dependency | C58: Estimated dependency on top 5 suppliers/vendors/inputs. | D58: Supply chain risk
A59: Critical supplier substitutability | C59: Availability of alternatives for critical suppliers. | D59: Supply chain resilience
A61: Business Criticality of Locations
A62: Location type | B62: Business criticality | C62: Disruption impact | D62: Continuity option | E62: Used by
A63: HQ | E63: Location and physical resilience logic
A64: Production site | E64: Location and physical resilience logic
A65: Warehouse | E65: Location and physical resilience logic
A66: Data center / core cloud region | E66: Location and physical resilience logic
A67: Call center / customer support center | E67: Location and physical resilience logic
A68: R&D / engineering center | E68: Location and physical resilience logic
A69: Sales office | E69: Location and physical resilience logic
A70: Retail / service branch | E70: Location and physical resilience logic
A72: Workforce Distribution
A73: Countries with workforce | C73: Workforce country footprint. | D73: Workforce/geographic concentration
A74: Largest country workforce share | C74: Estimated share of workforce in largest country. | D74: Workforce concentration risk
A75: Largest city/location workforce share | C75: Estimated share of workforce in largest city/site. | D75: Location concentration risk
A76: Remote work readiness | C76: Ability to continue work remotely. | D76: Pandemic/war/infrastructure resilience
A77: Cross-border mobility / relocation support | C77: Ability to relocate or support distributed workforce during crisis. | D77: Workforce continuity
A79: Critical Process List (select top processes)
A80: Critical process #1 | C80: Select one of the most business-critical processes. | D80: Risk, continuity and roadmap logic
A81: Critical process #2 | C81: Select one of the most business-critical processes. | D81: Risk, continuity and roadmap logic
A82: Critical process #3 | C82: Select one of the most business-critical processes. | D82: Risk, continuity and roadmap logic
A83: Critical process #4 | C83: Select one of the most business-critical processes. | D83: Risk, continuity and roadmap logic
A84: Critical process #5 | C84: Select one of the most business-critical processes. | D84: Risk, continuity and roadmap logic
A86: Critical Product / Service List (select top items)
A87: Critical product/service #1 | C87: Select one of the most critical products or services. | D87: Revenue and continuity logic
A88: Critical product/service #2 | C88: Select one of the most critical products or services. | D88: Revenue and continuity logic
A89: Critical product/service #3 | C89: Select one of the most critical products or services. | D89: Revenue and continuity logic
A90: Critical product/service #4 | C90: Select one of the most critical products or services. | D90: Revenue and continuity logic
A91: Critical product/service #5 | C91: Select one of the most critical products or services. | D91: Revenue and continuity logic
A93: Crisis History
A94: Experienced crisis | B94: Impact level | C94: Guidance | D94: Used by
A95: Pandemic | C95: Select a crisis the organization has already experienced and its observed impact. | D95: Calibration of scenario logic
A96: War / geopolitical escalation | C96: Select a crisis the organization has already experienced and its observed impact. | D96: Calibration of scenario logic
A97: Cyberattack / ransomware | C97: Select a crisis the organization has already experienced and its observed impact. | D97: Calibration of scenario logic
A98: Supply chain disruption | C98: Select a crisis the organization has already experienced and its observed impact. | D98: Calibration of scenario logic
A99: None experienced | C99: Select a crisis the organization has already experienced and its observed impact. | D99: Calibration of scenario logic
A101: Change Capacity and Brownfield
A102: Monthly change capacity (complexity points) | C102: Sum of initiative complexity points the organization can absorb per month. Rule of thumb: ~3 points per dedicated change FTE; adjust by transformation experience. Used as the overload threshold in Gantt Roadmap. | D102: Gantt Roadmap
A103: Transformation experience | C103: Low = few successful change programs (reduce capacity); High = mature PMO and delivery track record. | D103: Capacity guidance
A104: Brownfield note | C104: Mark initiatives already underway or completed on the Initiative Status sheet. Done / Not applicable items are excluded from rankings and the roadmap; In progress items keep consuming capacity.
A105: Company size band | C105: Peer benchmarks are size-adjusted. Eurostat DII shows ~1-level digital maturity gap between SMEs and large enterprises. | D105: Benchmark View
A107: Financial Anchors (hard data)
A108: Annual revenue band | C108: Pick the closest band. Used to monetize risks (cost of inaction) and size revenue-at-risk. | D108: Financial Resilience / Cost of inaction
A109: Gross margin % | C109: Approximate gross margin as decimal (0.35 = 35%). Used for EBITDA-proxy impact. | D109: Financial Resilience / Cost of inaction
A110: Cash runway (months if sales stop) | C110: Months the company survives on cash + committed financing with zero new sales. | D110: Financial Resilience / Cost of inaction
A111: Debt load | C111: Qualitative leverage level relative to EBITDA. | D111: Financial Resilience / Cost of inaction
A112: FX exposure (foreign-currency revenue share) | C112: Share of revenue in currencies other than the cost base. | D112: Financial Resilience / Cost of inaction
A113: Revenue midpoint used (EUR k) | B113: =_xlfn.IFNA(VLOOKUP($B$108,_CONFIG_Model_Settings!$A$154:$B$158,2,0),12500) | C113: Calculated from the revenue band. Override with the exact number if known.

Sheet Assessment Questions
A1: Assessment Questions — Consolidated Input
A2: Main assessment surface with all 424 questions. Use green/input columns for answers, evidence confidence, coverage, owners and comments.
A3: =HYPERLINK("#'① START HERE'!A1","⌂ START HERE") | C3: ✎ Input: edit answer / confidence / comment columns only — the rest is formula-driven.
A4: Domain | B4: Source sheet | C4: Source row | D4: ID | E4: Subdomain | F4: Question | G4: Crisis relevance / why it matters | H4: Standards / frameworks | I4: Evidence to request | J4: Weight 1-5 | K4: Score 0-5 (auto from answer) | L4: Weighted score | M4: Max score | N4: Gap | O4: Risk level | P4: Score 0 criteria | Q4: Score 1 criteria | R4: Score 2 criteria | S4: Score 3 criteria | T4: Score 4 criteria | U4: Score 5 criteria | V4: Crisis scenario tags | W4: Owner / SME | X4: Comments / findings | Y4: Recommended action | Z4: Digitalization relevance 0-5 | AA4: Resilience relevance 0-5 | AB4: Process maturity relevance 0-5 | AC4: Answer - select stage | AD4: Subarea | AE4: Questions | AF4: Avg score 0-5 | AG4: Maturity % | AH4: Critical/High | AI4: Gap to 5 | AJ4: Answered | AK4: Evidence confidence | AL4: Assessor confidence | AM4: Evidence factor | AN4: Assessor factor | AO4: Confidence-adjusted score 0-5 | AP4: Normalized score 0-100 | AQ4: Industry target 0-5 | AR4: Gap to industry target | AS4: Industry criticality multiplier | AT4: Industry-adjusted gap priority | AU4: Improved scoring note | AV4: v2 conf-adj score | AW4: v2 conf factor | AX4: Coverage (how widely deployed) | AY4: Coverage factor
A5: Company Geography | B5: Company Geography | C5: 5 | D5: COMP-001 | E5: Company profile | F5: How mature is the organization in managing legal entity structure, ownership, subsidiaries and operating countries, including ownership, evidence, metrics, fallback procedures and crisis stress testing? | G5: This topic affects exposure to Geopolitical risk; Physical site loss; Regulatory/legal shock. It helps identify how disruption may impact operations, people, revenue, systems, legal exposure or recovery time. | H5: ISO 22301; ISO 31000; ISO 9001; ISO 37000; PESTLE; Business Model Canvas | I5: Policy/SOP; owner/RACI; system report; dashboard; contracts; test records; incident history; interview evidence related to legal entity structure, ownership, subsidiaries and operating countries. | J5: 3 | K5: =_DATA_Assessment_Model!H5 | L5: =_DATA_Assessment_Model!I5 | M5: =_DATA_Assessment_Model!J5 | N5: =_DATA_Assessment_Model!K5 | O5: =_DATA_Assessment_Model!L5 | P5: No reliable evidence that legal entity structure, ownership, subsidiaries and operating countries is defined, owned or managed. | Q5: Legal entity structure, ownership, subsidiaries and operating countries is handled informally and depends on individual knowledge or heroic effort. | R5: Legal entity structure, ownership, subsidiaries and operating countries is partially documented or implemented, but coverage is inconsistent and not crisis-tested. | S5: Legal entity structure, ownership, subsidiaries and operating countries is documented, owned, used in normal operations and supported by basic evidence or metrics. | T5: Legal entity structure, ownership, subsidiaries and operating countries is measured, periodically reviewed, integrated with related processes and tested against relevant disruption scenarios. | U5: Legal entity structure, ownership, subsidiaries and operating countries is optimized, continuously improved, automated where practical and demonstrably supports crisis resilience. | V5: Geopolitical risk; Physical site loss; Regulatory/legal shock | Y5: Use the recommended action generated by the model; validate with domain owner during real assessment. | Z5: 4 | AA5: 5 | AB5: 5 | AD5: Company profile | AE5: =_DATA_Assessment_Model!AB5 | AF5: =_DATA_Assessment_Model!AC5 | AG5: =_DATA_Assessment_Model!AD5 | AH5: =_DATA_Assessment_Model!AE5 | AI5: =_DATA_Assessment_Model!AF5 | AJ5: =_DATA_Assessment_Model!AG5 | AM5: =_DATA_Assessment_Model!AJ5 | AN5: =_DATA_Assessment_Model!AK5 | AO5: =_DATA_Assessment_Model!AL5 | AP5: =_DATA_Assessment_Model!AM5 | AQ5: =_DATA_Assessment_Model!AN5 | AR5: =_DATA_Assessment_Model!AO5 | AS5: =_DATA_Assessment_Model!AP5 | AT5: =_DATA_Assessment_Model!AQ5 | ... AW5: =_DATA_Assessment_Model!AT5 | AY5: =_DATA_Assessment_Model!AV5
A6: Company Geography | B6: Company Geography | C6: 6 | D6: COMP-002 | E6: Company profile | F6: How mature is the organization in managing business model, value proposition, revenue streams and cost drivers, including ownership, evidence, metrics, fallback procedures and crisis stress testing? | G6: This topic affects exposure to Geopolitical risk; Physical site loss; Regulatory/legal shock. It helps identify how disruption may impact operations, people, revenue, systems, legal exposure or recovery time. | H6: ISO 22301; ISO 31000; ISO 9001; ISO 37000; PESTLE; Business Model Canvas | I6: Policy/SOP; owner/RACI; system report; dashboard; contracts; test records; incident history; interview evidence related to business model, value proposition, revenue streams and cost drivers. | J6: 5 | K6: =_DATA_Assessment_Model!H6 | L6: =_DATA_Assessment_Model!I6 | M6: =_DATA_Assessment_Model!J6 | N6: =_DATA_Assessment_Model!K6 | O6: =_DATA_Assessment_Model!L6 | P6: Does not exist; no owner, no documentation, no practice. | Q6: Ad hoc; depends entirely on specific individuals. | R6: Partially documented or implemented; coverage inconsistent; never tested under stress. | S6: Documented, owned, executed consistently; basic evidence and metrics exist. | T6: Measured and periodically tested/audited; integrated with adjacent processes. | U6: Optimized and automated where practical; stress-tested; benchmarked externally. | V6: Geopolitical risk; Physical site loss; Regulatory/legal shock | Y6: Use the recommended action generated by the model; validate with domain owner during real assessment. | Z6: 4 | AA6: 5 | AB6: 5 | AD6: Geographical distribution | AE6: =_DATA_Assessment_Model!AB6 | AF6: =_DATA_Assessment_Model!AC6 | AG6: =_DATA_Assessment_Model!AD6 | AH6: =_DATA_Assessment_Model!AE6 | AI6: =_DATA_Assessment_Model!AF6 | AJ6: =_DATA_Assessment_Model!AG6 | AM6: =_DATA_Assessment_Model!AJ6 | AN6: =_DATA_Assessment_Model!AK6 | AO6: =_DATA_Assessment_Model!AL6 | AP6: =_DATA_Assessment_Model!AM6 | AQ6: =_DATA_Assessment_Model!AN6 | AR6: =_DATA_Assessment_Model!AO6 | AS6: =_DATA_Assessment_Model!AP6 | AT6: =_DATA_Assessment_Model!AQ6 | ... AW6: =_DATA_Assessment_Model!AT6 | AY6: =_DATA_Assessment_Model!AV6
A7: Company Geography | B7: Company Geography | C7: 7 | D7: COMP-003 | E7: Company profile | F7: How mature is the organization in managing critical products and services ranked by revenue, margin and continuity priority, including ownership, evidence, metrics, fallback procedures and crisis stress testing? | G7: This topic affects exposure to Geopolitical risk; Physical site loss; Regulatory/legal shock. It helps identify how disruption may impact operations, people, revenue, systems, legal exposure or recovery time. | H7: ISO 22301; ISO 31000; ISO 9001; ISO 37000; PESTLE; Business Model Canvas | I7: Policy/SOP; owner/RACI; system report; dashboard; contracts; test records; incident history; interview evidence related to critical products and services ranked by revenue, margin and continuity priority. | J7: 5 | K7: =_DATA_Assessment_Model!H7 | L7: =_DATA_Assessment_Model!I7 | M7: =_DATA_Assessment_Model!J7 | N7: =_DATA_Assessment_Model!K7 | O7: =_DATA_Assessment_Model!L7 | P7: Does not exist; no owner, no documentation, no practice. | Q7: Ad hoc; depends entirely on specific individuals. | R7: Partially documented or implemented; coverage inconsistent; never tested under stress. | S7: Documented, owned, executed consistently; basic evidence and metrics exist. | T7: Measured and periodically tested/audited; integrated with adjacent processes. | U7: Optimized and automated where practical; stress-tested; benchmarked externally. | V7: Geopolitical risk; Physical site loss; Regulatory/legal shock | Y7: Use the recommended action generated by the model; validate with domain owner during real assessment. | Z7: 4 | AA7: 5 | AB7: 5 | AD7: Context and dependencies | AE7: =_DATA_Assessment_Model!AB7 | AF7: =_DATA_Assessment_Model!AC7 | AG7: =_DATA_Assessment_Model!AD7 | AH7: =_DATA_Assessment_Model!AE7 | AI7: =_DATA_Assessment_Model!AF7 | AJ7: =_DATA_Assessment_Model!AG7 | AM7: =_DATA_Assessment_Model!AJ7 | AN7: =_DATA_Assessment_Model!AK7 | AO7: =_DATA_Assessment_Model!AL7 | AP7: =_DATA_Assessment_Model!AM7 | AQ7: =_DATA_Assessment_Model!AN7 | AR7: =_DATA_Assessment_Model!AO7 | AS7: =_DATA_Assessment_Model!AP7 | AT7: =_DATA_Assessment_Model!AQ7 | ... AW7: =_DATA_Assessment_Model!AT7 | AY7: =_DATA_Assessment_Model!AV7
A8: Company Geography | B8: Company Geography | C8: 8 | D8: COMP-004 | E8: Company profile | F8: How mature is the organization in managing operating model: centralized, distributed, outsourced, remote or hybrid, including ownership, evidence, metrics, fallback procedures and crisis stress testing? | G8: This topic affects exposure to Geopolitical risk; Physical site loss; Regulatory/legal shock. It helps identify how disruption may impact operations, people, revenue, systems, legal exposure or recovery time. | H8: ISO 22301; ISO 31000; ISO 9001; ISO 37000; PESTLE; Business Model Canvas | I8: Policy/SOP; owner/RACI; system report; dashboard; contracts; test records; incident history; interview evidence related to operating model: centralized, distributed, outsourced, remote or hybrid. | J8: 4 | K8: =_DATA_Assessment_Model!H8 | L8: =_DATA_Assessment_Model!I8 | M8: =_DATA_Assessment_Model!J8 | N8: =_DATA_Assessment_Model!K8 | O8: =_DATA_Assessment_Model!L8 | P8: No reliable evidence that operating model: centralized, distributed, outsourced, remote or hybrid is defined, owned or managed. | Q8: Operating model: centralized, distributed, outsourced, remote or hybrid is handled informally and depends on individual knowledge or heroic effort. | R8: Operating model: centralized, distributed, outsourced, remote or hybrid is partially documented or implemented, but coverage is inconsistent and not crisis-tested. | S8: Operating model: centralized, distributed, outsourced, remote or hybrid is documented, owned, used in normal operations and supported by basic evidence or metrics. | T8: Operating model: centralized, distributed, outsourced, remote or hybrid is measured, periodically reviewed, integrated with related processes and tested against relevant disruption scenarios. | U8: Operating model: centralized, distributed, outsourced, remote or hybrid is optimized, continuously improved, automated where practical and demonstrably supports crisis resilience. | V8: Geopolitical risk; Physical site loss; Regulatory/legal shock | Y8: Use the recommended action generated by the model; validate with domain owner during real assessment. | Z8: 4 | AA8: 5 | AB8: 5 | AM8: =_DATA_Assessment_Model!AJ8 | AN8: =_DATA_Assessment_Model!AK8 | AO8: =_DATA_Assessment_Model!AL8 | AP8: =_DATA_Assessment_Model!AM8 | AQ8: =_DATA_Assessment_Model!AN8 | AR8: =_DATA_Assessment_Model!AO8 | AS8: =_DATA_Assessment_Model!AP8 | AT8: =_DATA_Assessment_Model!AQ8 | ... AW8: =_DATA_Assessment_Model!AT8 | AY8: =_DATA_Assessment_Model!AV8
A9: Company Geography | B9: Company Geography | C9: 9 | D9: COMP-005 | E9: Company profile | F9: How mature is the organization in managing critical assets: people, facilities, systems, data, equipment and intellectual property, including ownership, evidence, metrics, fallback procedures and crisis stress testing? | G9: This topic affects exposure to Geopolitical risk; Physical site loss; Regulatory/legal shock. It helps identify how disruption may impact operations, people, revenue, systems, legal exposure or recovery time. | H9: ISO 22301; ISO 31000; ISO 9001; ISO 37000; PESTLE; Business Model Canvas | I9: Policy/SOP; owner/RACI; system report; dashboard; contracts; test records; incident history; interview evidence related to critical assets: people, facilities, systems, data, equipment and intellectual property. | J9: 5 | K9: =_DATA_Assessment_Model!H9 | L9: =_DATA_Assessment_Model!I9 | M9: =_DATA_Assessment_Model!J9 | N9: =_DATA_Assessment_Model!K9 | O9: =_DATA_Assessment_Model!L9 | P9: Does not exist; no owner, no documentation, no practice. | Q9: Ad hoc; depends entirely on specific individuals. | R9: Partially documented or implemented; coverage inconsistent; never tested under stress. | S9: Documented, owned, executed consistently; basic evidence and metrics exist. | T9: Measured and periodically tested/audited; integrated with adjacent processes. | U9: Optimized and automated where practical; stress-tested; benchmarked externally. | V9: Geopolitical risk; Physical site loss; Regulatory/legal shock | Y9: Use the recommended action generated by the model; validate with domain owner during real assessment. | Z9: 5 | AA9: 5 | AB9: 5 | AM9: =_DATA_Assessment_Model!AJ9 | AN9: =_DATA_Assessment_Model!AK9 | AO9: =_DATA_Assessment_Model!AL9 | AP9: =_DATA_Assessment_Model!AM9 | AQ9: =_DATA_Assessment_Model!AN9 | AR9: =_DATA_Assessment_Model!AO9 | AS9: =_DATA_Assessment_Model!AP9 | AT9: =_DATA_Assessment_Model!AQ9 | ... AW9: =_DATA_Assessment_Model!AT9 | AY9: =_DATA_Assessment_Model!AV9
A10: Company Geography | B10: Company Geography | C10: 10 | D10: COMP-006 | E10: Company profile | F10: How mature is the organization in managing regulatory exposure by country, market, product and customer type, including ownership, evidence, metrics, fallback procedures and crisis stress testing? | G10: This topic affects exposure to Geopolitical risk; Physical site loss; Regulatory/legal shock. It helps identify how disruption may impact operations, people, revenue, systems, legal exposure or recovery time. | H10: ISO 22301; ISO 31000; ISO 9001; ISO 37000; PESTLE; Business Model Canvas | I10: Policy/SOP; owner/RACI; system report; dashboard; contracts; test records; incident history; interview evidence related to regulatory exposure by country, market, product and customer type. | J10: 4 | K10: =_DATA_Assessment_Model!H10 | L10: =_DATA_Assessment_Model!I10 | M10: =_DATA_Assessment_Model!J10 | N10: =_DATA_Assessment_Model!K10 | O10: =_DATA_Assessment_Model!L10 | P10: No reliable evidence that regulatory exposure by country, market, product and customer type is defined, owned or managed. | Q10: Regulatory exposure by country, market, product and customer type is handled informally and depends on individual knowledge or heroic effort. | R10: Regulatory exposure by country, market, product and customer type is partially documented or implemented, but coverage is inconsistent and not crisis-tested. | S10: Regulatory exposure by country, market, product and customer type is documented, owned, used in normal operations and supported by basic evidence or metrics. | T10: Regulatory exposure by country, market, product and customer type is measured, periodically reviewed, integrated with related processes and tested against relevant disruption scenarios. | U10: Regulatory exposure by country, market, product and customer type is optimized, continuously improved, automated where practical and demonstrably supports crisis resilience. | V10: Geopolitical risk; Physical site loss; Regulatory/legal shock | Y10: Use the recommended action generated by the model; validate with domain owner during real assessment. | Z10: 4 | AA10: 5 | AB10: 5 | AM10: =_DATA_Assessment_Model!AJ10 | AN10: =_DATA_Assessment_Model!AK10 | AO10: =_DATA_Assessment_Model!AL10 | AP10: =_DATA_Assessment_Model!AM10 | AQ10: =_DATA_Assessment_Model!AN10 | AR10: =_DATA_Assessment_Model!AO10 | AS10: =_DATA_Assessment_Model!AP10 | AT10: =_DATA_Assessment_Model!AQ10 | ... AW10: =_DATA_Assessment_Model!AT10 | AY10: =_DATA_Assessment_Model!AV10
A11: Company Geography | B11: Company Geography | C11: 11 | D11: COMP-007 | E11: Company profile | F11: How mature is the organization in managing insurance coverage for business interruption, cyber, liability, property and key assets, including ownership, evidence, metrics, fallback procedures and crisis stress testing? | G11: This topic affects exposure to Geopolitical risk; Physical site loss; Regulatory/legal shock. It helps identify how disruption may impact operations, people, revenue, systems, legal exposure or recovery time. | H11: ISO 22301; ISO 31000; ISO 9001; ISO 37000; PESTLE; Business Model Canvas | I11: Policy/SOP; owner/RACI; system report; dashboard; contracts; test records; incident history; interview evidence related to insurance coverage for business interruption, cyber, liability, property and key assets. | J11: 5 | K11: =_DATA_Assessment_Model!H11 | L11: =_DATA_Assessment_Model!I11 | M11: =_DATA_Assessment_Model!J11 | N11: =_DATA_Assessment_Model!K11 | O11: =_DATA_Assessment_Model!L11 | P11: Does not exist; no owner, no documentation, no practice. | Q11: Ad hoc; depends entirely on specific individuals. | R11: Partially documented or implemented; coverage inconsistent; never tested under stress. | S11: Documented, owned, executed consistently; basic evidence and metrics exist. | T11: Measured and periodically tested/audited; integrated with adjacent processes. | U11: Optimized and automated where practical; stress-tested; benchmarked externally. | V11: Geopolitical risk; Physical site loss; Regulatory/legal shock | Y11: Use the recommended action generated by the model; validate with domain owner during real assessment. | Z11: 5 | AA11: 5 | AB11: 5 | AM11: =_DATA_Assessment_Model!AJ11 | AN11: =_DATA_Assessment_Model!AK11 | AO11: =_DATA_Assessment_Model!AL11 | AP11: =_DATA_Assessment_Model!AM11 | AQ11: =_DATA_Assessment_Model!AN11 | AR11: =_DATA_Assessment_Model!AO11 | AS11: =_DATA_Assessment_Model!AP11 | AT11: =_DATA_Assessment_Model!AQ11 | ... AW11: =_DATA_Assessment_Model!AT11 | AY11: =_DATA_Assessment_Model!AV11
A12: Company Geography | B12: Company Geography | C12: 12 | D12: COMP-008 | E12: Geographical distribution | F12: How mature is the organization in managing workforce distribution by country, city, function, contract type and criticality, including ownership, evidence, metrics, fallback procedures and crisis stress testing? | G12: This topic affects exposure to Geopolitical risk; Physical site loss; Regulatory/legal shock. It helps identify how disruption may impact operations, people, revenue, systems, legal exposure or recovery time. | H12: ISO 22301; ISO 31000; ISO 9001; ISO 37000; PESTLE; Business Model Canvas | I12: Policy/SOP; owner/RACI; system report; dashboard; contracts; test records; incident history; interview evidence related to workforce distribution by country, city, function, contract type and criticality. | J12: 5 | K12: =_DATA_Assessment_Model!H12 | L12: =_DATA_Assessment_Model!I12 | M12: =_DATA_Assessment_Model!J12 | N12: =_DATA_Assessment_Model!K12 | O12: =_DATA_Assessment_Model!L12 | P12: Does not exist; no owner, no documentation, no practice. | Q12: Ad hoc; depends entirely on specific individuals. | R12: Partially documented or implemented; coverage inconsistent; never tested under stress. | S12: Documented, owned, executed consistently; basic evidence and metrics exist. | T12: Measured and periodically tested/audited; integrated with adjacent processes. | U12: Optimized and automated where practical; stress-tested; benchmarked externally. | V12: Geopolitical risk; Physical site loss; Regulatory/legal shock | Y12: Use the recommended action generated by the model; validate with domain owner during real assessment. | Z12: 4 | AA12: 5 | AB12: 5 | AM12: =_DATA_Assessment_Model!AJ12 | AN12: =_DATA_Assessment_Model!AK12 | AO12: =_DATA_Assessment_Model!AL12 | AP12: =_DATA_Assessment_Model!AM12 | AQ12: =_DATA_Assessment_Model!AN12 | AR12: =_DATA_Assessment_Model!AO12 | AS12: =_DATA_Assessment_Model!AP12 | AT12: =_DATA_Assessment_Model!AQ12 | ... AW12: =_DATA_Assessment_Model!AT12 | AY12: =_DATA_Assessment_Model!AV12
A13: Company Geography | B13: Company Geography | C13: 13 | D13: COMP-009 | E13: Geographical distribution | F13: How mature is the organization in managing site distribution across offices, plants, warehouses, stores, labs and data centers, including ownership, evidence, metrics, fallback procedures and crisis stress testing? | G13: This topic affects exposure to Geopolitical risk; Physical site loss; Regulatory/legal shock. It helps identify how disruption may impact operations, people, revenue, systems, legal exposure or recovery time. | H13: ISO 22301; ISO 31000; ISO 9001; ISO 37000; PESTLE; Business Model Canvas | I13: Policy/SOP; owner/RACI; system report; dashboard; contracts; test records; incident history; interview evidence related to site distribution across offices, plants, warehouses, stores, labs and data centers. | J13: 5 | K13: =_DATA_Assessment_Model!H13 | L13: =_DATA_Assessment_Model!I13 | M13: =_DATA_Assessment_Model!J13 | N13: =_DATA_Assessment_Model!K13 | O13: =_DATA_Assessment_Model!L13 | P13: No plan or procedure exists. | Q13: Knowledge lives with individuals; nothing usable is written down. | R13: Drafted but outdated, not approved, or unknown to the people who must use it. | S13: Approved and current; owners assigned; affected staff know it exists and where to find it. | T13: Tested against realistic scenarios; updated after each test or real incident. | U13: Exercised regularly including external parties; readiness measured; continuously improved. | V13: Geopolitical risk; Physical site loss; Regulatory/legal shock | Y13: Use the recommended action generated by the model; validate with domain owner during real assessment. | Z13: 5 | AA13: 5 | AB13: 5 | AM13: =_DATA_Assessment_Model!AJ13 | AN13: =_DATA_Assessment_Model!AK13 | AO13: =_DATA_Assessment_Model!AL13 | AP13: =_DATA_Assessment_Model!AM13 | AQ13: =_DATA_Assessment_Model!AN13 | AR13: =_DATA_Assessment_Model!AO13 | AS13: =_DATA_Assessment_Model!AP13 | AT13: =_DATA_Assessment_Model!AQ13 | ... AW13: =_DATA_Assessment_Model!AT13 | AY13: =_DATA_Assessment_Model!AV13
A14: Company Geography | B14: Company Geography | C14: 14 | D14: COMP-010 | E14: Geographical distribution | F14: How mature is the organization in managing revenue distribution by country, currency, customer geography and market exposure, including ownership, evidence, metrics, fallback procedures and crisis stress testing? | G14: This topic affects exposure to Geopolitical risk; Physical site loss; Regulatory/legal shock. It helps identify how disruption may impact operations, people, revenue, systems, legal exposure or recovery time. | H14: ISO 22301; ISO 31000; ISO 9001; ISO 37000; PESTLE; Business Model Canvas | I14: Policy/SOP; owner/RACI; system report; dashboard; contracts; test records; incident history; interview evidence related to revenue distribution by country, currency, customer geography and market exposure. | J14: 4 | K14: =_DATA_Assessment_Model!H14 | L14: =_DATA_Assessment_Model!I14 | M14: =_DATA_Assessment_Model!J14 | N14: =_DATA_Assessment_Model!K14 | O14: =_DATA_Assessment_Model!L14 | P14: No reliable evidence that revenue distribution by country, currency, customer geography and market exposure is defined, owned or managed. | Q14: Revenue distribution by country, currency, customer geography and market exposure is handled informally and depends on individual knowledge or heroic effort. | R14: Revenue distribution by country, currency, customer geography and market exposure is partially documented or implemented, but coverage is inconsistent and not crisis-tested. | S14: Revenue distribution by country, currency, customer geography and market exposure is documented, owned, used in normal operations and supported by basic evidence or metrics. | T14: Revenue distribution by country, currency, customer geography and market exposure is measured, periodically reviewed, integrated with related processes and tested against relevant disruption scenarios. | U14: Revenue distribution by country, currency, customer geography and market exposure is optimized, continuously improved, automated where practical and demonstrably supports crisis resilience. | V14: Geopolitical risk; Physical site loss; Regulatory/legal shock | Y14: Use the recommended action generated by the model; validate with domain owner during real assessment. | Z14: 4 | AA14: 5 | AB14: 5 | AM14: =_DATA_Assessment_Model!AJ14 | AN14: =_DATA_Assessment_Model!AK14 | AO14: =_DATA_Assessment_Model!AL14 | AP14: =_DATA_Assessment_Model!AM14 | AQ14: =_DATA_Assessment_Model!AN14 | AR14: =_DATA_Assessment_Model!AO14 | AS14: =_DATA_Assessment_Model!AP14 | AT14: =_DATA_Assessment_Model!AQ14 | ... AW14: =_DATA_Assessment_Model!AT14 | AY14: =_DATA_Assessment_Model!AV14
A15: Company Geography | B15: Company Geography | C15: 15 | D15: COMP-011 | E15: Geographical distribution | F15: How mature is the organization in managing supplier distribution by country, tier, criticality and replacement options, including ownership, evidence, metrics, fallback procedures and crisis stress testing? | G15: This topic affects exposure to Geopolitical risk; Physical site loss; Regulatory/legal shock. It helps identify how disruption may impact operations, people, revenue, systems, legal exposure or recovery time. | H15: ISO 22301; ISO 31000; ISO 9001; ISO 37000; PESTLE; Business Model Canvas | I15: Policy/SOP; owner/RACI; system report; dashboard; contracts; test records; incident history; interview evidence related to supplier distribution by country, tier, criticality and replacement options. | J15: 5 | K15: =_DATA_Assessment_Model!H15 | L15: =_DATA_Assessment_Model!I15 | M15: =_DATA_Assessment_Model!J15 | N15: =_DATA_Assessment_Model!K15 | O15: =_DATA_Assessment_Model!L15 | P15: Does not exist; no owner, no documentation, no practice. | Q15: Ad hoc; depends entirely on specific individuals. | R15: Partially documented or implemented; coverage inconsistent; never tested under stress. | S15: Documented, owned, executed consistently; basic evidence and metrics exist. | T15: Measured and periodically tested/audited; integrated with adjacent processes. | U15: Optimized and automated where practical; stress-tested; benchmarked externally. | V15: Geopolitical risk; Physical site loss; Regulatory/legal shock | Y15: Use the recommended action generated by the model; validate with domain owner during real assessment. | Z15: 4 | AA15: 5 | AB15: 5 | AM15: =_DATA_Assessment_Model!AJ15 | AN15: =_DATA_Assessment_Model!AK15 | AO15: =_DATA_Assessment_Model!AL15 | AP15: =_DATA_Assessment_Model!AM15 | AQ15: =_DATA_Assessment_Model!AN15 | AR15: =_DATA_Assessment_Model!AO15 | AS15: =_DATA_Assessment_Model!AP15 | AT15: =_DATA_Assessment_Model!AQ15 | ... AW15: =_DATA_Assessment_Model!AT15 | AY15: =_DATA_Assessment_Model!AV15
A16: Company Geography | B16: Company Geography | C16: 16 | D16: COMP-012 | E16: Geographical distribution | F16: How mature is the organization in managing customer distribution by geography, industry, contract and crisis sensitivity, including ownership, evidence, metrics, fallback procedures and crisis stress testing? | G16: This topic affects exposure to Geopolitical risk; Physical site loss; Regulatory/legal shock. It helps identify how disruption may impact operations, people, revenue, systems, legal exposure or recovery time. | H16: ISO 22301; ISO 31000; ISO 9001; ISO 37000; PESTLE; Business Model Canvas | I16: Policy/SOP; owner/RACI; system report; dashboard; contracts; test records; incident history; interview evidence related to customer distribution by geography, industry, contract and crisis sensitivity. | J16: 5 | K16: =_DATA_Assessment_Model!H16 | L16: =_DATA_Assessment_Model!I16 | M16: =_DATA_Assessment_Model!J16 | N16: =_DATA_Assessment_Model!K16 | O16: =_DATA_Assessment_Model!L16 | P16: Does not exist; no owner, no documentation, no practice. | Q16: Ad hoc; depends entirely on specific individuals. | R16: Partially documented or implemented; coverage inconsistent; never tested under stress. | S16: Documented, owned, executed consistently; basic evidence and metrics exist. | T16: Measured and periodically tested/audited; integrated with adjacent processes. | U16: Optimized and automated where practical; stress-tested; benchmarked externally. | V16: Geopolitical risk; Physical site loss; Regulatory/legal shock | Y16: Use the recommended action generated by the model; validate with domain owner during real assessment. | Z16: 4 | AA16: 5 | AB16: 5 | AM16: =_DATA_Assessment_Model!AJ16 | AN16: =_DATA_Assessment_Model!AK16 | AO16: =_DATA_Assessment_Model!AL16 | AP16: =_DATA_Assessment_Model!AM16 | AQ16: =_DATA_Assessment_Model!AN16 | AR16: =_DATA_Assessment_Model!AO16 | AS16: =_DATA_Assessment_Model!AP16 | AT16: =_DATA_Assessment_Model!AQ16 | ... AW16: =_DATA_Assessment_Model!AT16 | AY16: =_DATA_Assessment_Model!AV16
A17: Company Geography | B17: Company Geography | C17: 17 | D17: COMP-013 | E17: Geographical distribution | F17: How mature is the organization in managing country risk monitoring for war, sanctions, political instability, natural disaster and energy risks, including ownership, evidence, metrics, fallback procedures and crisis stress testing? | G17: This topic affects exposure to Geopolitical risk; Physical site loss; Regulatory/legal shock. It helps identify how disruption may impact operations, people, revenue, systems, legal exposure or recovery time. | H17: ISO 22301; ISO 31000; ISO 9001; ISO 37000; PESTLE; Business Model Canvas | I17: Policy/SOP; owner/RACI; system report; dashboard; contracts; test records; incident history; interview evidence related to country risk monitoring for war, sanctions, political instability, natural disaster and energy risks. | J17: 4 | K17: =_DATA_Assessment_Model!H17 | L17: =_DATA_Assessment_Model!I17 | M17: =_DATA_Assessment_Model!J17 | N17: =_DATA_Assessment_Model!K17 | O17: =_DATA_Assessment_Model!L17 | P17: No reliable evidence that country risk monitoring for war, sanctions, political instability, natural disaster and energy risks is defined, owned or managed. | Q17: Country risk monitoring for war, sanctions, political instability, natural disaster and energy risks is handled informally and depends on individual knowledge or heroic effort. | R17: Country risk monitoring for war, sanctions, political instability, natural disaster and energy risks is partially documented or implemented, but coverage is inconsistent and not crisis-tested. | S17: Country risk monitoring for war, sanctions, political instability, natural disaster and energy risks is documented, owned, used in normal operations and supported by basic evidence or metrics. | T17: Country risk monitoring for war, sanctions, political instability, natural disaster and energy risks is measured, periodically reviewed, integrated with related processes and tested against relevant disruption scenarios. | U17: Country risk monitoring for war, sanctions, political instability, natural disaster and energy risks is optimized, continuously improved, automated where practical and demonstrably supports crisis resilience. | V17: Geopolitical risk; Physical site loss; Regulatory/legal shock | Y17: Use the recommended action generated by the model; validate with domain owner during real assessment. | Z17: 4 | AA17: 5 | AB17: 5 | AM17: =_DATA_Assessment_Model!AJ17 | AN17: =_DATA_Assessment_Model!AK17 | AO17: =_DATA_Assessment_Model!AL17 | AP17: =_DATA_Assessment_Model!AM17 | AQ17: =_DATA_Assessment_Model!AN17 | AR17: =_DATA_Assessment_Model!AO17 | AS17: =_DATA_Assessment_Model!AP17 | AT17: =_DATA_Assessment_Model!AQ17 | ... AW17: =_DATA_Assessment_Model!AT17 | AY17: =_DATA_Assessment_Model!AV17
A18: Company Geography | B18: Company Geography | C18: 18 | D18: COMP-014 | E18: Geographical distribution | F18: How mature is the organization in managing relocation and alternative location options for critical teams and operations, including ownership, evidence, metrics, fallback procedures and crisis stress testing? | G18: This topic affects exposure to Geopolitical risk; Physical site loss; Regulatory/legal shock. It helps identify how disruption may impact operations, people, revenue, systems, legal exposure or recovery time. | H18: ISO 22301; ISO 31000; ISO 9001; ISO 37000; PESTLE; Business Model Canvas | I18: Policy/SOP; owner/RACI; system report; dashboard; contracts; test records; incident history; interview evidence related to relocation and alternative location options for critical teams and operations. | J18: 5 | K18: =_DATA_Assessment_Model!H18 | L18: =_DATA_Assessment_Model!I18 | M18: =_DATA_Assessment_Model!J18 | N18: =_DATA_Assessment_Model!K18 | O18: =_DATA_Assessment_Model!L18 | P18: Does not exist; no owner, no documentation, no practice. | Q18: Ad hoc; depends entirely on specific individuals. | R18: Partially documented or implemented; coverage inconsistent; never tested under stress. | S18: Documented, owned, executed consistently; basic evidence and metrics exist. | T18: Measured and periodically tested/audited; integrated with adjacent processes. | U18: Optimized and automated where practical; stress-tested; benchmarked externally. | V18: Geopolitical risk; Physical site loss; Regulatory/legal shock | Y18: Use the recommended action generated by the model; validate with domain owner during real assessment. | Z18: 4 | AA18: 5 | AB18: 5 | AM18: =_DATA_Assessment_Model!AJ18 | AN18: =_DATA_Assessment_Model!AK18 | AO18: =_DATA_Assessment_Model!AL18 | AP18: =_DATA_Assessment_Model!AM18 | AQ18: =_DATA_Assessment_Model!AN18 | AR18: =_DATA_Assessment_Model!AO18 | AS18: =_DATA_Assessment_Model!AP18 | AT18: =_DATA_Assessment_Model!AQ18 | ... AW18: =_DATA_Assessment_Model!AT18 | AY18: =_DATA_Assessment_Model!AV18
A19: Company Geography | B19: Company Geography | C19: 19 | D19: COMP-016 | E19: Context and dependencies | F19: How mature is the organization in managing single-country, single-site and single-provider concentration risks, including ownership, evidence, metrics, fallback procedures and crisis stress testing? | G19: This topic affects exposure to Geopolitical risk; Physical site loss; Regulatory/legal shock. It helps identify how disruption may impact operations, people, revenue, systems, legal exposure or recovery time. | H19: ISO 22301; ISO 31000; ISO 9001; ISO 37000; PESTLE; Business Model Canvas | I19: Policy/SOP; owner/RACI; system report; dashboard; contracts; test records; incident history; interview evidence related to single-country, single-site and single-provider concentration risks. | J19: 5 | K19: =_DATA_Assessment_Model!H19 | L19: =_DATA_Assessment_Model!I19 | M19: =_DATA_Assessment_Model!J19 | N19: =_DATA_Assessment_Model!K19 | O19: =_DATA_Assessment_Model!L19 | P19: Does not exist; no owner, no documentation, no practice. | Q19: Ad hoc; depends entirely on specific individuals. | R19: Partially documented or implemented; coverage inconsistent; never tested under stress. | S19: Documented, owned, executed consistently; basic evidence and metrics exist. | T19: Measured and periodically tested/audited; integrated with adjacent processes. | U19: Optimized and automated where practical; stress-tested; benchmarked externally. | V19: Geopolitical risk; Physical site loss; Regulatory/legal shock | Y19: Use the recommended action generated by the model; validate with domain owner during real assessment. | Z19: 4 | AA19: 5 | AB19: 5 | AM19: =_DATA_Assessment_Model!AJ19 | AN19: =_DATA_Assessment_Model!AK19 | AO19: =_DATA_Assessment_Model!AL19 | AP19: =_DATA_Assessment_Model!AM19 | AQ19: =_DATA_Assessment_Model!AN19 | AR19: =_DATA_Assessment_Model!AO19 | AS19: =_DATA_Assessment_Model!AP19 | AT19: =_DATA_Assessment_Model!AQ19 | ... AW19: =_DATA_Assessment_Model!AT19 | AY19: =_DATA_Assessment_Model!AV19
... A23: Company Geography | B23: Company Geography | C23: 23 | D23: COMP-021 | E23: Context and dependencies | F23: How mature is the organization in managing critical infrastructure status and government emergency obligations across operating geographies, including ownership, evidence, metrics, fallback procedures and crisis stress testing? | G23: This topic affects exposure to War/security crisis; Energy/utilities outage; Regulatory/legal shock. It helps identify how disruption may impact operations, people, revenue, systems, legal exposure or recovery time. | H23: ISO 22301; NIS2; national critical infrastructure regulation | I23: Policy/SOP; owner/RACI; system report; dashboard; contracts; test records; incident history; interview evidence | J23: 3 | K23: =_DATA_Assessment_Model!H23 | L23: =_DATA_Assessment_Model!I23 | M23: =_DATA_Assessment_Model!J23 | N23: =_DATA_Assessment_Model!K23 | O23: =_DATA_Assessment_Model!L23 | P23: No reliable evidence that critical infrastructure status and government emergency obligations across operating geographies is defined, owned or managed. | Q23: Critical infrastructure status and government emergency obligations across operating geographies is handled informally and depends on individual knowledge or heroic effort. | R23: Critical infrastructure status and government emergency obligations across operating geographies is partially documented or implemented, but coverage is inconsistent and not crisis-tested. | S23: Critical infrastructure status and government emergency obligations across operating geographies is documented, owned, used in normal operations and supported by basic evidence or metrics. | T23: Critical infrastructure status and government emergency obligations across operating geographies is measured, periodically reviewed, integrated with related processes and tested against relevant disruption scenarios. | U23: Critical infrastructure status and government emergency obligations across operating geographies is optimized, continuously improved, automated where practical and demonstrably supports crisis resilience. | V23: War/security crisis; Energy/utilities outage; Regulatory/legal shock | Y23: Use the recommended action generated by the model; validate with domain owner during real assessment. | Z23: 2 | AA23: 4 | AB23: 4 | AM23: =_DATA_Assessment_Model!AJ23 | AN23: =_DATA_Assessment_Model!AK23 | AO23: =_DATA_Assessment_Model!AL23 | AP23: =_DATA_Assessment_Model!AM23 | AQ23: =_DATA_Assessment_Model!AN23 | AR23: =_DATA_Assessment_Model!AO23 | AS23: =_DATA_Assessment_Model!AP23 | AT23: =_DATA_Assessment_Model!AQ23 | ... AW23: =_DATA_Assessment_Model!AT23 | AY23: =_DATA_Assessment_Model!AV23
A24: Strategy GTM | B24: Strategy GTM | C24: 5 | D24: STRA-001 | E24: Corporate strategy | F24: How mature is the organization in managing documented strategy translated into objectives, KPIs, budgets and accountable owners, including ownership, evidence, metrics, fallback procedures and crisis stress testing? | G24: This topic affects exposure to Demand shock; Financial liquidity crisis; Reputation crisis. It helps identify how disruption may impact operations, people, revenue, systems, legal exposure or recovery time. | H24: ISO 9001; ISO 31000; ISO 37000; McKinsey 7S; OHI; Bain Elements of Value; Jobs-to-be-Done; Porter Five Forces; OKR | I24: Policy/SOP; owner/RACI; system report; dashboard; contracts; test records; incident history; interview evidence related to documented strategy translated into objectives, KPIs, budgets and accountable owners. | J24: 4 | K24: =_DATA_Assessment_Model!H24 | L24: =_DATA_Assessment_Model!I24 | M24: =_DATA_Assessment_Model!J24 | N24: =_DATA_Assessment_Model!K24 | O24: =_DATA_Assessment_Model!L24 | P24: No reliable evidence that documented strategy translated into objectives, kpis, budgets and accountable owners is defined, owned or managed. | Q24: Documented strategy translated into objectives, KPIs, budgets and accountable owners is handled informally and depends on individual knowledge or heroic effort. | R24: Documented strategy translated into objectives, KPIs, budgets and accountable owners is partially documented or implemented, but coverage is inconsistent and not crisis-tested. | S24: Documented strategy translated into objectives, KPIs, budgets and accountable owners is documented, owned, used in normal operations and supported by basic evidence or metrics. | T24: Documented strategy translated into objectives, KPIs, budgets and accountable owners is measured, periodically reviewed, integrated with related processes and tested against relevant disruption scenarios. | U24: Documented strategy translated into objectives, KPIs, budgets and accountable owners is optimized, continuously improved, automated where practical and demonstrably supports crisis resilience. | V24: Demand shock; Financial liquidity crisis; Reputation crisis | Y24: Use the recommended action generated by the model; validate with domain owner during real assessment. | Z24: 4 | AA24: 5 | AB24: 5 | AD24: Corporate strategy | AE24: =_DATA_Assessment_Model!AB24 | AF24: =_DATA_Assessment_Model!AC24 | AG24: =_DATA_Assessment_Model!AD24 | AH24: =_DATA_Assessment_Model!AE24 | AI24: =_DATA_Assessment_Model!AF24 | AJ24: =_DATA_Assessment_Model!AG24 | AM24: =_DATA_Assessment_Model!AJ24 | AN24: =_DATA_Assessment_Model!AK24 | AO24: =_DATA_Assessment_Model!AL24 | AP24: =_DATA_Assessment_Model!AM24 | AQ24: =_DATA_Assessment_Model!AN24 | AR24: =_DATA_Assessment_Model!AO24 | AS24: =_DATA_Assessment_Model!AP24 | AT24: =_DATA_Assessment_Model!AQ24 | ... AW24: =_DATA_Assessment_Model!AT24 | AY24: =_DATA_Assessment_Model!AV24
A25: Strategy GTM | B25: Strategy GTM | C25: 6 | D25: STRA-002 | E25: Corporate strategy | F25: How mature is the organization in managing explicit strategic assumptions and periodic challenge of those assumptions, including ownership, evidence, metrics, fallback procedures and crisis stress testing? | G25: This topic affects exposure to Demand shock; Financial liquidity crisis; Reputation crisis. It helps identify how disruption may impact operations, people, revenue, systems, legal exposure or recovery time. | H25: ISO 9001; ISO 31000; ISO 37000; McKinsey 7S; OHI; Bain Elements of Value; Jobs-to-be-Done; Porter Five Forces; OKR | I25: Policy/SOP; owner/RACI; system report; dashboard; contracts; test records; incident history; interview evidence related to explicit strategic assumptions and periodic challenge of those assumptions. | J25: 3 | K25: =_DATA_Assessment_Model!H25 | L25: =_DATA_Assessment_Model!I25 | M25: =_DATA_Assessment_Model!J25 | N25: =_DATA_Assessment_Model!K25 | O25: =_DATA_Assessment_Model!L25 | P25: No reliable evidence that explicit strategic assumptions and periodic challenge of those assumptions is defined, owned or managed. | Q25: Explicit strategic assumptions and periodic challenge of those assumptions is handled informally and depends on individual knowledge or heroic effort. | R25: Explicit strategic assumptions and periodic challenge of those assumptions is partially documented or implemented, but coverage is inconsistent and not crisis-tested. | S25: Explicit strategic assumptions and periodic challenge of those assumptions is documented, owned, used in normal operations and supported by basic evidence or metrics. | T25: Explicit strategic assumptions and periodic challenge of those assumptions is measured, periodically reviewed, integrated with related processes and tested against relevant disruption scenarios. | U25: Explicit strategic assumptions and periodic challenge of those assumptions is optimized, continuously improved, automated where practical and demonstrably supports crisis resilience. | V25: Demand shock; Financial liquidity crisis; Reputation crisis | Y25: Use the recommended action generated by the model; validate with domain owner during real assessment. | Z25: 4 | AA25: 5 | AB25: 5 | AD25: Market and ICP | AE25: =_DATA_Assessment_Model!AB25 | AF25: =_DATA_Assessment_Model!AC25 | AG25: =_DATA_Assessment_Model!AD25 | AH25: =_DATA_Assessment_Model!AE25 | AI25: =_DATA_Assessment_Model!AF25 | AJ25: =_DATA_Assessment_Model!AG25 | AM25: =_DATA_Assessment_Model!AJ25 | AN25: =_DATA_Assessment_Model!AK25 | AO25: =_DATA_Assessment_Model!AL25 | AP25: =_DATA_Assessment_Model!AM25 | AQ25: =_DATA_Assessment_Model!AN25 | AR25: =_DATA_Assessment_Model!AO25 | AS25: =_DATA_Assessment_Model!AP25 | AT25: =_DATA_Assessment_Model!AQ25 | ... AW25: =_DATA_Assessment_Model!AT25 | AY25: =_DATA_Assessment_Model!AV25
A26: Strategy GTM | B26: Strategy GTM | C26: 7 | D26: STRA-003 | E26: Corporate strategy | F26: How mature is the organization in managing crisis-resilient strategy including adaptation, continuity, digital enablement and recovery options, including ownership, evidence, metrics, fallback procedures and crisis stress testing? | G26: This topic affects exposure to Demand shock; Financial liquidity crisis; Reputation crisis. It helps identify how disruption may impact operations, people, revenue, systems, legal exposure or recovery time. | H26: ISO 9001; ISO 31000; ISO 37000; McKinsey 7S; OHI; Bain Elements of Value; Jobs-to-be-Done; Porter Five Forces; OKR | I26: Policy/SOP; owner/RACI; system report; dashboard; contracts; test records; incident history; interview evidence related to crisis-resilient strategy including adaptation, continuity, digital enablement and recovery options. | J26: 5 | K26: =_DATA_Assessment_Model!H26 | L26: =_DATA_Assessment_Model!I26 | M26: =_DATA_Assessment_Model!J26 | N26: =_DATA_Assessment_Model!K26 | O26: =_DATA_Assessment_Model!L26 | P26: Does not exist; no owner, no documentation, no practice. | Q26: Ad hoc; depends entirely on specific individuals. | R26: Partially documented or implemented; coverage inconsistent; never tested under stress. | S26: Documented, owned, executed consistently; basic evidence and metrics exist. | T26: Measured and periodically tested/audited; integrated with adjacent processes. | U26: Optimized and automated where practical; stress-tested; benchmarked externally. | V26: Demand shock; Financial liquidity crisis; Reputation crisis | Y26: Use the recommended action generated by the model; validate with domain owner during real assessment. | Z26: 4 | AA26: 5 | AB26: 5 | AD26: Offering and positioning | AE26: =_DATA_Assessment_Model!AB26 | AF26: =_DATA_Assessment_Model!AC26 | AG26: =_DATA_Assessment_Model!AD26 | AH26: =_DATA_Assessment_Model!AE26 | AI26: =_DATA_Assessment_Model!AF26 | AJ26: =_DATA_Assessment_Model!AG26 | AM26: =_DATA_Assessment_Model!AJ26 | AN26: =_DATA_Assessment_Model!AK26 | AO26: =_DATA_Assessment_Model!AL26 | AP26: =_DATA_Assessment_Model!AM26 | AQ26: =_DATA_Assessment_Model!AN26 | AR26: =_DATA_Assessment_Model!AO26 | AS26: =_DATA_Assessment_Model!AP26 | AT26: =_DATA_Assessment_Model!AQ26 | ... AW26: =_DATA_Assessment_Model!AT26 | AY26: =_DATA_Assessment_Model!AV26
A27: Strategy GTM | B27: Strategy GTM | C27: 8 | D27: STRA-004 | E27: Corporate strategy | F27: How mature is the organization in managing strategic priorities ranked by business value, urgency, risk and resource constraints, including ownership, evidence, metrics, fallback procedures and crisis stress testing? | G27: This topic affects exposure to Demand shock; Financial liquidity crisis; Reputation crisis. It helps identify how disruption may impact operations, people, revenue, systems, legal exposure or recovery time. | H27: ISO 9001; ISO 31000; ISO 37000; McKinsey 7S; OHI; Bain Elements of Value; Jobs-to-be-Done; Porter Five Forces; OKR | I27: Policy/SOP; owner/RACI; system report; dashboard; contracts; test records; incident history; interview evidence related to strategic priorities ranked by business value, urgency, risk and resource constraints. | J27: 4 | K27: =_DATA_Assessment_Model!H27 | L27: =_DATA_Assessment_Model!I27 | M27: =_DATA_Assessment_Model!J27 | N27: =_DATA_Assessment_Model!K27 | O27: =_DATA_Assessment_Model!L27 | P27: No reliable evidence that strategic priorities ranked by business value, urgency, risk and resource constraints is defined, owned or managed. | Q27: Strategic priorities ranked by business value, urgency, risk and resource constraints is handled informally and depends on individual knowledge or heroic effort. | R27: Strategic priorities ranked by business value, urgency, risk and resource constraints is partially documented or implemented, but coverage is inconsistent and not crisis-tested. | S27: Strategic priorities ranked by business value, urgency, risk and resource constraints is documented, owned, used in normal operations and supported by basic evidence or metrics. | T27: Strategic priorities ranked by business value, urgency, risk and resource constraints is measured, periodically reviewed, integrated with related processes and tested against relevant disruption scenarios. | U27: Strategic priorities ranked by business value, urgency, risk and resource constraints is optimized, continuously improved, automated where practical and demonstrably supports crisis resilience. | V27: Demand shock; Financial liquidity crisis; Reputation crisis | Y27: Use the recommended action generated by the model; validate with domain owner during real assessment. | Z27: 4 | AA27: 5 | AB27: 5 | AD27: GTM execution | AE27: =_DATA_Assessment_Model!AB27 | AF27: =_DATA_Assessment_Model!AC27 | AG27: =_DATA_Assessment_Model!AD27 | AH27: =_DATA_Assessment_Model!AE27 | AI27: =_DATA_Assessment_Model!AF27 | AJ27: =_DATA_Assessment_Model!AG27 | AM27: =_DATA_Assessment_Model!AJ27 | AN27: =_DATA_Assessment_Model!AK27 | AO27: =_DATA_Assessment_Model!AL27 | AP27: =_DATA_Assessment_Model!AM27 | AQ27: =_DATA_Assessment_Model!AN27 | AR27: =_DATA_Assessment_Model!AO27 | AS27: =_DATA_Assessment_Model!AP27 | AT27: =_DATA_Assessment_Model!AQ27 | ... AW27: =_DATA_Assessment_Model!AT27 | AY27: =_DATA_Assessment_Model!AV27
A28: Strategy GTM | B28: Strategy GTM | C28: 9 | D28: STRA-005 | E28: Corporate strategy | F28: How mature is the organization in managing strategic options for pivoting under demand shock, war, regulation, supply or liquidity crisis, including ownership, evidence, metrics, fallback procedures and crisis stress testing? | G28: This topic affects exposure to Demand shock; Financial liquidity crisis; Reputation crisis. It helps identify how disruption may impact operations, people, revenue, systems, legal exposure or recovery time. | H28: ISO 9001; ISO 31000; ISO 37000; McKinsey 7S; OHI; Bain Elements of Value; Jobs-to-be-Done; Porter Five Forces; OKR | I28: Policy/SOP; owner/RACI; system report; dashboard; contracts; test records; incident history; interview evidence related to strategic options for pivoting under demand shock, war, regulation, supply or liquidity crisis. | J28: 5 | K28: =_DATA_Assessment_Model!H28 | L28: =_DATA_Assessment_Model!I28 | M28: =_DATA_Assessment_Model!J28 | N28: =_DATA_Assessment_Model!K28 | O28: =_DATA_Assessment_Model!L28 | P28: Does not exist; no owner, no documentation, no practice. | Q28: Ad hoc; depends entirely on specific individuals. | R28: Partially documented or implemented; coverage inconsistent; never tested under stress. | S28: Documented, owned, executed consistently; basic evidence and metrics exist. | T28: Measured and periodically tested/audited; integrated with adjacent processes. | U28: Optimized and automated where practical; stress-tested; benchmarked externally. | V28: Demand shock; Financial liquidity crisis; Reputation crisis | Y28: Use the recommended action generated by the model; validate with domain owner during real assessment. | Z28: 4 | AA28: 5 | AB28: 5 | AD28: External relations and partnerships | AE28: =_DATA_Assessment_Model!AB28 | AF28: =_DATA_Assessment_Model!AC28 | AG28: =_DATA_Assessment_Model!AD28 | AH28: =_DATA_Assessment_Model!AE28 | AI28: =_DATA_Assessment_Model!AF28 | AJ28: =_DATA_Assessment_Model!AG28 | AM28: =_DATA_Assessment_Model!AJ28 | AN28: =_DATA_Assessment_Model!AK28 | AO28: =_DATA_Assessment_Model!AL28 | AP28: =_DATA_Assessment_Model!AM28 | AQ28: =_DATA_Assessment_Model!AN28 | AR28: =_DATA_Assessment_Model!AO28 | AS28: =_DATA_Assessment_Model!AP28 | AT28: =_DATA_Assessment_Model!AQ28 | ... AW28: =_DATA_Assessment_Model!AT28 | AY28: =_DATA_Assessment_Model!AV28
A29: Strategy GTM | B29: Strategy GTM | C29: 10 | D29: STRA-006 | E29: Corporate strategy | F29: How mature is the organization in managing alignment between strategy, structure, systems, skills, staff, leadership style and culture, including ownership, evidence, metrics, fallback procedures and crisis stress testing? | G29: This topic affects exposure to Demand shock; Financial liquidity crisis; Reputation crisis. It helps identify how disruption may impact operations, people, revenue, systems, legal exposure or recovery time. | H29: ISO 9001; ISO 31000; ISO 37000; McKinsey 7S; OHI; Bain Elements of Value; Jobs-to-be-Done; Porter Five Forces; OKR | I29: Policy/SOP; owner/RACI; system report; dashboard; contracts; test records; incident history; interview evidence related to alignment between strategy, structure, systems, skills, staff, leadership style and culture. | J29: 4 | K29: =_DATA_Assessment_Model!H29 | L29: =_DATA_Assessment_Model!I29 | M29: =_DATA_Assessment_Model!J29 | N29: =_DATA_Assessment_Model!K29 | O29: =_DATA_Assessment_Model!L29 | P29: No reliable evidence that alignment between strategy, structure, systems, skills, staff, leadership style and culture is defined, owned or managed. | Q29: Alignment between strategy, structure, systems, skills, staff, leadership style and culture is handled informally and depends on individual knowledge or heroic effort. | R29: Alignment between strategy, structure, systems, skills, staff, leadership style and culture is partially documented or implemented, but coverage is inconsistent and not crisis-tested. | S29: Alignment between strategy, structure, systems, skills, staff, leadership style and culture is documented, owned, used in normal operations and supported by basic evidence or metrics. | T29: Alignment between strategy, structure, systems, skills, staff, leadership style and culture is measured, periodically reviewed, integrated with related processes and tested against relevant disruption scenarios. | U29: Alignment between strategy, structure, systems, skills, staff, leadership style and culture is optimized, continuously improved, automated where practical and demonstrably supports crisis resilience. | V29: Demand shock; Financial liquidity crisis; Reputation crisis | Y29: Use the recommended action generated by the model; validate with domain owner during real assessment. | Z29: 4 | AA29: 5 | AB29: 5 | AM29: =_DATA_Assessment_Model!AJ29 | AN29: =_DATA_Assessment_Model!AK29 | AO29: =_DATA_Assessment_Model!AL29 | AP29: =_DATA_Assessment_Model!AM29 | AQ29: =_DATA_Assessment_Model!AN29 | AR29: =_DATA_Assessment_Model!AO29 | AS29: =_DATA_Assessment_Model!AP29 | AT29: =_DATA_Assessment_Model!AQ29 | ... AW29: =_DATA_Assessment_Model!AT29 | AY29: =_DATA_Assessment_Model!AV29
A30: Strategy GTM | B30: Strategy GTM | C30: 11 | D30: STRA-007 | E30: Market and ICP | F30: How mature is the organization in managing ideal customer profile by segment, geography, industry, company size, pain, budget and buying trigger, including ownership, evidence, metrics, fallback procedures and crisis stress testing? | G30: This topic affects exposure to Demand shock; Financial liquidity crisis; Reputation crisis. It helps identify how disruption may impact operations, people, revenue, systems, legal exposure or recovery time. | H30: ISO 9001; ISO 31000; ISO 37000; McKinsey 7S; OHI; Bain Elements of Value; Jobs-to-be-Done; Porter Five Forces; OKR | I30: Policy/SOP; owner/RACI; system report; dashboard; contracts; test records; incident history; interview evidence related to ideal customer profile by segment, geography, industry, company size, pain, budget and buying trigger. | J30: 4 | K30: =_DATA_Assessment_Model!H30 | L30: =_DATA_Assessment_Model!I30 | M30: =_DATA_Assessment_Model!J30 | N30: =_DATA_Assessment_Model!K30 | O30: =_DATA_Assessment_Model!L30 | P30: No reliable evidence that ideal customer profile by segment, geography, industry, company size, pain, budget and buying trigger is defined, owned or managed. | Q30: Ideal customer profile by segment, geography, industry, company size, pain, budget and buying trigger is handled informally and depends on individual knowledge or heroic effort. | R30: Ideal customer profile by segment, geography, industry, company size, pain, budget and buying trigger is partially documented or implemented, but coverage is inconsistent and not crisis-tested. | S30: Ideal customer profile by segment, geography, industry, company size, pain, budget and buying trigger is documented, owned, used in normal operations and supported by basic evidence or metrics. | T30: Ideal customer profile by segment, geography, industry, company size, pain, budget and buying trigger is measured, periodically reviewed, integrated with related processes and tested against relevant disruption scenarios. | U30: Ideal customer profile by segment, geography, industry, company size, pain, budget and buying trigger is optimized, continuously improved, automated where practical and demonstrably supports crisis resilience. | V30: Demand shock; Financial liquidity crisis; Reputation crisis | Y30: Use the recommended action generated by the model; validate with domain owner during real assessment. | Z30: 4 | AA30: 5 | AB30: 5 | AM30: =_DATA_Assessment_Model!AJ30 | AN30: =_DATA_Assessment_Model!AK30 | AO30: =_DATA_Assessment_Model!AL30 | AP30: =_DATA_Assessment_Model!AM30 | AQ30: =_DATA_Assessment_Model!AN30 | AR30: =_DATA_Assessment_Model!AO30 | AS30: =_DATA_Assessment_Model!AP30 | AT30: =_DATA_Assessment_Model!AQ30 | ... AW30: =_DATA_Assessment_Model!AT30 | AY30: =_DATA_Assessment_Model!AV30
A31: Strategy GTM | B31: Strategy GTM | C31: 12 | D31: STRA-008 | E31: Market and ICP | F31: How mature is the organization in managing buyer personas covering economic buyer, technical buyer, user, influencer and blocker, including ownership, evidence, metrics, fallback procedures and crisis stress testing? | G31: This topic affects exposure to Demand shock; Financial liquidity crisis; Reputation crisis. It helps identify how disruption may impact operations, people, revenue, systems, legal exposure or recovery time. | H31: ISO 9001; ISO 31000; ISO 37000; McKinsey 7S; OHI; Bain Elements of Value; Jobs-to-be-Done; Porter Five Forces; OKR | I31: Policy/SOP; owner/RACI; system report; dashboard; contracts; test records; incident history; interview evidence related to buyer personas covering economic buyer, technical buyer, user, influencer and blocker. | J31: 3 | K31: =_DATA_Assessment_Model!H31 | L31: =_DATA_Assessment_Model!I31 | M31: =_DATA_Assessment_Model!J31 | N31: =_DATA_Assessment_Model!K31 | O31: =_DATA_Assessment_Model!L31 | P31: No reliable evidence that buyer personas covering economic buyer, technical buyer, user, influencer and blocker is defined, owned or managed. | Q31: Buyer personas covering economic buyer, technical buyer, user, influencer and blocker is handled informally and depends on individual knowledge or heroic effort. | R31: Buyer personas covering economic buyer, technical buyer, user, influencer and blocker is partially documented or implemented, but coverage is inconsistent and not crisis-tested. | S31: Buyer personas covering economic buyer, technical buyer, user, influencer and blocker is documented, owned, used in normal operations and supported by basic evidence or metrics. | T31: Buyer personas covering economic buyer, technical buyer, user, influencer and blocker is measured, periodically reviewed, integrated with related processes and tested against relevant disruption scenarios. | U31: Buyer personas covering economic buyer, technical buyer, user, influencer and blocker is optimized, continuously improved, automated where practical and demonstrably supports crisis resilience. | V31: Demand shock; Financial liquidity crisis; Reputation crisis | Y31: Use the recommended action generated by the model; validate with domain owner during real assessment. | Z31: 4 | AA31: 5 | AB31: 5 | AM31: =_DATA_Assessment_Model!AJ31 | AN31: =_DATA_Assessment_Model!AK31 | AO31: =_DATA_Assessment_Model!AL31 | AP31: =_DATA_Assessment_Model!AM31 | AQ31: =_DATA_Assessment_Model!AN31 | AR31: =_DATA_Assessment_Model!AO31 | AS31: =_DATA_Assessment_Model!AP31 | AT31: =_DATA_Assessment_Model!AQ31 | ... AW31: =_DATA_Assessment_Model!AT31 | AY31: =_DATA_Assessment_Model!AV31
A32: Strategy GTM | B32: Strategy GTM | C32: 13 | D32: STRA-009 | E32: Market and ICP | F32: How mature is the organization in managing validated customer problems, jobs-to-be-done, urgency triggers and willingness to pay, including ownership, evidence, metrics, fallback procedures and crisis stress testing? | G32: This topic affects exposure to Demand shock; Financial liquidity crisis; Reputation crisis. It helps identify how disruption may impact operations, people, revenue, systems, legal exposure or recovery time. | H32: ISO 9001; ISO 31000; ISO 37000; McKinsey 7S; OHI; Bain Elements of Value; Jobs-to-be-Done; Porter Five Forces; OKR | I32: Policy/SOP; owner/RACI; system report; dashboard; contracts; test records; incident history; interview evidence related to validated customer problems, jobs-to-be-done, urgency triggers and willingness to pay. | J32: 4 | K32: =_DATA_Assessment_Model!H32 | L32: =_DATA_Assessment_Model!I32 | M32: =_DATA_Assessment_Model!J32 | N32: =_DATA_Assessment_Model!K32 | O32: =_DATA_Assessment_Model!L32 | P32: No reliable evidence that validated customer problems, jobs-to-be-done, urgency triggers and willingness to pay is defined, owned or managed. | Q32: Validated customer problems, jobs-to-be-done, urgency triggers and willingness to pay is handled informally and depends on individual knowledge or heroic effort. | R32: Validated customer problems, jobs-to-be-done, urgency triggers and willingness to pay is partially documented or implemented, but coverage is inconsistent and not crisis-tested. | S32: Validated customer problems, jobs-to-be-done, urgency triggers and willingness to pay is documented, owned, used in normal operations and supported by basic evidence or metrics. | T32: Validated customer problems, jobs-to-be-done, urgency triggers and willingness to pay is measured, periodically reviewed, integrated with related processes and tested against relevant disruption scenarios. | U32: Validated customer problems, jobs-to-be-done, urgency triggers and willingness to pay is optimized, continuously improved, automated where practical and demonstrably supports crisis resilience. | V32: Demand shock; Financial liquidity crisis; Reputation crisis | Y32: Use the recommended action generated by the model; validate with domain owner during real assessment. | Z32: 4 | AA32: 5 | AB32: 5 | AM32: =_DATA_Assessment_Model!AJ32 | AN32: =_DATA_Assessment_Model!AK32 | AO32: =_DATA_Assessment_Model!AL32 | AP32: =_DATA_Assessment_Model!AM32 | AQ32: =_DATA_Assessment_Model!AN32 | AR32: =_DATA_Assessment_Model!AO32 | AS32: =_DATA_Assessment_Model!AP32 | AT32: =_DATA_Assessment_Model!AQ32 | ... AW32: =_DATA_Assessment_Model!AT32 | AY32: =_DATA_Assessment_Model!AV32
A33: Strategy GTM | B33: Strategy GTM | C33: 14 | D33: STRA-010 | E33: Market and ICP | F33: How mature is the organization in managing market segmentation by attractiveness, accessibility, profitability and crisis sensitivity, including ownership, evidence, metrics, fallback procedures and crisis stress testing? | G33: This topic affects exposure to Demand shock; Financial liquidity crisis; Reputation crisis. It helps identify how disruption may impact operations, people, revenue, systems, legal exposure or recovery time. | H33: ISO 9001; ISO 31000; ISO 37000; McKinsey 7S; OHI; Bain Elements of Value; Jobs-to-be-Done; Porter Five Forces; OKR | I33: Policy/SOP; owner/RACI; system report; dashboard; contracts; test records; incident history; interview evidence related to market segmentation by attractiveness, accessibility, profitability and crisis sensitivity. | J33: 5 | K33: =_DATA_Assessment_Model!H33 | L33: =_DATA_Assessment_Model!I33 | M33: =_DATA_Assessment_Model!J33 | N33: =_DATA_Assessment_Model!K33 | O33: =_DATA_Assessment_Model!L33 | P33: Does not exist; no owner, no documentation, no practice. | Q33: Ad hoc; depends entirely on specific individuals. | R33: Partially documented or implemented; coverage inconsistent; never tested under stress. | S33: Documented, owned, executed consistently; basic evidence and metrics exist. | T33: Measured and periodically tested/audited; integrated with adjacent processes. | U33: Optimized and automated where practical; stress-tested; benchmarked externally. | V33: Demand shock; Financial liquidity crisis; Reputation crisis | Y33: Use the recommended action generated by the model; validate with domain owner during real assessment. | Z33: 4 | AA33: 5 | AB33: 5 | AM33: =_DATA_Assessment_Model!AJ33 | AN33: =_DATA_Assessment_Model!AK33 | AO33: =_DATA_Assessment_Model!AL33 | AP33: =_DATA_Assessment_Model!AM33 | AQ33: =_DATA_Assessment_Model!AN33 | AR33: =_DATA_Assessment_Model!AO33 | AS33: =_DATA_Assessment_Model!AP33 | AT33: =_DATA_Assessment_Model!AQ33 | ... AW33: =_DATA_Assessment_Model!AT33 | AY33: =_DATA_Assessment_Model!AV33
A34: Strategy GTM | B34: Strategy GTM | C34: 15 | D34: STRA-011 | E34: Market and ICP | F34: How mature is the organization in managing market size and growth assumptions with explicit evidence and uncertainty level, including ownership, evidence, metrics, fallback procedures and crisis stress testing? | G34: This topic affects exposure to Demand shock; Financial liquidity crisis; Reputation crisis. It helps identify how disruption may impact operations, people, revenue, systems, legal exposure or recovery time. | H34: ISO 9001; ISO 31000; ISO 37000; McKinsey 7S; OHI; Bain Elements of Value; Jobs-to-be-Done; Porter Five Forces; OKR | I34: Policy/SOP; owner/RACI; system report; dashboard; contracts; test records; incident history; interview evidence related to market size and growth assumptions with explicit evidence and uncertainty level. | J34: 3 | K34: =_DATA_Assessment_Model!H34 | L34: =_DATA_Assessment_Model!I34 | M34: =_DATA_Assessment_Model!J34 | N34: =_DATA_Assessment_Model!K34 | O34: =_DATA_Assessment_Model!L34 | P34: No reliable evidence that market size and growth assumptions with explicit evidence and uncertainty level is defined, owned or managed. | Q34: Market size and growth assumptions with explicit evidence and uncertainty level is handled informally and depends on individual knowledge or heroic effort. | R34: Market size and growth assumptions with explicit evidence and uncertainty level is partially documented or implemented, but coverage is inconsistent and not crisis-tested. | S34: Market size and growth assumptions with explicit evidence and uncertainty level is documented, owned, used in normal operations and supported by basic evidence or metrics. | T34: Market size and growth assumptions with explicit evidence and uncertainty level is measured, periodically reviewed, integrated with related processes and tested against relevant disruption scenarios. | U34: Market size and growth assumptions with explicit evidence and uncertainty level is optimized, continuously improved, automated where practical and demonstrably supports crisis resilience. | V34: Demand shock; Financial liquidity crisis; Reputation crisis | Y34: Use the recommended action generated by the model; validate with domain owner during real assessment. | Z34: 4 | AA34: 5 | AB34: 5 | AM34: =_DATA_Assessment_Model!AJ34 | AN34: =_DATA_Assessment_Model!AK34 | AO34: =_DATA_Assessment_Model!AL34 | AP34: =_DATA_Assessment_Model!AM34 | AQ34: =_DATA_Assessment_Model!AN34 | AR34: =_DATA_Assessment_Model!AO34 | AS34: =_DATA_Assessment_Model!AP34 | AT34: =_DATA_Assessment_Model!AQ34 | ... AW34: =_DATA_Assessment_Model!AT34 | AY34: =_DATA_Assessment_Model!AV34
A35: Strategy GTM | B35: Strategy GTM | C35: 16 | D35: STRA-012 | E35: Market and ICP | F35: How mature is the organization in managing customer concentration and exposure to specific industries, geographies or budget cycles, including ownership, evidence, metrics, fallback procedures and crisis stress testing? | G35: This topic affects exposure to Demand shock; Financial liquidity crisis; Reputation crisis. It helps identify how disruption may impact operations, people, revenue, systems, legal exposure or recovery time. | H35: ISO 9001; ISO 31000; ISO 37000; McKinsey 7S; OHI; Bain Elements of Value; Jobs-to-be-Done; Porter Five Forces; OKR | I35: Policy/SOP; owner/RACI; system report; dashboard; contracts; test records; incident history; interview evidence related to customer concentration and exposure to specific industries, geographies or budget cycles. | J35: 4 | K35: =_DATA_Assessment_Model!H35 | L35: =_DATA_Assessment_Model!I35 | M35: =_DATA_Assessment_Model!J35 | N35: =_DATA_Assessment_Model!K35 | O35: =_DATA_Assessment_Model!L35 | P35: No reliable evidence that customer concentration and exposure to specific industries, geographies or budget cycles is defined, owned or managed. | Q35: Customer concentration and exposure to specific industries, geographies or budget cycles is handled informally and depends on individual knowledge or heroic effort. | R35: Customer concentration and exposure to specific industries, geographies or budget cycles is partially documented or implemented, but coverage is inconsistent and not crisis-tested. | S35: Customer concentration and exposure to specific industries, geographies or budget cycles is documented, owned, used in normal operations and supported by basic evidence or metrics. | T35: Customer concentration and exposure to specific industries, geographies or budget cycles is measured, periodically reviewed, integrated with related processes and tested against relevant disruption scenarios. | U35: Customer concentration and exposure to specific industries, geographies or budget cycles is optimized, continuously improved, automated where practical and demonstrably supports crisis resilience. | V35: Demand shock; Financial liquidity crisis; Reputation crisis | Y35: Use the recommended action generated by the model; validate with domain owner during real assessment. | Z35: 4 | AA35: 5 | AB35: 5 | AM35: =_DATA_Assessment_Model!AJ35 | AN35: =_DATA_Assessment_Model!AK35 | AO35: =_DATA_Assessment_Model!AL35 | AP35: =_DATA_Assessment_Model!AM35 | AQ35: =_DATA_Assessment_Model!AN35 | AR35: =_DATA_Assessment_Model!AO35 | AS35: =_DATA_Assessment_Model!AP35 | AT35: =_DATA_Assessment_Model!AQ35 | ... AW35: =_DATA_Assessment_Model!AT35 | AY35: =_DATA_Assessment_Model!AV35
A36: Strategy GTM | B36: Strategy GTM | C36: 17 | D36: STRA-013 | E36: Offering and positioning | F36: How mature is the organization in managing structured offering catalog with packages, scope, outcomes, assumptions and delivery requirements, including ownership, evidence, metrics, fallback procedures and crisis stress testing? | G36: This topic affects exposure to Demand shock; Financial liquidity crisis; Reputation crisis. It helps identify how disruption may impact operations, people, revenue, systems, legal exposure or recovery time. | H36: ISO 9001; ISO 31000; ISO 37000; McKinsey 7S; OHI; Bain Elements of Value; Jobs-to-be-Done; Porter Five Forces; OKR | I36: Policy/SOP; owner/RACI; system report; dashboard; contracts; test records; incident history; interview evidence related to structured offering catalog with packages, scope, outcomes, assumptions and delivery requirements. | J36: 5 | K36: =_DATA_Assessment_Model!H36 | L36: =_DATA_Assessment_Model!I36 | M36: =_DATA_Assessment_Model!J36 | N36: =_DATA_Assessment_Model!K36 | O36: =_DATA_Assessment_Model!L36 | P36: No inventory/register exists. | Q36: Partial lists live in individuals' heads or personal files. | R36: A register exists but is incomplete or outdated (>1 year) and has no owner. | S36: Owned, documented, updated on a defined schedule, covers the main scope. | T36: Complete and periodically reviewed; integrated with related processes; completeness measured. | U36: Maintained automatically or synced with systems; drives decisions; audited. | V36: Demand shock; Financial liquidity crisis; Reputation crisis | Y36: Use the recommended action generated by the model; validate with domain owner during real assessment. | Z36: 4 | AA36: 5 | AB36: 5 | AM36: =_DATA_Assessment_Model!AJ36 | AN36: =_DATA_Assessment_Model!AK36 | AO36: =_DATA_Assessment_Model!AL36 | AP36: =_DATA_Assessment_Model!AM36 | AQ36: =_DATA_Assessment_Model!AN36 | AR36: =_DATA_Assessment_Model!AO36 | AS36: =_DATA_Assessment_Model!AP36 | AT36: =_DATA_Assessment_Model!AQ36 | ... AW36: =_DATA_Assessment_Model!AT36 | AY36: =_DATA_Assessment_Model!AV36
A37: Strategy GTM | B37: Strategy GTM | C37: 18 | D37: STRA-014 | E37: Offering and positioning | F37: How mature is the organization in managing clear differentiation against direct competitors, substitutes and in-house alternatives, including ownership, evidence, metrics, fallback procedures and crisis stress testing? | G37: This topic affects exposure to Demand shock; Financial liquidity crisis; Reputation crisis. It helps identify how disruption may impact operations, people, revenue, systems, legal exposure or recovery time. | H37: ISO 9001; ISO 31000; ISO 37000; McKinsey 7S; OHI; Bain Elements of Value; Jobs-to-be-Done; Porter Five Forces; OKR | I37: Policy/SOP; owner/RACI; system report; dashboard; contracts; test records; incident history; interview evidence related to clear differentiation against direct competitors, substitutes and in-house alternatives. | J37: 3 | K37: =_DATA_Assessment_Model!H37 | L37: =_DATA_Assessment_Model!I37 | M37: =_DATA_Assessment_Model!J37 | N37: =_DATA_Assessment_Model!K37 | O37: =_DATA_Assessment_Model!L37 | P37: No reliable evidence that clear differentiation against direct competitors, substitutes and in-house alternatives is defined, owned or managed. | Q37: Clear differentiation against direct competitors, substitutes and in-house alternatives is handled informally and depends on individual knowledge or heroic effort. | R37: Clear differentiation against direct competitors, substitutes and in-house alternatives is partially documented or implemented, but coverage is inconsistent and not crisis-tested. | S37: Clear differentiation against direct competitors, substitutes and in-house alternatives is documented, owned, used in normal operations and supported by basic evidence or metrics. | T37: Clear differentiation against direct competitors, substitutes and in-house alternatives is measured, periodically reviewed, integrated with related processes and tested against relevant disruption scenarios. | U37: Clear differentiation against direct competitors, substitutes and in-house alternatives is optimized, continuously improved, automated where practical and demonstrably supports crisis resilience. | V37: Demand shock; Financial liquidity crisis; Reputation crisis | Y37: Use the recommended action generated by the model; validate with domain owner during real assessment. | Z37: 4 | AA37: 5 | AB37: 5 | AM37: =_DATA_Assessment_Model!AJ37 | AN37: =_DATA_Assessment_Model!AK37 | AO37: =_DATA_Assessment_Model!AL37 | AP37: =_DATA_Assessment_Model!AM37 | AQ37: =_DATA_Assessment_Model!AN37 | AR37: =_DATA_Assessment_Model!AO37 | AS37: =_DATA_Assessment_Model!AP37 | AT37: =_DATA_Assessment_Model!AQ37 | ... AW37: =_DATA_Assessment_Model!AT37 | AY37: =_DATA_Assessment_Model!AV37
A38: Strategy GTM | B38: Strategy GTM | C38: 19 | D38: STRA-015 | E38: Offering and positioning | F38: How mature is the organization in managing value proposition linked to measurable customer economic value, risk reduction or continuity impact, including ownership, evidence, metrics, fallback procedures and crisis stress testing? | G38: This topic affects exposure to Demand shock; Financial liquidity crisis; Reputation crisis. It helps identify how disruption may impact operations, people, revenue, systems, legal exposure or recovery time. | H38: ISO 9001; ISO 31000; ISO 37000; McKinsey 7S; OHI; Bain Elements of Value; Jobs-to-be-Done; Porter Five Forces; OKR | I38: Policy/SOP; owner/RACI; system report; dashboard; contracts; test records; incident history; interview evidence related to value proposition linked to measurable customer economic value, risk reduction or continuity impact. | J38: 5 | K38: =_DATA_Assessment_Model!H38 | L38: =_DATA_Assessment_Model!I38 | M38: =_DATA_Assessment_Model!J38 | N38: =_DATA_Assessment_Model!K38 | O38: =_DATA_Assessment_Model!L38 | P38: Nothing is monitored or measured. | Q38: Occasional manual checks by individuals. | R38: Some metrics exist but are not reviewed regularly and trigger no action. | S38: Defined metrics with an owner, reviewed on a set cadence. | T38: Thresholds and alerts in place; deviations trigger documented action; trends analyzed. | U38: Automated monitoring with leading indicators, integrated into management decisions. | V38: Demand shock; Financial liquidity crisis; Reputation crisis | Y38: Use the recommended action generated by the model; validate with domain owner during real assessment. | Z38: 4 | AA38: 5 | AB38: 5 | AM38: =_DATA_Assessment_Model!AJ38 | AN38: =_DATA_Assessment_Model!AK38 | AO38: =_DATA_Assessment_Model!AL38 | AP38: =_DATA_Assessment_Model!AM38 | AQ38: =_DATA_Assessment_Model!AN38 | AR38: =_DATA_Assessment_Model!AO38 | AS38: =_DATA_Assessment_Model!AP38 | AT38: =_DATA_Assessment_Model!AQ38 | ... AW38: =_DATA_Assessment_Model!AT38 | AY38: =_DATA_Assessment_Model!AV38
A39: Strategy GTM | B39: Strategy GTM | C39: 20 | D39: STRA-016 | E39: Offering and positioning | F39: How mature is the organization in managing pricing strategy with margin thresholds, discount governance and crisis boundaries, including ownership, evidence, metrics, fallback procedures and crisis stress testing? | G39: This topic affects exposure to Demand shock; Financial liquidity crisis; Reputation crisis. It helps identify how disruption may impact operations, people, revenue, systems, legal exposure or recovery time. | H39: ISO 9001; ISO 31000; ISO 37000; McKinsey 7S; OHI; Bain Elements of Value; Jobs-to-be-Done; Porter Five Forces; OKR | I39: Policy/SOP; owner/RACI; system report; dashboard; contracts; test records; incident history; interview evidence related to pricing strategy with margin thresholds, discount governance and crisis boundaries. | J39: 5 | K39: =_DATA_Assessment_Model!H39 | L39: =_DATA_Assessment_Model!I39 | M39: =_DATA_Assessment_Model!J39 | N39: =_DATA_Assessment_Model!K39 | O39: =_DATA_Assessment_Model!L39 | P39: Does not exist; no owner, no documentation, no practice. | Q39: Ad hoc; depends entirely on specific individuals. | R39: Partially documented or implemented; coverage inconsistent; never tested under stress. | S39: Documented, owned, executed consistently; basic evidence and metrics exist. | T39: Measured and periodically tested/audited; integrated with adjacent processes. | U39: Optimized and automated where practical; stress-tested; benchmarked externally. | V39: Demand shock; Financial liquidity crisis; Reputation crisis | Y39: Use the recommended action generated by the model; validate with domain owner during real assessment. | Z39: 4 | AA39: 5 | AB39: 5 | AM39: =_DATA_Assessment_Model!AJ39 | AN39: =_DATA_Assessment_Model!AK39 | AO39: =_DATA_Assessment_Model!AL39 | AP39: =_DATA_Assessment_Model!AM39 | AQ39: =_DATA_Assessment_Model!AN39 | AR39: =_DATA_Assessment_Model!AO39 | AS39: =_DATA_Assessment_Model!AP39 | AT39: =_DATA_Assessment_Model!AQ39 | ... AW39: =_DATA_Assessment_Model!AT39 | AY39: =_DATA_Assessment_Model!AV39
A40: Strategy GTM | B40: Strategy GTM | C40: 21 | D40: STRA-017 | E40: Offering and positioning | F40: How mature is the organization in managing proof assets such as case studies, references, certifications, security evidence and continuity commitments, including ownership, evidence, metrics, fallback procedures and crisis stress testing? | G40: This topic affects exposure to Demand shock; Financial liquidity crisis; Reputation crisis. It helps identify how disruption may impact operations, people, revenue, systems, legal exposure or recovery time. | H40: ISO 9001; ISO 31000; ISO 37000; McKinsey 7S; OHI; Bain Elements of Value; Jobs-to-be-Done; Porter Five Forces; OKR | I40: Policy/SOP; owner/RACI; system report; dashboard; contracts; test records; incident history; interview evidence related to proof assets such as case studies, references, certifications, security evidence and continuity commitments. | J40: 5 | K40: =_DATA_Assessment_Model!H40 | L40: =_DATA_Assessment_Model!I40 | M40: =_DATA_Assessment_Model!J40 | N40: =_DATA_Assessment_Model!K40 | O40: =_DATA_Assessment_Model!L40 | P40: Does not exist; no owner, no documentation, no practice. | Q40: Ad hoc; depends entirely on specific individuals. | R40: Partially documented or implemented; coverage inconsistent; never tested under stress. | S40: Documented, owned, executed consistently; basic evidence and metrics exist. | T40: Measured and periodically tested/audited; integrated with adjacent processes. | U40: Optimized and automated where practical; stress-tested; benchmarked externally. | V40: Demand shock; Financial liquidity crisis; Reputation crisis | Y40: Use the recommended action generated by the model; validate with domain owner during real assessment. | Z40: 4 | AA40: 5 | AB40: 5 | AM40: =_DATA_Assessment_Model!AJ40 | AN40: =_DATA_Assessment_Model!AK40 | AO40: =_DATA_Assessment_Model!AL40 | AP40: =_DATA_Assessment_Model!AM40 | AQ40: =_DATA_Assessment_Model!AN40 | AR40: =_DATA_Assessment_Model!AO40 | AS40: =_DATA_Assessment_Model!AP40 | AT40: =_DATA_Assessment_Model!AQ40 | ... AW40: =_DATA_Assessment_Model!AT40 | AY40: =_DATA_Assessment_Model!AV40
... A49: Strategy GTM | B49: Strategy GTM | C49: 30 | D49: STRA-028 | E49: External relations and partnerships | F49: How mature is the organization in managing owner, investor and lender communication discipline including bad-news protocols and crisis updates, including ownership, evidence, metrics, fallback procedures and crisis stress testing? | G49: This topic affects exposure to Financial/liquidity crisis; Reputation crisis. It helps identify how disruption may impact operations, people, revenue, systems, legal exposure or recovery time. | H49: APQC PCF 12.2; ISO 37000; COSO | I49: Policy/SOP; owner/RACI; system report; dashboard; contracts; test records; incident history; interview evidence related to documented strategy translated into objectives, KPIs, budgets and accountable owners. | J49: 4 | K49: =_DATA_Assessment_Model!H49 | L49: =_DATA_Assessment_Model!I49 | M49: =_DATA_Assessment_Model!J49 | N49: =_DATA_Assessment_Model!K49 | O49: =_DATA_Assessment_Model!L49 | P49: No reliable evidence that owner, investor and lender communication discipline including bad-news protocols and crisis updates is defined, owned or managed. | Q49: Owner, investor and lender communication discipline including bad-news protocols and crisis updates is handled informally and depends on individual knowledge or heroic effort. | R49: Owner, investor and lender communication discipline including bad-news protocols and crisis updates is partially documented or implemented, but coverage is inconsistent and not crisis-tested. | S49: Owner, investor and lender communication discipline including bad-news protocols and crisis updates is documented, owned, used in normal operations and supported by basic evidence or metrics. | T49: Owner, investor and lender communication discipline including bad-news protocols and crisis updates is measured, periodically reviewed, integrated with related processes and tested against relevant disruption scenarios. | U49: Owner, investor and lender communication discipline including bad-news protocols and crisis updates is optimized, continuously improved, automated where practical and demonstrably supports crisis resilience. | V49: Financial/liquidity crisis; Reputation crisis | Y49: Use the recommended action generated by the model; validate with domain owner during real assessment. | Z49: 2 | AA49: 4 | AB49: 4 | AM49: =_DATA_Assessment_Model!AJ49 | AN49: =_DATA_Assessment_Model!AK49 | AO49: =_DATA_Assessment_Model!AL49 | AP49: =_DATA_Assessment_Model!AM49 | AQ49: =_DATA_Assessment_Model!AN49 | AR49: =_DATA_Assessment_Model!AO49 | AS49: =_DATA_Assessment_Model!AP49 | AT49: =_DATA_Assessment_Model!AQ49 | ... AW49: =_DATA_Assessment_Model!AT49 | AY49: =_DATA_Assessment_Model!AV49
A50: Governance Crisis | B50: Governance Crisis | C50: 5 | D50: GOVE-001 | E50: Crisis governance | F50: How mature is the organization in managing formal crisis management structure with named roles, deputies, escalation paths and decision authority, including ownership, evidence, metrics, fallback procedures and crisis stress testing? | G50: This topic affects exposure to All crisis types. It helps identify how disruption may impact operations, people, revenue, systems, legal exposure or recovery time. | H50: ISO 22301; ISO 22320; ISO 31000; ISO 37000; NIST SP 800-34; BCI Good Practice Guidelines; Bain RAPID | I50: Policy/SOP; owner/RACI; system report; dashboard; contracts; test records; incident history; interview evidence related to formal crisis management structure with named roles, deputies, escalation paths and decision authority. | J50: 5 | K50: =_DATA_Assessment_Model!H50 | L50: =_DATA_Assessment_Model!I50 | M50: =_DATA_Assessment_Model!J50 | N50: =_DATA_Assessment_Model!K50 | O50: =_DATA_Assessment_Model!L50 | P50: Does not exist; no owner, no documentation, no practice. | Q50: Ad hoc; depends entirely on specific individuals. | R50: Partially documented or implemented; coverage inconsistent; never tested under stress. | S50: Documented, owned, executed consistently; basic evidence and metrics exist. | T50: Measured and periodically tested/audited; integrated with adjacent processes. | U50: Optimized and automated where practical; stress-tested; benchmarked externally. | V50: All crisis types | Y50: Use the recommended action generated by the model; validate with domain owner during real assessment. | Z50: 4 | AA50: 5 | AB50: 5 | AD50: Crisis governance | AE50: =_DATA_Assessment_Model!AB50 | AF50: =_DATA_Assessment_Model!AC50 | AG50: =_DATA_Assessment_Model!AD50 | AH50: =_DATA_Assessment_Model!AE50 | AI50: =_DATA_Assessment_Model!AF50 | AJ50: =_DATA_Assessment_Model!AG50 | AM50: =_DATA_Assessment_Model!AJ50 | AN50: =_DATA_Assessment_Model!AK50 | AO50: =_DATA_Assessment_Model!AL50 | AP50: =_DATA_Assessment_Model!AM50 | AQ50: =_DATA_Assessment_Model!AN50 | AR50: =_DATA_Assessment_Model!AO50 | AS50: =_DATA_Assessment_Model!AP50 | AT50: =_DATA_Assessment_Model!AQ50 | ... AW50: =_DATA_Assessment_Model!AT50 | AY50: =_DATA_Assessment_Model!AV50
A51: Governance Crisis | B51: Governance Crisis | C51: 6 | D51: GOVE-002 | E51: Crisis governance | F51: How mature is the organization in managing executive crisis team trained for cross-functional crisis response, including ownership, evidence, metrics, fallback procedures and crisis stress testing? | G51: This topic affects exposure to All crisis types. It helps identify how disruption may impact operations, people, revenue, systems, legal exposure or recovery time. | H51: ISO 22301; ISO 22320; ISO 31000; ISO 37000; NIST SP 800-34; BCI Good Practice Guidelines; Bain RAPID | I51: Policy/SOP; owner/RACI; system report; dashboard; contracts; test records; incident history; interview evidence related to executive crisis team trained for cross-functional crisis response. | J51: 5 | K51: =_DATA_Assessment_Model!H51 | L51: =_DATA_Assessment_Model!I51 | M51: =_DATA_Assessment_Model!J51 | N51: =_DATA_Assessment_Model!K51 | O51: =_DATA_Assessment_Model!L51 | P51: Does not exist; no owner, no documentation, no practice. | Q51: Ad hoc; depends entirely on specific individuals. | R51: Partially documented or implemented; coverage inconsistent; never tested under stress. | S51: Documented, owned, executed consistently; basic evidence and metrics exist. | T51: Measured and periodically tested/audited; integrated with adjacent processes. | U51: Optimized and automated where practical; stress-tested; benchmarked externally. | V51: All crisis types | Y51: Use the recommended action generated by the model; validate with domain owner during real assessment. | Z51: 4 | AA51: 5 | AB51: 5 | AD51: Risk and continuity | AE51: =_DATA_Assessment_Model!AB51 | AF51: =_DATA_Assessment_Model!AC51 | AG51: =_DATA_Assessment_Model!AD51 | AH51: =_DATA_Assessment_Model!AE51 | AI51: =_DATA_Assessment_Model!AF51 | AJ51: =_DATA_Assessment_Model!AG51 | AM51: =_DATA_Assessment_Model!AJ51 | AN51: =_DATA_Assessment_Model!AK51 | AO51: =_DATA_Assessment_Model!AL51 | AP51: =_DATA_Assessment_Model!AM51 | AQ51: =_DATA_Assessment_Model!AN51 | AR51: =_DATA_Assessment_Model!AO51 | AS51: =_DATA_Assessment_Model!AP51 | AT51: =_DATA_Assessment_Model!AQ51 | ... AW51: =_DATA_Assessment_Model!AT51 | AY51: =_DATA_Assessment_Model!AV51
A52: Governance Crisis | B52: Governance Crisis | C52: 7 | D52: GOVE-003 | E52: Crisis governance | F52: How mature is the organization in managing clear crisis decision rights for finance, people, operations, IT, legal, safety and communications, including ownership, evidence, metrics, fallback procedures and crisis stress testing? | G52: This topic affects exposure to All crisis types. It helps identify how disruption may impact operations, people, revenue, systems, legal exposure or recovery time. | H52: ISO 22301; ISO 22320; ISO 31000; ISO 37000; NIST SP 800-34; BCI Good Practice Guidelines; Bain RAPID | I52: Policy/SOP; owner/RACI; system report; dashboard; contracts; test records; incident history; interview evidence related to clear crisis decision rights for finance, people, operations, IT, legal, safety and communications. | J52: 5 | K52: =_DATA_Assessment_Model!H52 | L52: =_DATA_Assessment_Model!I52 | M52: =_DATA_Assessment_Model!J52 | N52: =_DATA_Assessment_Model!K52 | O52: =_DATA_Assessment_Model!L52 | P52: Does not exist; no owner, no documentation, no practice. | Q52: Ad hoc; depends entirely on specific individuals. | R52: Partially documented or implemented; coverage inconsistent; never tested under stress. | S52: Documented, owned, executed consistently; basic evidence and metrics exist. | T52: Measured and periodically tested/audited; integrated with adjacent processes. | U52: Optimized and automated where practical; stress-tested; benchmarked externally. | V52: All crisis types | Y52: Use the recommended action generated by the model; validate with domain owner during real assessment. | Z52: 4 | AA52: 5 | AB52: 5 | AD52: Incident management | AE52: =_DATA_Assessment_Model!AB52 | AF52: =_DATA_Assessment_Model!AC52 | AG52: =_DATA_Assessment_Model!AD52 | AH52: =_DATA_Assessment_Model!AE52 | AI52: =_DATA_Assessment_Model!AF52 | AJ52: =_DATA_Assessment_Model!AG52 | AM52: =_DATA_Assessment_Model!AJ52 | AN52: =_DATA_Assessment_Model!AK52 | AO52: =_DATA_Assessment_Model!AL52 | AP52: =_DATA_Assessment_Model!AM52 | AQ52: =_DATA_Assessment_Model!AN52 | AR52: =_DATA_Assessment_Model!AO52 | AS52: =_DATA_Assessment_Model!AP52 | AT52: =_DATA_Assessment_Model!AQ52 | ... AW52: =_DATA_Assessment_Model!AT52 | AY52: =_DATA_Assessment_Model!AV52
A53: Governance Crisis | B53: Governance Crisis | C53: 8 | D53: GOVE-004 | E53: Crisis governance | F53: How mature is the organization in managing crisis cadence for situation reports, decisions, action owners, deadlines and follow-up, including ownership, evidence, metrics, fallback procedures and crisis stress testing? | G53: This topic affects exposure to All crisis types. It helps identify how disruption may impact operations, people, revenue, systems, legal exposure or recovery time. | H53: ISO 22301; ISO 22320; ISO 31000; ISO 37000; NIST SP 800-34; BCI Good Practice Guidelines; Bain RAPID | I53: Policy/SOP; owner/RACI; system report; dashboard; contracts; test records; incident history; interview evidence related to crisis cadence for situation reports, decisions, action owners, deadlines and follow-up. | J53: 5 | K53: =_DATA_Assessment_Model!H53 | L53: =_DATA_Assessment_Model!I53 | M53: =_DATA_Assessment_Model!J53 | N53: =_DATA_Assessment_Model!K53 | O53: =_DATA_Assessment_Model!L53 | P53: Does not exist; no owner, no documentation, no practice. | Q53: Ad hoc; depends entirely on specific individuals. | R53: Partially documented or implemented; coverage inconsistent; never tested under stress. | S53: Documented, owned, executed consistently; basic evidence and metrics exist. | T53: Measured and periodically tested/audited; integrated with adjacent processes. | U53: Optimized and automated where practical; stress-tested; benchmarked externally. | V53: All crisis types | Y53: Use the recommended action generated by the model; validate with domain owner during real assessment. | Z53: 4 | AA53: 5 | AB53: 5 | AM53: =_DATA_Assessment_Model!AJ53 | AN53: =_DATA_Assessment_Model!AK53 | AO53: =_DATA_Assessment_Model!AL53 | AP53: =_DATA_Assessment_Model!AM53 | AQ53: =_DATA_Assessment_Model!AN53 | AR53: =_DATA_Assessment_Model!AO53 | AS53: =_DATA_Assessment_Model!AP53 | AT53: =_DATA_Assessment_Model!AQ53 | ... AW53: =_DATA_Assessment_Model!AT53 | AY53: =_DATA_Assessment_Model!AV53
A54: Governance Crisis | B54: Governance Crisis | C54: 9 | D54: GOVE-005 | E54: Crisis governance | F54: How mature is the organization in managing board or owner-level oversight of resilience, continuity and enterprise risk, including ownership, evidence, metrics, fallback procedures and crisis stress testing? | G54: This topic affects exposure to All crisis types. It helps identify how disruption may impact operations, people, revenue, systems, legal exposure or recovery time. | H54: ISO 22301; ISO 22320; ISO 31000; ISO 37000; NIST SP 800-34; BCI Good Practice Guidelines; Bain RAPID | I54: Policy/SOP; owner/RACI; system report; dashboard; contracts; test records; incident history; interview evidence related to board or owner-level oversight of resilience, continuity and enterprise risk. | J54: 5 | K54: =_DATA_Assessment_Model!H54 | L54: =_DATA_Assessment_Model!I54 | M54: =_DATA_Assessment_Model!J54 | N54: =_DATA_Assessment_Model!K54 | O54: =_DATA_Assessment_Model!L54 | P54: Does not exist; no owner, no documentation, no practice. | Q54: Ad hoc; depends entirely on specific individuals. | R54: Partially documented or implemented; coverage inconsistent; never tested under stress. | S54: Documented, owned, executed consistently; basic evidence and metrics exist. | T54: Measured and periodically tested/audited; integrated with adjacent processes. | U54: Optimized and automated where practical; stress-tested; benchmarked externally. | V54: All crisis types | Y54: Use the recommended action generated by the model; validate with domain owner during real assessment. | Z54: 4 | AA54: 5 | AB54: 5 | AM54: =_DATA_Assessment_Model!AJ54 | AN54: =_DATA_Assessment_Model!AK54 | AO54: =_DATA_Assessment_Model!AL54 | AP54: =_DATA_Assessment_Model!AM54 | AQ54: =_DATA_Assessment_Model!AN54 | AR54: =_DATA_Assessment_Model!AO54 | AS54: =_DATA_Assessment_Model!AP54 | AT54: =_DATA_Assessment_Model!AQ54 | ... AW54: =_DATA_Assessment_Model!AT54 | AY54: =_DATA_Assessment_Model!AV54
A55: Governance Crisis | B55: Governance Crisis | C55: 10 | D55: GOVE-006 | E55: Crisis governance | F55: How mature is the organization in managing emergency spending authority and budget release rules, including ownership, evidence, metrics, fallback procedures and crisis stress testing? | G55: This topic affects exposure to All crisis types. It helps identify how disruption may impact operations, people, revenue, systems, legal exposure or recovery time. | H55: ISO 22301; ISO 22320; ISO 31000; ISO 37000; NIST SP 800-34; BCI Good Practice Guidelines; Bain RAPID | I55: Policy/SOP; owner/RACI; system report; dashboard; contracts; test records; incident history; interview evidence related to emergency spending authority and budget release rules. | J55: 3 | K55: =_DATA_Assessment_Model!H55 | L55: =_DATA_Assessment_Model!I55 | M55: =_DATA_Assessment_Model!J55 | N55: =_DATA_Assessment_Model!K55 | O55: =_DATA_Assessment_Model!L55 | P55: No reliable evidence that emergency spending authority and budget release rules is defined, owned or managed. | Q55: Emergency spending authority and budget release rules is handled informally and depends on individual knowledge or heroic effort. | R55: Emergency spending authority and budget release rules is partially documented or implemented, but coverage is inconsistent and not crisis-tested. | S55: Emergency spending authority and budget release rules is documented, owned, used in normal operations and supported by basic evidence or metrics. | T55: Emergency spending authority and budget release rules is measured, periodically reviewed, integrated with related processes and tested against relevant disruption scenarios. | U55: Emergency spending authority and budget release rules is optimized, continuously improved, automated where practical and demonstrably supports crisis resilience. | V55: All crisis types | Y55: Use the recommended action generated by the model; validate with domain owner during real assessment. | Z55: 4 | AA55: 5 | AB55: 5 | AM55: =_DATA_Assessment_Model!AJ55 | AN55: =_DATA_Assessment_Model!AK55 | AO55: =_DATA_Assessment_Model!AL55 | AP55: =_DATA_Assessment_Model!AM55 | AQ55: =_DATA_Assessment_Model!AN55 | AR55: =_DATA_Assessment_Model!AO55 | AS55: =_DATA_Assessment_Model!AP55 | AT55: =_DATA_Assessment_Model!AQ55 | ... AW55: =_DATA_Assessment_Model!AT55 | AY55: =_DATA_Assessment_Model!AV55
A56: Governance Crisis | B56: Governance Crisis | C56: 11 | D56: GOVE-007 | E56: Risk and continuity | F56: How mature is the organization in managing enterprise risk register with owners, likelihood, impact, controls, triggers and residual risk, including ownership, evidence, metrics, fallback procedures and crisis stress testing? | G56: This topic affects exposure to All crisis types. It helps identify how disruption may impact operations, people, revenue, systems, legal exposure or recovery time. | H56: ISO 22301; ISO 22320; ISO 31000; ISO 37000; NIST SP 800-34; BCI Good Practice Guidelines; Bain RAPID | I56: Policy/SOP; owner/RACI; system report; dashboard; contracts; test records; incident history; interview evidence related to enterprise risk register with owners, likelihood, impact, controls, triggers and residual risk. | J56: 5 | K56: =_DATA_Assessment_Model!H56 | L56: =_DATA_Assessment_Model!I56 | M56: =_DATA_Assessment_Model!J56 | N56: =_DATA_Assessment_Model!K56 | O56: =_DATA_Assessment_Model!L56 | P56: No inventory/register exists. | Q56: Partial lists live in individuals' heads or personal files. | R56: A register exists but is incomplete or outdated (>1 year) and has no owner. | S56: Owned, documented, updated on a defined schedule, covers the main scope. | T56: Complete and periodically reviewed; integrated with related processes; completeness measured. | U56: Maintained automatically or synced with systems; drives decisions; audited. | V56: All crisis types | Y56: Use the recommended action generated by the model; validate with domain owner during real assessment. | Z56: 4 | AA56: 5 | AB56: 5 | AM56: =_DATA_Assessment_Model!AJ56 | AN56: =_DATA_Assessment_Model!AK56 | AO56: =_DATA_Assessment_Model!AL56 | AP56: =_DATA_Assessment_Model!AM56 | AQ56: =_DATA_Assessment_Model!AN56 | AR56: =_DATA_Assessment_Model!AO56 | AS56: =_DATA_Assessment_Model!AP56 | AT56: =_DATA_Assessment_Model!AQ56 | ... AW56: =_DATA_Assessment_Model!AT56 | AY56: =_DATA_Assessment_Model!AV56
A57: Governance Crisis | B57: Governance Crisis | C57: 12 | D57: GOVE-008 | E57: Risk and continuity | F57: How mature is the organization in managing risk appetite for safety, cash, cyber, delivery, compliance, reputation and operational continuity, including ownership, evidence, metrics, fallback procedures and crisis stress testing? | G57: This topic affects exposure to All crisis types. It helps identify how disruption may impact operations, people, revenue, systems, legal exposure or recovery time. | H57: ISO 22301; ISO 22320; ISO 31000; ISO 37000; NIST SP 800-34; BCI Good Practice Guidelines; Bain RAPID | I57: Policy/SOP; owner/RACI; system report; dashboard; contracts; test records; incident history; interview evidence related to risk appetite for safety, cash, cyber, delivery, compliance, reputation and operational continuity. | J57: 5 | K57: =_DATA_Assessment_Model!H57 | L57: =_DATA_Assessment_Model!I57 | M57: =_DATA_Assessment_Model!J57 | N57: =_DATA_Assessment_Model!K57 | O57: =_DATA_Assessment_Model!L57 | P57: Does not exist; no owner, no documentation, no practice. | Q57: Ad hoc; depends entirely on specific individuals. | R57: Partially documented or implemented; coverage inconsistent; never tested under stress. | S57: Documented, owned, executed consistently; basic evidence and metrics exist. | T57: Measured and periodically tested/audited; integrated with adjacent processes. | U57: Optimized and automated where practical; stress-tested; benchmarked externally. | V57: All crisis types | Y57: Use the recommended action generated by the model; validate with domain owner during real assessment. | Z57: 5 | AA57: 5 | AB57: 5 | AM57: =_DATA_Assessment_Model!AJ57 | AN57: =_DATA_Assessment_Model!AK57 | AO57: =_DATA_Assessment_Model!AL57 | AP57: =_DATA_Assessment_Model!AM57 | AQ57: =_DATA_Assessment_Model!AN57 | AR57: =_DATA_Assessment_Model!AO57 | AS57: =_DATA_Assessment_Model!AP57 | AT57: =_DATA_Assessment_Model!AQ57 | ... AW57: =_DATA_Assessment_Model!AT57 | AY57: =_DATA_Assessment_Model!AV57
A58: Governance Crisis | B58: Governance Crisis | C58: 13 | D58: GOVE-009 | E58: Risk and continuity | F58: How mature is the organization in managing early warning indicators for major crisis types and objective crisis activation triggers, including ownership, evidence, metrics, fallback procedures and crisis stress testing? | G58: This topic affects exposure to All crisis types. It helps identify how disruption may impact operations, people, revenue, systems, legal exposure or recovery time. | H58: ISO 22301; ISO 22320; ISO 31000; ISO 37000; NIST SP 800-34; BCI Good Practice Guidelines; Bain RAPID | I58: Policy/SOP; owner/RACI; system report; dashboard; contracts; test records; incident history; interview evidence related to early warning indicators for major crisis types and objective crisis activation triggers. | J58: 5 | K58: =_DATA_Assessment_Model!H58 | L58: =_DATA_Assessment_Model!I58 | M58: =_DATA_Assessment_Model!J58 | N58: =_DATA_Assessment_Model!K58 | O58: =_DATA_Assessment_Model!L58 | P58: Nothing is monitored or measured. | Q58: Occasional manual checks by individuals. | R58: Some metrics exist but are not reviewed regularly and trigger no action. | S58: Defined metrics with an owner, reviewed on a set cadence. | T58: Thresholds and alerts in place; deviations trigger documented action; trends analyzed. | U58: Automated monitoring with leading indicators, integrated into management decisions. | V58: All crisis types | Y58: Use the recommended action generated by the model; validate with domain owner during real assessment. | Z58: 4 | AA58: 5 | AB58: 5 | AM58: =_DATA_Assessment_Model!AJ58 | AN58: =_DATA_Assessment_Model!AK58 | AO58: =_DATA_Assessment_Model!AL58 | AP58: =_DATA_Assessment_Model!AM58 | AQ58: =_DATA_Assessment_Model!AN58 | AR58: =_DATA_Assessment_Model!AO58 | AS58: =_DATA_Assessment_Model!AP58 | AT58: =_DATA_Assessment_Model!AQ58 | ... AW58: =_DATA_Assessment_Model!AT58 | AY58: =_DATA_Assessment_Model!AV58
A59: Governance Crisis | B59: Governance Crisis | C59: 14 | D59: GOVE-010 | E59: Risk and continuity | F59: How mature is the organization in managing business impact analysis across functions, sites, systems, people and suppliers, including ownership, evidence, metrics, fallback procedures and crisis stress testing? | G59: This topic affects exposure to All crisis types. It helps identify how disruption may impact operations, people, revenue, systems, legal exposure or recovery time. | H59: ISO 22301; ISO 22320; ISO 31000; ISO 37000; NIST SP 800-34; BCI Good Practice Guidelines; Bain RAPID | I59: Policy/SOP; owner/RACI; system report; dashboard; contracts; test records; incident history; interview evidence related to business impact analysis across functions, sites, systems, people and suppliers. | J59: 5 | K59: =_DATA_Assessment_Model!H59 | L59: =_DATA_Assessment_Model!I59 | M59: =_DATA_Assessment_Model!J59 | N59: =_DATA_Assessment_Model!K59 | O59: =_DATA_Assessment_Model!L59 | P59: Does not exist; no owner, no documentation, no practice. | Q59: Ad hoc; depends entirely on specific individuals. | R59: Partially documented or implemented; coverage inconsistent; never tested under stress. | S59: Documented, owned, executed consistently; basic evidence and metrics exist. | T59: Measured and periodically tested/audited; integrated with adjacent processes. | U59: Optimized and automated where practical; stress-tested; benchmarked externally. | V59: All crisis types | Y59: Use the recommended action generated by the model; validate with domain owner during real assessment. | Z59: 4 | AA59: 5 | AB59: 5 | AM59: =_DATA_Assessment_Model!AJ59 | AN59: =_DATA_Assessment_Model!AK59 | AO59: =_DATA_Assessment_Model!AL59 | AP59: =_DATA_Assessment_Model!AM59 | AQ59: =_DATA_Assessment_Model!AN59 | AR59: =_DATA_Assessment_Model!AO59 | AS59: =_DATA_Assessment_Model!AP59 | AT59: =_DATA_Assessment_Model!AQ59 | ... AW59: =_DATA_Assessment_Model!AT59 | AY59: =_DATA_Assessment_Model!AV59
A60: Governance Crisis | B60: Governance Crisis | C60: 15 | D60: GOVE-011 | E60: Risk and continuity | F60: How mature is the organization in managing business continuity plans covering critical processes, people, systems, sites, suppliers and communication, including ownership, evidence, metrics, fallback procedures and crisis stress testing? | G60: This topic affects exposure to All crisis types. It helps identify how disruption may impact operations, people, revenue, systems, legal exposure or recovery time. | H60: ISO 22301; ISO 22320; ISO 31000; ISO 37000; NIST SP 800-34; BCI Good Practice Guidelines; Bain RAPID | I60: Policy/SOP; owner/RACI; system report; dashboard; contracts; test records; incident history; interview evidence related to business continuity plans covering critical processes, people, systems, sites, suppliers and communication. | J60: 5 | K60: =_DATA_Assessment_Model!H60 | L60: =_DATA_Assessment_Model!I60 | M60: =_DATA_Assessment_Model!J60 | N60: =_DATA_Assessment_Model!K60 | O60: =_DATA_Assessment_Model!L60 | P60: No plan or procedure exists. | Q60: Knowledge lives with individuals; nothing usable is written down. | R60: Drafted but outdated, not approved, or unknown to the people who must use it. | S60: Approved and current; owners assigned; affected staff know it exists and where to find it. | T60: Tested against realistic scenarios; updated after each test or real incident. | U60: Exercised regularly including external parties; readiness measured; continuously improved. | V60: All crisis types | Y60: Use the recommended action generated by the model; validate with domain owner during real assessment. | Z60: 4 | AA60: 5 | AB60: 5 | AM60: =_DATA_Assessment_Model!AJ60 | AN60: =_DATA_Assessment_Model!AK60 | AO60: =_DATA_Assessment_Model!AL60 | AP60: =_DATA_Assessment_Model!AM60 | AQ60: =_DATA_Assessment_Model!AN60 | AR60: =_DATA_Assessment_Model!AO60 | AS60: =_DATA_Assessment_Model!AP60 | AT60: =_DATA_Assessment_Model!AQ60 | ... AW60: =_DATA_Assessment_Model!AT60 | AY60: =_DATA_Assessment_Model!AV60
A61: Governance Crisis | B61: Governance Crisis | C61: 16 | D61: GOVE-012 | E61: Risk and continuity | F61: How mature is the organization in managing scenario library covering cyberattack, war/security, site loss, supplier disruption, cloud outage, pandemic, demand shock and liquidity crisis, including ownership, evidence, metrics, fallback procedures and crisis stress testing? | G61: This topic affects exposure to All crisis types. It helps identify how disruption may impact operations, people, revenue, systems, legal exposure or recovery time. | H61: ISO 22301; ISO 22320; ISO 31000; ISO 37000; NIST SP 800-34; BCI Good Practice Guidelines; Bain RAPID | I61: Policy/SOP; owner/RACI; system report; dashboard; contracts; test records; incident history; interview evidence related to scenario library covering cyberattack, war/security, site loss, supplier disruption, cloud outage, pandemic, demand shock and liquidity crisis. | J61: 5 | K61: =_DATA_Assessment_Model!H61 | L61: =_DATA_Assessment_Model!I61 | M61: =_DATA_Assessment_Model!J61 | N61: =_DATA_Assessment_Model!K61 | O61: =_DATA_Assessment_Model!L61 | P61: Does not exist; no owner, no documentation, no practice. | Q61: Ad hoc; depends entirely on specific individuals. | R61: Partially documented or implemented; coverage inconsistent; never tested under stress. | S61: Documented, owned, executed consistently; basic evidence and metrics exist. | T61: Measured and periodically tested/audited; integrated with adjacent processes. | U61: Optimized and automated where practical; stress-tested; benchmarked externally. | V61: All crisis types | Y61: Use the recommended action generated by the model; validate with domain owner during real assessment. | Z61: 5 | AA61: 5 | AB61: 5 | AM61: =_DATA_Assessment_Model!AJ61 | AN61: =_DATA_Assessment_Model!AK61 | AO61: =_DATA_Assessment_Model!AL61 | AP61: =_DATA_Assessment_Model!AM61 | AQ61: =_DATA_Assessment_Model!AN61 | AR61: =_DATA_Assessment_Model!AO61 | AS61: =_DATA_Assessment_Model!AP61 | AT61: =_DATA_Assessment_Model!AQ61 | ... AW61: =_DATA_Assessment_Model!AT61 | AY61: =_DATA_Assessment_Model!AV61
A62: Governance Crisis | B62: Governance Crisis | C62: 17 | D62: GOVE-013 | E62: Risk and continuity | F62: How mature is the organization in managing continuity testing through tabletop exercises, simulations and real incident reviews, including ownership, evidence, metrics, fallback procedures and crisis stress testing? | G62: This topic affects exposure to All crisis types. It helps identify how disruption may impact operations, people, revenue, systems, legal exposure or recovery time. | H62: ISO 22301; ISO 22320; ISO 31000; ISO 37000; NIST SP 800-34; BCI Good Practice Guidelines; Bain RAPID | I62: Policy/SOP; owner/RACI; system report; dashboard; contracts; test records; incident history; interview evidence related to continuity testing through tabletop exercises, simulations and real incident reviews. | J62: 5 | K62: =_DATA_Assessment_Model!H62 | L62: =_DATA_Assessment_Model!I62 | M62: =_DATA_Assessment_Model!J62 | N62: =_DATA_Assessment_Model!K62 | O62: =_DATA_Assessment_Model!L62 | P62: Never done; no records exist. | Q62: Done once long ago or only after an incident; no schedule, no records. | R62: Done irregularly; results are not documented and findings are not tracked. | S62: Done on a defined schedule (at least annually); results documented, owner assigned. | T62: Done quarterly/semi-annually; findings tracked to closure, effectiveness measured against targets. | U62: Continuous or automated where possible; results drive improvements and are validated externally (audit/customer). | V62: All crisis types | Y62: Use the recommended action generated by the model; validate with domain owner during real assessment. | Z62: 4 | AA62: 5 | AB62: 5 | AM62: =_DATA_Assessment_Model!AJ62 | AN62: =_DATA_Assessment_Model!AK62 | AO62: =_DATA_Assessment_Model!AL62 | AP62: =_DATA_Assessment_Model!AM62 | AQ62: =_DATA_Assessment_Model!AN62 | AR62: =_DATA_Assessment_Model!AO62 | AS62: =_DATA_Assessment_Model!AP62 | AT62: =_DATA_Assessment_Model!AQ62 | ... AW62: =_DATA_Assessment_Model!AT62 | AY62: =_DATA_Assessment_Model!AV62
A63: Governance Crisis | B63: Governance Crisis | C63: 18 | D63: GOVE-014 | E63: Incident management | F63: How mature is the organization in managing common incident classification model for severity, impact, escalation and communication, including ownership, evidence, metrics, fallback procedures and crisis stress testing? | G63: This topic affects exposure to All crisis types. It helps identify how disruption may impact operations, people, revenue, systems, legal exposure or recovery time. | H63: ISO 22301; ISO 22320; ISO 31000; ISO 37000; NIST SP 800-34; BCI Good Practice Guidelines; Bain RAPID | I63: Policy/SOP; owner/RACI; system report; dashboard; contracts; test records; incident history; interview evidence related to common incident classification model for severity, impact, escalation and communication. | J63: 5 | K63: =_DATA_Assessment_Model!H63 | L63: =_DATA_Assessment_Model!I63 | M63: =_DATA_Assessment_Model!J63 | N63: =_DATA_Assessment_Model!K63 | O63: =_DATA_Assessment_Model!L63 | P63: Does not exist; no owner, no documentation, no practice. | Q63: Ad hoc; depends entirely on specific individuals. | R63: Partially documented or implemented; coverage inconsistent; never tested under stress. | S63: Documented, owned, executed consistently; basic evidence and metrics exist. | T63: Measured and periodically tested/audited; integrated with adjacent processes. | U63: Optimized and automated where practical; stress-tested; benchmarked externally. | V63: All crisis types | Y63: Use the recommended action generated by the model; validate with domain owner during real assessment. | Z63: 4 | AA63: 5 | AB63: 5 | AM63: =_DATA_Assessment_Model!AJ63 | AN63: =_DATA_Assessment_Model!AK63 | AO63: =_DATA_Assessment_Model!AL63 | AP63: =_DATA_Assessment_Model!AM63 | AQ63: =_DATA_Assessment_Model!AN63 | AR63: =_DATA_Assessment_Model!AO63 | AS63: =_DATA_Assessment_Model!AP63 | AT63: =_DATA_Assessment_Model!AQ63 | ... AW63: =_DATA_Assessment_Model!AT63 | AY63: =_DATA_Assessment_Model!AV63
A64: Governance Crisis | B64: Governance Crisis | C64: 19 | D64: GOVE-015 | E64: Incident management | F64: How mature is the organization in managing post-incident review process that converts incidents into corrective and preventive actions, including ownership, evidence, metrics, fallback procedures and crisis stress testing? | G64: This topic affects exposure to All crisis types. It helps identify how disruption may impact operations, people, revenue, systems, legal exposure or recovery time. | H64: ISO 22301; ISO 22320; ISO 31000; ISO 37000; NIST SP 800-34; BCI Good Practice Guidelines; Bain RAPID | I64: Policy/SOP; owner/RACI; system report; dashboard; contracts; test records; incident history; interview evidence related to post-incident review process that converts incidents into corrective and preventive actions. | J64: 5 | K64: =_DATA_Assessment_Model!H64 | L64: =_DATA_Assessment_Model!I64 | M64: =_DATA_Assessment_Model!J64 | N64: =_DATA_Assessment_Model!K64 | O64: =_DATA_Assessment_Model!L64 | P64: Does not exist; no owner, no documentation, no practice. | Q64: Ad hoc; depends entirely on specific individuals. | R64: Partially documented or implemented; coverage inconsistent; never tested under stress. | S64: Documented, owned, executed consistently; basic evidence and metrics exist. | T64: Measured and periodically tested/audited; integrated with adjacent processes. | U64: Optimized and automated where practical; stress-tested; benchmarked externally. | V64: All crisis types | Y64: Use the recommended action generated by the model; validate with domain owner during real assessment. | Z64: 4 | AA64: 5 | AB64: 5 | AM64: =_DATA_Assessment_Model!AJ64 | AN64: =_DATA_Assessment_Model!AK64 | AO64: =_DATA_Assessment_Model!AL64 | AP64: =_DATA_Assessment_Model!AM64 | AQ64: =_DATA_Assessment_Model!AN64 | AR64: =_DATA_Assessment_Model!AO64 | AS64: =_DATA_Assessment_Model!AP64 | AT64: =_DATA_Assessment_Model!AQ64 | ... AW64: =_DATA_Assessment_Model!AT64 | AY64: =_DATA_Assessment_Model!AV64
... A71: Governance Crisis | B71: Governance Crisis | C71: 26 | D71: GOVE-022 | E71: Risk and continuity | F71: How mature is the organization in managing joint crisis exercises with critical suppliers, customers, authorities and insurers, including ownership, evidence, metrics, fallback procedures and crisis stress testing? | G71: This topic affects exposure to Supplier/logistics disruption; War/security crisis; Cyberattack/ransomware. It helps identify how disruption may impact operations, people, revenue, systems, legal exposure or recovery time. | H71: ISO 22301; ISO 22398 | I71: Policy/SOP; owner/RACI; system report; dashboard; contracts; test records; incident history; interview evidence | J71: 3 | K71: =_DATA_Assessment_Model!H71 | L71: =_DATA_Assessment_Model!I71 | M71: =_DATA_Assessment_Model!J71 | N71: =_DATA_Assessment_Model!K71 | O71: =_DATA_Assessment_Model!L71 | P71: Never done; no records exist. | Q71: Done once long ago or only after an incident; no schedule, no records. | R71: Done irregularly; results are not documented and findings are not tracked. | S71: Done on a defined schedule (at least annually); results documented, owner assigned. | T71: Done quarterly/semi-annually; findings tracked to closure, effectiveness measured against targets. | U71: Continuous or automated where possible; results drive improvements and are validated externally (audit/customer). | V71: Supplier/logistics disruption; War/security crisis; Cyberattack/ransomware | Y71: Use the recommended action generated by the model; validate with domain owner during real assessment. | Z71: 2 | AA71: 5 | AB71: 3 | AM71: =_DATA_Assessment_Model!AJ71 | AN71: =_DATA_Assessment_Model!AK71 | AO71: =_DATA_Assessment_Model!AL71 | AP71: =_DATA_Assessment_Model!AM71 | AQ71: =_DATA_Assessment_Model!AN71 | AR71: =_DATA_Assessment_Model!AO71 | AS71: =_DATA_Assessment_Model!AP71 | AT71: =_DATA_Assessment_Model!AQ71 | ... AW71: =_DATA_Assessment_Model!AT71 | AY71: =_DATA_Assessment_Model!AV71
A72: HR Workforce | B72: HR Workforce | C72: 5 | D72: HRWO-001 | E72: Workforce visibility | F72: How mature is the organization in managing workforce inventory by role, location, manager, contract type, employment entity, skill and criticality, including ownership, evidence, metrics, fallback procedures and crisis stress testing? | G72: This topic affects exposure to Workforce disruption; Pandemic/health crisis; War/security crisis. It helps identify how disruption may impact operations, people, revenue, systems, legal exposure or recovery time. | H72: ISO 30414; ISO 30405; ISO 45001; ISO 22301; CIPD; SHRM | I72: Policy/SOP; owner/RACI; system report; dashboard; contracts; test records; incident history; interview evidence related to workforce inventory by role, location, manager, contract type, employment entity, skill and criticality. | J72: 5 | K72: =_DATA_Assessment_Model!H72 | L72: =_DATA_Assessment_Model!I72 | M72: =_DATA_Assessment_Model!J72 | N72: =_DATA_Assessment_Model!K72 | O72: =_DATA_Assessment_Model!L72 | P72: No inventory/register exists. | Q72: Partial lists live in individuals' heads or personal files. | R72: A register exists but is incomplete or outdated (>1 year) and has no owner. | S72: Owned, documented, updated on a defined schedule, covers the main scope. | T72: Complete and periodically reviewed; integrated with related processes; completeness measured. | U72: Maintained automatically or synced with systems; drives decisions; audited. | V72: Workforce disruption; Pandemic/health crisis; War/security crisis | Y72: Use the recommended action generated by the model; validate with domain owner during real assessment. | Z72: 4 | AA72: 5 | AB72: 5 | AD72: Workforce visibility | AE72: =_DATA_Assessment_Model!AB72 | AF72: =_DATA_Assessment_Model!AC72 | AG72: =_DATA_Assessment_Model!AD72 | AH72: =_DATA_Assessment_Model!AE72 | AI72: =_DATA_Assessment_Model!AF72 | AJ72: =_DATA_Assessment_Model!AG72 | AM72: =_DATA_Assessment_Model!AJ72 | AN72: =_DATA_Assessment_Model!AK72 | AO72: =_DATA_Assessment_Model!AL72 | AP72: =_DATA_Assessment_Model!AM72 | AQ72: =_DATA_Assessment_Model!AN72 | AR72: =_DATA_Assessment_Model!AO72 | AS72: =_DATA_Assessment_Model!AP72 | AT72: =_DATA_Assessment_Model!AQ72 | ... AW72: =_DATA_Assessment_Model!AT72 | AY72: =_DATA_Assessment_Model!AV72
A73: HR Workforce | B73: HR Workforce | C73: 6 | D73: HRWO-002 | E73: Workforce visibility | F73: How mature is the organization in managing critical role mapping by process dependency, customer impact, system access and knowledge concentration, including ownership, evidence, metrics, fallback procedures and crisis stress testing? | G73: This topic affects exposure to Workforce disruption; Pandemic/health crisis; War/security crisis. It helps identify how disruption may impact operations, people, revenue, systems, legal exposure or recovery time. | H73: ISO 30414; ISO 30405; ISO 45001; ISO 22301; CIPD; SHRM | I73: Policy/SOP; owner/RACI; system report; dashboard; contracts; test records; incident history; interview evidence related to critical role mapping by process dependency, customer impact, system access and knowledge concentration. | J73: 5 | K73: =_DATA_Assessment_Model!H73 | L73: =_DATA_Assessment_Model!I73 | M73: =_DATA_Assessment_Model!J73 | N73: =_DATA_Assessment_Model!K73 | O73: =_DATA_Assessment_Model!L73 | P73: No inventory/register exists. | Q73: Partial lists live in individuals' heads or personal files. | R73: A register exists but is incomplete or outdated (>1 year) and has no owner. | S73: Owned, documented, updated on a defined schedule, covers the main scope. | T73: Complete and periodically reviewed; integrated with related processes; completeness measured. | U73: Maintained automatically or synced with systems; drives decisions; audited. | V73: Workforce disruption; Pandemic/health crisis; War/security crisis | Y73: Use the recommended action generated by the model; validate with domain owner during real assessment. | Z73: 4 | AA73: 5 | AB73: 5 | AD73: Recruitment and retention | AE73: =_DATA_Assessment_Model!AB73 | AF73: =_DATA_Assessment_Model!AC73 | AG73: =_DATA_Assessment_Model!AD73 | AH73: =_DATA_Assessment_Model!AE73 | AI73: =_DATA_Assessment_Model!AF73 | AJ73: =_DATA_Assessment_Model!AG73 | AM73: =_DATA_Assessment_Model!AJ73 | AN73: =_DATA_Assessment_Model!AK73 | AO73: =_DATA_Assessment_Model!AL73 | AP73: =_DATA_Assessment_Model!AM73 | AQ73: =_DATA_Assessment_Model!AN73 | AR73: =_DATA_Assessment_Model!AO73 | AS73: =_DATA_Assessment_Model!AP73 | AT73: =_DATA_Assessment_Model!AQ73 | ... AW73: =_DATA_Assessment_Model!AT73 | AY73: =_DATA_Assessment_Model!AV73
A74: HR Workforce | B74: HR Workforce | C74: 7 | D74: HRWO-003 | E74: Workforce visibility | F74: How mature is the organization in managing key-person risk for executives, founders, architects, plant specialists, client owners and finance signatories, including ownership, evidence, metrics, fallback procedures and crisis stress testing? | G74: This topic affects exposure to Workforce disruption; Pandemic/health crisis; War/security crisis. It helps identify how disruption may impact operations, people, revenue, systems, legal exposure or recovery time. | H74: ISO 30414; ISO 30405; ISO 45001; ISO 22301; CIPD; SHRM | I74: Policy/SOP; owner/RACI; system report; dashboard; contracts; test records; incident history; interview evidence related to key-person risk for executives, founders, architects, plant specialists, client owners and finance signatories. | J74: 5 | K74: =_DATA_Assessment_Model!H74 | L74: =_DATA_Assessment_Model!I74 | M74: =_DATA_Assessment_Model!J74 | N74: =_DATA_Assessment_Model!K74 | O74: =_DATA_Assessment_Model!L74 | P74: No plan or procedure exists. | Q74: Knowledge lives with individuals; nothing usable is written down. | R74: Drafted but outdated, not approved, or unknown to the people who must use it. | S74: Approved and current; owners assigned; affected staff know it exists and where to find it. | T74: Tested against realistic scenarios; updated after each test or real incident. | U74: Exercised regularly including external parties; readiness measured; continuously improved. | V74: Workforce disruption; Pandemic/health crisis; War/security crisis | Y74: Use the recommended action generated by the model; validate with domain owner during real assessment. | Z74: 4 | AA74: 5 | AB74: 5 | AD74: Continuity and wellbeing | AE74: =_DATA_Assessment_Model!AB74 | AF74: =_DATA_Assessment_Model!AC74 | AG74: =_DATA_Assessment_Model!AD74 | AH74: =_DATA_Assessment_Model!AE74 | AI74: =_DATA_Assessment_Model!AF74 | AJ74: =_DATA_Assessment_Model!AG74 | AM74: =_DATA_Assessment_Model!AJ74 | AN74: =_DATA_Assessment_Model!AK74 | AO74: =_DATA_Assessment_Model!AL74 | AP74: =_DATA_Assessment_Model!AM74 | AQ74: =_DATA_Assessment_Model!AN74 | AR74: =_DATA_Assessment_Model!AO74 | AS74: =_DATA_Assessment_Model!AP74 | AT74: =_DATA_Assessment_Model!AQ74 | ... AW74: =_DATA_Assessment_Model!AT74 | AY74: =_DATA_Assessment_Model!AV74
A75: HR Workforce | B75: HR Workforce | C75: 8 | D75: HRWO-004 | E75: Workforce visibility | F75: How mature is the organization in managing skills matrix linked to critical processes, systems, products, sites and backup coverage, including ownership, evidence, metrics, fallback procedures and crisis stress testing? | G75: This topic affects exposure to Workforce disruption; Pandemic/health crisis; War/security crisis. It helps identify how disruption may impact operations, people, revenue, systems, legal exposure or recovery time. | H75: ISO 30414; ISO 30405; ISO 45001; ISO 22301; CIPD; SHRM | I75: Policy/SOP; owner/RACI; system report; dashboard; contracts; test records; incident history; interview evidence related to skills matrix linked to critical processes, systems, products, sites and backup coverage. | J75: 5 | K75: =_DATA_Assessment_Model!H75 | L75: =_DATA_Assessment_Model!I75 | M75: =_DATA_Assessment_Model!J75 | N75: =_DATA_Assessment_Model!K75 | O75: =_DATA_Assessment_Model!L75 | P75: No inventory/register exists. | Q75: Partial lists live in individuals' heads or personal files. | R75: A register exists but is incomplete or outdated (>1 year) and has no owner. | S75: Owned, documented, updated on a defined schedule, covers the main scope. | T75: Complete and periodically reviewed; integrated with related processes; completeness measured. | U75: Maintained automatically or synced with systems; drives decisions; audited. | V75: Workforce disruption; Pandemic/health crisis; War/security crisis | Y75: Use the recommended action generated by the model; validate with domain owner during real assessment. | Z75: 5 | AA75: 5 | AB75: 5 | AD75: HR systems and compliance | AE75: =_DATA_Assessment_Model!AB75 | AF75: =_DATA_Assessment_Model!AC75 | AG75: =_DATA_Assessment_Model!AD75 | AH75: =_DATA_Assessment_Model!AE75 | AI75: =_DATA_Assessment_Model!AF75 | AJ75: =_DATA_Assessment_Model!AG75 | AM75: =_DATA_Assessment_Model!AJ75 | AN75: =_DATA_Assessment_Model!AK75 | AO75: =_DATA_Assessment_Model!AL75 | AP75: =_DATA_Assessment_Model!AM75 | AQ75: =_DATA_Assessment_Model!AN75 | AR75: =_DATA_Assessment_Model!AO75 | AS75: =_DATA_Assessment_Model!AP75 | AT75: =_DATA_Assessment_Model!AQ75 | ... AW75: =_DATA_Assessment_Model!AT75 | AY75: =_DATA_Assessment_Model!AV75
A76: HR Workforce | B76: HR Workforce | C76: 9 | D76: HRWO-005 | E76: Workforce visibility | F76: How mature is the organization in managing minimum staffing levels for critical functions, shifts, production lines and customer support, including ownership, evidence, metrics, fallback procedures and crisis stress testing? | G76: This topic affects exposure to Workforce disruption; Pandemic/health crisis; War/security crisis. It helps identify how disruption may impact operations, people, revenue, systems, legal exposure or recovery time. | H76: ISO 30414; ISO 30405; ISO 45001; ISO 22301; CIPD; SHRM | I76: Policy/SOP; owner/RACI; system report; dashboard; contracts; test records; incident history; interview evidence related to minimum staffing levels for critical functions, shifts, production lines and customer support. | J76: 5 | K76: =_DATA_Assessment_Model!H76 | L76: =_DATA_Assessment_Model!I76 | M76: =_DATA_Assessment_Model!J76 | N76: =_DATA_Assessment_Model!K76 | O76: =_DATA_Assessment_Model!L76 | P76: Does not exist; no owner, no documentation, no practice. | Q76: Ad hoc; depends entirely on specific individuals. | R76: Partially documented or implemented; coverage inconsistent; never tested under stress. | S76: Documented, owned, executed consistently; basic evidence and metrics exist. | T76: Measured and periodically tested/audited; integrated with adjacent processes. | U76: Optimized and automated where practical; stress-tested; benchmarked externally. | V76: Workforce disruption; Pandemic/health crisis; War/security crisis | Y76: Use the recommended action generated by the model; validate with domain owner during real assessment. | Z76: 4 | AA76: 5 | AB76: 5 | AM76: =_DATA_Assessment_Model!AJ76 | AN76: =_DATA_Assessment_Model!AK76 | AO76: =_DATA_Assessment_Model!AL76 | AP76: =_DATA_Assessment_Model!AM76 | AQ76: =_DATA_Assessment_Model!AN76 | AR76: =_DATA_Assessment_Model!AO76 | AS76: =_DATA_Assessment_Model!AP76 | AT76: =_DATA_Assessment_Model!AQ76 | ... AW76: =_DATA_Assessment_Model!AT76 | AY76: =_DATA_Assessment_Model!AV76
A77: HR Workforce | B77: HR Workforce | C77: 10 | D77: HRWO-006 | E77: Workforce visibility | F77: How mature is the organization in managing absence trends, sick leave spikes and workforce availability monitoring, including ownership, evidence, metrics, fallback procedures and crisis stress testing? | G77: This topic affects exposure to Workforce disruption; Pandemic/health crisis; War/security crisis. It helps identify how disruption may impact operations, people, revenue, systems, legal exposure or recovery time. | H77: ISO 30414; ISO 30405; ISO 45001; ISO 22301; CIPD; SHRM | I77: Policy/SOP; owner/RACI; system report; dashboard; contracts; test records; incident history; interview evidence related to absence trends, sick leave spikes and workforce availability monitoring. | J77: 3 | K77: =_DATA_Assessment_Model!H77 | L77: =_DATA_Assessment_Model!I77 | M77: =_DATA_Assessment_Model!J77 | N77: =_DATA_Assessment_Model!K77 | O77: =_DATA_Assessment_Model!L77 | P77: No reliable evidence that absence trends, sick leave spikes and workforce availability monitoring is defined, owned or managed. | Q77: Absence trends, sick leave spikes and workforce availability monitoring is handled informally and depends on individual knowledge or heroic effort. | R77: Absence trends, sick leave spikes and workforce availability monitoring is partially documented or implemented, but coverage is inconsistent and not crisis-tested. | S77: Absence trends, sick leave spikes and workforce availability monitoring is documented, owned, used in normal operations and supported by basic evidence or metrics. | T77: Absence trends, sick leave spikes and workforce availability monitoring is measured, periodically reviewed, integrated with related processes and tested against relevant disruption scenarios. | U77: Absence trends, sick leave spikes and workforce availability monitoring is optimized, continuously improved, automated where practical and demonstrably supports crisis resilience. | V77: Workforce disruption; Pandemic/health crisis; War/security crisis | Y77: Use the recommended action generated by the model; validate with domain owner during real assessment. | Z77: 4 | AA77: 5 | AB77: 5 | AM77: =_DATA_Assessment_Model!AJ77 | AN77: =_DATA_Assessment_Model!AK77 | AO77: =_DATA_Assessment_Model!AL77 | AP77: =_DATA_Assessment_Model!AM77 | AQ77: =_DATA_Assessment_Model!AN77 | AR77: =_DATA_Assessment_Model!AO77 | AS77: =_DATA_Assessment_Model!AP77 | AT77: =_DATA_Assessment_Model!AQ77 | ... AW77: =_DATA_Assessment_Model!AT77 | AY77: =_DATA_Assessment_Model!AV77
A78: HR Workforce | B78: HR Workforce | C78: 11 | D78: HRWO-007 | E78: Recruitment and retention | F78: How mature is the organization in managing hiring pipeline resilience for critical roles under market shortage or geographic disruption, including ownership, evidence, metrics, fallback procedures and crisis stress testing? | G78: This topic affects exposure to Workforce disruption; Pandemic/health crisis; War/security crisis. It helps identify how disruption may impact operations, people, revenue, systems, legal exposure or recovery time. | H78: ISO 30414; ISO 30405; ISO 45001; ISO 22301; CIPD; SHRM | I78: Policy/SOP; owner/RACI; system report; dashboard; contracts; test records; incident history; interview evidence related to hiring pipeline resilience for critical roles under market shortage or geographic disruption. | J78: 5 | K78: =_DATA_Assessment_Model!H78 | L78: =_DATA_Assessment_Model!I78 | M78: =_DATA_Assessment_Model!J78 | N78: =_DATA_Assessment_Model!K78 | O78: =_DATA_Assessment_Model!L78 | P78: Does not exist; no owner, no documentation, no practice. | Q78: Ad hoc; depends entirely on specific individuals. | R78: Partially documented or implemented; coverage inconsistent; never tested under stress. | S78: Documented, owned, executed consistently; basic evidence and metrics exist. | T78: Measured and periodically tested/audited; integrated with adjacent processes. | U78: Optimized and automated where practical; stress-tested; benchmarked externally. | V78: Workforce disruption; Pandemic/health crisis; War/security crisis | Y78: Use the recommended action generated by the model; validate with domain owner during real assessment. | Z78: 4 | AA78: 5 | AB78: 5 | AM78: =_DATA_Assessment_Model!AJ78 | AN78: =_DATA_Assessment_Model!AK78 | AO78: =_DATA_Assessment_Model!AL78 | AP78: =_DATA_Assessment_Model!AM78 | AQ78: =_DATA_Assessment_Model!AN78 | AR78: =_DATA_Assessment_Model!AO78 | AS78: =_DATA_Assessment_Model!AP78 | AT78: =_DATA_Assessment_Model!AQ78 | ... AW78: =_DATA_Assessment_Model!AT78 | AY78: =_DATA_Assessment_Model!AV78
A79: HR Workforce | B79: HR Workforce | C79: 12 | D79: HRWO-008 | E79: Recruitment and retention | F79: How mature is the organization in managing time-to-hire tracking by critical role, geography and seniority, including ownership, evidence, metrics, fallback procedures and crisis stress testing? | G79: This topic affects exposure to Workforce disruption; Pandemic/health crisis; War/security crisis. It helps identify how disruption may impact operations, people, revenue, systems, legal exposure or recovery time. | H79: ISO 30414; ISO 30405; ISO 45001; ISO 22301; CIPD; SHRM | I79: Policy/SOP; owner/RACI; system report; dashboard; contracts; test records; incident history; interview evidence related to time-to-hire tracking by critical role, geography and seniority. | J79: 5 | K79: =_DATA_Assessment_Model!H79 | L79: =_DATA_Assessment_Model!I79 | M79: =_DATA_Assessment_Model!J79 | N79: =_DATA_Assessment_Model!K79 | O79: =_DATA_Assessment_Model!L79 | P79: Nothing is monitored or measured. | Q79: Occasional manual checks by individuals. | R79: Some metrics exist but are not reviewed regularly and trigger no action. | S79: Defined metrics with an owner, reviewed on a set cadence. | T79: Thresholds and alerts in place; deviations trigger documented action; trends analyzed. | U79: Automated monitoring with leading indicators, integrated into management decisions. | V79: Workforce disruption; Pandemic/health crisis; War/security crisis | Y79: Use the recommended action generated by the model; validate with domain owner during real assessment. | Z79: 4 | AA79: 5 | AB79: 5 | AM79: =_DATA_Assessment_Model!AJ79 | AN79: =_DATA_Assessment_Model!AK79 | AO79: =_DATA_Assessment_Model!AL79 | AP79: =_DATA_Assessment_Model!AM79 | AQ79: =_DATA_Assessment_Model!AN79 | AR79: =_DATA_Assessment_Model!AO79 | AS79: =_DATA_Assessment_Model!AP79 | AT79: =_DATA_Assessment_Model!AQ79 | ... AW79: =_DATA_Assessment_Model!AT79 | AY79: =_DATA_Assessment_Model!AV79
A80: HR Workforce | B80: HR Workforce | C80: 13 | D80: HRWO-009 | E80: Recruitment and retention | F80: How mature is the organization in managing alternative sourcing channels for critical roles, geographies and rare skills, including ownership, evidence, metrics, fallback procedures and crisis stress testing? | G80: This topic affects exposure to Workforce disruption; Pandemic/health crisis; War/security crisis. It helps identify how disruption may impact operations, people, revenue, systems, legal exposure or recovery time. | H80: ISO 30414; ISO 30405; ISO 45001; ISO 22301; CIPD; SHRM | I80: Policy/SOP; owner/RACI; system report; dashboard; contracts; test records; incident history; interview evidence related to alternative sourcing channels for critical roles, geographies and rare skills. | J80: 5 | K80: =_DATA_Assessment_Model!H80 | L80: =_DATA_Assessment_Model!I80 | M80: =_DATA_Assessment_Model!J80 | N80: =_DATA_Assessment_Model!K80 | O80: =_DATA_Assessment_Model!L80 | P80: Does not exist; no owner, no documentation, no practice. | Q80: Ad hoc; depends entirely on specific individuals. | R80: Partially documented or implemented; coverage inconsistent; never tested under stress. | S80: Documented, owned, executed consistently; basic evidence and metrics exist. | T80: Measured and periodically tested/audited; integrated with adjacent processes. | U80: Optimized and automated where practical; stress-tested; benchmarked externally. | V80: Workforce disruption; Pandemic/health crisis; War/security crisis | Y80: Use the recommended action generated by the model; validate with domain owner during real assessment. | Z80: 4 | AA80: 5 | AB80: 5 | AM80: =_DATA_Assessment_Model!AJ80 | AN80: =_DATA_Assessment_Model!AK80 | AO80: =_DATA_Assessment_Model!AL80 | AP80: =_DATA_Assessment_Model!AM80 | AQ80: =_DATA_Assessment_Model!AN80 | AR80: =_DATA_Assessment_Model!AO80 | AS80: =_DATA_Assessment_Model!AP80 | AT80: =_DATA_Assessment_Model!AQ80 | ... AW80: =_DATA_Assessment_Model!AT80 | AY80: =_DATA_Assessment_Model!AV80
A81: HR Workforce | B81: HR Workforce | C81: 14 | D81: HRWO-010 | E81: Recruitment and retention | F81: How mature is the organization in managing retention risk monitoring for critical people, high performers and scarce-skill roles, including ownership, evidence, metrics, fallback procedures and crisis stress testing? | G81: This topic affects exposure to Workforce disruption; Pandemic/health crisis; War/security crisis. It helps identify how disruption may impact operations, people, revenue, systems, legal exposure or recovery time. | H81: ISO 30414; ISO 30405; ISO 45001; ISO 22301; CIPD; SHRM | I81: Policy/SOP; owner/RACI; system report; dashboard; contracts; test records; incident history; interview evidence related to retention risk monitoring for critical people, high performers and scarce-skill roles. | J81: 5 | K81: =_DATA_Assessment_Model!H81 | L81: =_DATA_Assessment_Model!I81 | M81: =_DATA_Assessment_Model!J81 | N81: =_DATA_Assessment_Model!K81 | O81: =_DATA_Assessment_Model!L81 | P81: Nothing is monitored or measured. | Q81: Occasional manual checks by individuals. | R81: Some metrics exist but are not reviewed regularly and trigger no action. | S81: Defined metrics with an owner, reviewed on a set cadence. | T81: Thresholds and alerts in place; deviations trigger documented action; trends analyzed. | U81: Automated monitoring with leading indicators, integrated into management decisions. | V81: Workforce disruption; Pandemic/health crisis; War/security crisis | Y81: Use the recommended action generated by the model; validate with domain owner during real assessment. | Z81: 4 | AA81: 5 | AB81: 5 | AM81: =_DATA_Assessment_Model!AJ81 | AN81: =_DATA_Assessment_Model!AK81 | AO81: =_DATA_Assessment_Model!AL81 | AP81: =_DATA_Assessment_Model!AM81 | AQ81: =_DATA_Assessment_Model!AN81 | AR81: =_DATA_Assessment_Model!AO81 | AS81: =_DATA_Assessment_Model!AP81 | AT81: =_DATA_Assessment_Model!AQ81 | ... AW81: =_DATA_Assessment_Model!AT81 | AY81: =_DATA_Assessment_Model!AV81
A82: HR Workforce | B82: HR Workforce | C82: 15 | D82: HRWO-011 | E82: Recruitment and retention | F82: How mature is the organization in managing compensation and payroll continuity during banking, legal or system disruption, including ownership, evidence, metrics, fallback procedures and crisis stress testing? | G82: This topic affects exposure to Workforce disruption; Pandemic/health crisis; War/security crisis. It helps identify how disruption may impact operations, people, revenue, systems, legal exposure or recovery time. | H82: ISO 30414; ISO 30405; ISO 45001; ISO 22301; CIPD; SHRM | I82: Policy/SOP; owner/RACI; system report; dashboard; contracts; test records; incident history; interview evidence related to compensation and payroll continuity during banking, legal or system disruption. | J82: 5 | K82: =_DATA_Assessment_Model!H82 | L82: =_DATA_Assessment_Model!I82 | M82: =_DATA_Assessment_Model!J82 | N82: =_DATA_Assessment_Model!K82 | O82: =_DATA_Assessment_Model!L82 | P82: Does not exist; no owner, no documentation, no practice. | Q82: Ad hoc; depends entirely on specific individuals. | R82: Partially documented or implemented; coverage inconsistent; never tested under stress. | S82: Documented, owned, executed consistently; basic evidence and metrics exist. | T82: Measured and periodically tested/audited; integrated with adjacent processes. | U82: Optimized and automated where practical; stress-tested; benchmarked externally. | V82: Workforce disruption; Pandemic/health crisis; War/security crisis | Y82: Use the recommended action generated by the model; validate with domain owner during real assessment. | Z82: 4 | AA82: 5 | AB82: 5 | AM82: =_DATA_Assessment_Model!AJ82 | AN82: =_DATA_Assessment_Model!AK82 | AO82: =_DATA_Assessment_Model!AL82 | AP82: =_DATA_Assessment_Model!AM82 | AQ82: =_DATA_Assessment_Model!AN82 | AR82: =_DATA_Assessment_Model!AO82 | AS82: =_DATA_Assessment_Model!AP82 | AT82: =_DATA_Assessment_Model!AQ82 | ... AW82: =_DATA_Assessment_Model!AT82 | AY82: =_DATA_Assessment_Model!AV82
A83: HR Workforce | B83: HR Workforce | C83: 16 | D83: HRWO-012 | E83: Recruitment and retention | F83: How mature is the organization in managing succession planning and deputies for all critical leadership and operational roles, including ownership, evidence, metrics, fallback procedures and crisis stress testing? | G83: This topic affects exposure to Workforce disruption; Pandemic/health crisis; War/security crisis. It helps identify how disruption may impact operations, people, revenue, systems, legal exposure or recovery time. | H83: ISO 30414; ISO 30405; ISO 45001; ISO 22301; CIPD; SHRM | I83: Policy/SOP; owner/RACI; system report; dashboard; contracts; test records; incident history; interview evidence related to succession planning and deputies for all critical leadership and operational roles. | J83: 5 | K83: =_DATA_Assessment_Model!H83 | L83: =_DATA_Assessment_Model!I83 | M83: =_DATA_Assessment_Model!J83 | N83: =_DATA_Assessment_Model!K83 | O83: =_DATA_Assessment_Model!L83 | P83: No plan or procedure exists. | Q83: Knowledge lives with individuals; nothing usable is written down. | R83: Drafted but outdated, not approved, or unknown to the people who must use it. | S83: Approved and current; owners assigned; affected staff know it exists and where to find it. | T83: Tested against realistic scenarios; updated after each test or real incident. | U83: Exercised regularly including external parties; readiness measured; continuously improved. | V83: Workforce disruption; Pandemic/health crisis; War/security crisis | Y83: Use the recommended action generated by the model; validate with domain owner during real assessment. | Z83: 4 | AA83: 5 | AB83: 5 | AM83: =_DATA_Assessment_Model!AJ83 | AN83: =_DATA_Assessment_Model!AK83 | AO83: =_DATA_Assessment_Model!AL83 | AP83: =_DATA_Assessment_Model!AM83 | AQ83: =_DATA_Assessment_Model!AN83 | AR83: =_DATA_Assessment_Model!AO83 | AS83: =_DATA_Assessment_Model!AP83 | AT83: =_DATA_Assessment_Model!AQ83 | ... AW83: =_DATA_Assessment_Model!AT83 | AY83: =_DATA_Assessment_Model!AV83
A84: HR Workforce | B84: HR Workforce | C84: 17 | D84: HRWO-013 | E84: Continuity and wellbeing | F84: How mature is the organization in managing remote onboarding with secure access, equipment, training and manager support, including ownership, evidence, metrics, fallback procedures and crisis stress testing? | G84: This topic affects exposure to Workforce disruption; Pandemic/health crisis; War/security crisis. It helps identify how disruption may impact operations, people, revenue, systems, legal exposure or recovery time. | H84: ISO 30414; ISO 30405; ISO 45001; ISO 22301; CIPD; SHRM | I84: Policy/SOP; owner/RACI; system report; dashboard; contracts; test records; incident history; interview evidence related to remote onboarding with secure access, equipment, training and manager support. | J84: 4 | K84: =_DATA_Assessment_Model!H84 | L84: =_DATA_Assessment_Model!I84 | M84: =_DATA_Assessment_Model!J84 | N84: =_DATA_Assessment_Model!K84 | O84: =_DATA_Assessment_Model!L84 | P84: Never done; no records exist. | Q84: Done once long ago or only after an incident; no schedule, no records. | R84: Done irregularly; results are not documented and findings are not tracked. | S84: Done on a defined schedule (at least annually); results documented, owner assigned. | T84: Done quarterly/semi-annually; findings tracked to closure, effectiveness measured against targets. | U84: Continuous or automated where possible; results drive improvements and are validated externally (audit/customer). | V84: Workforce disruption; Pandemic/health crisis; War/security crisis | Y84: Use the recommended action generated by the model; validate with domain owner during real assessment. | Z84: 4 | AA84: 5 | AB84: 5 | AM84: =_DATA_Assessment_Model!AJ84 | AN84: =_DATA_Assessment_Model!AK84 | AO84: =_DATA_Assessment_Model!AL84 | AP84: =_DATA_Assessment_Model!AM84 | AQ84: =_DATA_Assessment_Model!AN84 | AR84: =_DATA_Assessment_Model!AO84 | AS84: =_DATA_Assessment_Model!AP84 | AT84: =_DATA_Assessment_Model!AQ84 | ... AW84: =_DATA_Assessment_Model!AT84 | AY84: =_DATA_Assessment_Model!AV84
A85: HR Workforce | B85: HR Workforce | C85: 18 | D85: HRWO-014 | E85: Continuity and wellbeing | F85: How mature is the organization in managing remote work capability with secure access, connectivity, equipment and documented procedures, including ownership, evidence, metrics, fallback procedures and crisis stress testing? | G85: This topic affects exposure to Workforce disruption; Pandemic/health crisis; War/security crisis. It helps identify how disruption may impact operations, people, revenue, systems, legal exposure or recovery time. | H85: ISO 30414; ISO 30405; ISO 45001; ISO 22301; CIPD; SHRM | I85: Policy/SOP; owner/RACI; system report; dashboard; contracts; test records; incident history; interview evidence related to remote work capability with secure access, connectivity, equipment and documented procedures. | J85: 4 | K85: =_DATA_Assessment_Model!H85 | L85: =_DATA_Assessment_Model!I85 | M85: =_DATA_Assessment_Model!J85 | N85: =_DATA_Assessment_Model!K85 | O85: =_DATA_Assessment_Model!L85 | P85: No reliable evidence that remote work capability with secure access, connectivity, equipment and documented procedures is defined, owned or managed. | Q85: Remote work capability with secure access, connectivity, equipment and documented procedures is handled informally and depends on individual knowledge or heroic effort. | R85: Remote work capability with secure access, connectivity, equipment and documented procedures is partially documented or implemented, but coverage is inconsistent and not crisis-tested. | S85: Remote work capability with secure access, connectivity, equipment and documented procedures is documented, owned, used in normal operations and supported by basic evidence or metrics. | T85: Remote work capability with secure access, connectivity, equipment and documented procedures is measured, periodically reviewed, integrated with related processes and tested against relevant disruption scenarios. | U85: Remote work capability with secure access, connectivity, equipment and documented procedures is optimized, continuously improved, automated where practical and demonstrably supports crisis resilience. | V85: Workforce disruption; Pandemic/health crisis; War/security crisis | Y85: Use the recommended action generated by the model; validate with domain owner during real assessment. | Z85: 4 | AA85: 5 | AB85: 5 | AM85: =_DATA_Assessment_Model!AJ85 | AN85: =_DATA_Assessment_Model!AK85 | AO85: =_DATA_Assessment_Model!AL85 | AP85: =_DATA_Assessment_Model!AM85 | AQ85: =_DATA_Assessment_Model!AN85 | AR85: =_DATA_Assessment_Model!AO85 | AS85: =_DATA_Assessment_Model!AP85 | AT85: =_DATA_Assessment_Model!AQ85 | ... AW85: =_DATA_Assessment_Model!AT85 | AY85: =_DATA_Assessment_Model!AV85
A86: HR Workforce | B86: HR Workforce | C86: 19 | D86: HRWO-015 | E86: Continuity and wellbeing | F86: How mature is the organization in managing backup connectivity options for critical staff and locations, including ownership, evidence, metrics, fallback procedures and crisis stress testing? | G86: This topic affects exposure to Workforce disruption; Pandemic/health crisis; War/security crisis. It helps identify how disruption may impact operations, people, revenue, systems, legal exposure or recovery time. | H86: ISO 30414; ISO 30405; ISO 45001; ISO 22301; CIPD; SHRM | I86: Policy/SOP; owner/RACI; system report; dashboard; contracts; test records; incident history; interview evidence related to backup connectivity options for critical staff and locations. | J86: 5 | K86: =_DATA_Assessment_Model!H86 | L86: =_DATA_Assessment_Model!I86 | M86: =_DATA_Assessment_Model!J86 | N86: =_DATA_Assessment_Model!K86 | O86: =_DATA_Assessment_Model!L86 | P86: Does not exist; no owner, no documentation, no practice. | Q86: Ad hoc; depends entirely on specific individuals. | R86: Partially documented or implemented; coverage inconsistent; never tested under stress. | S86: Documented, owned, executed consistently; basic evidence and metrics exist. | T86: Measured and periodically tested/audited; integrated with adjacent processes. | U86: Optimized and automated where practical; stress-tested; benchmarked externally. | V86: Workforce disruption; Pandemic/health crisis; War/security crisis | Y86: Use the recommended action generated by the model; validate with domain owner during real assessment. | Z86: 5 | AA86: 5 | AB86: 5 | AM86: =_DATA_Assessment_Model!AJ86 | AN86: =_DATA_Assessment_Model!AK86 | AO86: =_DATA_Assessment_Model!AL86 | AP86: =_DATA_Assessment_Model!AM86 | AQ86: =_DATA_Assessment_Model!AN86 | AR86: =_DATA_Assessment_Model!AO86 | AS86: =_DATA_Assessment_Model!AP86 | AT86: =_DATA_Assessment_Model!AQ86 | ... AW86: =_DATA_Assessment_Model!AT86 | AY86: =_DATA_Assessment_Model!AV86
A87: HR Workforce | B87: HR Workforce | C87: 20 | D87: HRWO-016 | E87: Continuity and wellbeing | F87: How mature is the organization in managing employee location and safety check process during severe incidents, including ownership, evidence, metrics, fallback procedures and crisis stress testing? | G87: This topic affects exposure to Workforce disruption; Pandemic/health crisis; War/security crisis. It helps identify how disruption may impact operations, people, revenue, systems, legal exposure or recovery time. | H87: ISO 30414; ISO 30405; ISO 45001; ISO 22301; CIPD; SHRM | I87: Policy/SOP; owner/RACI; system report; dashboard; contracts; test records; incident history; interview evidence related to employee location and safety check process during severe incidents. | J87: 5 | K87: =_DATA_Assessment_Model!H87 | L87: =_DATA_Assessment_Model!I87 | M87: =_DATA_Assessment_Model!J87 | N87: =_DATA_Assessment_Model!K87 | O87: =_DATA_Assessment_Model!L87 | P87: Does not exist; no owner, no documentation, no practice. | Q87: Ad hoc; depends entirely on specific individuals. | R87: Partially documented or implemented; coverage inconsistent; never tested under stress. | S87: Documented, owned, executed consistently; basic evidence and metrics exist. | T87: Measured and periodically tested/audited; integrated with adjacent processes. | U87: Optimized and automated where practical; stress-tested; benchmarked externally. | V87: Workforce disruption; Pandemic/health crisis; War/security crisis | Y87: Use the recommended action generated by the model; validate with domain owner during real assessment. | Z87: 4 | AA87: 5 | AB87: 5 | AM87: =_DATA_Assessment_Model!AJ87 | AN87: =_DATA_Assessment_Model!AK87 | AO87: =_DATA_Assessment_Model!AL87 | AP87: =_DATA_Assessment_Model!AM87 | AQ87: =_DATA_Assessment_Model!AN87 | AR87: =_DATA_Assessment_Model!AO87 | AS87: =_DATA_Assessment_Model!AP87 | AT87: =_DATA_Assessment_Model!AQ87 | ... AW87: =_DATA_Assessment_Model!AT87 | AY87: =_DATA_Assessment_Model!AV87
... A97: HR Workforce | B97: HR Workforce | C97: 30 | D97: HRWO-028 | E97: Workforce visibility | F97: How mature is the organization in managing workforce exposure to national emergency duties such as conscription, reservist service or civil mobilization, including exemption processes and continuity planning, including ownership, evidence, metrics, fallback procedures and crisis stress testing? | G97: This topic affects exposure to War/security crisis; Workforce disruption. It helps identify how disruption may impact operations, people, revenue, systems, legal exposure or recovery time. | H97: ISO 22301; national emergency and labor legislation; workforce planning | I97: Policy/SOP; owner/RACI; system report; dashboard; contracts; test records; incident history; interview evidence | J97: 4 | K97: =_DATA_Assessment_Model!H97 | L97: =_DATA_Assessment_Model!I97 | M97: =_DATA_Assessment_Model!J97 | N97: =_DATA_Assessment_Model!K97 | O97: =_DATA_Assessment_Model!L97 | P97: No reliable evidence that workforce exposure to national emergency duties such as conscription, reservist service or civil mobilization, including exemption processes and continuity planning is defined, owned or managed. | Q97: Workforce exposure to national emergency duties such as conscription, reservist service or civil mobilization, including exemption processes and continuity planning is handled informally and depends on individual knowledge or heroic effort. | R97: Workforce exposure to national emergency duties such as conscription, reservist service or civil mobilization, including exemption processes and continuity planning is partially documented or implemented, but coverage is inconsistent and not crisis-tested. | S97: Workforce exposure to national emergency duties such as conscription, reservist service or civil mobilization, including exemption processes and continuity planning is documented, owned, used in normal operations and supported by basic evidence or metrics. | T97: Workforce exposure to national emergency duties such as conscription, reservist service or civil mobilization, including exemption processes and continuity planning is measured, periodically reviewed, integrated with related processes and tested against relevant disruption scenarios. | U97: Workforce exposure to national emergency duties such as conscription, reservist service or civil mobilization, including exemption processes and continuity planning is optimized, continuously improved, automated where practical and demonstrably supports crisis resilience. | V97: War/security crisis; Workforce disruption | Y97: Use the recommended action generated by the model; validate with domain owner during real assessment. | Z97: 2 | AA97: 5 | AB97: 4 | AM97: =_DATA_Assessment_Model!AJ97 | AN97: =_DATA_Assessment_Model!AK97 | AO97: =_DATA_Assessment_Model!AL97 | AP97: =_DATA_Assessment_Model!AM97 | AQ97: =_DATA_Assessment_Model!AN97 | AR97: =_DATA_Assessment_Model!AO97 | AS97: =_DATA_Assessment_Model!AP97 | AT97: =_DATA_Assessment_Model!AQ97 | ... AW97: =_DATA_Assessment_Model!AT97 | AY97: =_DATA_Assessment_Model!AV97
A98: Finance Procurement | B98: Finance Procurement | C98: 5 | D98: FINA-001 | E98: Financial resilience | F98: How mature is the organization in managing cash visibility by legal entity, bank, currency, restrictions and emergency access, including ownership, evidence, metrics, fallback procedures and crisis stress testing? | G98: This topic affects exposure to Financial liquidity crisis; Supplier disruption; Fraud risk. It helps identify how disruption may impact operations, people, revenue, systems, legal exposure or recovery time. | H98: COSO Internal Control; COSO ERM; IFRS; ISO 20400; ISO 37001; CIPS | I98: Policy/SOP; owner/RACI; system report; dashboard; contracts; test records; incident history; interview evidence related to cash visibility by legal entity, bank, currency, restrictions and emergency access. | J98: 5 | K98: =_DATA_Assessment_Model!H98 | L98: =_DATA_Assessment_Model!I98 | M98: =_DATA_Assessment_Model!J98 | N98: =_DATA_Assessment_Model!K98 | O98: =_DATA_Assessment_Model!L98 | P98: Nothing is monitored or measured. | Q98: Occasional manual checks by individuals. | R98: Some metrics exist but are not reviewed regularly and trigger no action. | S98: Defined metrics with an owner, reviewed on a set cadence. | T98: Thresholds and alerts in place; deviations trigger documented action; trends analyzed. | U98: Automated monitoring with leading indicators, integrated into management decisions. | V98: Financial liquidity crisis; Supplier disruption; Fraud risk | Y98: Use the recommended action generated by the model; validate with domain owner during real assessment. | Z98: 4 | AA98: 5 | AB98: 5 | AD98: Financial resilience | AE98: =_DATA_Assessment_Model!AB98 | AF98: =_DATA_Assessment_Model!AC98 | AG98: =_DATA_Assessment_Model!AD98 | AH98: =_DATA_Assessment_Model!AE98 | AI98: =_DATA_Assessment_Model!AF98 | AJ98: =_DATA_Assessment_Model!AG98 | AM98: =_DATA_Assessment_Model!AJ98 | AN98: =_DATA_Assessment_Model!AK98 | AO98: =_DATA_Assessment_Model!AL98 | AP98: =_DATA_Assessment_Model!AM98 | AQ98: =_DATA_Assessment_Model!AN98 | AR98: =_DATA_Assessment_Model!AO98 | AS98: =_DATA_Assessment_Model!AP98 | AT98: =_DATA_Assessment_Model!AQ98 | ... AW98: =_DATA_Assessment_Model!AT98 | AY98: =_DATA_Assessment_Model!AV98
A99: Finance Procurement | B99: Finance Procurement | C99: 6 | D99: FINA-002 | E99: Financial resilience | F99: How mature is the organization in managing cash-flow forecasting under base, downside and severe crisis scenarios, including ownership, evidence, metrics, fallback procedures and crisis stress testing? | G99: This topic affects exposure to Financial liquidity crisis; Supplier disruption; Fraud risk. It helps identify how disruption may impact operations, people, revenue, systems, legal exposure or recovery time. | H99: COSO Internal Control; COSO ERM; IFRS; ISO 20400; ISO 37001; CIPS | I99: Policy/SOP; owner/RACI; system report; dashboard; contracts; test records; incident history; interview evidence related to cash-flow forecasting under base, downside and severe crisis scenarios. | J99: 5 | K99: =_DATA_Assessment_Model!H99 | L99: =_DATA_Assessment_Model!I99 | M99: =_DATA_Assessment_Model!J99 | N99: =_DATA_Assessment_Model!K99 | O99: =_DATA_Assessment_Model!L99 | P99: Does not exist; no owner, no documentation, no practice. | Q99: Ad hoc; depends entirely on specific individuals. | R99: Partially documented or implemented; coverage inconsistent; never tested under stress. | S99: Documented, owned, executed consistently; basic evidence and metrics exist. | T99: Measured and periodically tested/audited; integrated with adjacent processes. | U99: Optimized and automated where practical; stress-tested; benchmarked externally. | V99: Financial liquidity crisis; Supplier disruption; Fraud risk | Y99: Use the recommended action generated by the model; validate with domain owner during real assessment. | Z99: 4 | AA99: 5 | AB99: 5 | AD99: Controls and accounting | AE99: =_DATA_Assessment_Model!AB99 | AF99: =_DATA_Assessment_Model!AC99 | AG99: =_DATA_Assessment_Model!AD99 | AH99: =_DATA_Assessment_Model!AE99 | AI99: =_DATA_Assessment_Model!AF99 | AJ99: =_DATA_Assessment_Model!AG99 | AM99: =_DATA_Assessment_Model!AJ99 | AN99: =_DATA_Assessment_Model!AK99 | AO99: =_DATA_Assessment_Model!AL99 | AP99: =_DATA_Assessment_Model!AM99 | AQ99: =_DATA_Assessment_Model!AN99 | AR99: =_DATA_Assessment_Model!AO99 | AS99: =_DATA_Assessment_Model!AP99 | AT99: =_DATA_Assessment_Model!AQ99 | ... AW99: =_DATA_Assessment_Model!AT99 | AY99: =_DATA_Assessment_Model!AV99
A100: Finance Procurement | B100: Finance Procurement | C100: 7 | D100: FINA-003 | E100: Financial resilience | F100: How mature is the organization in managing liquidity buffers, credit lines, emergency funding options and covenant monitoring, including ownership, evidence, metrics, fallback procedures and crisis stress testing? | G100: This topic affects exposure to Financial liquidity crisis; Supplier disruption; Fraud risk. It helps identify how disruption may impact operations, people, revenue, systems, legal exposure or recovery time. | H100: COSO Internal Control; COSO ERM; IFRS; ISO 20400; ISO 37001; CIPS | I100: Policy/SOP; owner/RACI; system report; dashboard; contracts; test records; incident history; interview evidence related to liquidity buffers, credit lines, emergency funding options and covenant monitoring. | J100: 3 | K100: =_DATA_Assessment_Model!H100 | L100: =_DATA_Assessment_Model!I100 | M100: =_DATA_Assessment_Model!J100 | N100: =_DATA_Assessment_Model!K100 | O100: =_DATA_Assessment_Model!L100 | P100: No liquidity buffer; no credit lines; cash position unclear. | Q100: Buffer exists informally; size not based on analysis. | R100: Buffer or credit line exists but covers under 1 month of fixed costs or is untested. | S100: Defined buffer target (>=1-3 months) plus committed credit lines; covenants monitored. | T100: Buffer sized from stress scenarios; emergency funding options pre-negotiated and reviewed. | U100: Multi-source liquidity strategy tested in real or simulated stress; covenant headroom actively managed. | V100: Financial liquidity crisis; Supplier disruption; Fraud risk | Y100: Use the recommended action generated by the model; validate with domain owner during real assessment. | Z100: 4 | AA100: 5 | AB100: 5 | AD100: Procurement and suppliers | AE100: =_DATA_Assessment_Model!AB100 | AF100: =_DATA_Assessment_Model!AC100 | AG100: =_DATA_Assessment_Model!AD100 | AH100: =_DATA_Assessment_Model!AE100 | AI100: =_DATA_Assessment_Model!AF100 | AJ100: =_DATA_Assessment_Model!AG100 | AM100: =_DATA_Assessment_Model!AJ100 | AN100: =_DATA_Assessment_Model!AK100 | AO100: =_DATA_Assessment_Model!AL100 | AP100: =_DATA_Assessment_Model!AM100 | AQ100: =_DATA_Assessment_Model!AN100 | AR100: =_DATA_Assessment_Model!AO100 | AS100: =_DATA_Assessment_Model!AP100 | AT100: =_DATA_Assessment_Model!AQ100 | ... AW100: =_DATA_Assessment_Model!AT100 | AY100: =_DATA_Assessment_Model!AV100
A101: Finance Procurement | B101: Finance Procurement | C101: 8 | D101: FINA-004 | E101: Financial resilience | F101: How mature is the organization in managing driver-based financial forecasting linked to sales, delivery, workforce, inventory and production, including ownership, evidence, metrics, fallback procedures and crisis stress testing? | G101: This topic affects exposure to Financial liquidity crisis; Supplier disruption; Fraud risk. It helps identify how disruption may impact operations, people, revenue, systems, legal exposure or recovery time. | H101: COSO Internal Control; COSO ERM; IFRS; ISO 20400; ISO 37001; CIPS | I101: Policy/SOP; owner/RACI; system report; dashboard; contracts; test records; incident history; interview evidence related to driver-based financial forecasting linked to sales, delivery, workforce, inventory and production. | J101: 5 | K101: =_DATA_Assessment_Model!H101 | L101: =_DATA_Assessment_Model!I101 | M101: =_DATA_Assessment_Model!J101 | N101: =_DATA_Assessment_Model!K101 | O101: =_DATA_Assessment_Model!L101 | P101: No inventory/register exists. | Q101: Partial lists live in individuals' heads or personal files. | R101: A register exists but is incomplete or outdated (>1 year) and has no owner. | S101: Owned, documented, updated on a defined schedule, covers the main scope. | T101: Complete and periodically reviewed; integrated with related processes; completeness measured. | U101: Maintained automatically or synced with systems; drives decisions; audited. | V101: Financial liquidity crisis; Supplier disruption; Fraud risk | Y101: Use the recommended action generated by the model; validate with domain owner during real assessment. | Z101: 4 | AA101: 5 | AB101: 5 | AD101: Working capital | AE101: =_DATA_Assessment_Model!AB101 | AF101: =_DATA_Assessment_Model!AC101 | AG101: =_DATA_Assessment_Model!AD101 | AH101: =_DATA_Assessment_Model!AE101 | AI101: =_DATA_Assessment_Model!AF101 | AJ101: =_DATA_Assessment_Model!AG101 | AM101: =_DATA_Assessment_Model!AJ101 | AN101: =_DATA_Assessment_Model!AK101 | AO101: =_DATA_Assessment_Model!AL101 | AP101: =_DATA_Assessment_Model!AM101 | AQ101: =_DATA_Assessment_Model!AN101 | AR101: =_DATA_Assessment_Model!AO101 | AS101: =_DATA_Assessment_Model!AP101 | AT101: =_DATA_Assessment_Model!AQ101 | ... AW101: =_DATA_Assessment_Model!AT101 | AY101: =_DATA_Assessment_Model!AV101
A102: Finance Procurement | B102: Finance Procurement | C102: 9 | D102: FINA-005 | E102: Financial resilience | F102: How mature is the organization in managing budget flexibility and emergency reallocation rules, including ownership, evidence, metrics, fallback procedures and crisis stress testing? | G102: This topic affects exposure to Financial liquidity crisis; Supplier disruption; Fraud risk. It helps identify how disruption may impact operations, people, revenue, systems, legal exposure or recovery time. | H102: COSO Internal Control; COSO ERM; IFRS; ISO 20400; ISO 37001; CIPS | I102: Policy/SOP; owner/RACI; system report; dashboard; contracts; test records; incident history; interview evidence related to budget flexibility and emergency reallocation rules. | J102: 3 | K102: =_DATA_Assessment_Model!H102 | L102: =_DATA_Assessment_Model!I102 | M102: =_DATA_Assessment_Model!J102 | N102: =_DATA_Assessment_Model!K102 | O102: =_DATA_Assessment_Model!L102 | P102: No reliable evidence that budget flexibility and emergency reallocation rules is defined, owned or managed. | Q102: Budget flexibility and emergency reallocation rules is handled informally and depends on individual knowledge or heroic effort. | R102: Budget flexibility and emergency reallocation rules is partially documented or implemented, but coverage is inconsistent and not crisis-tested. | S102: Budget flexibility and emergency reallocation rules is documented, owned, used in normal operations and supported by basic evidence or metrics. | T102: Budget flexibility and emergency reallocation rules is measured, periodically reviewed, integrated with related processes and tested against relevant disruption scenarios. | U102: Budget flexibility and emergency reallocation rules is optimized, continuously improved, automated where practical and demonstrably supports crisis resilience. | V102: Financial liquidity crisis; Supplier disruption; Fraud risk | Y102: Use the recommended action generated by the model; validate with domain owner during real assessment. | Z102: 4 | AA102: 5 | AB102: 5 | AM102: =_DATA_Assessment_Model!AJ102 | AN102: =_DATA_Assessment_Model!AK102 | AO102: =_DATA_Assessment_Model!AL102 | AP102: =_DATA_Assessment_Model!AM102 | AQ102: =_DATA_Assessment_Model!AN102 | AR102: =_DATA_Assessment_Model!AO102 | AS102: =_DATA_Assessment_Model!AP102 | AT102: =_DATA_Assessment_Model!AQ102 | ... AW102: =_DATA_Assessment_Model!AT102 | AY102: =_DATA_Assessment_Model!AV102
A103: Finance Procurement | B103: Finance Procurement | C103: 10 | D103: FINA-006 | E103: Financial resilience | F103: How mature is the organization in managing financial stress tests for revenue collapse, currency shock, supplier price spikes, debt pressure and delayed receivables, including ownership, evidence, metrics, fallback procedures and crisis stress testing? | G103: This topic affects exposure to Financial liquidity crisis; Supplier disruption; Fraud risk. It helps identify how disruption may impact operations, people, revenue, systems, legal exposure or recovery time. | H103: COSO Internal Control; COSO ERM; IFRS; ISO 20400; ISO 37001; CIPS | I103: Policy/SOP; owner/RACI; system report; dashboard; contracts; test records; incident history; interview evidence related to financial stress tests for revenue collapse, currency shock, supplier price spikes, debt pressure and delayed receivables. | J103: 5 | K103: =_DATA_Assessment_Model!H103 | L103: =_DATA_Assessment_Model!I103 | M103: =_DATA_Assessment_Model!J103 | N103: =_DATA_Assessment_Model!K103 | O103: =_DATA_Assessment_Model!L103 | P103: Never done; no records exist. | Q103: Done once long ago or only after an incident; no schedule, no records. | R103: Done irregularly; results are not documented and findings are not tracked. | S103: Done on a defined schedule (at least annually); results documented, owner assigned. | T103: Done quarterly/semi-annually; findings tracked to closure, effectiveness measured against targets. | U103: Continuous or automated where possible; results drive improvements and are validated externally (audit/customer). | V103: Financial liquidity crisis; Supplier disruption; Fraud risk | Y103: Use the recommended action generated by the model; validate with domain owner during real assessment. | Z103: 4 | AA103: 5 | AB103: 5 | AM103: =_DATA_Assessment_Model!AJ103 | AN103: =_DATA_Assessment_Model!AK103 | AO103: =_DATA_Assessment_Model!AL103 | AP103: =_DATA_Assessment_Model!AM103 | AQ103: =_DATA_Assessment_Model!AN103 | AR103: =_DATA_Assessment_Model!AO103 | AS103: =_DATA_Assessment_Model!AP103 | AT103: =_DATA_Assessment_Model!AQ103 | ... AW103: =_DATA_Assessment_Model!AT103 | AY103: =_DATA_Assessment_Model!AV103
A104: Finance Procurement | B104: Finance Procurement | C104: 11 | D104: FINA-007 | E104: Controls and accounting | F104: How mature is the organization in managing approval limits and emergency approvals resilient if key approvers are unavailable, including ownership, evidence, metrics, fallback procedures and crisis stress testing? | G104: This topic affects exposure to Financial liquidity crisis; Supplier disruption; Fraud risk. It helps identify how disruption may impact operations, people, revenue, systems, legal exposure or recovery time. | H104: COSO Internal Control; COSO ERM; IFRS; ISO 20400; ISO 37001; CIPS | I104: Policy/SOP; owner/RACI; system report; dashboard; contracts; test records; incident history; interview evidence related to approval limits and emergency approvals resilient if key approvers are unavailable. | J104: 3 | K104: =_DATA_Assessment_Model!H104 | L104: =_DATA_Assessment_Model!I104 | M104: =_DATA_Assessment_Model!J104 | N104: =_DATA_Assessment_Model!K104 | O104: =_DATA_Assessment_Model!L104 | P104: No reliable evidence that approval limits and emergency approvals resilient if key approvers are unavailable is defined, owned or managed. | Q104: Approval limits and emergency approvals resilient if key approvers are unavailable is handled informally and depends on individual knowledge or heroic effort. | R104: Approval limits and emergency approvals resilient if key approvers are unavailable is partially documented or implemented, but coverage is inconsistent and not crisis-tested. | S104: Approval limits and emergency approvals resilient if key approvers are unavailable is documented, owned, used in normal operations and supported by basic evidence or metrics. | T104: Approval limits and emergency approvals resilient if key approvers are unavailable is measured, periodically reviewed, integrated with related processes and tested against relevant disruption scenarios. | U104: Approval limits and emergency approvals resilient if key approvers are unavailable is optimized, continuously improved, automated where practical and demonstrably supports crisis resilience. | V104: Financial liquidity crisis; Supplier disruption; Fraud risk | Y104: Use the recommended action generated by the model; validate with domain owner during real assessment. | Z104: 4 | AA104: 5 | AB104: 5 | AM104: =_DATA_Assessment_Model!AJ104 | AN104: =_DATA_Assessment_Model!AK104 | AO104: =_DATA_Assessment_Model!AL104 | AP104: =_DATA_Assessment_Model!AM104 | AQ104: =_DATA_Assessment_Model!AN104 | AR104: =_DATA_Assessment_Model!AO104 | AS104: =_DATA_Assessment_Model!AP104 | AT104: =_DATA_Assessment_Model!AQ104 | ... AW104: =_DATA_Assessment_Model!AT104 | AY104: =_DATA_Assessment_Model!AV104
A105: Finance Procurement | B105: Finance Procurement | C105: 12 | D105: FINA-008 | E105: Controls and accounting | F105: How mature is the organization in managing segregation of duties in finance, procurement, ERP and payment processes, including ownership, evidence, metrics, fallback procedures and crisis stress testing? | G105: This topic affects exposure to Financial liquidity crisis; Supplier disruption; Fraud risk. It helps identify how disruption may impact operations, people, revenue, systems, legal exposure or recovery time. | H105: COSO Internal Control; COSO ERM; IFRS; ISO 20400; ISO 37001; CIPS | I105: Policy/SOP; owner/RACI; system report; dashboard; contracts; test records; incident history; interview evidence related to segregation of duties in finance, procurement, ERP and payment processes. | J105: 5 | K105: =_DATA_Assessment_Model!H105 | L105: =_DATA_Assessment_Model!I105 | M105: =_DATA_Assessment_Model!J105 | N105: =_DATA_Assessment_Model!K105 | O105: =_DATA_Assessment_Model!L105 | P105: Does not exist; no owner, no documentation, no practice. | Q105: Ad hoc; depends entirely on specific individuals. | R105: Partially documented or implemented; coverage inconsistent; never tested under stress. | S105: Documented, owned, executed consistently; basic evidence and metrics exist. | T105: Measured and periodically tested/audited; integrated with adjacent processes. | U105: Optimized and automated where practical; stress-tested; benchmarked externally. | V105: Financial liquidity crisis; Supplier disruption; Fraud risk | Y105: Use the recommended action generated by the model; validate with domain owner during real assessment. | Z105: 5 | AA105: 5 | AB105: 5 | AM105: =_DATA_Assessment_Model!AJ105 | AN105: =_DATA_Assessment_Model!AK105 | AO105: =_DATA_Assessment_Model!AL105 | AP105: =_DATA_Assessment_Model!AM105 | AQ105: =_DATA_Assessment_Model!AN105 | AR105: =_DATA_Assessment_Model!AO105 | AS105: =_DATA_Assessment_Model!AP105 | AT105: =_DATA_Assessment_Model!AQ105 | ... AW105: =_DATA_Assessment_Model!AT105 | AY105: =_DATA_Assessment_Model!AV105
A106: Finance Procurement | B106: Finance Procurement | C106: 13 | D106: FINA-009 | E106: Controls and accounting | F106: How mature is the organization in managing month-end close continuity under remote work, system outage or unavailable finance staff, including ownership, evidence, metrics, fallback procedures and crisis stress testing? | G106: This topic affects exposure to Financial liquidity crisis; Supplier disruption; Fraud risk. It helps identify how disruption may impact operations, people, revenue, systems, legal exposure or recovery time. | H106: COSO Internal Control; COSO ERM; IFRS; ISO 20400; ISO 37001; CIPS | I106: Policy/SOP; owner/RACI; system report; dashboard; contracts; test records; incident history; interview evidence related to month-end close continuity under remote work, system outage or unavailable finance staff. | J106: 5 | K106: =_DATA_Assessment_Model!H106 | L106: =_DATA_Assessment_Model!I106 | M106: =_DATA_Assessment_Model!J106 | N106: =_DATA_Assessment_Model!K106 | O106: =_DATA_Assessment_Model!L106 | P106: Does not exist; no owner, no documentation, no practice. | Q106: Ad hoc; depends entirely on specific individuals. | R106: Partially documented or implemented; coverage inconsistent; never tested under stress. | S106: Documented, owned, executed consistently; basic evidence and metrics exist. | T106: Measured and periodically tested/audited; integrated with adjacent processes. | U106: Optimized and automated where practical; stress-tested; benchmarked externally. | V106: Financial liquidity crisis; Supplier disruption; Fraud risk | Y106: Use the recommended action generated by the model; validate with domain owner during real assessment. | Z106: 4 | AA106: 5 | AB106: 5 | AM106: =_DATA_Assessment_Model!AJ106 | AN106: =_DATA_Assessment_Model!AK106 | AO106: =_DATA_Assessment_Model!AL106 | AP106: =_DATA_Assessment_Model!AM106 | AQ106: =_DATA_Assessment_Model!AN106 | AR106: =_DATA_Assessment_Model!AO106 | AS106: =_DATA_Assessment_Model!AP106 | AT106: =_DATA_Assessment_Model!AQ106 | ... AW106: =_DATA_Assessment_Model!AT106 | AY106: =_DATA_Assessment_Model!AV106
