Workbook

Sheet ① START HERE
B1: Business Resilience Workbook — Start Here
B2: How to read this file, what to fill in, and where to look for answers.
B4: TAB COLOUR LEGEND (see the coloured tabs at the bottom)
C5: Start / guide — This sheet.
C6: Green = Executive insight — Outputs to read & present. Do NOT type here — they update automatically.
C7: Orange = Your input — Fill these in. Assessment scores, company profile, crisis selection.
C8: Gold = Calibration (careful) — Weights / pairwise judgements. Powerful — change deliberately, watch the consistency check.
C9: Blue = Reference / guide — Read-only explanations, scoring scales, standards, methodology.
C10: Grey = Internal engine — Hidden calculation libraries. Don't edit unless you know the model. Right-click a tab > Unhide to view.
B12: CELL COLOUR LEGEND
C13: Enter a value — Yellow cells are inputs — type your answer / number here.
C14: Adjust carefully — Light-orange cells are weights or parameters. Sensible defaults are set; change deliberately.
C15: Optional input — Pale-yellow cells are optional refinements (e.g., evidence/assessor confidence).
C16: No fill = automatic — Uncoloured cells are formula-driven. Don't type over them or you'll break the logic.
B18: RECOMMENDED WORKFLOW
B19: 1. Company Profile | C19: Fill the orange cells: industry, size, geography, concentration, critical processes. This drives targets, SPOF and strategy logic.
B20: 2. Score the 17 domains | C20: On each orange domain tab (Company Geography … Cyber Privacy), enter a 0–5 score in the yellow Score column. Use the Scoring Guide (blue) for the scale. Optionally set evidence/assessor confidence.
B21: 3. Pick a crisis | C21: On Crisis Simulator choose a scenario and severity (1–5).
B22: 4. Calibrate weights (optional) | C22: On AHP Domain Weights (gold) adjust the pillar pairwise judgements; keep the Consistency Ratio < 0.10.
B23: 5. Read the outputs | C23: Green tabs: Dashboard, Scoring Model v2, Resilience Engine (Cascade), Risk Summary, Executive Recommendations, Initiative Economics, Gantt Roadmap.
B24: 6. Quality check | C24: Quality Control (blue) flags missing/low-confidence answers before you present.
B26: GOOD TO KNOW
C27: • Unanswered domains are treated as blank (not zero) and excluded from averages — fill what's relevant, mark the rest N/A.
C28: • Two maturity views exist: the original Dashboard (simple weighted average) and Scoring Model v2 (confidence-adjusted, with additive / geometric / penalty aggregation). Geometric & penalty punish weak links.
C29: • Risk has a cross-domain Cascade view (Resilience Engine) — a failure in one domain raises risk in coupled domains.
C30: • Initiative Economics needs you to enter € investment/benefit (yellow) for ROI/NPV and budget selection to mean anything.
C31: • Methodology tabs (blue) explain every formula. Internal grey _TECH_ tabs are the engine — leave them alone.

Sheet Dashboard
A1: Crisis Management Assessment Dashboard
A2: How to use: fill Score 0-5 or N/A in each domain tab; add evidence and comments; review Critical/High gaps; then build crisis-specific mitigation roadmaps. The focus is crisis impact across people, geography, physical safety, suppliers, manufacturing, systems, cloud, data, cybersecurity, strategy and GTM.
A4: Domain | B4: Questions | C4: Answered | D4: Completion % | E4: Weighted score | F4: Max score | G4: Maturity % | H4: Maturity 0-5 | I4: Gap | J4: Critical | K4: High | L4: Medium | M4: Low | N4: Resilient | O4: Priority note | Q4: Overall metric | R4: Value | S4: Interpretation
A5: Company Geography | B5: 20 | C5: =COUNTIF('Company Geography'!$H$5:$H$24,"N/A")+COUNTIF('Company Geography'!$H$5:$H$24,"0")+COUNTIF('Company Geography'!$H$5:$H$24,"1")+COUNTIF('Company Geography'!$H$5:$H$24,"2")+COUNTIF('Company Geography'!$H$5:$H$24,"3")+COUNTIF('Company Geography'!$H$5:$H$24,"4")+COUNTIF('Company Geography'!$H$5:$H$24,"5") -> 0 | D5: =IFERROR(C5/B5,0) -> 0 | E5: =SUM('Company Geography'!$I$5:$I$24) -> 0 | F5: =SUM('Company Geography'!$J$5:$J$24) -> 0 | G5: =IFERROR(E5/F5,0) -> 0 | H5: =G5*5 -> 0 | I5: =SUM('Company Geography'!$K$5:$K$24) -> 0 | J5: =COUNTIF('Company Geography'!$L$5:$L$24,"Critical") -> 0 | K5: =COUNTIF('Company Geography'!$L$5:$L$24,"High") -> 0 | L5: =COUNTIF('Company Geography'!$L$5:$L$24,"Medium") -> 0 | M5: =COUNTIF('Company Geography'!$L$5:$L$24,"Low") -> 0 | N5: =COUNTIF('Company Geography'!$L$5:$L$24,"Resilient") -> 0 | O5: =IF(J5+K5>0,"Review critical/high-risk gaps",IF(D5<1,"Complete assessment","Monitor and improve")) -> Complete assessment | Q5: Total questions | R5: =SUM(B5:B21) -> 407 | S5: Total number of questions across all domains.
A6: Strategy GTM | B6: 24 | C6: =COUNTIF('Strategy GTM'!$H$5:$H$28,"N/A")+COUNTIF('Strategy GTM'!$H$5:$H$28,"0")+COUNTIF('Strategy GTM'!$H$5:$H$28,"1")+COUNTIF('Strategy GTM'!$H$5:$H$28,"2")+COUNTIF('Strategy GTM'!$H$5:$H$28,"3")+COUNTIF('Strategy GTM'!$H$5:$H$28,"4")+COUNTIF('Strategy GTM'!$H$5:$H$28,"5") -> 0 | D6: =IFERROR(C6/B6,0) -> 0 | E6: =SUM('Strategy GTM'!$I$5:$I$28) -> 0 | F6: =SUM('Strategy GTM'!$J$5:$J$28) -> 0 | G6: =IFERROR(E6/F6,0) -> 0 | H6: =G6*5 -> 0 | I6: =SUM('Strategy GTM'!$K$5:$K$28) -> 0 | J6: =COUNTIF('Strategy GTM'!$L$5:$L$28,"Critical") -> 0 | K6: =COUNTIF('Strategy GTM'!$L$5:$L$28,"High") -> 0 | L6: =COUNTIF('Strategy GTM'!$L$5:$L$28,"Medium") -> 0 | M6: =COUNTIF('Strategy GTM'!$L$5:$L$28,"Low") -> 0 | N6: =COUNTIF('Strategy GTM'!$L$5:$L$28,"Resilient") -> 0 | O6: =IF(J6+K6>0,"Review critical/high-risk gaps",IF(D6<1,"Complete assessment","Monitor and improve")) -> Complete assessment | Q6: Answered questions | R6: =SUM(C5:C21) -> 0 | S6: Includes N/A as answered.
A7: Governance Crisis | B7: 19 | C7: =COUNTIF('Governance Crisis'!$H$5:$H$23,"N/A")+COUNTIF('Governance Crisis'!$H$5:$H$23,"0")+COUNTIF('Governance Crisis'!$H$5:$H$23,"1")+COUNTIF('Governance Crisis'!$H$5:$H$23,"2")+COUNTIF('Governance Crisis'!$H$5:$H$23,"3")+COUNTIF('Governance Crisis'!$H$5:$H$23,"4")+COUNTIF('Governance Crisis'!$H$5:$H$23,"5") -> 0 | D7: =IFERROR(C7/B7,0) -> 0 | E7: =SUM('Governance Crisis'!$I$5:$I$23) -> 0 | F7: =SUM('Governance Crisis'!$J$5:$J$23) -> 0 | G7: =IFERROR(E7/F7,0) -> 0 | H7: =G7*5 -> 0 | I7: =SUM('Governance Crisis'!$K$5:$K$23) -> 0 | J7: =COUNTIF('Governance Crisis'!$L$5:$L$23,"Critical") -> 0 | K7: =COUNTIF('Governance Crisis'!$L$5:$L$23,"High") -> 0 | L7: =COUNTIF('Governance Crisis'!$L$5:$L$23,"Medium") -> 0 | M7: =COUNTIF('Governance Crisis'!$L$5:$L$23,"Low") -> 0 | N7: =COUNTIF('Governance Crisis'!$L$5:$L$23,"Resilient") -> 0 | O7: =IF(J7+K7>0,"Review critical/high-risk gaps",IF(D7<1,"Complete assessment","Monitor and improve")) -> Complete assessment | Q7: Overall completion | R7: =IFERROR(R6/R5,0) -> 0 | S7: Target: 100% before final diagnosis.
A8: HR Workforce | B8: 24 | C8: =COUNTIF('HR Workforce'!$H$5:$H$28,"N/A")+COUNTIF('HR Workforce'!$H$5:$H$28,"0")+COUNTIF('HR Workforce'!$H$5:$H$28,"1")+COUNTIF('HR Workforce'!$H$5:$H$28,"2")+COUNTIF('HR Workforce'!$H$5:$H$28,"3")+COUNTIF('HR Workforce'!$H$5:$H$28,"4")+COUNTIF('HR Workforce'!$H$5:$H$28,"5") -> 0 | D8: =IFERROR(C8/B8,0) -> 0 | E8: =SUM('HR Workforce'!$I$5:$I$28) -> 0 | F8: =SUM('HR Workforce'!$J$5:$J$28) -> 0 | G8: =IFERROR(E8/F8,0) -> 0 | H8: =G8*5 -> 0 | I8: =SUM('HR Workforce'!$K$5:$K$28) -> 0 | J8: =COUNTIF('HR Workforce'!$L$5:$L$28,"Critical") -> 0 | K8: =COUNTIF('HR Workforce'!$L$5:$L$28,"High") -> 0 | L8: =COUNTIF('HR Workforce'!$L$5:$L$28,"Medium") -> 0 | M8: =COUNTIF('HR Workforce'!$L$5:$L$28,"Low") -> 0 | N8: =COUNTIF('HR Workforce'!$L$5:$L$28,"Resilient") -> 0 | O8: =IF(J8+K8>0,"Review critical/high-risk gaps",IF(D8<1,"Complete assessment","Monitor and improve")) -> Complete assessment | Q8: Overall maturity % | R8: =IFERROR(SUM(E5:E21)/SUM(F5:F21),0) -> 0 | S8: Weighted resilience maturity across answered items.
A9: Finance Procurement | B9: 24 | C9: =COUNTIF('Finance Procurement'!$H$5:$H$28,"N/A")+COUNTIF('Finance Procurement'!$H$5:$H$28,"0")+COUNTIF('Finance Procurement'!$H$5:$H$28,"1")+COUNTIF('Finance Procurement'!$H$5:$H$28,"2")+COUNTIF('Finance Procurement'!$H$5:$H$28,"3")+COUNTIF('Finance Procurement'!$H$5:$H$28,"4")+COUNTIF('Finance Procurement'!$H$5:$H$28,"5") -> 0 | D9: =IFERROR(C9/B9,0) -> 0 | E9: =SUM('Finance Procurement'!$I$5:$I$28) -> 0 | F9: =SUM('Finance Procurement'!$J$5:$J$28) -> 0 | G9: =IFERROR(E9/F9,0) -> 0 | H9: =G9*5 -> 0 | I9: =SUM('Finance Procurement'!$K$5:$K$28) -> 0 | J9: =COUNTIF('Finance Procurement'!$L$5:$L$28,"Critical") -> 0 | K9: =COUNTIF('Finance Procurement'!$L$5:$L$28,"High") -> 0 | L9: =COUNTIF('Finance Procurement'!$L$5:$L$28,"Medium") -> 0 | M9: =COUNTIF('Finance Procurement'!$L$5:$L$28,"Low") -> 0 | N9: =COUNTIF('Finance Procurement'!$L$5:$L$28,"Resilient") -> 0 | O9: =IF(J9+K9>0,"Review critical/high-risk gaps",IF(D9<1,"Complete assessment","Monitor and improve")) -> Complete assessment | Q9: Overall maturity 0-5 | R9: =R8*5 -> 0 | S9: 0 = absent, 5 = optimized/resilient.
A10: Legal Risk | B10: 20 | C10: =COUNTIF('Legal Risk'!$H$5:$H$24,"N/A")+COUNTIF('Legal Risk'!$H$5:$H$24,"0")+COUNTIF('Legal Risk'!$H$5:$H$24,"1")+COUNTIF('Legal Risk'!$H$5:$H$24,"2")+COUNTIF('Legal Risk'!$H$5:$H$24,"3")+COUNTIF('Legal Risk'!$H$5:$H$24,"4")+COUNTIF('Legal Risk'!$H$5:$H$24,"5") -> 0 | D10: =IFERROR(C10/B10,0) -> 0 | E10: =SUM('Legal Risk'!$I$5:$I$24) -> 0 | F10: =SUM('Legal Risk'!$J$5:$J$24) -> 0 | G10: =IFERROR(E10/F10,0) -> 0 | H10: =G10*5 -> 0 | I10: =SUM('Legal Risk'!$K$5:$K$24) -> 0 | J10: =COUNTIF('Legal Risk'!$L$5:$L$24,"Critical") -> 0 | K10: =COUNTIF('Legal Risk'!$L$5:$L$24,"High") -> 0 | L10: =COUNTIF('Legal Risk'!$L$5:$L$24,"Medium") -> 0 | M10: =COUNTIF('Legal Risk'!$L$5:$L$24,"Low") -> 0 | N10: =COUNTIF('Legal Risk'!$L$5:$L$24,"Resilient") -> 0 | O10: =IF(J10+K10>0,"Review critical/high-risk gaps",IF(D10<1,"Complete assessment","Monitor and improve")) -> Complete assessment | Q10: Critical items | R10: =SUM(J5:J21) -> 0 | S10: Immediate action required.
A11: Physical Safety | B11: 28 | C11: =COUNTIF('Physical Safety'!$H$5:$H$32,"N/A")+COUNTIF('Physical Safety'!$H$5:$H$32,"0")+COUNTIF('Physical Safety'!$H$5:$H$32,"1")+COUNTIF('Physical Safety'!$H$5:$H$32,"2")+COUNTIF('Physical Safety'!$H$5:$H$32,"3")+COUNTIF('Physical Safety'!$H$5:$H$32,"4")+COUNTIF('Physical Safety'!$H$5:$H$32,"5") -> 0 | D11: =IFERROR(C11/B11,0) -> 0 | E11: =SUM('Physical Safety'!$I$5:$I$32) -> 0 | F11: =SUM('Physical Safety'!$J$5:$J$32) -> 0 | G11: =IFERROR(E11/F11,0) -> 0 | H11: =G11*5 -> 0 | I11: =SUM('Physical Safety'!$K$5:$K$32) -> 0 | J11: =COUNTIF('Physical Safety'!$L$5:$L$32,"Critical") -> 0 | K11: =COUNTIF('Physical Safety'!$L$5:$L$32,"High") -> 0 | L11: =COUNTIF('Physical Safety'!$L$5:$L$32,"Medium") -> 0 | M11: =COUNTIF('Physical Safety'!$L$5:$L$32,"Low") -> 0 | N11: =COUNTIF('Physical Safety'!$L$5:$L$32,"Resilient") -> 0 | O11: =IF(J11+K11>0,"Review critical/high-risk gaps",IF(D11<1,"Complete assessment","Monitor and improve")) -> Complete assessment | Q11: High-risk items | R11: =SUM(K5:K21) -> 0 | S11: Near-term mitigation required.
A12: Delivery Ops | B12: 24 | C12: =COUNTIF('Delivery Ops'!$H$5:$H$28,"N/A")+COUNTIF('Delivery Ops'!$H$5:$H$28,"0")+COUNTIF('Delivery Ops'!$H$5:$H$28,"1")+COUNTIF('Delivery Ops'!$H$5:$H$28,"2")+COUNTIF('Delivery Ops'!$H$5:$H$28,"3")+COUNTIF('Delivery Ops'!$H$5:$H$28,"4")+COUNTIF('Delivery Ops'!$H$5:$H$28,"5") -> 0 | D12: =IFERROR(C12/B12,0) -> 0 | E12: =SUM('Delivery Ops'!$I$5:$I$28) -> 0 | F12: =SUM('Delivery Ops'!$J$5:$J$28) -> 0 | G12: =IFERROR(E12/F12,0) -> 0 | H12: =G12*5 -> 0 | I12: =SUM('Delivery Ops'!$K$5:$K$28) -> 0 | J12: =COUNTIF('Delivery Ops'!$L$5:$L$28,"Critical") -> 0 | K12: =COUNTIF('Delivery Ops'!$L$5:$L$28,"High") -> 0 | L12: =COUNTIF('Delivery Ops'!$L$5:$L$28,"Medium") -> 0 | M12: =COUNTIF('Delivery Ops'!$L$5:$L$28,"Low") -> 0 | N12: =COUNTIF('Delivery Ops'!$L$5:$L$28,"Resilient") -> 0 | O12: =IF(J12+K12>0,"Review critical/high-risk gaps",IF(D12<1,"Complete assessment","Monitor and improve")) -> Complete assessment | Q12: Total weighted gap | R12: =SUM(I5:I21) -> 0 | S12: Weighted improvement opportunity.
A13: Supply Chain | B13: 25 | C13: =COUNTIF('Supply Chain'!$H$5:$H$29,"N/A")+COUNTIF('Supply Chain'!$H$5:$H$29,"0")+COUNTIF('Supply Chain'!$H$5:$H$29,"1")+COUNTIF('Supply Chain'!$H$5:$H$29,"2")+COUNTIF('Supply Chain'!$H$5:$H$29,"3")+COUNTIF('Supply Chain'!$H$5:$H$29,"4")+COUNTIF('Supply Chain'!$H$5:$H$29,"5") -> 0 | D13: =IFERROR(C13/B13,0) -> 0 | E13: =SUM('Supply Chain'!$I$5:$I$29) -> 0 | F13: =SUM('Supply Chain'!$J$5:$J$29) -> 0 | G13: =IFERROR(E13/F13,0) -> 0 | H13: =G13*5 -> 0 | I13: =SUM('Supply Chain'!$K$5:$K$29) -> 0 | J13: =COUNTIF('Supply Chain'!$L$5:$L$29,"Critical") -> 0 | K13: =COUNTIF('Supply Chain'!$L$5:$L$29,"High") -> 0 | L13: =COUNTIF('Supply Chain'!$L$5:$L$29,"Medium") -> 0 | M13: =COUNTIF('Supply Chain'!$L$5:$L$29,"Low") -> 0 | N13: =COUNTIF('Supply Chain'!$L$5:$L$29,"Resilient") -> 0 | O13: =IF(J13+K13>0,"Review critical/high-risk gaps",IF(D13<1,"Complete assessment","Monitor and improve")) -> Complete assessment | Q13: Selected crisis scenario | R13: ='Crisis Simulator'!$B$4 -> War / security crisis | S13: Used by scenario-adjusted risk and strategy logic.
A14: Manufacturing MES | B14: 28 | C14: =COUNTIF('Manufacturing MES'!$H$5:$H$32,"N/A")+COUNTIF('Manufacturing MES'!$H$5:$H$32,"0")+COUNTIF('Manufacturing MES'!$H$5:$H$32,"1")+COUNTIF('Manufacturing MES'!$H$5:$H$32,"2")+COUNTIF('Manufacturing MES'!$H$5:$H$32,"3")+COUNTIF('Manufacturing MES'!$H$5:$H$32,"4")+COUNTIF('Manufacturing MES'!$H$5:$H$32,"5") -> 0 | D14: =IFERROR(C14/B14,0) -> 0 | E14: =SUM('Manufacturing MES'!$I$5:$I$32) -> 0 | F14: =SUM('Manufacturing MES'!$J$5:$J$32) -> 0 | G14: =IFERROR(E14/F14,0) -> 0 | H14: =G14*5 -> 0 | I14: =SUM('Manufacturing MES'!$K$5:$K$32) -> 0 | J14: =COUNTIF('Manufacturing MES'!$L$5:$L$32,"Critical") -> 0 | K14: =COUNTIF('Manufacturing MES'!$L$5:$L$32,"High") -> 0 | L14: =COUNTIF('Manufacturing MES'!$L$5:$L$32,"Medium") -> 0 | M14: =COUNTIF('Manufacturing MES'!$L$5:$L$32,"Low") -> 0 | N14: =COUNTIF('Manufacturing MES'!$L$5:$L$32,"Resilient") -> 0 | O14: =IF(J14+K14>0,"Review critical/high-risk gaps",IF(D14<1,"Complete assessment","Monitor and improve")) -> Complete assessment | Q14: Crisis severity | R14: ='Crisis Simulator'!$B$5 -> 3 | S14: 1 mild; 3 base; 5 severe.
A15: Sales CRM | B15: 21 | C15: =COUNTIF('Sales CRM'!$H$5:$H$25,"N/A")+COUNTIF('Sales CRM'!$H$5:$H$25,"0")+COUNTIF('Sales CRM'!$H$5:$H$25,"1")+COUNTIF('Sales CRM'!$H$5:$H$25,"2")+COUNTIF('Sales CRM'!$H$5:$H$25,"3")+COUNTIF('Sales CRM'!$H$5:$H$25,"4")+COUNTIF('Sales CRM'!$H$5:$H$25,"5") -> 0 | D15: =IFERROR(C15/B15,0) -> 0 | E15: =SUM('Sales CRM'!$I$5:$I$25) -> 0 | F15: =SUM('Sales CRM'!$J$5:$J$25) -> 0 | G15: =IFERROR(E15/F15,0) -> 0 | H15: =G15*5 -> 0 | I15: =SUM('Sales CRM'!$K$5:$K$25) -> 0 | J15: =COUNTIF('Sales CRM'!$L$5:$L$25,"Critical") -> 0 | K15: =COUNTIF('Sales CRM'!$L$5:$L$25,"High") -> 0 | L15: =COUNTIF('Sales CRM'!$L$5:$L$25,"Medium") -> 0 | M15: =COUNTIF('Sales CRM'!$L$5:$L$25,"Low") -> 0 | N15: =COUNTIF('Sales CRM'!$L$5:$L$25,"Resilient") -> 0 | O15: =IF(J15+K15>0,"Review critical/high-risk gaps",IF(D15<1,"Complete assessment","Monitor and improve")) -> Complete assessment | Q15: Top exposed domain | R15: ='Crisis Simulator'!$O$7 | S15: Domain with highest scenario-adjusted exposure.
A16: Marketing Comms | B16: 17 | C16: =COUNTIF('Marketing Comms'!$H$5:$H$21,"N/A")+COUNTIF('Marketing Comms'!$H$5:$H$21,"0")+COUNTIF('Marketing Comms'!$H$5:$H$21,"1")+COUNTIF('Marketing Comms'!$H$5:$H$21,"2")+COUNTIF('Marketing Comms'!$H$5:$H$21,"3")+COUNTIF('Marketing Comms'!$H$5:$H$21,"4")+COUNTIF('Marketing Comms'!$H$5:$H$21,"5") -> 0 | D16: =IFERROR(C16/B16,0) -> 0 | E16: =SUM('Marketing Comms'!$I$5:$I$21) -> 0 | F16: =SUM('Marketing Comms'!$J$5:$J$21) -> 0 | G16: =IFERROR(E16/F16,0) -> 0 | H16: =G16*5 -> 0 | I16: =SUM('Marketing Comms'!$K$5:$K$21) -> 0 | J16: =COUNTIF('Marketing Comms'!$L$5:$L$21,"Critical") -> 0 | K16: =COUNTIF('Marketing Comms'!$L$5:$L$21,"High") -> 0 | L16: =COUNTIF('Marketing Comms'!$L$5:$L$21,"Medium") -> 0 | M16: =COUNTIF('Marketing Comms'!$L$5:$L$21,"Low") -> 0 | N16: =COUNTIF('Marketing Comms'!$L$5:$L$21,"Resilient") -> 0 | O16: =IF(J16+K16>0,"Review critical/high-risk gaps",IF(D16<1,"Complete assessment","Monitor and improve")) -> Complete assessment | Q16: Primary strategy | R16: ='Strategy Selection'!$B$6 | S16: Highest-scoring strategy under the selected crisis scenario.
A17: IT Cloud DR | B17: 29 | C17: =COUNTIF('IT Cloud DR'!$H$5:$H$33,"N/A")+COUNTIF('IT Cloud DR'!$H$5:$H$33,"0")+COUNTIF('IT Cloud DR'!$H$5:$H$33,"1")+COUNTIF('IT Cloud DR'!$H$5:$H$33,"2")+COUNTIF('IT Cloud DR'!$H$5:$H$33,"3")+COUNTIF('IT Cloud DR'!$H$5:$H$33,"4")+COUNTIF('IT Cloud DR'!$H$5:$H$33,"5") -> 0 | D17: =IFERROR(C17/B17,0) -> 0 | E17: =SUM('IT Cloud DR'!$I$5:$I$33) -> 0 | F17: =SUM('IT Cloud DR'!$J$5:$J$33) -> 0 | G17: =IFERROR(E17/F17,0) -> 0 | H17: =G17*5 -> 0 | I17: =SUM('IT Cloud DR'!$K$5:$K$33) -> 0 | J17: =COUNTIF('IT Cloud DR'!$L$5:$L$33,"Critical") -> 0 | K17: =COUNTIF('IT Cloud DR'!$L$5:$L$33,"High") -> 0 | L17: =COUNTIF('IT Cloud DR'!$L$5:$L$33,"Medium") -> 0 | M17: =COUNTIF('IT Cloud DR'!$L$5:$L$33,"Low") -> 0 | N17: =COUNTIF('IT Cloud DR'!$L$5:$L$33,"Resilient") -> 0 | O17: =IF(J17+K17>0,"Review critical/high-risk gaps",IF(D17<1,"Complete assessment","Monitor and improve")) -> Complete assessment
A18: Business Systems | B18: 23 | C18: =COUNTIF('Business Systems'!$H$5:$H$27,"N/A")+COUNTIF('Business Systems'!$H$5:$H$27,"0")+COUNTIF('Business Systems'!$H$5:$H$27,"1")+COUNTIF('Business Systems'!$H$5:$H$27,"2")+COUNTIF('Business Systems'!$H$5:$H$27,"3")+COUNTIF('Business Systems'!$H$5:$H$27,"4")+COUNTIF('Business Systems'!$H$5:$H$27,"5") -> 0 | D18: =IFERROR(C18/B18,0) -> 0 | E18: =SUM('Business Systems'!$I$5:$I$27) -> 0 | F18: =SUM('Business Systems'!$J$5:$J$27) -> 0 | G18: =IFERROR(E18/F18,0) -> 0 | H18: =G18*5 -> 0 | I18: =SUM('Business Systems'!$K$5:$K$27) -> 0 | J18: =COUNTIF('Business Systems'!$L$5:$L$27,"Critical") -> 0 | K18: =COUNTIF('Business Systems'!$L$5:$L$27,"High") -> 0 | L18: =COUNTIF('Business Systems'!$L$5:$L$27,"Medium") -> 0 | M18: =COUNTIF('Business Systems'!$L$5:$L$27,"Low") -> 0 | N18: =COUNTIF('Business Systems'!$L$5:$L$27,"Resilient") -> 0 | O18: =IF(J18+K18>0,"Review critical/high-risk gaps",IF(D18<1,"Complete assessment","Monitor and improve")) -> Complete assessment
A19: Data BI AI | B19: 27 | C19: =COUNTIF('Data BI AI'!$H$5:$H$31,"N/A")+COUNTIF('Data BI AI'!$H$5:$H$31,"0")+COUNTIF('Data BI AI'!$H$5:$H$31,"1")+COUNTIF('Data BI AI'!$H$5:$H$31,"2")+COUNTIF('Data BI AI'!$H$5:$H$31,"3")+COUNTIF('Data BI AI'!$H$5:$H$31,"4")+COUNTIF('Data BI AI'!$H$5:$H$31,"5") -> 0 | D19: =IFERROR(C19/B19,0) -> 0 | E19: =SUM('Data BI AI'!$I$5:$I$31) -> 0 | F19: =SUM('Data BI AI'!$J$5:$J$31) -> 0 | G19: =IFERROR(E19/F19,0) -> 0 | H19: =G19*5 -> 0 | I19: =SUM('Data BI AI'!$K$5:$K$31) -> 0 | J19: =COUNTIF('Data BI AI'!$L$5:$L$31,"Critical") -> 0 | K19: =COUNTIF('Data BI AI'!$L$5:$L$31,"High") -> 0 | L19: =COUNTIF('Data BI AI'!$L$5:$L$31,"Medium") -> 0 | M19: =COUNTIF('Data BI AI'!$L$5:$L$31,"Low") -> 0 | N19: =COUNTIF('Data BI AI'!$L$5:$L$31,"Resilient") -> 0 | O19: =IF(J19+K19>0,"Review critical/high-risk gaps",IF(D19<1,"Complete assessment","Monitor and improve")) -> Complete assessment
A20: Cyber Privacy | B20: 34 | C20: =COUNTIF('Cyber Privacy'!$H$5:$H$38,"N/A")+COUNTIF('Cyber Privacy'!$H$5:$H$38,"0")+COUNTIF('Cyber Privacy'!$H$5:$H$38,"1")+COUNTIF('Cyber Privacy'!$H$5:$H$38,"2")+COUNTIF('Cyber Privacy'!$H$5:$H$38,"3")+COUNTIF('Cyber Privacy'!$H$5:$H$38,"4")+COUNTIF('Cyber Privacy'!$H$5:$H$38,"5") -> 0 | D20: =IFERROR(C20/B20,0) -> 0 | E20: =SUM('Cyber Privacy'!$I$5:$I$38) -> 0 | F20: =SUM('Cyber Privacy'!$J$5:$J$38) -> 0 | G20: =IFERROR(E20/F20,0) -> 0 | H20: =G20*5 -> 0 | I20: =SUM('Cyber Privacy'!$K$5:$K$38) -> 0 | J20: =COUNTIF('Cyber Privacy'!$L$5:$L$38,"Critical") -> 0 | K20: =COUNTIF('Cyber Privacy'!$L$5:$L$38,"High") -> 0 | L20: =COUNTIF('Cyber Privacy'!$L$5:$L$38,"Medium") -> 0 | M20: =COUNTIF('Cyber Privacy'!$L$5:$L$38,"Low") -> 0 | N20: =COUNTIF('Cyber Privacy'!$L$5:$L$38,"Resilient") -> 0 | O20: =IF(J20+K20>0,"Review critical/high-risk gaps",IF(D20<1,"Complete assessment","Monitor and improve")) -> Complete assessment
A21: Quality Portfolio | B21: 20 | C21: =COUNTIF('Quality Portfolio'!$H$5:$H$24,"N/A")+COUNTIF('Quality Portfolio'!$H$5:$H$24,"0")+COUNTIF('Quality Portfolio'!$H$5:$H$24,"1")+COUNTIF('Quality Portfolio'!$H$5:$H$24,"2")+COUNTIF('Quality Portfolio'!$H$5:$H$24,"3")+COUNTIF('Quality Portfolio'!$H$5:$H$24,"4")+COUNTIF('Quality Portfolio'!$H$5:$H$24,"5") -> 0 | D21: =IFERROR(C21/B21,0) -> 0 | E21: =SUM('Quality Portfolio'!$I$5:$I$24) -> 0 | F21: =SUM('Quality Portfolio'!$J$5:$J$24) -> 0 | G21: =IFERROR(E21/F21,0) -> 0 | H21: =G21*5 -> 0 | I21: =SUM('Quality Portfolio'!$K$5:$K$24) -> 0 | J21: =COUNTIF('Quality Portfolio'!$L$5:$L$24,"Critical") -> 0 | K21: =COUNTIF('Quality Portfolio'!$L$5:$L$24,"High") -> 0 | L21: =COUNTIF('Quality Portfolio'!$L$5:$L$24,"Medium") -> 0 | M21: =COUNTIF('Quality Portfolio'!$L$5:$L$24,"Low") -> 0 | N21: =COUNTIF('Quality Portfolio'!$L$5:$L$24,"Resilient") -> 0 | O21: =IF(J21+K21>0,"Review critical/high-risk gaps",IF(D21<1,"Complete assessment","Monitor and improve")) -> Complete assessment
Q40: Crisis scenario | R40: Primary diagnostic tabs | S40: Typical management output
Q41: War / security crisis | R41: Company Geography; Physical Safety; HR Workforce; Supply Chain; IT Cloud DR | S41: Employee safety map; site recovery plan; relocation options; logistics fallback; remote operations plan
Q42: Physical site loss | R42: Physical Safety; Delivery Ops; Manufacturing MES; IT Cloud DR; Business Systems | S42: Alternative site plan; production/service transfer plan; insurance/evidence package; recovery sequencing
Q43: Cyberattack / ransomware | R43: Cyber Privacy; IT Cloud DR; Business Systems; Legal Risk; Marketing Comms | S43: Incident response plan; isolation and restore runbook; notification workflow; customer communication pack
Q44: Cloud / SaaS outage | R44: IT Cloud DR; Business Systems; Data BI AI; Sales CRM | S44: Cloud/SaaS dependency map; RTO/RPO gaps; backup/export strategy; failover exercise
Q45: Supplier / logistics disruption | R45: Supply Chain; Finance Procurement; Manufacturing MES; Delivery Ops | S45: Critical supplier map; alternate suppliers; inventory buffer model; customer allocation rules
Q46: Energy / utilities outage | R46: Physical Safety; Manufacturing MES; IT Cloud DR; Delivery Ops | S46: Backup power/fuel plan; utility dependency map; minimum viable operations
Q47: Financial liquidity crisis | R47: Finance Procurement; Strategy GTM; Sales CRM; Governance Crisis | S47: Cash-flow stress test; payment priority rules; revenue defense plan; emergency budget actions
Q48: Demand shock | R48: Strategy GTM; Sales CRM; Marketing Comms; Finance Procurement | S48: ICP/offering review; pipeline stress test; pricing response; market pivot options
Q49: Pandemic / health crisis | R49: HR Workforce; Physical Safety; IT Cloud DR; Delivery Ops | S49: Remote operating model; absence plan; health protocols; minimum staffing
Q50: Regulatory / legal shock | R50: Legal Risk; Data BI AI; Cyber Privacy; Finance Procurement | S50: Compliance gap map; contract/legal exposure; data/privacy remediation plan
Q51: Reputation crisis | R51: Marketing Comms; Sales CRM; Legal Risk; Cyber Privacy | S51: Crisis communication playbook; customer notification plan; spokesperson matrix
Q52: Natural disaster / climate event | R52: Physical Safety; Supply Chain; HR Workforce; Delivery Ops | S52: Site risk map; emergency supplies; alternate routes; employee notification
A55: Initiative roadmap summary
A56: Metric | B56: Value | C56: How it is calculated | D56: Action
A57: Primary strategy | B57: ='Strategy Selection'!$B$6 | C57: Top-ranked strategy from Strategy Selection. | D57: Use as portfolio theme.
A58: Selected crisis | B58: ='Crisis Simulator'!$B$4 -> War / security crisis | C58: Scenario selected in Crisis Simulator. | D58: Review if scenario changed.
A59: Active / triggered initiatives | B59: ='Initiatives Roadmap'!$E$5 -> 0 | C59: Initiatives ranked into 0-90 days through 6-12 months. | D59: Start with top 10.
A60: Top WSJF | B60: ='Initiatives Roadmap'!$G$5 | C60: Highest WSJF across initiative library. | D60: Use for first wave.
A61: 0-90 days initiatives | B61: ='Initiatives Roadmap'!$H$5 -> 0 | C61: Roadmap wave based on rank and WSJF. | D61: Assign owners.
A62: 3-6 months initiatives | B62: ='Initiatives Roadmap'!$I$5 -> 0 | C62: Roadmap wave based on rank and WSJF. | D62: Prepare budget.
A64: Scope update
A65: Company Profile | B65: Context and target settings
A66: Quality Control | B66: Completeness and quality checks
A67: Gantt Roadmap | B67: Time-based initiative roadmap
A68: Standards per Question | B68: Question-level standards mapping
A72: Industry-adjusted scoring overview
A73: Selected industry | B73: ='Company Profile'!$B$9 -> IT Services | D73: Domain | E73: Adjusted score | F73: Target | G73: Gap | H73: Threshold status
A74: Industry-adjusted weighted score 0-5 | B74: ='Improved Scoring Model'!$Q$4 | D74: Company Geography | E74: =IFERROR(INDEX('Improved Scoring Model'!$C$6:$C$22,MATCH($D74,'Improved Scoring Model'!$A$6:$A$22,0)),"") | F74: =IFERROR(INDEX('Improved Scoring Model'!$D$6:$D$22,MATCH($D74,'Improved Scoring Model'!$A$6:$A$22,0)),"") -> 3.5 | G74: =IFERROR(INDEX('Improved Scoring Model'!$E$6:$E$22,MATCH($D74,'Improved Scoring Model'!$A$6:$A$22,0)),"") | H74: =IFERROR(INDEX('Improved Scoring Model'!$I$6:$I$22,MATCH($D74,'Improved Scoring Model'!$A$6:$A$22,0)),"")
A75: Average gap to industry target | B75: ='Improved Scoring Model'!$Q$5 | D75: Strategy GTM | E75: =IFERROR(INDEX('Improved Scoring Model'!$C$6:$C$22,MATCH($D75,'Improved Scoring Model'!$A$6:$A$22,0)),"") | F75: =IFERROR(INDEX('Improved Scoring Model'!$D$6:$D$22,MATCH($D75,'Improved Scoring Model'!$A$6:$A$22,0)),"") -> 3.5 | G75: =IFERROR(INDEX('Improved Scoring Model'!$E$6:$E$22,MATCH($D75,'Improved Scoring Model'!$A$6:$A$22,0)),"") | H75: =IFERROR(INDEX('Improved Scoring Model'!$I$6:$I$22,MATCH($D75,'Improved Scoring Model'!$A$6:$A$22,0)),"")
A76: Red-line threshold breaches | B76: ='Improved Scoring Model'!$Q$6 -> 0 | D76: Governance Crisis | E76: =IFERROR(INDEX('Improved Scoring Model'!$C$6:$C$22,MATCH($D76,'Improved Scoring Model'!$A$6:$A$22,0)),"") | F76: =IFERROR(INDEX('Improved Scoring Model'!$D$6:$D$22,MATCH($D76,'Improved Scoring Model'!$A$6:$A$22,0)),"") -> 4 | G76: =IFERROR(INDEX('Improved Scoring Model'!$E$6:$E$22,MATCH($D76,'Improved Scoring Model'!$A$6:$A$22,0)),"") | H76: =IFERROR(INDEX('Improved Scoring Model'!$I$6:$I$22,MATCH($D76,'Improved Scoring Model'!$A$6:$A$22,0)),"")
A77: Primary industry-adjusted strategy | B77: ='Strategy Selection'!$B$6 | D77: HR Workforce | E77: =IFERROR(INDEX('Improved Scoring Model'!$C$6:$C$22,MATCH($D77,'Improved Scoring Model'!$A$6:$A$22,0)),"") | F77: =IFERROR(INDEX('Improved Scoring Model'!$D$6:$D$22,MATCH($D77,'Improved Scoring Model'!$A$6:$A$22,0)),"") -> 4 | G77: =IFERROR(INDEX('Improved Scoring Model'!$E$6:$E$22,MATCH($D77,'Improved Scoring Model'!$A$6:$A$22,0)),"") | H77: =IFERROR(INDEX('Improved Scoring Model'!$I$6:$I$22,MATCH($D77,'Improved Scoring Model'!$A$6:$A$22,0)),"")
D78: Finance Procurement | E78: =IFERROR(INDEX('Improved Scoring Model'!$C$6:$C$22,MATCH($D78,'Improved Scoring Model'!$A$6:$A$22,0)),"") | F78: =IFERROR(INDEX('Improved Scoring Model'!$D$6:$D$22,MATCH($D78,'Improved Scoring Model'!$A$6:$A$22,0)),"") -> 3.5 | G78: =IFERROR(INDEX('Improved Scoring Model'!$E$6:$E$22,MATCH($D78,'Improved Scoring Model'!$A$6:$A$22,0)),"") | H78: =IFERROR(INDEX('Improved Scoring Model'!$I$6:$I$22,MATCH($D78,'Improved Scoring Model'!$A$6:$A$22,0)),"")
D79: Legal Risk | E79: =IFERROR(INDEX('Improved Scoring Model'!$C$6:$C$22,MATCH($D79,'Improved Scoring Model'!$A$6:$A$22,0)),"") | F79: =IFERROR(INDEX('Improved Scoring Model'!$D$6:$D$22,MATCH($D79,'Improved Scoring Model'!$A$6:$A$22,0)),"") -> 3.5 | G79: =IFERROR(INDEX('Improved Scoring Model'!$E$6:$E$22,MATCH($D79,'Improved Scoring Model'!$A$6:$A$22,0)),"") | H79: =IFERROR(INDEX('Improved Scoring Model'!$I$6:$I$22,MATCH($D79,'Improved Scoring Model'!$A$6:$A$22,0)),"")
D80: Physical Safety | E80: =IFERROR(INDEX('Improved Scoring Model'!$C$6:$C$22,MATCH($D80,'Improved Scoring Model'!$A$6:$A$22,0)),"") | F80: =IFERROR(INDEX('Improved Scoring Model'!$D$6:$D$22,MATCH($D80,'Improved Scoring Model'!$A$6:$A$22,0)),"") -> 2.8 | G80: =IFERROR(INDEX('Improved Scoring Model'!$E$6:$E$22,MATCH($D80,'Improved Scoring Model'!$A$6:$A$22,0)),"") | H80: =IFERROR(INDEX('Improved Scoring Model'!$I$6:$I$22,MATCH($D80,'Improved Scoring Model'!$A$6:$A$22,0)),"")
D81: Delivery Ops | E81: =IFERROR(INDEX('Improved Scoring Model'!$C$6:$C$22,MATCH($D81,'Improved Scoring Model'!$A$6:$A$22,0)),"") | F81: =IFERROR(INDEX('Improved Scoring Model'!$D$6:$D$22,MATCH($D81,'Improved Scoring Model'!$A$6:$A$22,0)),"") -> 4 | G81: =IFERROR(INDEX('Improved Scoring Model'!$E$6:$E$22,MATCH($D81,'Improved Scoring Model'!$A$6:$A$22,0)),"") | H81: =IFERROR(INDEX('Improved Scoring Model'!$I$6:$I$22,MATCH($D81,'Improved Scoring Model'!$A$6:$A$22,0)),"")
D82: Supply Chain | E82: =IFERROR(INDEX('Improved Scoring Model'!$C$6:$C$22,MATCH($D82,'Improved Scoring Model'!$A$6:$A$22,0)),"") | F82: =IFERROR(INDEX('Improved Scoring Model'!$D$6:$D$22,MATCH($D82,'Improved Scoring Model'!$A$6:$A$22,0)),"") -> 3.5 | G82: =IFERROR(INDEX('Improved Scoring Model'!$E$6:$E$22,MATCH($D82,'Improved Scoring Model'!$A$6:$A$22,0)),"") | H82: =IFERROR(INDEX('Improved Scoring Model'!$I$6:$I$22,MATCH($D82,'Improved Scoring Model'!$A$6:$A$22,0)),"")
D83: Manufacturing MES | E83: =IFERROR(INDEX('Improved Scoring Model'!$C$6:$C$22,MATCH($D83,'Improved Scoring Model'!$A$6:$A$22,0)),"") | F83: =IFERROR(INDEX('Improved Scoring Model'!$D$6:$D$22,MATCH($D83,'Improved Scoring Model'!$A$6:$A$22,0)),"") -> 1 | G83: =IFERROR(INDEX('Improved Scoring Model'!$E$6:$E$22,MATCH($D83,'Improved Scoring Model'!$A$6:$A$22,0)),"") | H83: =IFERROR(INDEX('Improved Scoring Model'!$I$6:$I$22,MATCH($D83,'Improved Scoring Model'!$A$6:$A$22,0)),"")
A84: Roadmap and heatmap outputs | D84: Sales CRM | E84: =IFERROR(INDEX('Improved Scoring Model'!$C$6:$C$22,MATCH($D84,'Improved Scoring Model'!$A$6:$A$22,0)),"") | F84: =IFERROR(INDEX('Improved Scoring Model'!$D$6:$D$22,MATCH($D84,'Improved Scoring Model'!$A$6:$A$22,0)),"") -> 3.8 | G84: =IFERROR(INDEX('Improved Scoring Model'!$E$6:$E$22,MATCH($D84,'Improved Scoring Model'!$A$6:$A$22,0)),"") | H84: =IFERROR(INDEX('Improved Scoring Model'!$I$6:$I$22,MATCH($D84,'Improved Scoring Model'!$A$6:$A$22,0)),"")
A85: Gantt Roadmap | B85: Open the Gantt Roadmap tab to review initiative sequencing, capacity load, overload months, dependencies and decision flags. | D85: Marketing Comms | E85: =IFERROR(INDEX('Improved Scoring Model'!$C$6:$C$22,MATCH($D85,'Improved Scoring Model'!$A$6:$A$22,0)),"") | F85: =IFERROR(INDEX('Improved Scoring Model'!$D$6:$D$22,MATCH($D85,'Improved Scoring Model'!$A$6:$A$22,0)),"") -> 3.5 | G85: =IFERROR(INDEX('Improved Scoring Model'!$E$6:$E$22,MATCH($D85,'Improved Scoring Model'!$A$6:$A$22,0)),"") | H85: =IFERROR(INDEX('Improved Scoring Model'!$I$6:$I$22,MATCH($D85,'Improved Scoring Model'!$A$6:$A$22,0)),"")
A86: Heatmaps | B86: Open the Heatmaps tab to review domain-by-crisis exposure, risk category concentration and roadmap capacity pressure. | D86: IT Cloud DR | E86: =IFERROR(INDEX('Improved Scoring Model'!$C$6:$C$22,MATCH($D86,'Improved Scoring Model'!$A$6:$A$22,0)),"") | F86: =IFERROR(INDEX('Improved Scoring Model'!$D$6:$D$22,MATCH($D86,'Improved Scoring Model'!$A$6:$A$22,0)),"") -> 4 | G86: =IFERROR(INDEX('Improved Scoring Model'!$E$6:$E$22,MATCH($D86,'Improved Scoring Model'!$A$6:$A$22,0)),"") | H86: =IFERROR(INDEX('Improved Scoring Model'!$I$6:$I$22,MATCH($D86,'Improved Scoring Model'!$A$6:$A$22,0)),"")
D87: Business Systems | E87: =IFERROR(INDEX('Improved Scoring Model'!$C$6:$C$22,MATCH($D87,'Improved Scoring Model'!$A$6:$A$22,0)),"") | F87: =IFERROR(INDEX('Improved Scoring Model'!$D$6:$D$22,MATCH($D87,'Improved Scoring Model'!$A$6:$A$22,0)),"") -> 4 | G87: =IFERROR(INDEX('Improved Scoring Model'!$E$6:$E$22,MATCH($D87,'Improved Scoring Model'!$A$6:$A$22,0)),"") | H87: =IFERROR(INDEX('Improved Scoring Model'!$I$6:$I$22,MATCH($D87,'Improved Scoring Model'!$A$6:$A$22,0)),"")
D88: Data BI AI | E88: =IFERROR(INDEX('Improved Scoring Model'!$C$6:$C$22,MATCH($D88,'Improved Scoring Model'!$A$6:$A$22,0)),"") | F88: =IFERROR(INDEX('Improved Scoring Model'!$D$6:$D$22,MATCH($D88,'Improved Scoring Model'!$A$6:$A$22,0)),"") -> 3.5 | G88: =IFERROR(INDEX('Improved Scoring Model'!$E$6:$E$22,MATCH($D88,'Improved Scoring Model'!$A$6:$A$22,0)),"") | H88: =IFERROR(INDEX('Improved Scoring Model'!$I$6:$I$22,MATCH($D88,'Improved Scoring Model'!$A$6:$A$22,0)),"")
D89: Cyber Privacy | E89: =IFERROR(INDEX('Improved Scoring Model'!$C$6:$C$22,MATCH($D89,'Improved Scoring Model'!$A$6:$A$22,0)),"") | F89: =IFERROR(INDEX('Improved Scoring Model'!$D$6:$D$22,MATCH($D89,'Improved Scoring Model'!$A$6:$A$22,0)),"") -> 4 | G89: =IFERROR(INDEX('Improved Scoring Model'!$E$6:$E$22,MATCH($D89,'Improved Scoring Model'!$A$6:$A$22,0)),"") | H89: =IFERROR(INDEX('Improved Scoring Model'!$I$6:$I$22,MATCH($D89,'Improved Scoring Model'!$A$6:$A$22,0)),"")
D90: Quality Portfolio | E90: =IFERROR(INDEX('Improved Scoring Model'!$C$6:$C$22,MATCH($D90,'Improved Scoring Model'!$A$6:$A$22,0)),"") | F90: =IFERROR(INDEX('Improved Scoring Model'!$D$6:$D$22,MATCH($D90,'Improved Scoring Model'!$A$6:$A$22,0)),"") -> 4 | G90: =IFERROR(INDEX('Improved Scoring Model'!$E$6:$E$22,MATCH($D90,'Improved Scoring Model'!$A$6:$A$22,0)),"") | H90: =IFERROR(INDEX('Improved Scoring Model'!$I$6:$I$22,MATCH($D90,'Improved Scoring Model'!$A$6:$A$22,0)),"")

Sheet Heatmaps
A1: Crisis and Risk Heatmaps
A2: Visual heatmaps to help executives see which domains are most exposed to selected crisis scenarios, risk categories and roadmap workload. Values recalculate when the questionnaire, crisis scenario or industry template changes.
A4: Selected industry | B4: ='Company Profile'!$B$9 -> IT Services | C4: Selected crisis | D4: ='Crisis Simulator'!$B$4 -> War / security crisis | E4: Severity | F4: ='Crisis Simulator'!$B$5 -> 3
A5: Primary strategy | B5: ='Strategy Selection'!$B$6 | C5: Business resilience score | D5: =Dashboard!$B$31 -> 0 | E5: Active risks | F5: ='Risk Summary'!$A$5 -> 0
A8: Heatmap 1. Domain vs crisis scenario exposure
A9: Domain | B9: War / security crisis | C9: Physical site loss | D9: Cyberattack / ransomware | E9: Cloud / SaaS outage | F9: Supplier / logistics disruption | G9: Energy / utilities outage | H9: Financial liquidity crisis | I9: Demand shock | J9: Pandemic / health crisis | K9: Regulatory / legal shock | L9: Reputation crisis
A10: Company Geography | B10: =IFERROR(SUMIFS(_TECH_Crisis_Model!$D:$D,_TECH_Crisis_Model!$A:$A,B$9,_TECH_Crisis_Model!$B:$B,$A10),"") -> 1.6 | C10: =IFERROR(SUMIFS(_TECH_Crisis_Model!$D:$D,_TECH_Crisis_Model!$A:$A,C$9,_TECH_Crisis_Model!$B:$B,$A10),"") -> 1.3 | D10: =IFERROR(SUMIFS(_TECH_Crisis_Model!$D:$D,_TECH_Crisis_Model!$A:$A,D$9,_TECH_Crisis_Model!$B:$B,$A10),"") -> 1 | E10: =IFERROR(SUMIFS(_TECH_Crisis_Model!$D:$D,_TECH_Crisis_Model!$A:$A,E$9,_TECH_Crisis_Model!$B:$B,$A10),"") -> 1 | F10: =IFERROR(SUMIFS(_TECH_Crisis_Model!$D:$D,_TECH_Crisis_Model!$A:$A,F$9,_TECH_Crisis_Model!$B:$B,$A10),"") -> 1.3 | G10: =IFERROR(SUMIFS(_TECH_Crisis_Model!$D:$D,_TECH_Crisis_Model!$A:$A,G$9,_TECH_Crisis_Model!$B:$B,$A10),"") -> 1 | H10: =IFERROR(SUMIFS(_TECH_Crisis_Model!$D:$D,_TECH_Crisis_Model!$A:$A,H$9,_TECH_Crisis_Model!$B:$B,$A10),"") -> 1 | I10: =IFERROR(SUMIFS(_TECH_Crisis_Model!$D:$D,_TECH_Crisis_Model!$A:$A,I$9,_TECH_Crisis_Model!$B:$B,$A10),"") -> 1 | ... L10: =IFERROR(SUMIFS(_TECH_Crisis_Model!$D:$D,_TECH_Crisis_Model!$A:$A,L$9,_TECH_Crisis_Model!$B:$B,$A10),"") -> 1
A11: Strategy GTM | B11: =IFERROR(SUMIFS(_TECH_Crisis_Model!$D:$D,_TECH_Crisis_Model!$A:$A,B$9,_TECH_Crisis_Model!$B:$B,$A11),"") -> 1 | C11: =IFERROR(SUMIFS(_TECH_Crisis_Model!$D:$D,_TECH_Crisis_Model!$A:$A,C$9,_TECH_Crisis_Model!$B:$B,$A11),"") -> 1 | D11: =IFERROR(SUMIFS(_TECH_Crisis_Model!$D:$D,_TECH_Crisis_Model!$A:$A,D$9,_TECH_Crisis_Model!$B:$B,$A11),"") -> 1 | E11: =IFERROR(SUMIFS(_TECH_Crisis_Model!$D:$D,_TECH_Crisis_Model!$A:$A,E$9,_TECH_Crisis_Model!$B:$B,$A11),"") -> 1 | F11: =IFERROR(SUMIFS(_TECH_Crisis_Model!$D:$D,_TECH_Crisis_Model!$A:$A,F$9,_TECH_Crisis_Model!$B:$B,$A11),"") -> 1.2 | G11: =IFERROR(SUMIFS(_TECH_Crisis_Model!$D:$D,_TECH_Crisis_Model!$A:$A,G$9,_TECH_Crisis_Model!$B:$B,$A11),"") -> 1 | H11: =IFERROR(SUMIFS(_TECH_Crisis_Model!$D:$D,_TECH_Crisis_Model!$A:$A,H$9,_TECH_Crisis_Model!$B:$B,$A11),"") -> 1.8 | I11: =IFERROR(SUMIFS(_TECH_Crisis_Model!$D:$D,_TECH_Crisis_Model!$A:$A,I$9,_TECH_Crisis_Model!$B:$B,$A11),"") -> 2 | ... L11: =IFERROR(SUMIFS(_TECH_Crisis_Model!$D:$D,_TECH_Crisis_Model!$A:$A,L$9,_TECH_Crisis_Model!$B:$B,$A11),"") -> 1.3
A12: Governance Crisis | B12: =IFERROR(SUMIFS(_TECH_Crisis_Model!$D:$D,_TECH_Crisis_Model!$A:$A,B$9,_TECH_Crisis_Model!$B:$B,$A12),"") -> 1.4 | C12: =IFERROR(SUMIFS(_TECH_Crisis_Model!$D:$D,_TECH_Crisis_Model!$A:$A,C$9,_TECH_Crisis_Model!$B:$B,$A12),"") -> 1 | D12: =IFERROR(SUMIFS(_TECH_Crisis_Model!$D:$D,_TECH_Crisis_Model!$A:$A,D$9,_TECH_Crisis_Model!$B:$B,$A12),"") -> 1.2 | E12: =IFERROR(SUMIFS(_TECH_Crisis_Model!$D:$D,_TECH_Crisis_Model!$A:$A,E$9,_TECH_Crisis_Model!$B:$B,$A12),"") -> 1 | F12: =IFERROR(SUMIFS(_TECH_Crisis_Model!$D:$D,_TECH_Crisis_Model!$A:$A,F$9,_TECH_Crisis_Model!$B:$B,$A12),"") -> 1 | G12: =IFERROR(SUMIFS(_TECH_Crisis_Model!$D:$D,_TECH_Crisis_Model!$A:$A,G$9,_TECH_Crisis_Model!$B:$B,$A12),"") -> 1 | H12: =IFERROR(SUMIFS(_TECH_Crisis_Model!$D:$D,_TECH_Crisis_Model!$A:$A,H$9,_TECH_Crisis_Model!$B:$B,$A12),"") -> 1.4 | I12: =IFERROR(SUMIFS(_TECH_Crisis_Model!$D:$D,_TECH_Crisis_Model!$A:$A,I$9,_TECH_Crisis_Model!$B:$B,$A12),"") -> 1 | ... L12: =IFERROR(SUMIFS(_TECH_Crisis_Model!$D:$D,_TECH_Crisis_Model!$A:$A,L$9,_TECH_Crisis_Model!$B:$B,$A12),"") -> 1.5
A13: HR Workforce | B13: =IFERROR(SUMIFS(_TECH_Crisis_Model!$D:$D,_TECH_Crisis_Model!$A:$A,B$9,_TECH_Crisis_Model!$B:$B,$A13),"") -> 1.8 | C13: =IFERROR(SUMIFS(_TECH_Crisis_Model!$D:$D,_TECH_Crisis_Model!$A:$A,C$9,_TECH_Crisis_Model!$B:$B,$A13),"") -> 1.3 | D13: =IFERROR(SUMIFS(_TECH_Crisis_Model!$D:$D,_TECH_Crisis_Model!$A:$A,D$9,_TECH_Crisis_Model!$B:$B,$A13),"") -> 1 | E13: =IFERROR(SUMIFS(_TECH_Crisis_Model!$D:$D,_TECH_Crisis_Model!$A:$A,E$9,_TECH_Crisis_Model!$B:$B,$A13),"") -> 1 | F13: =IFERROR(SUMIFS(_TECH_Crisis_Model!$D:$D,_TECH_Crisis_Model!$A:$A,F$9,_TECH_Crisis_Model!$B:$B,$A13),"") -> 1 | G13: =IFERROR(SUMIFS(_TECH_Crisis_Model!$D:$D,_TECH_Crisis_Model!$A:$A,G$9,_TECH_Crisis_Model!$B:$B,$A13),"") -> 1.2 | H13: =IFERROR(SUMIFS(_TECH_Crisis_Model!$D:$D,_TECH_Crisis_Model!$A:$A,H$9,_TECH_Crisis_Model!$B:$B,$A13),"") -> 1.2 | I13: =IFERROR(SUMIFS(_TECH_Crisis_Model!$D:$D,_TECH_Crisis_Model!$A:$A,I$9,_TECH_Crisis_Model!$B:$B,$A13),"") -> 1 | ... L13: =IFERROR(SUMIFS(_TECH_Crisis_Model!$D:$D,_TECH_Crisis_Model!$A:$A,L$9,_TECH_Crisis_Model!$B:$B,$A13),"") -> 1.2
A14: Finance Procurement | B14: =IFERROR(SUMIFS(_TECH_Crisis_Model!$D:$D,_TECH_Crisis_Model!$A:$A,B$9,_TECH_Crisis_Model!$B:$B,$A14),"") -> 1.3 | C14: =IFERROR(SUMIFS(_TECH_Crisis_Model!$D:$D,_TECH_Crisis_Model!$A:$A,C$9,_TECH_Crisis_Model!$B:$B,$A14),"") -> 1 | D14: =IFERROR(SUMIFS(_TECH_Crisis_Model!$D:$D,_TECH_Crisis_Model!$A:$A,D$9,_TECH_Crisis_Model!$B:$B,$A14),"") -> 1.3 | E14: =IFERROR(SUMIFS(_TECH_Crisis_Model!$D:$D,_TECH_Crisis_Model!$A:$A,E$9,_TECH_Crisis_Model!$B:$B,$A14),"") -> 1.2 | F14: =IFERROR(SUMIFS(_TECH_Crisis_Model!$D:$D,_TECH_Crisis_Model!$A:$A,F$9,_TECH_Crisis_Model!$B:$B,$A14),"") -> 1.4 | G14: =IFERROR(SUMIFS(_TECH_Crisis_Model!$D:$D,_TECH_Crisis_Model!$A:$A,G$9,_TECH_Crisis_Model!$B:$B,$A14),"") -> 1 | H14: =IFERROR(SUMIFS(_TECH_Crisis_Model!$D:$D,_TECH_Crisis_Model!$A:$A,H$9,_TECH_Crisis_Model!$B:$B,$A14),"") -> 2 | I14: =IFERROR(SUMIFS(_TECH_Crisis_Model!$D:$D,_TECH_Crisis_Model!$A:$A,I$9,_TECH_Crisis_Model!$B:$B,$A14),"") -> 1.5 | ... L14: =IFERROR(SUMIFS(_TECH_Crisis_Model!$D:$D,_TECH_Crisis_Model!$A:$A,L$9,_TECH_Crisis_Model!$B:$B,$A14),"") -> 1
A15: Legal Risk | B15: =IFERROR(SUMIFS(_TECH_Crisis_Model!$D:$D,_TECH_Crisis_Model!$A:$A,B$9,_TECH_Crisis_Model!$B:$B,$A15),"") -> 1.4 | C15: =IFERROR(SUMIFS(_TECH_Crisis_Model!$D:$D,_TECH_Crisis_Model!$A:$A,C$9,_TECH_Crisis_Model!$B:$B,$A15),"") -> 1 | D15: =IFERROR(SUMIFS(_TECH_Crisis_Model!$D:$D,_TECH_Crisis_Model!$A:$A,D$9,_TECH_Crisis_Model!$B:$B,$A15),"") -> 1.5 | E15: =IFERROR(SUMIFS(_TECH_Crisis_Model!$D:$D,_TECH_Crisis_Model!$A:$A,E$9,_TECH_Crisis_Model!$B:$B,$A15),"") -> 1 | F15: =IFERROR(SUMIFS(_TECH_Crisis_Model!$D:$D,_TECH_Crisis_Model!$A:$A,F$9,_TECH_Crisis_Model!$B:$B,$A15),"") -> 1 | G15: =IFERROR(SUMIFS(_TECH_Crisis_Model!$D:$D,_TECH_Crisis_Model!$A:$A,G$9,_TECH_Crisis_Model!$B:$B,$A15),"") -> 1 | H15: =IFERROR(SUMIFS(_TECH_Crisis_Model!$D:$D,_TECH_Crisis_Model!$A:$A,H$9,_TECH_Crisis_Model!$B:$B,$A15),"") -> 1 | I15: =IFERROR(SUMIFS(_TECH_Crisis_Model!$D:$D,_TECH_Crisis_Model!$A:$A,I$9,_TECH_Crisis_Model!$B:$B,$A15),"") -> 1 | ... L15: =IFERROR(SUMIFS(_TECH_Crisis_Model!$D:$D,_TECH_Crisis_Model!$A:$A,L$9,_TECH_Crisis_Model!$B:$B,$A15),"") -> 1.4
A16: Physical Safety | B16: =IFERROR(SUMIFS(_TECH_Crisis_Model!$D:$D,_TECH_Crisis_Model!$A:$A,B$9,_TECH_Crisis_Model!$B:$B,$A16),"") -> 2 | C16: =IFERROR(SUMIFS(_TECH_Crisis_Model!$D:$D,_TECH_Crisis_Model!$A:$A,C$9,_TECH_Crisis_Model!$B:$B,$A16),"") -> 2 | D16: =IFERROR(SUMIFS(_TECH_Crisis_Model!$D:$D,_TECH_Crisis_Model!$A:$A,D$9,_TECH_Crisis_Model!$B:$B,$A16),"") -> 1 | E16: =IFERROR(SUMIFS(_TECH_Crisis_Model!$D:$D,_TECH_Crisis_Model!$A:$A,E$9,_TECH_Crisis_Model!$B:$B,$A16),"") -> 1 | F16: =IFERROR(SUMIFS(_TECH_Crisis_Model!$D:$D,_TECH_Crisis_Model!$A:$A,F$9,_TECH_Crisis_Model!$B:$B,$A16),"") -> 1.2 | G16: =IFERROR(SUMIFS(_TECH_Crisis_Model!$D:$D,_TECH_Crisis_Model!$A:$A,G$9,_TECH_Crisis_Model!$B:$B,$A16),"") -> 1.8 | H16: =IFERROR(SUMIFS(_TECH_Crisis_Model!$D:$D,_TECH_Crisis_Model!$A:$A,H$9,_TECH_Crisis_Model!$B:$B,$A16),"") -> 1 | I16: =IFERROR(SUMIFS(_TECH_Crisis_Model!$D:$D,_TECH_Crisis_Model!$A:$A,I$9,_TECH_Crisis_Model!$B:$B,$A16),"") -> 1 | ... L16: =IFERROR(SUMIFS(_TECH_Crisis_Model!$D:$D,_TECH_Crisis_Model!$A:$A,L$9,_TECH_Crisis_Model!$B:$B,$A16),"") -> 1
A17: Delivery Ops | B17: =IFERROR(SUMIFS(_TECH_Crisis_Model!$D:$D,_TECH_Crisis_Model!$A:$A,B$9,_TECH_Crisis_Model!$B:$B,$A17),"") -> 1.7 | C17: =IFERROR(SUMIFS(_TECH_Crisis_Model!$D:$D,_TECH_Crisis_Model!$A:$A,C$9,_TECH_Crisis_Model!$B:$B,$A17),"") -> 1.7 | D17: =IFERROR(SUMIFS(_TECH_Crisis_Model!$D:$D,_TECH_Crisis_Model!$A:$A,D$9,_TECH_Crisis_Model!$B:$B,$A17),"") -> 1 | E17: =IFERROR(SUMIFS(_TECH_Crisis_Model!$D:$D,_TECH_Crisis_Model!$A:$A,E$9,_TECH_Crisis_Model!$B:$B,$A17),"") -> 1.4 | F17: =IFERROR(SUMIFS(_TECH_Crisis_Model!$D:$D,_TECH_Crisis_Model!$A:$A,F$9,_TECH_Crisis_Model!$B:$B,$A17),"") -> 1.7 | G17: =IFERROR(SUMIFS(_TECH_Crisis_Model!$D:$D,_TECH_Crisis_Model!$A:$A,G$9,_TECH_Crisis_Model!$B:$B,$A17),"") -> 1.4 | H17: =IFERROR(SUMIFS(_TECH_Crisis_Model!$D:$D,_TECH_Crisis_Model!$A:$A,H$9,_TECH_Crisis_Model!$B:$B,$A17),"") -> 1 | I17: =IFERROR(SUMIFS(_TECH_Crisis_Model!$D:$D,_TECH_Crisis_Model!$A:$A,I$9,_TECH_Crisis_Model!$B:$B,$A17),"") -> 1.2 | ... L17: =IFERROR(SUMIFS(_TECH_Crisis_Model!$D:$D,_TECH_Crisis_Model!$A:$A,L$9,_TECH_Crisis_Model!$B:$B,$A17),"") -> 1
A18: Supply Chain | B18: =IFERROR(SUMIFS(_TECH_Crisis_Model!$D:$D,_TECH_Crisis_Model!$A:$A,B$9,_TECH_Crisis_Model!$B:$B,$A18),"") -> 1.7 | C18: =IFERROR(SUMIFS(_TECH_Crisis_Model!$D:$D,_TECH_Crisis_Model!$A:$A,C$9,_TECH_Crisis_Model!$B:$B,$A18),"") -> 1.5 | D18: =IFERROR(SUMIFS(_TECH_Crisis_Model!$D:$D,_TECH_Crisis_Model!$A:$A,D$9,_TECH_Crisis_Model!$B:$B,$A18),"") -> 1 | E18: =IFERROR(SUMIFS(_TECH_Crisis_Model!$D:$D,_TECH_Crisis_Model!$A:$A,E$9,_TECH_Crisis_Model!$B:$B,$A18),"") -> 1 | F18: =IFERROR(SUMIFS(_TECH_Crisis_Model!$D:$D,_TECH_Crisis_Model!$A:$A,F$9,_TECH_Crisis_Model!$B:$B,$A18),"") -> 2 | G18: =IFERROR(SUMIFS(_TECH_Crisis_Model!$D:$D,_TECH_Crisis_Model!$A:$A,G$9,_TECH_Crisis_Model!$B:$B,$A18),"") -> 1.3 | H18: =IFERROR(SUMIFS(_TECH_Crisis_Model!$D:$D,_TECH_Crisis_Model!$A:$A,H$9,_TECH_Crisis_Model!$B:$B,$A18),"") -> 1 | I18: =IFERROR(SUMIFS(_TECH_Crisis_Model!$D:$D,_TECH_Crisis_Model!$A:$A,I$9,_TECH_Crisis_Model!$B:$B,$A18),"") -> 1 | ... L18: =IFERROR(SUMIFS(_TECH_Crisis_Model!$D:$D,_TECH_Crisis_Model!$A:$A,L$9,_TECH_Crisis_Model!$B:$B,$A18),"") -> 1
A19: Manufacturing MES | B19: =IFERROR(SUMIFS(_TECH_Crisis_Model!$D:$D,_TECH_Crisis_Model!$A:$A,B$9,_TECH_Crisis_Model!$B:$B,$A19),"") -> 1.4 | C19: =IFERROR(SUMIFS(_TECH_Crisis_Model!$D:$D,_TECH_Crisis_Model!$A:$A,C$9,_TECH_Crisis_Model!$B:$B,$A19),"") -> 1.9 | D19: =IFERROR(SUMIFS(_TECH_Crisis_Model!$D:$D,_TECH_Crisis_Model!$A:$A,D$9,_TECH_Crisis_Model!$B:$B,$A19),"") -> 1 | E19: =IFERROR(SUMIFS(_TECH_Crisis_Model!$D:$D,_TECH_Crisis_Model!$A:$A,E$9,_TECH_Crisis_Model!$B:$B,$A19),"") -> 1 | F19: =IFERROR(SUMIFS(_TECH_Crisis_Model!$D:$D,_TECH_Crisis_Model!$A:$A,F$9,_TECH_Crisis_Model!$B:$B,$A19),"") -> 1.8 | G19: =IFERROR(SUMIFS(_TECH_Crisis_Model!$D:$D,_TECH_Crisis_Model!$A:$A,G$9,_TECH_Crisis_Model!$B:$B,$A19),"") -> 2 | H19: =IFERROR(SUMIFS(_TECH_Crisis_Model!$D:$D,_TECH_Crisis_Model!$A:$A,H$9,_TECH_Crisis_Model!$B:$B,$A19),"") -> 1 | I19: =IFERROR(SUMIFS(_TECH_Crisis_Model!$D:$D,_TECH_Crisis_Model!$A:$A,I$9,_TECH_Crisis_Model!$B:$B,$A19),"") -> 1 | ... L19: =IFERROR(SUMIFS(_TECH_Crisis_Model!$D:$D,_TECH_Crisis_Model!$A:$A,L$9,_TECH_Crisis_Model!$B:$B,$A19),"") -> 1
A20: Sales CRM | B20: =IFERROR(SUMIFS(_TECH_Crisis_Model!$D:$D,_TECH_Crisis_Model!$A:$A,B$9,_TECH_Crisis_Model!$B:$B,$A20),"") -> 1 | C20: =IFERROR(SUMIFS(_TECH_Crisis_Model!$D:$D,_TECH_Crisis_Model!$A:$A,C$9,_TECH_Crisis_Model!$B:$B,$A20),"") -> 1 | D20: =IFERROR(SUMIFS(_TECH_Crisis_Model!$D:$D,_TECH_Crisis_Model!$A:$A,D$9,_TECH_Crisis_Model!$B:$B,$A20),"") -> 1.2 | E20: =IFERROR(SUMIFS(_TECH_Crisis_Model!$D:$D,_TECH_Crisis_Model!$A:$A,E$9,_TECH_Crisis_Model!$B:$B,$A20),"") -> 1.5 | F20: =IFERROR(SUMIFS(_TECH_Crisis_Model!$D:$D,_TECH_Crisis_Model!$A:$A,F$9,_TECH_Crisis_Model!$B:$B,$A20),"") -> 1 | G20: =IFERROR(SUMIFS(_TECH_Crisis_Model!$D:$D,_TECH_Crisis_Model!$A:$A,G$9,_TECH_Crisis_Model!$B:$B,$A20),"") -> 1 | H20: =IFERROR(SUMIFS(_TECH_Crisis_Model!$D:$D,_TECH_Crisis_Model!$A:$A,H$9,_TECH_Crisis_Model!$B:$B,$A20),"") -> 1.6 | I20: =IFERROR(SUMIFS(_TECH_Crisis_Model!$D:$D,_TECH_Crisis_Model!$A:$A,I$9,_TECH_Crisis_Model!$B:$B,$A20),"") -> 1.9 | ... L20: =IFERROR(SUMIFS(_TECH_Crisis_Model!$D:$D,_TECH_Crisis_Model!$A:$A,L$9,_TECH_Crisis_Model!$B:$B,$A20),"") -> 1.8
A21: Marketing Comms | B21: =IFERROR(SUMIFS(_TECH_Crisis_Model!$D:$D,_TECH_Crisis_Model!$A:$A,B$9,_TECH_Crisis_Model!$B:$B,$A21),"") -> 1.2 | C21: =IFERROR(SUMIFS(_TECH_Crisis_Model!$D:$D,_TECH_Crisis_Model!$A:$A,C$9,_TECH_Crisis_Model!$B:$B,$A21),"") -> 1 | D21: =IFERROR(SUMIFS(_TECH_Crisis_Model!$D:$D,_TECH_Crisis_Model!$A:$A,D$9,_TECH_Crisis_Model!$B:$B,$A21),"") -> 1.4 | E21: =IFERROR(SUMIFS(_TECH_Crisis_Model!$D:$D,_TECH_Crisis_Model!$A:$A,E$9,_TECH_Crisis_Model!$B:$B,$A21),"") -> 1.3 | F21: =IFERROR(SUMIFS(_TECH_Crisis_Model!$D:$D,_TECH_Crisis_Model!$A:$A,F$9,_TECH_Crisis_Model!$B:$B,$A21),"") -> 1 | G21: =IFERROR(SUMIFS(_TECH_Crisis_Model!$D:$D,_TECH_Crisis_Model!$A:$A,G$9,_TECH_Crisis_Model!$B:$B,$A21),"") -> 1 | H21: =IFERROR(SUMIFS(_TECH_Crisis_Model!$D:$D,_TECH_Crisis_Model!$A:$A,H$9,_TECH_Crisis_Model!$B:$B,$A21),"") -> 1 | I21: =IFERROR(SUMIFS(_TECH_Crisis_Model!$D:$D,_TECH_Crisis_Model!$A:$A,I$9,_TECH_Crisis_Model!$B:$B,$A21),"") -> 1.7 | ... L21: =IFERROR(SUMIFS(_TECH_Crisis_Model!$D:$D,_TECH_Crisis_Model!$A:$A,L$9,_TECH_Crisis_Model!$B:$B,$A21),"") -> 2
... A26: Quality Portfolio | B26: =IFERROR(SUMIFS(_TECH_Crisis_Model!$D:$D,_TECH_Crisis_Model!$A:$A,B$9,_TECH_Crisis_Model!$B:$B,$A26),"") -> 1 | C26: =IFERROR(SUMIFS(_TECH_Crisis_Model!$D:$D,_TECH_Crisis_Model!$A:$A,C$9,_TECH_Crisis_Model!$B:$B,$A26),"") -> 1 | D26: =IFERROR(SUMIFS(_TECH_Crisis_Model!$D:$D,_TECH_Crisis_Model!$A:$A,D$9,_TECH_Crisis_Model!$B:$B,$A26),"") -> 1 | E26: =IFERROR(SUMIFS(_TECH_Crisis_Model!$D:$D,_TECH_Crisis_Model!$A:$A,E$9,_TECH_Crisis_Model!$B:$B,$A26),"") -> 1 | F26: =IFERROR(SUMIFS(_TECH_Crisis_Model!$D:$D,_TECH_Crisis_Model!$A:$A,F$9,_TECH_Crisis_Model!$B:$B,$A26),"") -> 1 | G26: =IFERROR(SUMIFS(_TECH_Crisis_Model!$D:$D,_TECH_Crisis_Model!$A:$A,G$9,_TECH_Crisis_Model!$B:$B,$A26),"") -> 1 | H26: =IFERROR(SUMIFS(_TECH_Crisis_Model!$D:$D,_TECH_Crisis_Model!$A:$A,H$9,_TECH_Crisis_Model!$B:$B,$A26),"") -> 1.3 | I26: =IFERROR(SUMIFS(_TECH_Crisis_Model!$D:$D,_TECH_Crisis_Model!$A:$A,I$9,_TECH_Crisis_Model!$B:$B,$A26),"") -> 1.2 | ... L26: =IFERROR(SUMIFS(_TECH_Crisis_Model!$D:$D,_TECH_Crisis_Model!$A:$A,L$9,_TECH_Crisis_Model!$B:$B,$A26),"") -> 1
A30: Heatmap 2. Domain vs active risk category score
A31: Domain | B31: Geographic, entity and market exposure | C31: Strategic and go-to-market resilience | D31: Crisis governance and decision-making | E31: People, critical roles and knowledge continuity | F31: Financial control and procurement resilience | G31: Legal, compliance and contractual exposure | H31: Physical safety, security and facility resilience | I31: Delivery, service continuity and operational execution | J31: Supply chain, logistics and supplier continuity | K31: Manufacturing, MES and production continuity | L31: Revenue, sales pipeline and CRM continuity | M31: Market communication and reputation resilience
A32: Company Geography | B32: =IFERROR(ROUND(AVERAGEIFS('Risk Summary'!$L$8:$L$414,'Risk Summary'!$B$8:$B$414,"Yes",'Risk Summary'!$C$8:$C$414,$A32,'Risk Summary'!$F$8:$F$414,B$31),1),"") | C32: =IFERROR(ROUND(AVERAGEIFS('Risk Summary'!$L$8:$L$414,'Risk Summary'!$B$8:$B$414,"Yes",'Risk Summary'!$C$8:$C$414,$A32,'Risk Summary'!$F$8:$F$414,C$31),1),"") | D32: =IFERROR(ROUND(AVERAGEIFS('Risk Summary'!$L$8:$L$414,'Risk Summary'!$B$8:$B$414,"Yes",'Risk Summary'!$C$8:$C$414,$A32,'Risk Summary'!$F$8:$F$414,D$31),1),"") | E32: =IFERROR(ROUND(AVERAGEIFS('Risk Summary'!$L$8:$L$414,'Risk Summary'!$B$8:$B$414,"Yes",'Risk Summary'!$C$8:$C$414,$A32,'Risk Summary'!$F$8:$F$414,E$31),1),"") | F32: =IFERROR(ROUND(AVERAGEIFS('Risk Summary'!$L$8:$L$414,'Risk Summary'!$B$8:$B$414,"Yes",'Risk Summary'!$C$8:$C$414,$A32,'Risk Summary'!$F$8:$F$414,F$31),1),"") | G32: =IFERROR(ROUND(AVERAGEIFS('Risk Summary'!$L$8:$L$414,'Risk Summary'!$B$8:$B$414,"Yes",'Risk Summary'!$C$8:$C$414,$A32,'Risk Summary'!$F$8:$F$414,G$31),1),"") | H32: =IFERROR(ROUND(AVERAGEIFS('Risk Summary'!$L$8:$L$414,'Risk Summary'!$B$8:$B$414,"Yes",'Risk Summary'!$C$8:$C$414,$A32,'Risk Summary'!$F$8:$F$414,H$31),1),"") | I32: =IFERROR(ROUND(AVERAGEIFS('Risk Summary'!$L$8:$L$414,'Risk Summary'!$B$8:$B$414,"Yes",'Risk Summary'!$C$8:$C$414,$A32,'Risk Summary'!$F$8:$F$414,I$31),1),"") | ... M32: =IFERROR(ROUND(AVERAGEIFS('Risk Summary'!$L$8:$L$414,'Risk Summary'!$B$8:$B$414,"Yes",'Risk Summary'!$C$8:$C$414,$A32,'Risk Summary'!$F$8:$F$414,M$31),1),"")
A33: Strategy GTM | B33: =IFERROR(ROUND(AVERAGEIFS('Risk Summary'!$L$8:$L$414,'Risk Summary'!$B$8:$B$414,"Yes",'Risk Summary'!$C$8:$C$414,$A33,'Risk Summary'!$F$8:$F$414,B$31),1),"") | C33: =IFERROR(ROUND(AVERAGEIFS('Risk Summary'!$L$8:$L$414,'Risk Summary'!$B$8:$B$414,"Yes",'Risk Summary'!$C$8:$C$414,$A33,'Risk Summary'!$F$8:$F$414,C$31),1),"") | D33: =IFERROR(ROUND(AVERAGEIFS('Risk Summary'!$L$8:$L$414,'Risk Summary'!$B$8:$B$414,"Yes",'Risk Summary'!$C$8:$C$414,$A33,'Risk Summary'!$F$8:$F$414,D$31),1),"") | E33: =IFERROR(ROUND(AVERAGEIFS('Risk Summary'!$L$8:$L$414,'Risk Summary'!$B$8:$B$414,"Yes",'Risk Summary'!$C$8:$C$414,$A33,'Risk Summary'!$F$8:$F$414,E$31),1),"") | F33: =IFERROR(ROUND(AVERAGEIFS('Risk Summary'!$L$8:$L$414,'Risk Summary'!$B$8:$B$414,"Yes",'Risk Summary'!$C$8:$C$414,$A33,'Risk Summary'!$F$8:$F$414,F$31),1),"") | G33: =IFERROR(ROUND(AVERAGEIFS('Risk Summary'!$L$8:$L$414,'Risk Summary'!$B$8:$B$414,"Yes",'Risk Summary'!$C$8:$C$414,$A33,'Risk Summary'!$F$8:$F$414,G$31),1),"") | H33: =IFERROR(ROUND(AVERAGEIFS('Risk Summary'!$L$8:$L$414,'Risk Summary'!$B$8:$B$414,"Yes",'Risk Summary'!$C$8:$C$414,$A33,'Risk Summary'!$F$8:$F$414,H$31),1),"") | I33: =IFERROR(ROUND(AVERAGEIFS('Risk Summary'!$L$8:$L$414,'Risk Summary'!$B$8:$B$414,"Yes",'Risk Summary'!$C$8:$C$414,$A33,'Risk Summary'!$F$8:$F$414,I$31),1),"") | ... M33: =IFERROR(ROUND(AVERAGEIFS('Risk Summary'!$L$8:$L$414,'Risk Summary'!$B$8:$B$414,"Yes",'Risk Summary'!$C$8:$C$414,$A33,'Risk Summary'!$F$8:$F$414,M$31),1),"")
A34: Governance Crisis | B34: =IFERROR(ROUND(AVERAGEIFS('Risk Summary'!$L$8:$L$414,'Risk Summary'!$B$8:$B$414,"Yes",'Risk Summary'!$C$8:$C$414,$A34,'Risk Summary'!$F$8:$F$414,B$31),1),"") | C34: =IFERROR(ROUND(AVERAGEIFS('Risk Summary'!$L$8:$L$414,'Risk Summary'!$B$8:$B$414,"Yes",'Risk Summary'!$C$8:$C$414,$A34,'Risk Summary'!$F$8:$F$414,C$31),1),"") | D34: =IFERROR(ROUND(AVERAGEIFS('Risk Summary'!$L$8:$L$414,'Risk Summary'!$B$8:$B$414,"Yes",'Risk Summary'!$C$8:$C$414,$A34,'Risk Summary'!$F$8:$F$414,D$31),1),"") | E34: =IFERROR(ROUND(AVERAGEIFS('Risk Summary'!$L$8:$L$414,'Risk Summary'!$B$8:$B$414,"Yes",'Risk Summary'!$C$8:$C$414,$A34,'Risk Summary'!$F$8:$F$414,E$31),1),"") | F34: =IFERROR(ROUND(AVERAGEIFS('Risk Summary'!$L$8:$L$414,'Risk Summary'!$B$8:$B$414,"Yes",'Risk Summary'!$C$8:$C$414,$A34,'Risk Summary'!$F$8:$F$414,F$31),1),"") | G34: =IFERROR(ROUND(AVERAGEIFS('Risk Summary'!$L$8:$L$414,'Risk Summary'!$B$8:$B$414,"Yes",'Risk Summary'!$C$8:$C$414,$A34,'Risk Summary'!$F$8:$F$414,G$31),1),"") | H34: =IFERROR(ROUND(AVERAGEIFS('Risk Summary'!$L$8:$L$414,'Risk Summary'!$B$8:$B$414,"Yes",'Risk Summary'!$C$8:$C$414,$A34,'Risk Summary'!$F$8:$F$414,H$31),1),"") | I34: =IFERROR(ROUND(AVERAGEIFS('Risk Summary'!$L$8:$L$414,'Risk Summary'!$B$8:$B$414,"Yes",'Risk Summary'!$C$8:$C$414,$A34,'Risk Summary'!$F$8:$F$414,I$31),1),"") | ... M34: =IFERROR(ROUND(AVERAGEIFS('Risk Summary'!$L$8:$L$414,'Risk Summary'!$B$8:$B$414,"Yes",'Risk Summary'!$C$8:$C$414,$A34,'Risk Summary'!$F$8:$F$414,M$31),1),"")
A35: HR Workforce | B35: =IFERROR(ROUND(AVERAGEIFS('Risk Summary'!$L$8:$L$414,'Risk Summary'!$B$8:$B$414,"Yes",'Risk Summary'!$C$8:$C$414,$A35,'Risk Summary'!$F$8:$F$414,B$31),1),"") | C35: =IFERROR(ROUND(AVERAGEIFS('Risk Summary'!$L$8:$L$414,'Risk Summary'!$B$8:$B$414,"Yes",'Risk Summary'!$C$8:$C$414,$A35,'Risk Summary'!$F$8:$F$414,C$31),1),"") | D35: =IFERROR(ROUND(AVERAGEIFS('Risk Summary'!$L$8:$L$414,'Risk Summary'!$B$8:$B$414,"Yes",'Risk Summary'!$C$8:$C$414,$A35,'Risk Summary'!$F$8:$F$414,D$31),1),"") | E35: =IFERROR(ROUND(AVERAGEIFS('Risk Summary'!$L$8:$L$414,'Risk Summary'!$B$8:$B$414,"Yes",'Risk Summary'!$C$8:$C$414,$A35,'Risk Summary'!$F$8:$F$414,E$31),1),"") | F35: =IFERROR(ROUND(AVERAGEIFS('Risk Summary'!$L$8:$L$414,'Risk Summary'!$B$8:$B$414,"Yes",'Risk Summary'!$C$8:$C$414,$A35,'Risk Summary'!$F$8:$F$414,F$31),1),"") | G35: =IFERROR(ROUND(AVERAGEIFS('Risk Summary'!$L$8:$L$414,'Risk Summary'!$B$8:$B$414,"Yes",'Risk Summary'!$C$8:$C$414,$A35,'Risk Summary'!$F$8:$F$414,G$31),1),"") | H35: =IFERROR(ROUND(AVERAGEIFS('Risk Summary'!$L$8:$L$414,'Risk Summary'!$B$8:$B$414,"Yes",'Risk Summary'!$C$8:$C$414,$A35,'Risk Summary'!$F$8:$F$414,H$31),1),"") | I35: =IFERROR(ROUND(AVERAGEIFS('Risk Summary'!$L$8:$L$414,'Risk Summary'!$B$8:$B$414,"Yes",'Risk Summary'!$C$8:$C$414,$A35,'Risk Summary'!$F$8:$F$414,I$31),1),"") | ... M35: =IFERROR(ROUND(AVERAGEIFS('Risk Summary'!$L$8:$L$414,'Risk Summary'!$B$8:$B$414,"Yes",'Risk Summary'!$C$8:$C$414,$A35,'Risk Summary'!$F$8:$F$414,M$31),1),"")
A36: Finance Procurement | B36: =IFERROR(ROUND(AVERAGEIFS('Risk Summary'!$L$8:$L$414,'Risk Summary'!$B$8:$B$414,"Yes",'Risk Summary'!$C$8:$C$414,$A36,'Risk Summary'!$F$8:$F$414,B$31),1),"") | C36: =IFERROR(ROUND(AVERAGEIFS('Risk Summary'!$L$8:$L$414,'Risk Summary'!$B$8:$B$414,"Yes",'Risk Summary'!$C$8:$C$414,$A36,'Risk Summary'!$F$8:$F$414,C$31),1),"") | D36: =IFERROR(ROUND(AVERAGEIFS('Risk Summary'!$L$8:$L$414,'Risk Summary'!$B$8:$B$414,"Yes",'Risk Summary'!$C$8:$C$414,$A36,'Risk Summary'!$F$8:$F$414,D$31),1),"") | E36: =IFERROR(ROUND(AVERAGEIFS('Risk Summary'!$L$8:$L$414,'Risk Summary'!$B$8:$B$414,"Yes",'Risk Summary'!$C$8:$C$414,$A36,'Risk Summary'!$F$8:$F$414,E$31),1),"") | F36: =IFERROR(ROUND(AVERAGEIFS('Risk Summary'!$L$8:$L$414,'Risk Summary'!$B$8:$B$414,"Yes",'Risk Summary'!$C$8:$C$414,$A36,'Risk Summary'!$F$8:$F$414,F$31),1),"") | G36: =IFERROR(ROUND(AVERAGEIFS('Risk Summary'!$L$8:$L$414,'Risk Summary'!$B$8:$B$414,"Yes",'Risk Summary'!$C$8:$C$414,$A36,'Risk Summary'!$F$8:$F$414,G$31),1),"") | H36: =IFERROR(ROUND(AVERAGEIFS('Risk Summary'!$L$8:$L$414,'Risk Summary'!$B$8:$B$414,"Yes",'Risk Summary'!$C$8:$C$414,$A36,'Risk Summary'!$F$8:$F$414,H$31),1),"") | I36: =IFERROR(ROUND(AVERAGEIFS('Risk Summary'!$L$8:$L$414,'Risk Summary'!$B$8:$B$414,"Yes",'Risk Summary'!$C$8:$C$414,$A36,'Risk Summary'!$F$8:$F$414,I$31),1),"") | ... M36: =IFERROR(ROUND(AVERAGEIFS('Risk Summary'!$L$8:$L$414,'Risk Summary'!$B$8:$B$414,"Yes",'Risk Summary'!$C$8:$C$414,$A36,'Risk Summary'!$F$8:$F$414,M$31),1),"")
A37: Legal Risk | B37: =IFERROR(ROUND(AVERAGEIFS('Risk Summary'!$L$8:$L$414,'Risk Summary'!$B$8:$B$414,"Yes",'Risk Summary'!$C$8:$C$414,$A37,'Risk Summary'!$F$8:$F$414,B$31),1),"") | C37: =IFERROR(ROUND(AVERAGEIFS('Risk Summary'!$L$8:$L$414,'Risk Summary'!$B$8:$B$414,"Yes",'Risk Summary'!$C$8:$C$414,$A37,'Risk Summary'!$F$8:$F$414,C$31),1),"") | D37: =IFERROR(ROUND(AVERAGEIFS('Risk Summary'!$L$8:$L$414,'Risk Summary'!$B$8:$B$414,"Yes",'Risk Summary'!$C$8:$C$414,$A37,'Risk Summary'!$F$8:$F$414,D$31),1),"") | E37: =IFERROR(ROUND(AVERAGEIFS('Risk Summary'!$L$8:$L$414,'Risk Summary'!$B$8:$B$414,"Yes",'Risk Summary'!$C$8:$C$414,$A37,'Risk Summary'!$F$8:$F$414,E$31),1),"") | F37: =IFERROR(ROUND(AVERAGEIFS('Risk Summary'!$L$8:$L$414,'Risk Summary'!$B$8:$B$414,"Yes",'Risk Summary'!$C$8:$C$414,$A37,'Risk Summary'!$F$8:$F$414,F$31),1),"") | G37: =IFERROR(ROUND(AVERAGEIFS('Risk Summary'!$L$8:$L$414,'Risk Summary'!$B$8:$B$414,"Yes",'Risk Summary'!$C$8:$C$414,$A37,'Risk Summary'!$F$8:$F$414,G$31),1),"") | H37: =IFERROR(ROUND(AVERAGEIFS('Risk Summary'!$L$8:$L$414,'Risk Summary'!$B$8:$B$414,"Yes",'Risk Summary'!$C$8:$C$414,$A37,'Risk Summary'!$F$8:$F$414,H$31),1),"") | I37: =IFERROR(ROUND(AVERAGEIFS('Risk Summary'!$L$8:$L$414,'Risk Summary'!$B$8:$B$414,"Yes",'Risk Summary'!$C$8:$C$414,$A37,'Risk Summary'!$F$8:$F$414,I$31),1),"") | ... M37: =IFERROR(ROUND(AVERAGEIFS('Risk Summary'!$L$8:$L$414,'Risk Summary'!$B$8:$B$414,"Yes",'Risk Summary'!$C$8:$C$414,$A37,'Risk Summary'!$F$8:$F$414,M$31),1),"")
A38: Physical Safety | B38: =IFERROR(ROUND(AVERAGEIFS('Risk Summary'!$L$8:$L$414,'Risk Summary'!$B$8:$B$414,"Yes",'Risk Summary'!$C$8:$C$414,$A38,'Risk Summary'!$F$8:$F$414,B$31),1),"") | C38: =IFERROR(ROUND(AVERAGEIFS('Risk Summary'!$L$8:$L$414,'Risk Summary'!$B$8:$B$414,"Yes",'Risk Summary'!$C$8:$C$414,$A38,'Risk Summary'!$F$8:$F$414,C$31),1),"") | D38: =IFERROR(ROUND(AVERAGEIFS('Risk Summary'!$L$8:$L$414,'Risk Summary'!$B$8:$B$414,"Yes",'Risk Summary'!$C$8:$C$414,$A38,'Risk Summary'!$F$8:$F$414,D$31),1),"") | E38: =IFERROR(ROUND(AVERAGEIFS('Risk Summary'!$L$8:$L$414,'Risk Summary'!$B$8:$B$414,"Yes",'Risk Summary'!$C$8:$C$414,$A38,'Risk Summary'!$F$8:$F$414,E$31),1),"") | F38: =IFERROR(ROUND(AVERAGEIFS('Risk Summary'!$L$8:$L$414,'Risk Summary'!$B$8:$B$414,"Yes",'Risk Summary'!$C$8:$C$414,$A38,'Risk Summary'!$F$8:$F$414,F$31),1),"") | G38: =IFERROR(ROUND(AVERAGEIFS('Risk Summary'!$L$8:$L$414,'Risk Summary'!$B$8:$B$414,"Yes",'Risk Summary'!$C$8:$C$414,$A38,'Risk Summary'!$F$8:$F$414,G$31),1),"") | H38: =IFERROR(ROUND(AVERAGEIFS('Risk Summary'!$L$8:$L$414,'Risk Summary'!$B$8:$B$414,"Yes",'Risk Summary'!$C$8:$C$414,$A38,'Risk Summary'!$F$8:$F$414,H$31),1),"") | I38: =IFERROR(ROUND(AVERAGEIFS('Risk Summary'!$L$8:$L$414,'Risk Summary'!$B$8:$B$414,"Yes",'Risk Summary'!$C$8:$C$414,$A38,'Risk Summary'!$F$8:$F$414,I$31),1),"") | ... M38: =IFERROR(ROUND(AVERAGEIFS('Risk Summary'!$L$8:$L$414,'Risk Summary'!$B$8:$B$414,"Yes",'Risk Summary'!$C$8:$C$414,$A38,'Risk Summary'!$F$8:$F$414,M$31),1),"")
A39: Delivery Ops | B39: =IFERROR(ROUND(AVERAGEIFS('Risk Summary'!$L$8:$L$414,'Risk Summary'!$B$8:$B$414,"Yes",'Risk Summary'!$C$8:$C$414,$A39,'Risk Summary'!$F$8:$F$414,B$31),1),"") | C39: =IFERROR(ROUND(AVERAGEIFS('Risk Summary'!$L$8:$L$414,'Risk Summary'!$B$8:$B$414,"Yes",'Risk Summary'!$C$8:$C$414,$A39,'Risk Summary'!$F$8:$F$414,C$31),1),"") | D39: =IFERROR(ROUND(AVERAGEIFS('Risk Summary'!$L$8:$L$414,'Risk Summary'!$B$8:$B$414,"Yes",'Risk Summary'!$C$8:$C$414,$A39,'Risk Summary'!$F$8:$F$414,D$31),1),"") | E39: =IFERROR(ROUND(AVERAGEIFS('Risk Summary'!$L$8:$L$414,'Risk Summary'!$B$8:$B$414,"Yes",'Risk Summary'!$C$8:$C$414,$A39,'Risk Summary'!$F$8:$F$414,E$31),1),"") | F39: =IFERROR(ROUND(AVERAGEIFS('Risk Summary'!$L$8:$L$414,'Risk Summary'!$B$8:$B$414,"Yes",'Risk Summary'!$C$8:$C$414,$A39,'Risk Summary'!$F$8:$F$414,F$31),1),"") | G39: =IFERROR(ROUND(AVERAGEIFS('Risk Summary'!$L$8:$L$414,'Risk Summary'!$B$8:$B$414,"Yes",'Risk Summary'!$C$8:$C$414,$A39,'Risk Summary'!$F$8:$F$414,G$31),1),"") | H39: =IFERROR(ROUND(AVERAGEIFS('Risk Summary'!$L$8:$L$414,'Risk Summary'!$B$8:$B$414,"Yes",'Risk Summary'!$C$8:$C$414,$A39,'Risk Summary'!$F$8:$F$414,H$31),1),"") | I39: =IFERROR(ROUND(AVERAGEIFS('Risk Summary'!$L$8:$L$414,'Risk Summary'!$B$8:$B$414,"Yes",'Risk Summary'!$C$8:$C$414,$A39,'Risk Summary'!$F$8:$F$414,I$31),1),"") | ... M39: =IFERROR(ROUND(AVERAGEIFS('Risk Summary'!$L$8:$L$414,'Risk Summary'!$B$8:$B$414,"Yes",'Risk Summary'!$C$8:$C$414,$A39,'Risk Summary'!$F$8:$F$414,M$31),1),"")
A40: Supply Chain | B40: =IFERROR(ROUND(AVERAGEIFS('Risk Summary'!$L$8:$L$414,'Risk Summary'!$B$8:$B$414,"Yes",'Risk Summary'!$C$8:$C$414,$A40,'Risk Summary'!$F$8:$F$414,B$31),1),"") | C40: =IFERROR(ROUND(AVERAGEIFS('Risk Summary'!$L$8:$L$414,'Risk Summary'!$B$8:$B$414,"Yes",'Risk Summary'!$C$8:$C$414,$A40,'Risk Summary'!$F$8:$F$414,C$31),1),"") | D40: =IFERROR(ROUND(AVERAGEIFS('Risk Summary'!$L$8:$L$414,'Risk Summary'!$B$8:$B$414,"Yes",'Risk Summary'!$C$8:$C$414,$A40,'Risk Summary'!$F$8:$F$414,D$31),1),"") | E40: =IFERROR(ROUND(AVERAGEIFS('Risk Summary'!$L$8:$L$414,'Risk Summary'!$B$8:$B$414,"Yes",'Risk Summary'!$C$8:$C$414,$A40,'Risk Summary'!$F$8:$F$414,E$31),1),"") | F40: =IFERROR(ROUND(AVERAGEIFS('Risk Summary'!$L$8:$L$414,'Risk Summary'!$B$8:$B$414,"Yes",'Risk Summary'!$C$8:$C$414,$A40,'Risk Summary'!$F$8:$F$414,F$31),1),"") | G40: =IFERROR(ROUND(AVERAGEIFS('Risk Summary'!$L$8:$L$414,'Risk Summary'!$B$8:$B$414,"Yes",'Risk Summary'!$C$8:$C$414,$A40,'Risk Summary'!$F$8:$F$414,G$31),1),"") | H40: =IFERROR(ROUND(AVERAGEIFS('Risk Summary'!$L$8:$L$414,'Risk Summary'!$B$8:$B$414,"Yes",'Risk Summary'!$C$8:$C$414,$A40,'Risk Summary'!$F$8:$F$414,H$31),1),"") | I40: =IFERROR(ROUND(AVERAGEIFS('Risk Summary'!$L$8:$L$414,'Risk Summary'!$B$8:$B$414,"Yes",'Risk Summary'!$C$8:$C$414,$A40,'Risk Summary'!$F$8:$F$414,I$31),1),"") | ... M40: =IFERROR(ROUND(AVERAGEIFS('Risk Summary'!$L$8:$L$414,'Risk Summary'!$B$8:$B$414,"Yes",'Risk Summary'!$C$8:$C$414,$A40,'Risk Summary'!$F$8:$F$414,M$31),1),"")
A41: Manufacturing MES | B41: =IFERROR(ROUND(AVERAGEIFS('Risk Summary'!$L$8:$L$414,'Risk Summary'!$B$8:$B$414,"Yes",'Risk Summary'!$C$8:$C$414,$A41,'Risk Summary'!$F$8:$F$414,B$31),1),"") | C41: =IFERROR(ROUND(AVERAGEIFS('Risk Summary'!$L$8:$L$414,'Risk Summary'!$B$8:$B$414,"Yes",'Risk Summary'!$C$8:$C$414,$A41,'Risk Summary'!$F$8:$F$414,C$31),1),"") | D41: =IFERROR(ROUND(AVERAGEIFS('Risk Summary'!$L$8:$L$414,'Risk Summary'!$B$8:$B$414,"Yes",'Risk Summary'!$C$8:$C$414,$A41,'Risk Summary'!$F$8:$F$414,D$31),1),"") | E41: =IFERROR(ROUND(AVERAGEIFS('Risk Summary'!$L$8:$L$414,'Risk Summary'!$B$8:$B$414,"Yes",'Risk Summary'!$C$8:$C$414,$A41,'Risk Summary'!$F$8:$F$414,E$31),1),"") | F41: =IFERROR(ROUND(AVERAGEIFS('Risk Summary'!$L$8:$L$414,'Risk Summary'!$B$8:$B$414,"Yes",'Risk Summary'!$C$8:$C$414,$A41,'Risk Summary'!$F$8:$F$414,F$31),1),"") | G41: =IFERROR(ROUND(AVERAGEIFS('Risk Summary'!$L$8:$L$414,'Risk Summary'!$B$8:$B$414,"Yes",'Risk Summary'!$C$8:$C$414,$A41,'Risk Summary'!$F$8:$F$414,G$31),1),"") | H41: =IFERROR(ROUND(AVERAGEIFS('Risk Summary'!$L$8:$L$414,'Risk Summary'!$B$8:$B$414,"Yes",'Risk Summary'!$C$8:$C$414,$A41,'Risk Summary'!$F$8:$F$414,H$31),1),"") | I41: =IFERROR(ROUND(AVERAGEIFS('Risk Summary'!$L$8:$L$414,'Risk Summary'!$B$8:$B$414,"Yes",'Risk Summary'!$C$8:$C$414,$A41,'Risk Summary'!$F$8:$F$414,I$31),1),"") | ... M41: =IFERROR(ROUND(AVERAGEIFS('Risk Summary'!$L$8:$L$414,'Risk Summary'!$B$8:$B$414,"Yes",'Risk Summary'!$C$8:$C$414,$A41,'Risk Summary'!$F$8:$F$414,M$31),1),"")
A42: Sales CRM | B42: =IFERROR(ROUND(AVERAGEIFS('Risk Summary'!$L$8:$L$414,'Risk Summary'!$B$8:$B$414,"Yes",'Risk Summary'!$C$8:$C$414,$A42,'Risk Summary'!$F$8:$F$414,B$31),1),"") | C42: =IFERROR(ROUND(AVERAGEIFS('Risk Summary'!$L$8:$L$414,'Risk Summary'!$B$8:$B$414,"Yes",'Risk Summary'!$C$8:$C$414,$A42,'Risk Summary'!$F$8:$F$414,C$31),1),"") | D42: =IFERROR(ROUND(AVERAGEIFS('Risk Summary'!$L$8:$L$414,'Risk Summary'!$B$8:$B$414,"Yes",'Risk Summary'!$C$8:$C$414,$A42,'Risk Summary'!$F$8:$F$414,D$31),1),"") | E42: =IFERROR(ROUND(AVERAGEIFS('Risk Summary'!$L$8:$L$414,'Risk Summary'!$B$8:$B$414,"Yes",'Risk Summary'!$C$8:$C$414,$A42,'Risk Summary'!$F$8:$F$414,E$31),1),"") | F42: =IFERROR(ROUND(AVERAGEIFS('Risk Summary'!$L$8:$L$414,'Risk Summary'!$B$8:$B$414,"Yes",'Risk Summary'!$C$8:$C$414,$A42,'Risk Summary'!$F$8:$F$414,F$31),1),"") | G42: =IFERROR(ROUND(AVERAGEIFS('Risk Summary'!$L$8:$L$414,'Risk Summary'!$B$8:$B$414,"Yes",'Risk Summary'!$C$8:$C$414,$A42,'Risk Summary'!$F$8:$F$414,G$31),1),"") | H42: =IFERROR(ROUND(AVERAGEIFS('Risk Summary'!$L$8:$L$414,'Risk Summary'!$B$8:$B$414,"Yes",'Risk Summary'!$C$8:$C$414,$A42,'Risk Summary'!$F$8:$F$414,H$31),1),"") | I42: =IFERROR(ROUND(AVERAGEIFS('Risk Summary'!$L$8:$L$414,'Risk Summary'!$B$8:$B$414,"Yes",'Risk Summary'!$C$8:$C$414,$A42,'Risk Summary'!$F$8:$F$414,I$31),1),"") | ... M42: =IFERROR(ROUND(AVERAGEIFS('Risk Summary'!$L$8:$L$414,'Risk Summary'!$B$8:$B$414,"Yes",'Risk Summary'!$C$8:$C$414,$A42,'Risk Summary'!$F$8:$F$414,M$31),1),"")
A43: Marketing Comms | B43: =IFERROR(ROUND(AVERAGEIFS('Risk Summary'!$L$8:$L$414,'Risk Summary'!$B$8:$B$414,"Yes",'Risk Summary'!$C$8:$C$414,$A43,'Risk Summary'!$F$8:$F$414,B$31),1),"") | C43: =IFERROR(ROUND(AVERAGEIFS('Risk Summary'!$L$8:$L$414,'Risk Summary'!$B$8:$B$414,"Yes",'Risk Summary'!$C$8:$C$414,$A43,'Risk Summary'!$F$8:$F$414,C$31),1),"") | D43: =IFERROR(ROUND(AVERAGEIFS('Risk Summary'!$L$8:$L$414,'Risk Summary'!$B$8:$B$414,"Yes",'Risk Summary'!$C$8:$C$414,$A43,'Risk Summary'!$F$8:$F$414,D$31),1),"") | E43: =IFERROR(ROUND(AVERAGEIFS('Risk Summary'!$L$8:$L$414,'Risk Summary'!$B$8:$B$414,"Yes",'Risk Summary'!$C$8:$C$414,$A43,'Risk Summary'!$F$8:$F$414,E$31),1),"") | F43: =IFERROR(ROUND(AVERAGEIFS('Risk Summary'!$L$8:$L$414,'Risk Summary'!$B$8:$B$414,"Yes",'Risk Summary'!$C$8:$C$414,$A43,'Risk Summary'!$F$8:$F$414,F$31),1),"") | G43: =IFERROR(ROUND(AVERAGEIFS('Risk Summary'!$L$8:$L$414,'Risk Summary'!$B$8:$B$414,"Yes",'Risk Summary'!$C$8:$C$414,$A43,'Risk Summary'!$F$8:$F$414,G$31),1),"") | H43: =IFERROR(ROUND(AVERAGEIFS('Risk Summary'!$L$8:$L$414,'Risk Summary'!$B$8:$B$414,"Yes",'Risk Summary'!$C$8:$C$414,$A43,'Risk Summary'!$F$8:$F$414,H$31),1),"") | I43: =IFERROR(ROUND(AVERAGEIFS('Risk Summary'!$L$8:$L$414,'Risk Summary'!$B$8:$B$414,"Yes",'Risk Summary'!$C$8:$C$414,$A43,'Risk Summary'!$F$8:$F$414,I$31),1),"") | ... M43: =IFERROR(ROUND(AVERAGEIFS('Risk Summary'!$L$8:$L$414,'Risk Summary'!$B$8:$B$414,"Yes",'Risk Summary'!$C$8:$C$414,$A43,'Risk Summary'!$F$8:$F$414,M$31),1),"")
... A48: Quality Portfolio | B48: =IFERROR(ROUND(AVERAGEIFS('Risk Summary'!$L$8:$L$414,'Risk Summary'!$B$8:$B$414,"Yes",'Risk Summary'!$C$8:$C$414,$A48,'Risk Summary'!$F$8:$F$414,B$31),1),"") | C48: =IFERROR(ROUND(AVERAGEIFS('Risk Summary'!$L$8:$L$414,'Risk Summary'!$B$8:$B$414,"Yes",'Risk Summary'!$C$8:$C$414,$A48,'Risk Summary'!$F$8:$F$414,C$31),1),"") | D48: =IFERROR(ROUND(AVERAGEIFS('Risk Summary'!$L$8:$L$414,'Risk Summary'!$B$8:$B$414,"Yes",'Risk Summary'!$C$8:$C$414,$A48,'Risk Summary'!$F$8:$F$414,D$31),1),"") | E48: =IFERROR(ROUND(AVERAGEIFS('Risk Summary'!$L$8:$L$414,'Risk Summary'!$B$8:$B$414,"Yes",'Risk Summary'!$C$8:$C$414,$A48,'Risk Summary'!$F$8:$F$414,E$31),1),"") | F48: =IFERROR(ROUND(AVERAGEIFS('Risk Summary'!$L$8:$L$414,'Risk Summary'!$B$8:$B$414,"Yes",'Risk Summary'!$C$8:$C$414,$A48,'Risk Summary'!$F$8:$F$414,F$31),1),"") | G48: =IFERROR(ROUND(AVERAGEIFS('Risk Summary'!$L$8:$L$414,'Risk Summary'!$B$8:$B$414,"Yes",'Risk Summary'!$C$8:$C$414,$A48,'Risk Summary'!$F$8:$F$414,G$31),1),"") | H48: =IFERROR(ROUND(AVERAGEIFS('Risk Summary'!$L$8:$L$414,'Risk Summary'!$B$8:$B$414,"Yes",'Risk Summary'!$C$8:$C$414,$A48,'Risk Summary'!$F$8:$F$414,H$31),1),"") | I48: =IFERROR(ROUND(AVERAGEIFS('Risk Summary'!$L$8:$L$414,'Risk Summary'!$B$8:$B$414,"Yes",'Risk Summary'!$C$8:$C$414,$A48,'Risk Summary'!$F$8:$F$414,I$31),1),"") | ... M48: =IFERROR(ROUND(AVERAGEIFS('Risk Summary'!$L$8:$L$414,'Risk Summary'!$B$8:$B$414,"Yes",'Risk Summary'!$C$8:$C$414,$A48,'Risk Summary'!$F$8:$F$414,M$31),1),"")
A52: Heatmap 3. Top 20 prioritized initiatives vs timeline
A53: Rank | B53: Initiative | C53: ='Gantt Roadmap'!S$13 -> 46179 | D53: ='Gantt Roadmap'!T$13 -> 46209 | E53: ='Gantt Roadmap'!U$13 -> 46240 | F53: ='Gantt Roadmap'!V$13 -> 46271 | G53: ='Gantt Roadmap'!W$13 -> 46301 | H53: ='Gantt Roadmap'!X$13 -> 46332 | I53: ='Gantt Roadmap'!Y$13 -> 46362 | J53: ='Gantt Roadmap'!Z$13 -> 46393 | ... T53: ='Gantt Roadmap'!AJ$13 -> 46697
A54: 1 | B54: ='Gantt Roadmap'!$C$14 | C54: =IF('Gantt Roadmap'!S$14="■",1,"") | D54: =IF('Gantt Roadmap'!T$14="■",1,"") | E54: =IF('Gantt Roadmap'!U$14="■",1,"") | F54: =IF('Gantt Roadmap'!V$14="■",1,"") | G54: =IF('Gantt Roadmap'!W$14="■",1,"") | H54: =IF('Gantt Roadmap'!X$14="■",1,"") | I54: =IF('Gantt Roadmap'!Y$14="■",1,"") | J54: =IF('Gantt Roadmap'!Z$14="■",1,"") | ... T54: =IF('Gantt Roadmap'!AJ$14="■",1,"")
A55: 2 | B55: ='Gantt Roadmap'!$C$15 | C55: =IF('Gantt Roadmap'!S$15="■",1,"") | D55: =IF('Gantt Roadmap'!T$15="■",1,"") | E55: =IF('Gantt Roadmap'!U$15="■",1,"") | F55: =IF('Gantt Roadmap'!V$15="■",1,"") | G55: =IF('Gantt Roadmap'!W$15="■",1,"") | H55: =IF('Gantt Roadmap'!X$15="■",1,"") | I55: =IF('Gantt Roadmap'!Y$15="■",1,"") | J55: =IF('Gantt Roadmap'!Z$15="■",1,"") | ... T55: =IF('Gantt Roadmap'!AJ$15="■",1,"")
A56: 3 | B56: ='Gantt Roadmap'!$C$16 | C56: =IF('Gantt Roadmap'!S$16="■",1,"") | D56: =IF('Gantt Roadmap'!T$16="■",1,"") | E56: =IF('Gantt Roadmap'!U$16="■",1,"") | F56: =IF('Gantt Roadmap'!V$16="■",1,"") | G56: =IF('Gantt Roadmap'!W$16="■",1,"") | H56: =IF('Gantt Roadmap'!X$16="■",1,"") | I56: =IF('Gantt Roadmap'!Y$16="■",1,"") | J56: =IF('Gantt Roadmap'!Z$16="■",1,"") | ... T56: =IF('Gantt Roadmap'!AJ$16="■",1,"")
A57: 4 | B57: ='Gantt Roadmap'!$C$17 | C57: =IF('Gantt Roadmap'!S$17="■",1,"") | D57: =IF('Gantt Roadmap'!T$17="■",1,"") | E57: =IF('Gantt Roadmap'!U$17="■",1,"") | F57: =IF('Gantt Roadmap'!V$17="■",1,"") | G57: =IF('Gantt Roadmap'!W$17="■",1,"") | H57: =IF('Gantt Roadmap'!X$17="■",1,"") | I57: =IF('Gantt Roadmap'!Y$17="■",1,"") | J57: =IF('Gantt Roadmap'!Z$17="■",1,"") | ... T57: =IF('Gantt Roadmap'!AJ$17="■",1,"")
A58: 5 | B58: ='Gantt Roadmap'!$C$18 | C58: =IF('Gantt Roadmap'!S$18="■",1,"") | D58: =IF('Gantt Roadmap'!T$18="■",1,"") | E58: =IF('Gantt Roadmap'!U$18="■",1,"") | F58: =IF('Gantt Roadmap'!V$18="■",1,"") | G58: =IF('Gantt Roadmap'!W$18="■",1,"") | H58: =IF('Gantt Roadmap'!X$18="■",1,"") | I58: =IF('Gantt Roadmap'!Y$18="■",1,"") | J58: =IF('Gantt Roadmap'!Z$18="■",1,"") | ... T58: =IF('Gantt Roadmap'!AJ$18="■",1,"")
A59: 6 | B59: ='Gantt Roadmap'!$C$19 | C59: =IF('Gantt Roadmap'!S$19="■",1,"") | D59: =IF('Gantt Roadmap'!T$19="■",1,"") | E59: =IF('Gantt Roadmap'!U$19="■",1,"") | F59: =IF('Gantt Roadmap'!V$19="■",1,"") | G59: =IF('Gantt Roadmap'!W$19="■",1,"") | H59: =IF('Gantt Roadmap'!X$19="■",1,"") | I59: =IF('Gantt Roadmap'!Y$19="■",1,"") | J59: =IF('Gantt Roadmap'!Z$19="■",1,"") | ... T59: =IF('Gantt Roadmap'!AJ$19="■",1,"")
A60: 7 | B60: ='Gantt Roadmap'!$C$20 | C60: =IF('Gantt Roadmap'!S$20="■",1,"") | D60: =IF('Gantt Roadmap'!T$20="■",1,"") | E60: =IF('Gantt Roadmap'!U$20="■",1,"") | F60: =IF('Gantt Roadmap'!V$20="■",1,"") | G60: =IF('Gantt Roadmap'!W$20="■",1,"") | H60: =IF('Gantt Roadmap'!X$20="■",1,"") | I60: =IF('Gantt Roadmap'!Y$20="■",1,"") | J60: =IF('Gantt Roadmap'!Z$20="■",1,"") | ... T60: =IF('Gantt Roadmap'!AJ$20="■",1,"")
A61: 8 | B61: ='Gantt Roadmap'!$C$21 | C61: =IF('Gantt Roadmap'!S$21="■",1,"") | D61: =IF('Gantt Roadmap'!T$21="■",1,"") | E61: =IF('Gantt Roadmap'!U$21="■",1,"") | F61: =IF('Gantt Roadmap'!V$21="■",1,"") | G61: =IF('Gantt Roadmap'!W$21="■",1,"") | H61: =IF('Gantt Roadmap'!X$21="■",1,"") | I61: =IF('Gantt Roadmap'!Y$21="■",1,"") | J61: =IF('Gantt Roadmap'!Z$21="■",1,"") | ... T61: =IF('Gantt Roadmap'!AJ$21="■",1,"")
A62: 9 | B62: ='Gantt Roadmap'!$C$22 | C62: =IF('Gantt Roadmap'!S$22="■",1,"") | D62: =IF('Gantt Roadmap'!T$22="■",1,"") | E62: =IF('Gantt Roadmap'!U$22="■",1,"") | F62: =IF('Gantt Roadmap'!V$22="■",1,"") | G62: =IF('Gantt Roadmap'!W$22="■",1,"") | H62: =IF('Gantt Roadmap'!X$22="■",1,"") | I62: =IF('Gantt Roadmap'!Y$22="■",1,"") | J62: =IF('Gantt Roadmap'!Z$22="■",1,"") | ... T62: =IF('Gantt Roadmap'!AJ$22="■",1,"")
A63: 10 | B63: ='Gantt Roadmap'!$C$23 | C63: =IF('Gantt Roadmap'!S$23="■",1,"") | D63: =IF('Gantt Roadmap'!T$23="■",1,"") | E63: =IF('Gantt Roadmap'!U$23="■",1,"") | F63: =IF('Gantt Roadmap'!V$23="■",1,"") | G63: =IF('Gantt Roadmap'!W$23="■",1,"") | H63: =IF('Gantt Roadmap'!X$23="■",1,"") | I63: =IF('Gantt Roadmap'!Y$23="■",1,"") | J63: =IF('Gantt Roadmap'!Z$23="■",1,"") | ... T63: =IF('Gantt Roadmap'!AJ$23="■",1,"")
A64: 11 | B64: ='Gantt Roadmap'!$C$24 | C64: =IF('Gantt Roadmap'!S$24="■",1,"") | D64: =IF('Gantt Roadmap'!T$24="■",1,"") | E64: =IF('Gantt Roadmap'!U$24="■",1,"") | F64: =IF('Gantt Roadmap'!V$24="■",1,"") | G64: =IF('Gantt Roadmap'!W$24="■",1,"") | H64: =IF('Gantt Roadmap'!X$24="■",1,"") | I64: =IF('Gantt Roadmap'!Y$24="■",1,"") | J64: =IF('Gantt Roadmap'!Z$24="■",1,"") | ... T64: =IF('Gantt Roadmap'!AJ$24="■",1,"")
A65: 12 | B65: ='Gantt Roadmap'!$C$25 | C65: =IF('Gantt Roadmap'!S$25="■",1,"") | D65: =IF('Gantt Roadmap'!T$25="■",1,"") | E65: =IF('Gantt Roadmap'!U$25="■",1,"") | F65: =IF('Gantt Roadmap'!V$25="■",1,"") | G65: =IF('Gantt Roadmap'!W$25="■",1,"") | H65: =IF('Gantt Roadmap'!X$25="■",1,"") | I65: =IF('Gantt Roadmap'!Y$25="■",1,"") | J65: =IF('Gantt Roadmap'!Z$25="■",1,"") | ... T65: =IF('Gantt Roadmap'!AJ$25="■",1,"")
A66: 13 | B66: ='Gantt Roadmap'!$C$26 | C66: =IF('Gantt Roadmap'!S$26="■",1,"") | D66: =IF('Gantt Roadmap'!T$26="■",1,"") | E66: =IF('Gantt Roadmap'!U$26="■",1,"") | F66: =IF('Gantt Roadmap'!V$26="■",1,"") | G66: =IF('Gantt Roadmap'!W$26="■",1,"") | H66: =IF('Gantt Roadmap'!X$26="■",1,"") | I66: =IF('Gantt Roadmap'!Y$26="■",1,"") | J66: =IF('Gantt Roadmap'!Z$26="■",1,"") | ... T66: =IF('Gantt Roadmap'!AJ$26="■",1,"")
A67: 14 | B67: ='Gantt Roadmap'!$C$27 | C67: =IF('Gantt Roadmap'!S$27="■",1,"") | D67: =IF('Gantt Roadmap'!T$27="■",1,"") | E67: =IF('Gantt Roadmap'!U$27="■",1,"") | F67: =IF('Gantt Roadmap'!V$27="■",1,"") | G67: =IF('Gantt Roadmap'!W$27="■",1,"") | H67: =IF('Gantt Roadmap'!X$27="■",1,"") | I67: =IF('Gantt Roadmap'!Y$27="■",1,"") | J67: =IF('Gantt Roadmap'!Z$27="■",1,"") | ... T67: =IF('Gantt Roadmap'!AJ$27="■",1,"")
A68: 15 | B68: ='Gantt Roadmap'!$C$28 | C68: =IF('Gantt Roadmap'!S$28="■",1,"") | D68: =IF('Gantt Roadmap'!T$28="■",1,"") | E68: =IF('Gantt Roadmap'!U$28="■",1,"") | F68: =IF('Gantt Roadmap'!V$28="■",1,"") | G68: =IF('Gantt Roadmap'!W$28="■",1,"") | H68: =IF('Gantt Roadmap'!X$28="■",1,"") | I68: =IF('Gantt Roadmap'!Y$28="■",1,"") | J68: =IF('Gantt Roadmap'!Z$28="■",1,"") | ... T68: =IF('Gantt Roadmap'!AJ$28="■",1,"")
A69: 16 | B69: ='Gantt Roadmap'!$C$29 | C69: =IF('Gantt Roadmap'!S$29="■",1,"") | D69: =IF('Gantt Roadmap'!T$29="■",1,"") | E69: =IF('Gantt Roadmap'!U$29="■",1,"") | F69: =IF('Gantt Roadmap'!V$29="■",1,"") | G69: =IF('Gantt Roadmap'!W$29="■",1,"") | H69: =IF('Gantt Roadmap'!X$29="■",1,"") | I69: =IF('Gantt Roadmap'!Y$29="■",1,"") | J69: =IF('Gantt Roadmap'!Z$29="■",1,"") | ... T69: =IF('Gantt Roadmap'!AJ$29="■",1,"")
A70: 17 | B70: ='Gantt Roadmap'!$C$30 | C70: =IF('Gantt Roadmap'!S$30="■",1,"") | D70: =IF('Gantt Roadmap'!T$30="■",1,"") | E70: =IF('Gantt Roadmap'!U$30="■",1,"") | F70: =IF('Gantt Roadmap'!V$30="■",1,"") | G70: =IF('Gantt Roadmap'!W$30="■",1,"") | H70: =IF('Gantt Roadmap'!X$30="■",1,"") | I70: =IF('Gantt Roadmap'!Y$30="■",1,"") | J70: =IF('Gantt Roadmap'!Z$30="■",1,"") | ... T70: =IF('Gantt Roadmap'!AJ$30="■",1,"")
A71: 18 | B71: ='Gantt Roadmap'!$C$31 | C71: =IF('Gantt Roadmap'!S$31="■",1,"") | D71: =IF('Gantt Roadmap'!T$31="■",1,"") | E71: =IF('Gantt Roadmap'!U$31="■",1,"") | F71: =IF('Gantt Roadmap'!V$31="■",1,"") | G71: =IF('Gantt Roadmap'!W$31="■",1,"") | H71: =IF('Gantt Roadmap'!X$31="■",1,"") | I71: =IF('Gantt Roadmap'!Y$31="■",1,"") | J71: =IF('Gantt Roadmap'!Z$31="■",1,"") | ... T71: =IF('Gantt Roadmap'!AJ$31="■",1,"")
A72: 19 | B72: ='Gantt Roadmap'!$C$32 | C72: =IF('Gantt Roadmap'!S$32="■",1,"") | D72: =IF('Gantt Roadmap'!T$32="■",1,"") | E72: =IF('Gantt Roadmap'!U$32="■",1,"") | F72: =IF('Gantt Roadmap'!V$32="■",1,"") | G72: =IF('Gantt Roadmap'!W$32="■",1,"") | H72: =IF('Gantt Roadmap'!X$32="■",1,"") | I72: =IF('Gantt Roadmap'!Y$32="■",1,"") | J72: =IF('Gantt Roadmap'!Z$32="■",1,"") | ... T72: =IF('Gantt Roadmap'!AJ$32="■",1,"")
A73: 20 | B73: ='Gantt Roadmap'!$C$33 | C73: =IF('Gantt Roadmap'!S$33="■",1,"") | D73: =IF('Gantt Roadmap'!T$33="■",1,"") | E73: =IF('Gantt Roadmap'!U$33="■",1,"") | F73: =IF('Gantt Roadmap'!V$33="■",1,"") | G73: =IF('Gantt Roadmap'!W$33="■",1,"") | H73: =IF('Gantt Roadmap'!X$33="■",1,"") | I73: =IF('Gantt Roadmap'!Y$33="■",1,"") | J73: =IF('Gantt Roadmap'!Z$33="■",1,"") | ... T73: =IF('Gantt Roadmap'!AJ$33="■",1,"")
A77: Heatmap 4. Monthly capacity load and overload signal
A78: Metric | B78: ='Gantt Roadmap'!S$13 -> 46179 | C78: ='Gantt Roadmap'!T$13 -> 46209 | D78: ='Gantt Roadmap'!U$13 -> 46240 | E78: ='Gantt Roadmap'!V$13 -> 46271 | F78: ='Gantt Roadmap'!W$13 -> 46301 | G78: ='Gantt Roadmap'!X$13 -> 46332 | H78: ='Gantt Roadmap'!Y$13 -> 46362 | I78: ='Gantt Roadmap'!Z$13 -> 46393 | ... S78: ='Gantt Roadmap'!AJ$13 -> 46697
A79: Capacity load | B79: ='Gantt Roadmap'!S$9 -> 0 | C79: ='Gantt Roadmap'!T$9 -> 0 | D79: ='Gantt Roadmap'!U$9 -> 0 | E79: ='Gantt Roadmap'!V$9 -> 0 | F79: ='Gantt Roadmap'!W$9 -> 0 | G79: ='Gantt Roadmap'!X$9 -> 0 | H79: ='Gantt Roadmap'!Y$9 -> 0 | I79: ='Gantt Roadmap'!Z$9 -> 0 | ... S79: ='Gantt Roadmap'!AJ$9 -> 0
A80: Active initiatives | B80: ='Gantt Roadmap'!S$11 -> 0 | C80: ='Gantt Roadmap'!T$11 -> 0 | D80: ='Gantt Roadmap'!U$11 -> 0 | E80: ='Gantt Roadmap'!V$11 -> 0 | F80: ='Gantt Roadmap'!W$11 -> 0 | G80: ='Gantt Roadmap'!X$11 -> 0 | H80: ='Gantt Roadmap'!Y$11 -> 0 | I80: ='Gantt Roadmap'!Z$11 -> 0 | ... S80: ='Gantt Roadmap'!AJ$11 -> 0
A81: Overload flag | B81: ='Gantt Roadmap'!S$10 -> OK | C81: ='Gantt Roadmap'!T$10 -> OK | D81: ='Gantt Roadmap'!U$10 -> OK | E81: ='Gantt Roadmap'!V$10 -> OK | F81: ='Gantt Roadmap'!W$10 -> OK | G81: ='Gantt Roadmap'!X$10 -> OK | H81: ='Gantt Roadmap'!Y$10 -> OK | I81: ='Gantt Roadmap'!Z$10 -> OK | ... S81: ='Gantt Roadmap'!AJ$10 -> OK

Sheet Resilience Engine (Cascade)
A1: Resilience Engine — Cascade & Nonlinear View
A2: Enhanced read of your assessment: weak-link aggregation, red-line gates, single-point-of-failure load, cross-domain cascades, and scenario propagation. Source scores are unchanged — compare against the standard Dashboard.
A4: Active scenario | B4: ='Crisis Simulator'!$B$4 -> War / security crisis
A5: Severity (1-5) | B5: ='Crisis Simulator'!$B$5 -> 3
A6: Org base maturity (0-5) | B6: =_TECH_Cascade_Engine!$B$23
A7: Org effective resilience | B7: =_TECH_Cascade_Engine!$B$26
A8: Org weakest domain | B8: =_TECH_Cascade_Engine!$B$25 -> 0
A9: Peak effective risk | B9: =_TECH_Cascade_Engine!$B$27 -> 0
A10: Critical / High domains | B10: =_TECH_Cascade_Engine!$B$28&" / "&_TECH_Cascade_Engine!$B$29 -> 0 / 0
A11: Peak scenario exposure | B11: =_TECH_Cascade_Engine!$B$30 -> 0
A12: Top exposed (scenario) | B12: =_TECH_Cascade_Engine!$B$31
A13: Top cascade amplifier | B13: =_TECH_Cascade_Engine!$B$32 -> IT Cloud DR
A16: Domain | B16: Base maturity | C16: Weakest control | D16: Adj. maturity (weak-link) | E16: Red-line breach | F16: SPOF factor | G16: Own risk | H16: + Cascade risk | I16: Effective risk | J16: Risk level | K16: Effective maturity | L16: Scenario exposure | M16: Exposure level | N16: Rank
A17: =_TECH_Cascade_Engine!A5 -> Company Geography | B17: =_TECH_Cascade_Engine!B5 | C17: =_TECH_Cascade_Engine!C5 | D17: =_TECH_Cascade_Engine!D5 | E17: =IF(_TECH_Cascade_Engine!F5=1,"BREACH","") | F17: =_TECH_Cascade_Engine!H5 -> 1.4 | G17: =_TECH_Cascade_Engine!I5 -> 0 | H17: =_TECH_Cascade_Engine!L5 -> 0 | I17: =_TECH_Cascade_Engine!N5 | J17: =_TECH_Cascade_Engine!O5 | K17: =_TECH_Cascade_Engine!W5 | L17: =_TECH_Cascade_Engine!U5 | M17: =_TECH_Cascade_Engine!V5 | N17: =_TECH_Cascade_Engine!X5
A18: =_TECH_Cascade_Engine!A6 -> Strategy GTM | B18: =_TECH_Cascade_Engine!B6 | C18: =_TECH_Cascade_Engine!C6 | D18: =_TECH_Cascade_Engine!D6 | E18: =IF(_TECH_Cascade_Engine!F6=1,"BREACH","") | F18: =_TECH_Cascade_Engine!H6 -> 1.1 | G18: =_TECH_Cascade_Engine!I6 -> 0 | H18: =_TECH_Cascade_Engine!L6 -> 0 | I18: =_TECH_Cascade_Engine!N6 | J18: =_TECH_Cascade_Engine!O6 | K18: =_TECH_Cascade_Engine!W6 | L18: =_TECH_Cascade_Engine!U6 | M18: =_TECH_Cascade_Engine!V6 | N18: =_TECH_Cascade_Engine!X6
A19: =_TECH_Cascade_Engine!A7 -> Governance Crisis | B19: =_TECH_Cascade_Engine!B7 | C19: =_TECH_Cascade_Engine!C7 | D19: =_TECH_Cascade_Engine!D7 | E19: =IF(_TECH_Cascade_Engine!F7=1,"BREACH","") | F19: =_TECH_Cascade_Engine!H7 -> 1 | G19: =_TECH_Cascade_Engine!I7 -> 0 | H19: =_TECH_Cascade_Engine!L7 -> 0 | I19: =_TECH_Cascade_Engine!N7 | J19: =_TECH_Cascade_Engine!O7 | K19: =_TECH_Cascade_Engine!W7 | L19: =_TECH_Cascade_Engine!U7 | M19: =_TECH_Cascade_Engine!V7 | N19: =_TECH_Cascade_Engine!X7
A20: =_TECH_Cascade_Engine!A8 -> HR Workforce | B20: =_TECH_Cascade_Engine!B8 | C20: =_TECH_Cascade_Engine!C8 | D20: =_TECH_Cascade_Engine!D8 | E20: =IF(_TECH_Cascade_Engine!F8=1,"BREACH","") | F20: =_TECH_Cascade_Engine!H8 -> 1.4 | G20: =_TECH_Cascade_Engine!I8 -> 0 | H20: =_TECH_Cascade_Engine!L8 -> 0 | I20: =_TECH_Cascade_Engine!N8 | J20: =_TECH_Cascade_Engine!O8 | K20: =_TECH_Cascade_Engine!W8 | L20: =_TECH_Cascade_Engine!U8 | M20: =_TECH_Cascade_Engine!V8 | N20: =_TECH_Cascade_Engine!X8
A21: =_TECH_Cascade_Engine!A9 -> Finance Procurement | B21: =_TECH_Cascade_Engine!B9 | C21: =_TECH_Cascade_Engine!C9 | D21: =_TECH_Cascade_Engine!D9 | E21: =IF(_TECH_Cascade_Engine!F9=1,"BREACH","") | F21: =_TECH_Cascade_Engine!H9 -> 1.3 | G21: =_TECH_Cascade_Engine!I9 -> 0 | H21: =_TECH_Cascade_Engine!L9 -> 0 | I21: =_TECH_Cascade_Engine!N9 | J21: =_TECH_Cascade_Engine!O9 | K21: =_TECH_Cascade_Engine!W9 | L21: =_TECH_Cascade_Engine!U9 | M21: =_TECH_Cascade_Engine!V9 | N21: =_TECH_Cascade_Engine!X9
A22: =_TECH_Cascade_Engine!A10 -> Legal Risk | B22: =_TECH_Cascade_Engine!B10 | C22: =_TECH_Cascade_Engine!C10 | D22: =_TECH_Cascade_Engine!D10 | E22: =IF(_TECH_Cascade_Engine!F10=1,"BREACH","") | F22: =_TECH_Cascade_Engine!H10 -> 1 | G22: =_TECH_Cascade_Engine!I10 -> 0 | H22: =_TECH_Cascade_Engine!L10 -> 0 | I22: =_TECH_Cascade_Engine!N10 | J22: =_TECH_Cascade_Engine!O10 | K22: =_TECH_Cascade_Engine!W10 | L22: =_TECH_Cascade_Engine!U10 | M22: =_TECH_Cascade_Engine!V10 | N22: =_TECH_Cascade_Engine!X10
A23: =_TECH_Cascade_Engine!A11 -> Physical Safety | B23: =_TECH_Cascade_Engine!B11 | C23: =_TECH_Cascade_Engine!C11 | D23: =_TECH_Cascade_Engine!D11 | E23: =IF(_TECH_Cascade_Engine!F11=1,"BREACH","") | F23: =_TECH_Cascade_Engine!H11 -> 1.4 | G23: =_TECH_Cascade_Engine!I11 -> 0 | H23: =_TECH_Cascade_Engine!L11 -> 0 | I23: =_TECH_Cascade_Engine!N11 | J23: =_TECH_Cascade_Engine!O11 | K23: =_TECH_Cascade_Engine!W11 | L23: =_TECH_Cascade_Engine!U11 | M23: =_TECH_Cascade_Engine!V11 | N23: =_TECH_Cascade_Engine!X11
A24: =_TECH_Cascade_Engine!A12 -> Delivery Ops | B24: =_TECH_Cascade_Engine!B12 | C24: =_TECH_Cascade_Engine!C12 | D24: =_TECH_Cascade_Engine!D12 | E24: =IF(_TECH_Cascade_Engine!F12=1,"BREACH","") | F24: =_TECH_Cascade_Engine!H12 -> 1.3 | G24: =_TECH_Cascade_Engine!I12 -> 0 | H24: =_TECH_Cascade_Engine!L12 -> 0 | I24: =_TECH_Cascade_Engine!N12 | J24: =_TECH_Cascade_Engine!O12 | K24: =_TECH_Cascade_Engine!W12 | L24: =_TECH_Cascade_Engine!U12 | M24: =_TECH_Cascade_Engine!V12 | N24: =_TECH_Cascade_Engine!X12
A25: =_TECH_Cascade_Engine!A13 -> Supply Chain | B25: =_TECH_Cascade_Engine!B13 | C25: =_TECH_Cascade_Engine!C13 | D25: =_TECH_Cascade_Engine!D13 | E25: =IF(_TECH_Cascade_Engine!F13=1,"BREACH","") | F25: =_TECH_Cascade_Engine!H13 -> 1.3 | G25: =_TECH_Cascade_Engine!I13 -> 0 | H25: =_TECH_Cascade_Engine!L13 -> 0 | I25: =_TECH_Cascade_Engine!N13 | J25: =_TECH_Cascade_Engine!O13 | K25: =_TECH_Cascade_Engine!W13 | L25: =_TECH_Cascade_Engine!U13 | M25: =_TECH_Cascade_Engine!V13 | N25: =_TECH_Cascade_Engine!X13
A26: =_TECH_Cascade_Engine!A14 -> Manufacturing MES | B26: =_TECH_Cascade_Engine!B14 | C26: =_TECH_Cascade_Engine!C14 | D26: =_TECH_Cascade_Engine!D14 | E26: =IF(_TECH_Cascade_Engine!F14=1,"BREACH","") | F26: =_TECH_Cascade_Engine!H14 -> 1.3 | G26: =_TECH_Cascade_Engine!I14 -> 0 | H26: =_TECH_Cascade_Engine!L14 -> 0 | I26: =_TECH_Cascade_Engine!N14 | J26: =_TECH_Cascade_Engine!O14 | K26: =_TECH_Cascade_Engine!W14 | L26: =_TECH_Cascade_Engine!U14 | M26: =_TECH_Cascade_Engine!V14 | N26: =_TECH_Cascade_Engine!X14
A27: =_TECH_Cascade_Engine!A15 -> Sales CRM | B27: =_TECH_Cascade_Engine!B15 | C27: =_TECH_Cascade_Engine!C15 | D27: =_TECH_Cascade_Engine!D15 | E27: =IF(_TECH_Cascade_Engine!F15=1,"BREACH","") | F27: =_TECH_Cascade_Engine!H15 -> 1.1 | G27: =_TECH_Cascade_Engine!I15 -> 0 | H27: =_TECH_Cascade_Engine!L15 -> 0 | I27: =_TECH_Cascade_Engine!N15 | J27: =_TECH_Cascade_Engine!O15 | K27: =_TECH_Cascade_Engine!W15 | L27: =_TECH_Cascade_Engine!U15 | M27: =_TECH_Cascade_Engine!V15 | N27: =_TECH_Cascade_Engine!X15
A28: =_TECH_Cascade_Engine!A16 -> Marketing Comms | B28: =_TECH_Cascade_Engine!B16 | C28: =_TECH_Cascade_Engine!C16 | D28: =_TECH_Cascade_Engine!D16 | E28: =IF(_TECH_Cascade_Engine!F16=1,"BREACH","") | F28: =_TECH_Cascade_Engine!H16 -> 1.1 | G28: =_TECH_Cascade_Engine!I16 -> 0 | H28: =_TECH_Cascade_Engine!L16 -> 0 | I28: =_TECH_Cascade_Engine!N16 | J28: =_TECH_Cascade_Engine!O16 | K28: =_TECH_Cascade_Engine!W16 | L28: =_TECH_Cascade_Engine!U16 | M28: =_TECH_Cascade_Engine!V16 | N28: =_TECH_Cascade_Engine!X16
... A33: =_TECH_Cascade_Engine!A21 -> Quality Portfolio | B33: =_TECH_Cascade_Engine!B21 | C33: =_TECH_Cascade_Engine!C21 | D33: =_TECH_Cascade_Engine!D21 | E33: =IF(_TECH_Cascade_Engine!F21=1,"BREACH","") | F33: =_TECH_Cascade_Engine!H21 -> 1 | G33: =_TECH_Cascade_Engine!I21 -> 0 | H33: =_TECH_Cascade_Engine!L21 -> 0 | I33: =_TECH_Cascade_Engine!N21 | J33: =_TECH_Cascade_Engine!O21 | K33: =_TECH_Cascade_Engine!W21 | L33: =_TECH_Cascade_Engine!U21 | M33: =_TECH_Cascade_Engine!V21 | N33: =_TECH_Cascade_Engine!X21
A35: How to read
A36: • Adjusted maturity falls below base when a domain has a weak control (weak-link). • Red-line BREACH caps the domain's maturity regardless of other strengths. • Effective risk = own risk x SPOF + cascade inflow from coupled domains. • Scenario exposure applies the active crisis + severity through the dependency network. • Tune all behaviour in _TECH_Dependency_Map (unhide it).

Sheet Resilience Stress Test
A1: Resilience Stress Test & Sensitivity
A2: Tests whether severity overpowers maturity and how sensitive results are to the model parameters. All cells are live — change scores or parameters and these update.
A4: 1) Scenario exposure by severity (active scenario, all domains)
A5: Domain | B5: Severity 1 | C5: Severity 2 | D5: Severity 3 | E5: Severity 4 | F5: Severity 5
A6: =_TECH_Cascade_Engine!A5 -> Company Geography | B6: =IF(_TECH_Cascade_Engine!$B5="","",MIN(5,_TECH_Cascade_Engine!$M5*MIN(_TECH_Dependency_Map!$B$34,1+(1/5)*(_TECH_Cascade_Engine!$Q5+_TECH_Dependency_Map!$B$29*_TECH_Cascade_Engine!$R5)))) | C6: =IF(_TECH_Cascade_Engine!$B5="","",MIN(5,_TECH_Cascade_Engine!$M5*MIN(_TECH_Dependency_Map!$B$34,1+(2/5)*(_TECH_Cascade_Engine!$Q5+_TECH_Dependency_Map!$B$29*_TECH_Cascade_Engine!$R5)))) | D6: =IF(_TECH_Cascade_Engine!$B5="","",MIN(5,_TECH_Cascade_Engine!$M5*MIN(_TECH_Dependency_Map!$B$34,1+(3/5)*(_TECH_Cascade_Engine!$Q5+_TECH_Dependency_Map!$B$29*_TECH_Cascade_Engine!$R5)))) | E6: =IF(_TECH_Cascade_Engine!$B5="","",MIN(5,_TECH_Cascade_Engine!$M5*MIN(_TECH_Dependency_Map!$B$34,1+(4/5)*(_TECH_Cascade_Engine!$Q5+_TECH_Dependency_Map!$B$29*_TECH_Cascade_Engine!$R5)))) | F6: =IF(_TECH_Cascade_Engine!$B5="","",MIN(5,_TECH_Cascade_Engine!$M5*MIN(_TECH_Dependency_Map!$B$34,1+(5/5)*(_TECH_Cascade_Engine!$Q5+_TECH_Dependency_Map!$B$29*_TECH_Cascade_Engine!$R5))))
A7: =_TECH_Cascade_Engine!A6 -> Strategy GTM | B7: =IF(_TECH_Cascade_Engine!$B6="","",MIN(5,_TECH_Cascade_Engine!$M6*MIN(_TECH_Dependency_Map!$B$34,1+(1/5)*(_TECH_Cascade_Engine!$Q6+_TECH_Dependency_Map!$B$29*_TECH_Cascade_Engine!$R6)))) | C7: =IF(_TECH_Cascade_Engine!$B6="","",MIN(5,_TECH_Cascade_Engine!$M6*MIN(_TECH_Dependency_Map!$B$34,1+(2/5)*(_TECH_Cascade_Engine!$Q6+_TECH_Dependency_Map!$B$29*_TECH_Cascade_Engine!$R6)))) | D7: =IF(_TECH_Cascade_Engine!$B6="","",MIN(5,_TECH_Cascade_Engine!$M6*MIN(_TECH_Dependency_Map!$B$34,1+(3/5)*(_TECH_Cascade_Engine!$Q6+_TECH_Dependency_Map!$B$29*_TECH_Cascade_Engine!$R6)))) | E7: =IF(_TECH_Cascade_Engine!$B6="","",MIN(5,_TECH_Cascade_Engine!$M6*MIN(_TECH_Dependency_Map!$B$34,1+(4/5)*(_TECH_Cascade_Engine!$Q6+_TECH_Dependency_Map!$B$29*_TECH_Cascade_Engine!$R6)))) | F7: =IF(_TECH_Cascade_Engine!$B6="","",MIN(5,_TECH_Cascade_Engine!$M6*MIN(_TECH_Dependency_Map!$B$34,1+(5/5)*(_TECH_Cascade_Engine!$Q6+_TECH_Dependency_Map!$B$29*_TECH_Cascade_Engine!$R6))))
A8: =_TECH_Cascade_Engine!A7 -> Governance Crisis | B8: =IF(_TECH_Cascade_Engine!$B7="","",MIN(5,_TECH_Cascade_Engine!$M7*MIN(_TECH_Dependency_Map!$B$34,1+(1/5)*(_TECH_Cascade_Engine!$Q7+_TECH_Dependency_Map!$B$29*_TECH_Cascade_Engine!$R7)))) | C8: =IF(_TECH_Cascade_Engine!$B7="","",MIN(5,_TECH_Cascade_Engine!$M7*MIN(_TECH_Dependency_Map!$B$34,1+(2/5)*(_TECH_Cascade_Engine!$Q7+_TECH_Dependency_Map!$B$29*_TECH_Cascade_Engine!$R7)))) | D8: =IF(_TECH_Cascade_Engine!$B7="","",MIN(5,_TECH_Cascade_Engine!$M7*MIN(_TECH_Dependency_Map!$B$34,1+(3/5)*(_TECH_Cascade_Engine!$Q7+_TECH_Dependency_Map!$B$29*_TECH_Cascade_Engine!$R7)))) | E8: =IF(_TECH_Cascade_Engine!$B7="","",MIN(5,_TECH_Cascade_Engine!$M7*MIN(_TECH_Dependency_Map!$B$34,1+(4/5)*(_TECH_Cascade_Engine!$Q7+_TECH_Dependency_Map!$B$29*_TECH_Cascade_Engine!$R7)))) | F8: =IF(_TECH_Cascade_Engine!$B7="","",MIN(5,_TECH_Cascade_Engine!$M7*MIN(_TECH_Dependency_Map!$B$34,1+(5/5)*(_TECH_Cascade_Engine!$Q7+_TECH_Dependency_Map!$B$29*_TECH_Cascade_Engine!$R7))))
A9: =_TECH_Cascade_Engine!A8 -> HR Workforce | B9: =IF(_TECH_Cascade_Engine!$B8="","",MIN(5,_TECH_Cascade_Engine!$M8*MIN(_TECH_Dependency_Map!$B$34,1+(1/5)*(_TECH_Cascade_Engine!$Q8+_TECH_Dependency_Map!$B$29*_TECH_Cascade_Engine!$R8)))) | C9: =IF(_TECH_Cascade_Engine!$B8="","",MIN(5,_TECH_Cascade_Engine!$M8*MIN(_TECH_Dependency_Map!$B$34,1+(2/5)*(_TECH_Cascade_Engine!$Q8+_TECH_Dependency_Map!$B$29*_TECH_Cascade_Engine!$R8)))) | D9: =IF(_TECH_Cascade_Engine!$B8="","",MIN(5,_TECH_Cascade_Engine!$M8*MIN(_TECH_Dependency_Map!$B$34,1+(3/5)*(_TECH_Cascade_Engine!$Q8+_TECH_Dependency_Map!$B$29*_TECH_Cascade_Engine!$R8)))) | E9: =IF(_TECH_Cascade_Engine!$B8="","",MIN(5,_TECH_Cascade_Engine!$M8*MIN(_TECH_Dependency_Map!$B$34,1+(4/5)*(_TECH_Cascade_Engine!$Q8+_TECH_Dependency_Map!$B$29*_TECH_Cascade_Engine!$R8)))) | F9: =IF(_TECH_Cascade_Engine!$B8="","",MIN(5,_TECH_Cascade_Engine!$M8*MIN(_TECH_Dependency_Map!$B$34,1+(5/5)*(_TECH_Cascade_Engine!$Q8+_TECH_Dependency_Map!$B$29*_TECH_Cascade_Engine!$R8))))
A10: =_TECH_Cascade_Engine!A9 -> Finance Procurement | B10: =IF(_TECH_Cascade_Engine!$B9="","",MIN(5,_TECH_Cascade_Engine!$M9*MIN(_TECH_Dependency_Map!$B$34,1+(1/5)*(_TECH_Cascade_Engine!$Q9+_TECH_Dependency_Map!$B$29*_TECH_Cascade_Engine!$R9)))) | C10: =IF(_TECH_Cascade_Engine!$B9="","",MIN(5,_TECH_Cascade_Engine!$M9*MIN(_TECH_Dependency_Map!$B$34,1+(2/5)*(_TECH_Cascade_Engine!$Q9+_TECH_Dependency_Map!$B$29*_TECH_Cascade_Engine!$R9)))) | D10: =IF(_TECH_Cascade_Engine!$B9="","",MIN(5,_TECH_Cascade_Engine!$M9*MIN(_TECH_Dependency_Map!$B$34,1+(3/5)*(_TECH_Cascade_Engine!$Q9+_TECH_Dependency_Map!$B$29*_TECH_Cascade_Engine!$R9)))) | E10: =IF(_TECH_Cascade_Engine!$B9="","",MIN(5,_TECH_Cascade_Engine!$M9*MIN(_TECH_Dependency_Map!$B$34,1+(4/5)*(_TECH_Cascade_Engine!$Q9+_TECH_Dependency_Map!$B$29*_TECH_Cascade_Engine!$R9)))) | F10: =IF(_TECH_Cascade_Engine!$B9="","",MIN(5,_TECH_Cascade_Engine!$M9*MIN(_TECH_Dependency_Map!$B$34,1+(5/5)*(_TECH_Cascade_Engine!$Q9+_TECH_Dependency_Map!$B$29*_TECH_Cascade_Engine!$R9))))
A11: =_TECH_Cascade_Engine!A10 -> Legal Risk | B11: =IF(_TECH_Cascade_Engine!$B10="","",MIN(5,_TECH_Cascade_Engine!$M10*MIN(_TECH_Dependency_Map!$B$34,1+(1/5)*(_TECH_Cascade_Engine!$Q10+_TECH_Dependency_Map!$B$29*_TECH_Cascade_Engine!$R10)))) | C11: =IF(_TECH_Cascade_Engine!$B10="","",MIN(5,_TECH_Cascade_Engine!$M10*MIN(_TECH_Dependency_Map!$B$34,1+(2/5)*(_TECH_Cascade_Engine!$Q10+_TECH_Dependency_Map!$B$29*_TECH_Cascade_Engine!$R10)))) | D11: =IF(_TECH_Cascade_Engine!$B10="","",MIN(5,_TECH_Cascade_Engine!$M10*MIN(_TECH_Dependency_Map!$B$34,1+(3/5)*(_TECH_Cascade_Engine!$Q10+_TECH_Dependency_Map!$B$29*_TECH_Cascade_Engine!$R10)))) | E11: =IF(_TECH_Cascade_Engine!$B10="","",MIN(5,_TECH_Cascade_Engine!$M10*MIN(_TECH_Dependency_Map!$B$34,1+(4/5)*(_TECH_Cascade_Engine!$Q10+_TECH_Dependency_Map!$B$29*_TECH_Cascade_Engine!$R10)))) | F11: =IF(_TECH_Cascade_Engine!$B10="","",MIN(5,_TECH_Cascade_Engine!$M10*MIN(_TECH_Dependency_Map!$B$34,1+(5/5)*(_TECH_Cascade_Engine!$Q10+_TECH_Dependency_Map!$B$29*_TECH_Cascade_Engine!$R10))))
A12: =_TECH_Cascade_Engine!A11 -> Physical Safety | B12: =IF(_TECH_Cascade_Engine!$B11="","",MIN(5,_TECH_Cascade_Engine!$M11*MIN(_TECH_Dependency_Map!$B$34,1+(1/5)*(_TECH_Cascade_Engine!$Q11+_TECH_Dependency_Map!$B$29*_TECH_Cascade_Engine!$R11)))) | C12: =IF(_TECH_Cascade_Engine!$B11="","",MIN(5,_TECH_Cascade_Engine!$M11*MIN(_TECH_Dependency_Map!$B$34,1+(2/5)*(_TECH_Cascade_Engine!$Q11+_TECH_Dependency_Map!$B$29*_TECH_Cascade_Engine!$R11)))) | D12: =IF(_TECH_Cascade_Engine!$B11="","",MIN(5,_TECH_Cascade_Engine!$M11*MIN(_TECH_Dependency_Map!$B$34,1+(3/5)*(_TECH_Cascade_Engine!$Q11+_TECH_Dependency_Map!$B$29*_TECH_Cascade_Engine!$R11)))) | E12: =IF(_TECH_Cascade_Engine!$B11="","",MIN(5,_TECH_Cascade_Engine!$M11*MIN(_TECH_Dependency_Map!$B$34,1+(4/5)*(_TECH_Cascade_Engine!$Q11+_TECH_Dependency_Map!$B$29*_TECH_Cascade_Engine!$R11)))) | F12: =IF(_TECH_Cascade_Engine!$B11="","",MIN(5,_TECH_Cascade_Engine!$M11*MIN(_TECH_Dependency_Map!$B$34,1+(5/5)*(_TECH_Cascade_Engine!$Q11+_TECH_Dependency_Map!$B$29*_TECH_Cascade_Engine!$R11))))
A13: =_TECH_Cascade_Engine!A12 -> Delivery Ops | B13: =IF(_TECH_Cascade_Engine!$B12="","",MIN(5,_TECH_Cascade_Engine!$M12*MIN(_TECH_Dependency_Map!$B$34,1+(1/5)*(_TECH_Cascade_Engine!$Q12+_TECH_Dependency_Map!$B$29*_TECH_Cascade_Engine!$R12)))) | C13: =IF(_TECH_Cascade_Engine!$B12="","",MIN(5,_TECH_Cascade_Engine!$M12*MIN(_TECH_Dependency_Map!$B$34,1+(2/5)*(_TECH_Cascade_Engine!$Q12+_TECH_Dependency_Map!$B$29*_TECH_Cascade_Engine!$R12)))) | D13: =IF(_TECH_Cascade_Engine!$B12="","",MIN(5,_TECH_Cascade_Engine!$M12*MIN(_TECH_Dependency_Map!$B$34,1+(3/5)*(_TECH_Cascade_Engine!$Q12+_TECH_Dependency_Map!$B$29*_TECH_Cascade_Engine!$R12)))) | E13: =IF(_TECH_Cascade_Engine!$B12="","",MIN(5,_TECH_Cascade_Engine!$M12*MIN(_TECH_Dependency_Map!$B$34,1+(4/5)*(_TECH_Cascade_Engine!$Q12+_TECH_Dependency_Map!$B$29*_TECH_Cascade_Engine!$R12)))) | F13: =IF(_TECH_Cascade_Engine!$B12="","",MIN(5,_TECH_Cascade_Engine!$M12*MIN(_TECH_Dependency_Map!$B$34,1+(5/5)*(_TECH_Cascade_Engine!$Q12+_TECH_Dependency_Map!$B$29*_TECH_Cascade_Engine!$R12))))
A14: =_TECH_Cascade_Engine!A13 -> Supply Chain | B14: =IF(_TECH_Cascade_Engine!$B13="","",MIN(5,_TECH_Cascade_Engine!$M13*MIN(_TECH_Dependency_Map!$B$34,1+(1/5)*(_TECH_Cascade_Engine!$Q13+_TECH_Dependency_Map!$B$29*_TECH_Cascade_Engine!$R13)))) | C14: =IF(_TECH_Cascade_Engine!$B13="","",MIN(5,_TECH_Cascade_Engine!$M13*MIN(_TECH_Dependency_Map!$B$34,1+(2/5)*(_TECH_Cascade_Engine!$Q13+_TECH_Dependency_Map!$B$29*_TECH_Cascade_Engine!$R13)))) | D14: =IF(_TECH_Cascade_Engine!$B13="","",MIN(5,_TECH_Cascade_Engine!$M13*MIN(_TECH_Dependency_Map!$B$34,1+(3/5)*(_TECH_Cascade_Engine!$Q13+_TECH_Dependency_Map!$B$29*_TECH_Cascade_Engine!$R13)))) | E14: =IF(_TECH_Cascade_Engine!$B13="","",MIN(5,_TECH_Cascade_Engine!$M13*MIN(_TECH_Dependency_Map!$B$34,1+(4/5)*(_TECH_Cascade_Engine!$Q13+_TECH_Dependency_Map!$B$29*_TECH_Cascade_Engine!$R13)))) | F14: =IF(_TECH_Cascade_Engine!$B13="","",MIN(5,_TECH_Cascade_Engine!$M13*MIN(_TECH_Dependency_Map!$B$34,1+(5/5)*(_TECH_Cascade_Engine!$Q13+_TECH_Dependency_Map!$B$29*_TECH_Cascade_Engine!$R13))))
A15: =_TECH_Cascade_Engine!A14 -> Manufacturing MES | B15: =IF(_TECH_Cascade_Engine!$B14="","",MIN(5,_TECH_Cascade_Engine!$M14*MIN(_TECH_Dependency_Map!$B$34,1+(1/5)*(_TECH_Cascade_Engine!$Q14+_TECH_Dependency_Map!$B$29*_TECH_Cascade_Engine!$R14)))) | C15: =IF(_TECH_Cascade_Engine!$B14="","",MIN(5,_TECH_Cascade_Engine!$M14*MIN(_TECH_Dependency_Map!$B$34,1+(2/5)*(_TECH_Cascade_Engine!$Q14+_TECH_Dependency_Map!$B$29*_TECH_Cascade_Engine!$R14)))) | D15: =IF(_TECH_Cascade_Engine!$B14="","",MIN(5,_TECH_Cascade_Engine!$M14*MIN(_TECH_Dependency_Map!$B$34,1+(3/5)*(_TECH_Cascade_Engine!$Q14+_TECH_Dependency_Map!$B$29*_TECH_Cascade_Engine!$R14)))) | E15: =IF(_TECH_Cascade_Engine!$B14="","",MIN(5,_TECH_Cascade_Engine!$M14*MIN(_TECH_Dependency_Map!$B$34,1+(4/5)*(_TECH_Cascade_Engine!$Q14+_TECH_Dependency_Map!$B$29*_TECH_Cascade_Engine!$R14)))) | F15: =IF(_TECH_Cascade_Engine!$B14="","",MIN(5,_TECH_Cascade_Engine!$M14*MIN(_TECH_Dependency_Map!$B$34,1+(5/5)*(_TECH_Cascade_Engine!$Q14+_TECH_Dependency_Map!$B$29*_TECH_Cascade_Engine!$R14))))
A16: =_TECH_Cascade_Engine!A15 -> Sales CRM | B16: =IF(_TECH_Cascade_Engine!$B15="","",MIN(5,_TECH_Cascade_Engine!$M15*MIN(_TECH_Dependency_Map!$B$34,1+(1/5)*(_TECH_Cascade_Engine!$Q15+_TECH_Dependency_Map!$B$29*_TECH_Cascade_Engine!$R15)))) | C16: =IF(_TECH_Cascade_Engine!$B15="","",MIN(5,_TECH_Cascade_Engine!$M15*MIN(_TECH_Dependency_Map!$B$34,1+(2/5)*(_TECH_Cascade_Engine!$Q15+_TECH_Dependency_Map!$B$29*_TECH_Cascade_Engine!$R15)))) | D16: =IF(_TECH_Cascade_Engine!$B15="","",MIN(5,_TECH_Cascade_Engine!$M15*MIN(_TECH_Dependency_Map!$B$34,1+(3/5)*(_TECH_Cascade_Engine!$Q15+_TECH_Dependency_Map!$B$29*_TECH_Cascade_Engine!$R15)))) | E16: =IF(_TECH_Cascade_Engine!$B15="","",MIN(5,_TECH_Cascade_Engine!$M15*MIN(_TECH_Dependency_Map!$B$34,1+(4/5)*(_TECH_Cascade_Engine!$Q15+_TECH_Dependency_Map!$B$29*_TECH_Cascade_Engine!$R15)))) | F16: =IF(_TECH_Cascade_Engine!$B15="","",MIN(5,_TECH_Cascade_Engine!$M15*MIN(_TECH_Dependency_Map!$B$34,1+(5/5)*(_TECH_Cascade_Engine!$Q15+_TECH_Dependency_Map!$B$29*_TECH_Cascade_Engine!$R15))))
A17: =_TECH_Cascade_Engine!A16 -> Marketing Comms | B17: =IF(_TECH_Cascade_Engine!$B16="","",MIN(5,_TECH_Cascade_Engine!$M16*MIN(_TECH_Dependency_Map!$B$34,1+(1/5)*(_TECH_Cascade_Engine!$Q16+_TECH_Dependency_Map!$B$29*_TECH_Cascade_Engine!$R16)))) | C17: =IF(_TECH_Cascade_Engine!$B16="","",MIN(5,_TECH_Cascade_Engine!$M16*MIN(_TECH_Dependency_Map!$B$34,1+(2/5)*(_TECH_Cascade_Engine!$Q16+_TECH_Dependency_Map!$B$29*_TECH_Cascade_Engine!$R16)))) | D17: =IF(_TECH_Cascade_Engine!$B16="","",MIN(5,_TECH_Cascade_Engine!$M16*MIN(_TECH_Dependency_Map!$B$34,1+(3/5)*(_TECH_Cascade_Engine!$Q16+_TECH_Dependency_Map!$B$29*_TECH_Cascade_Engine!$R16)))) | E17: =IF(_TECH_Cascade_Engine!$B16="","",MIN(5,_TECH_Cascade_Engine!$M16*MIN(_TECH_Dependency_Map!$B$34,1+(4/5)*(_TECH_Cascade_Engine!$Q16+_TECH_Dependency_Map!$B$29*_TECH_Cascade_Engine!$R16)))) | F17: =IF(_TECH_Cascade_Engine!$B16="","",MIN(5,_TECH_Cascade_Engine!$M16*MIN(_TECH_Dependency_Map!$B$34,1+(5/5)*(_TECH_Cascade_Engine!$Q16+_TECH_Dependency_Map!$B$29*_TECH_Cascade_Engine!$R16))))
... A22: =_TECH_Cascade_Engine!A21 -> Quality Portfolio | B22: =IF(_TECH_Cascade_Engine!$B21="","",MIN(5,_TECH_Cascade_Engine!$M21*MIN(_TECH_Dependency_Map!$B$34,1+(1/5)*(_TECH_Cascade_Engine!$Q21+_TECH_Dependency_Map!$B$29*_TECH_Cascade_Engine!$R21)))) | C22: =IF(_TECH_Cascade_Engine!$B21="","",MIN(5,_TECH_Cascade_Engine!$M21*MIN(_TECH_Dependency_Map!$B$34,1+(2/5)*(_TECH_Cascade_Engine!$Q21+_TECH_Dependency_Map!$B$29*_TECH_Cascade_Engine!$R21)))) | D22: =IF(_TECH_Cascade_Engine!$B21="","",MIN(5,_TECH_Cascade_Engine!$M21*MIN(_TECH_Dependency_Map!$B$34,1+(3/5)*(_TECH_Cascade_Engine!$Q21+_TECH_Dependency_Map!$B$29*_TECH_Cascade_Engine!$R21)))) | E22: =IF(_TECH_Cascade_Engine!$B21="","",MIN(5,_TECH_Cascade_Engine!$M21*MIN(_TECH_Dependency_Map!$B$34,1+(4/5)*(_TECH_Cascade_Engine!$Q21+_TECH_Dependency_Map!$B$29*_TECH_Cascade_Engine!$R21)))) | F22: =IF(_TECH_Cascade_Engine!$B21="","",MIN(5,_TECH_Cascade_Engine!$M21*MIN(_TECH_Dependency_Map!$B$34,1+(5/5)*(_TECH_Cascade_Engine!$Q21+_TECH_Dependency_Map!$B$29*_TECH_Cascade_Engine!$R21))))
A23: Org average | B23: =IFERROR(AVERAGE(B6:B22),"") | C23: =IFERROR(AVERAGE(C6:C22),"") | D23: =IFERROR(AVERAGE(D6:D22),"") | E23: =IFERROR(AVERAGE(E6:E22),"") | F23: =IFERROR(AVERAGE(F6:F22),"")
A24: Org peak | B24: =IFERROR(MAX(B6:B22),"") -> 0 | C24: =IFERROR(MAX(C6:C22),"") -> 0 | D24: =IFERROR(MAX(D6:D22),"") -> 0 | E24: =IFERROR(MAX(E6:E22),"") -> 0 | F24: =IFERROR(MAX(F6:F22),"") -> 0
A27: 2) Cascade-gain (beta) sensitivity — effect on effective risk
A28: Domain | B28: beta=0.0 | C28: beta=0.2 | D28: beta=0.35 | E28: beta=0.5 | F28: beta=0.7
A29: =_TECH_Cascade_Engine!A5 -> Company Geography | B29: =IF(_TECH_Cascade_Engine!$B5="","",MIN(5,_TECH_Cascade_Engine!$J5+0*_TECH_Cascade_Engine!$K5)) | C29: =IF(_TECH_Cascade_Engine!$B5="","",MIN(5,_TECH_Cascade_Engine!$J5+0.2*_TECH_Cascade_Engine!$K5)) | D29: =IF(_TECH_Cascade_Engine!$B5="","",MIN(5,_TECH_Cascade_Engine!$J5+0.35*_TECH_Cascade_Engine!$K5)) | E29: =IF(_TECH_Cascade_Engine!$B5="","",MIN(5,_TECH_Cascade_Engine!$J5+0.5*_TECH_Cascade_Engine!$K5)) | F29: =IF(_TECH_Cascade_Engine!$B5="","",MIN(5,_TECH_Cascade_Engine!$J5+0.7*_TECH_Cascade_Engine!$K5))
A30: =_TECH_Cascade_Engine!A6 -> Strategy GTM | B30: =IF(_TECH_Cascade_Engine!$B6="","",MIN(5,_TECH_Cascade_Engine!$J6+0*_TECH_Cascade_Engine!$K6)) | C30: =IF(_TECH_Cascade_Engine!$B6="","",MIN(5,_TECH_Cascade_Engine!$J6+0.2*_TECH_Cascade_Engine!$K6)) | D30: =IF(_TECH_Cascade_Engine!$B6="","",MIN(5,_TECH_Cascade_Engine!$J6+0.35*_TECH_Cascade_Engine!$K6)) | E30: =IF(_TECH_Cascade_Engine!$B6="","",MIN(5,_TECH_Cascade_Engine!$J6+0.5*_TECH_Cascade_Engine!$K6)) | F30: =IF(_TECH_Cascade_Engine!$B6="","",MIN(5,_TECH_Cascade_Engine!$J6+0.7*_TECH_Cascade_Engine!$K6))
A31: =_TECH_Cascade_Engine!A7 -> Governance Crisis | B31: =IF(_TECH_Cascade_Engine!$B7="","",MIN(5,_TECH_Cascade_Engine!$J7+0*_TECH_Cascade_Engine!$K7)) | C31: =IF(_TECH_Cascade_Engine!$B7="","",MIN(5,_TECH_Cascade_Engine!$J7+0.2*_TECH_Cascade_Engine!$K7)) | D31: =IF(_TECH_Cascade_Engine!$B7="","",MIN(5,_TECH_Cascade_Engine!$J7+0.35*_TECH_Cascade_Engine!$K7)) | E31: =IF(_TECH_Cascade_Engine!$B7="","",MIN(5,_TECH_Cascade_Engine!$J7+0.5*_TECH_Cascade_Engine!$K7)) | F31: =IF(_TECH_Cascade_Engine!$B7="","",MIN(5,_TECH_Cascade_Engine!$J7+0.7*_TECH_Cascade_Engine!$K7))
A32: =_TECH_Cascade_Engine!A8 -> HR Workforce | B32: =IF(_TECH_Cascade_Engine!$B8="","",MIN(5,_TECH_Cascade_Engine!$J8+0*_TECH_Cascade_Engine!$K8)) | C32: =IF(_TECH_Cascade_Engine!$B8="","",MIN(5,_TECH_Cascade_Engine!$J8+0.2*_TECH_Cascade_Engine!$K8)) | D32: =IF(_TECH_Cascade_Engine!$B8="","",MIN(5,_TECH_Cascade_Engine!$J8+0.35*_TECH_Cascade_Engine!$K8)) | E32: =IF(_TECH_Cascade_Engine!$B8="","",MIN(5,_TECH_Cascade_Engine!$J8+0.5*_TECH_Cascade_Engine!$K8)) | F32: =IF(_TECH_Cascade_Engine!$B8="","",MIN(5,_TECH_Cascade_Engine!$J8+0.7*_TECH_Cascade_Engine!$K8))
A33: =_TECH_Cascade_Engine!A9 -> Finance Procurement | B33: =IF(_TECH_Cascade_Engine!$B9="","",MIN(5,_TECH_Cascade_Engine!$J9+0*_TECH_Cascade_Engine!$K9)) | C33: =IF(_TECH_Cascade_Engine!$B9="","",MIN(5,_TECH_Cascade_Engine!$J9+0.2*_TECH_Cascade_Engine!$K9)) | D33: =IF(_TECH_Cascade_Engine!$B9="","",MIN(5,_TECH_Cascade_Engine!$J9+0.35*_TECH_Cascade_Engine!$K9)) | E33: =IF(_TECH_Cascade_Engine!$B9="","",MIN(5,_TECH_Cascade_Engine!$J9+0.5*_TECH_Cascade_Engine!$K9)) | F33: =IF(_TECH_Cascade_Engine!$B9="","",MIN(5,_TECH_Cascade_Engine!$J9+0.7*_TECH_Cascade_Engine!$K9))
A34: =_TECH_Cascade_Engine!A10 -> Legal Risk | B34: =IF(_TECH_Cascade_Engine!$B10="","",MIN(5,_TECH_Cascade_Engine!$J10+0*_TECH_Cascade_Engine!$K10)) | C34: =IF(_TECH_Cascade_Engine!$B10="","",MIN(5,_TECH_Cascade_Engine!$J10+0.2*_TECH_Cascade_Engine!$K10)) | D34: =IF(_TECH_Cascade_Engine!$B10="","",MIN(5,_TECH_Cascade_Engine!$J10+0.35*_TECH_Cascade_Engine!$K10)) | E34: =IF(_TECH_Cascade_Engine!$B10="","",MIN(5,_TECH_Cascade_Engine!$J10+0.5*_TECH_Cascade_Engine!$K10)) | F34: =IF(_TECH_Cascade_Engine!$B10="","",MIN(5,_TECH_Cascade_Engine!$J10+0.7*_TECH_Cascade_Engine!$K10))
A35: =_TECH_Cascade_Engine!A11 -> Physical Safety | B35: =IF(_TECH_Cascade_Engine!$B11="","",MIN(5,_TECH_Cascade_Engine!$J11+0*_TECH_Cascade_Engine!$K11)) | C35: =IF(_TECH_Cascade_Engine!$B11="","",MIN(5,_TECH_Cascade_Engine!$J11+0.2*_TECH_Cascade_Engine!$K11)) | D35: =IF(_TECH_Cascade_Engine!$B11="","",MIN(5,_TECH_Cascade_Engine!$J11+0.35*_TECH_Cascade_Engine!$K11)) | E35: =IF(_TECH_Cascade_Engine!$B11="","",MIN(5,_TECH_Cascade_Engine!$J11+0.5*_TECH_Cascade_Engine!$K11)) | F35: =IF(_TECH_Cascade_Engine!$B11="","",MIN(5,_TECH_Cascade_Engine!$J11+0.7*_TECH_Cascade_Engine!$K11))
A36: =_TECH_Cascade_Engine!A12 -> Delivery Ops | B36: =IF(_TECH_Cascade_Engine!$B12="","",MIN(5,_TECH_Cascade_Engine!$J12+0*_TECH_Cascade_Engine!$K12)) | C36: =IF(_TECH_Cascade_Engine!$B12="","",MIN(5,_TECH_Cascade_Engine!$J12+0.2*_TECH_Cascade_Engine!$K12)) | D36: =IF(_TECH_Cascade_Engine!$B12="","",MIN(5,_TECH_Cascade_Engine!$J12+0.35*_TECH_Cascade_Engine!$K12)) | E36: =IF(_TECH_Cascade_Engine!$B12="","",MIN(5,_TECH_Cascade_Engine!$J12+0.5*_TECH_Cascade_Engine!$K12)) | F36: =IF(_TECH_Cascade_Engine!$B12="","",MIN(5,_TECH_Cascade_Engine!$J12+0.7*_TECH_Cascade_Engine!$K12))
A37: =_TECH_Cascade_Engine!A13 -> Supply Chain | B37: =IF(_TECH_Cascade_Engine!$B13="","",MIN(5,_TECH_Cascade_Engine!$J13+0*_TECH_Cascade_Engine!$K13)) | C37: =IF(_TECH_Cascade_Engine!$B13="","",MIN(5,_TECH_Cascade_Engine!$J13+0.2*_TECH_Cascade_Engine!$K13)) | D37: =IF(_TECH_Cascade_Engine!$B13="","",MIN(5,_TECH_Cascade_Engine!$J13+0.35*_TECH_Cascade_Engine!$K13)) | E37: =IF(_TECH_Cascade_Engine!$B13="","",MIN(5,_TECH_Cascade_Engine!$J13+0.5*_TECH_Cascade_Engine!$K13)) | F37: =IF(_TECH_Cascade_Engine!$B13="","",MIN(5,_TECH_Cascade_Engine!$J13+0.7*_TECH_Cascade_Engine!$K13))
A38: =_TECH_Cascade_Engine!A14 -> Manufacturing MES | B38: =IF(_TECH_Cascade_Engine!$B14="","",MIN(5,_TECH_Cascade_Engine!$J14+0*_TECH_Cascade_Engine!$K14)) | C38: =IF(_TECH_Cascade_Engine!$B14="","",MIN(5,_TECH_Cascade_Engine!$J14+0.2*_TECH_Cascade_Engine!$K14)) | D38: =IF(_TECH_Cascade_Engine!$B14="","",MIN(5,_TECH_Cascade_Engine!$J14+0.35*_TECH_Cascade_Engine!$K14)) | E38: =IF(_TECH_Cascade_Engine!$B14="","",MIN(5,_TECH_Cascade_Engine!$J14+0.5*_TECH_Cascade_Engine!$K14)) | F38: =IF(_TECH_Cascade_Engine!$B14="","",MIN(5,_TECH_Cascade_Engine!$J14+0.7*_TECH_Cascade_Engine!$K14))
A39: =_TECH_Cascade_Engine!A15 -> Sales CRM | B39: =IF(_TECH_Cascade_Engine!$B15="","",MIN(5,_TECH_Cascade_Engine!$J15+0*_TECH_Cascade_Engine!$K15)) | C39: =IF(_TECH_Cascade_Engine!$B15="","",MIN(5,_TECH_Cascade_Engine!$J15+0.2*_TECH_Cascade_Engine!$K15)) | D39: =IF(_TECH_Cascade_Engine!$B15="","",MIN(5,_TECH_Cascade_Engine!$J15+0.35*_TECH_Cascade_Engine!$K15)) | E39: =IF(_TECH_Cascade_Engine!$B15="","",MIN(5,_TECH_Cascade_Engine!$J15+0.5*_TECH_Cascade_Engine!$K15)) | F39: =IF(_TECH_Cascade_Engine!$B15="","",MIN(5,_TECH_Cascade_Engine!$J15+0.7*_TECH_Cascade_Engine!$K15))
A40: =_TECH_Cascade_Engine!A16 -> Marketing Comms | B40: =IF(_TECH_Cascade_Engine!$B16="","",MIN(5,_TECH_Cascade_Engine!$J16+0*_TECH_Cascade_Engine!$K16)) | C40: =IF(_TECH_Cascade_Engine!$B16="","",MIN(5,_TECH_Cascade_Engine!$J16+0.2*_TECH_Cascade_Engine!$K16)) | D40: =IF(_TECH_Cascade_Engine!$B16="","",MIN(5,_TECH_Cascade_Engine!$J16+0.35*_TECH_Cascade_Engine!$K16)) | E40: =IF(_TECH_Cascade_Engine!$B16="","",MIN(5,_TECH_Cascade_Engine!$J16+0.5*_TECH_Cascade_Engine!$K16)) | F40: =IF(_TECH_Cascade_Engine!$B16="","",MIN(5,_TECH_Cascade_Engine!$J16+0.7*_TECH_Cascade_Engine!$K16))
... A45: =_TECH_Cascade_Engine!A21 -> Quality Portfolio | B45: =IF(_TECH_Cascade_Engine!$B21="","",MIN(5,_TECH_Cascade_Engine!$J21+0*_TECH_Cascade_Engine!$K21)) | C45: =IF(_TECH_Cascade_Engine!$B21="","",MIN(5,_TECH_Cascade_Engine!$J21+0.2*_TECH_Cascade_Engine!$K21)) | D45: =IF(_TECH_Cascade_Engine!$B21="","",MIN(5,_TECH_Cascade_Engine!$J21+0.35*_TECH_Cascade_Engine!$K21)) | E45: =IF(_TECH_Cascade_Engine!$B21="","",MIN(5,_TECH_Cascade_Engine!$J21+0.5*_TECH_Cascade_Engine!$K21)) | F45: =IF(_TECH_Cascade_Engine!$B21="","",MIN(5,_TECH_Cascade_Engine!$J21+0.7*_TECH_Cascade_Engine!$K21))
A46: Org average | B46: =IFERROR(AVERAGE(B29:B45),"") | C46: =IFERROR(AVERAGE(C29:C45),"") | D46: =IFERROR(AVERAGE(D29:D45),"") | E46: =IFERROR(AVERAGE(E29:E45),"") | F46: =IFERROR(AVERAGE(F29:F45),"")
A47: Org peak | B47: =IFERROR(MAX(B29:B45),"") -> 0 | C47: =IFERROR(MAX(C29:C45),"") -> 0 | D47: =IFERROR(MAX(D29:D45),"") -> 0 | E47: =IFERROR(MAX(E29:E45),"") -> 0 | F47: =IFERROR(MAX(F29:F45),"") -> 0
A48: Current beta = '_TECH_Dependency_Map'!$B$28 (edit in _TECH_Dependency_Map)
A51: 3) Weak-link (alpha) sensitivity — effect on gated maturity
A52: Domain | B52: alpha=0.4 | C52: alpha=0.55 | D52: alpha=0.65 | E52: alpha=0.8 | F52: alpha=0.95
A53: =_TECH_Cascade_Engine!A5 -> Company Geography | B53: =IF(_TECH_Cascade_Engine!$B5="","",IF(AND(_TECH_Cascade_Engine!$E5<>"",_TECH_Cascade_Engine!$E5<_TECH_Dependency_Map!$B$30),MIN((0.4*_TECH_Cascade_Engine!$B5+(1-0.4)*_TECH_Cascade_Engine!$C5),_TECH_Dependency_Map!$B$31),(0.4*_TECH_Cascade_Engine!$B5+(1-0.4)*_TECH_Cascade_Engine!$C5))) | C53: =IF(_TECH_Cascade_Engine!$B5="","",IF(AND(_TECH_Cascade_Engine!$E5<>"",_TECH_Cascade_Engine!$E5<_TECH_Dependency_Map!$B$30),MIN((0.55*_TECH_Cascade_Engine!$B5+(1-0.55)*_TECH_Cascade_Engine!$C5),_TECH_Dependency_Map!$B$31),(0.55*_TECH_Cascade_Engine!$B5+(1-0.55)*_TECH_Cascade_Engine!$C5))) | D53: =IF(_TECH_Cascade_Engine!$B5="","",IF(AND(_TECH_Cascade_Engine!$E5<>"",_TECH_Cascade_Engine!$E5<_TECH_Dependency_Map!$B$30),MIN((0.65*_TECH_Cascade_Engine!$B5+(1-0.65)*_TECH_Cascade_Engine!$C5),_TECH_Dependency_Map!$B$31),(0.65*_TECH_Cascade_Engine!$B5+(1-0.65)*_TECH_Cascade_Engine!$C5))) | E53: =IF(_TECH_Cascade_Engine!$B5="","",IF(AND(_TECH_Cascade_Engine!$E5<>"",_TECH_Cascade_Engine!$E5<_TECH_Dependency_Map!$B$30),MIN((0.8*_TECH_Cascade_Engine!$B5+(1-0.8)*_TECH_Cascade_Engine!$C5),_TECH_Dependency_Map!$B$31),(0.8*_TECH_Cascade_Engine!$B5+(1-0.8)*_TECH_Cascade_Engine!$C5))) | F53: =IF(_TECH_Cascade_Engine!$B5="","",IF(AND(_TECH_Cascade_Engine!$E5<>"",_TECH_Cascade_Engine!$E5<_TECH_Dependency_Map!$B$30),MIN((0.95*_TECH_Cascade_Engine!$B5+(1-0.95)*_TECH_Cascade_Engine!$C5),_TECH_Dependency_Map!$B$31),(0.95*_TECH_Cascade_Engine!$B5+(1-0.95)*_TECH_Cascade_Engine!$C5)))
A54: =_TECH_Cascade_Engine!A6 -> Strategy GTM | B54: =IF(_TECH_Cascade_Engine!$B6="","",IF(AND(_TECH_Cascade_Engine!$E6<>"",_TECH_Cascade_Engine!$E6<_TECH_Dependency_Map!$B$30),MIN((0.4*_TECH_Cascade_Engine!$B6+(1-0.4)*_TECH_Cascade_Engine!$C6),_TECH_Dependency_Map!$B$31),(0.4*_TECH_Cascade_Engine!$B6+(1-0.4)*_TECH_Cascade_Engine!$C6))) | C54: =IF(_TECH_Cascade_Engine!$B6="","",IF(AND(_TECH_Cascade_Engine!$E6<>"",_TECH_Cascade_Engine!$E6<_TECH_Dependency_Map!$B$30),MIN((0.55*_TECH_Cascade_Engine!$B6+(1-0.55)*_TECH_Cascade_Engine!$C6),_TECH_Dependency_Map!$B$31),(0.55*_TECH_Cascade_Engine!$B6+(1-0.55)*_TECH_Cascade_Engine!$C6))) | D54: =IF(_TECH_Cascade_Engine!$B6="","",IF(AND(_TECH_Cascade_Engine!$E6<>"",_TECH_Cascade_Engine!$E6<_TECH_Dependency_Map!$B$30),MIN((0.65*_TECH_Cascade_Engine!$B6+(1-0.65)*_TECH_Cascade_Engine!$C6),_TECH_Dependency_Map!$B$31),(0.65*_TECH_Cascade_Engine!$B6+(1-0.65)*_TECH_Cascade_Engine!$C6))) | E54: =IF(_TECH_Cascade_Engine!$B6="","",IF(AND(_TECH_Cascade_Engine!$E6<>"",_TECH_Cascade_Engine!$E6<_TECH_Dependency_Map!$B$30),MIN((0.8*_TECH_Cascade_Engine!$B6+(1-0.8)*_TECH_Cascade_Engine!$C6),_TECH_Dependency_Map!$B$31),(0.8*_TECH_Cascade_Engine!$B6+(1-0.8)*_TECH_Cascade_Engine!$C6))) | F54: =IF(_TECH_Cascade_Engine!$B6="","",IF(AND(_TECH_Cascade_Engine!$E6<>"",_TECH_Cascade_Engine!$E6<_TECH_Dependency_Map!$B$30),MIN((0.95*_TECH_Cascade_Engine!$B6+(1-0.95)*_TECH_Cascade_Engine!$C6),_TECH_Dependency_Map!$B$31),(0.95*_TECH_Cascade_Engine!$B6+(1-0.95)*_TECH_Cascade_Engine!$C6)))
A55: =_TECH_Cascade_Engine!A7 -> Governance Crisis | B55: =IF(_TECH_Cascade_Engine!$B7="","",IF(AND(_TECH_Cascade_Engine!$E7<>"",_TECH_Cascade_Engine!$E7<_TECH_Dependency_Map!$B$30),MIN((0.4*_TECH_Cascade_Engine!$B7+(1-0.4)*_TECH_Cascade_Engine!$C7),_TECH_Dependency_Map!$B$31),(0.4*_TECH_Cascade_Engine!$B7+(1-0.4)*_TECH_Cascade_Engine!$C7))) | C55: =IF(_TECH_Cascade_Engine!$B7="","",IF(AND(_TECH_Cascade_Engine!$E7<>"",_TECH_Cascade_Engine!$E7<_TECH_Dependency_Map!$B$30),MIN((0.55*_TECH_Cascade_Engine!$B7+(1-0.55)*_TECH_Cascade_Engine!$C7),_TECH_Dependency_Map!$B$31),(0.55*_TECH_Cascade_Engine!$B7+(1-0.55)*_TECH_Cascade_Engine!$C7))) | D55: =IF(_TECH_Cascade_Engine!$B7="","",IF(AND(_TECH_Cascade_Engine!$E7<>"",_TECH_Cascade_Engine!$E7<_TECH_Dependency_Map!$B$30),MIN((0.65*_TECH_Cascade_Engine!$B7+(1-0.65)*_TECH_Cascade_Engine!$C7),_TECH_Dependency_Map!$B$31),(0.65*_TECH_Cascade_Engine!$B7+(1-0.65)*_TECH_Cascade_Engine!$C7))) | E55: =IF(_TECH_Cascade_Engine!$B7="","",IF(AND(_TECH_Cascade_Engine!$E7<>"",_TECH_Cascade_Engine!$E7<_TECH_Dependency_Map!$B$30),MIN((0.8*_TECH_Cascade_Engine!$B7+(1-0.8)*_TECH_Cascade_Engine!$C7),_TECH_Dependency_Map!$B$31),(0.8*_TECH_Cascade_Engine!$B7+(1-0.8)*_TECH_Cascade_Engine!$C7))) | F55: =IF(_TECH_Cascade_Engine!$B7="","",IF(AND(_TECH_Cascade_Engine!$E7<>"",_TECH_Cascade_Engine!$E7<_TECH_Dependency_Map!$B$30),MIN((0.95*_TECH_Cascade_Engine!$B7+(1-0.95)*_TECH_Cascade_Engine!$C7),_TECH_Dependency_Map!$B$31),(0.95*_TECH_Cascade_Engine!$B7+(1-0.95)*_TECH_Cascade_Engine!$C7)))
A56: =_TECH_Cascade_Engine!A8 -> HR Workforce | B56: =IF(_TECH_Cascade_Engine!$B8="","",IF(AND(_TECH_Cascade_Engine!$E8<>"",_TECH_Cascade_Engine!$E8<_TECH_Dependency_Map!$B$30),MIN((0.4*_TECH_Cascade_Engine!$B8+(1-0.4)*_TECH_Cascade_Engine!$C8),_TECH_Dependency_Map!$B$31),(0.4*_TECH_Cascade_Engine!$B8+(1-0.4)*_TECH_Cascade_Engine!$C8))) | C56: =IF(_TECH_Cascade_Engine!$B8="","",IF(AND(_TECH_Cascade_Engine!$E8<>"",_TECH_Cascade_Engine!$E8<_TECH_Dependency_Map!$B$30),MIN((0.55*_TECH_Cascade_Engine!$B8+(1-0.55)*_TECH_Cascade_Engine!$C8),_TECH_Dependency_Map!$B$31),(0.55*_TECH_Cascade_Engine!$B8+(1-0.55)*_TECH_Cascade_Engine!$C8))) | D56: =IF(_TECH_Cascade_Engine!$B8="","",IF(AND(_TECH_Cascade_Engine!$E8<>"",_TECH_Cascade_Engine!$E8<_TECH_Dependency_Map!$B$30),MIN((0.65*_TECH_Cascade_Engine!$B8+(1-0.65)*_TECH_Cascade_Engine!$C8),_TECH_Dependency_Map!$B$31),(0.65*_TECH_Cascade_Engine!$B8+(1-0.65)*_TECH_Cascade_Engine!$C8))) | E56: =IF(_TECH_Cascade_Engine!$B8="","",IF(AND(_TECH_Cascade_Engine!$E8<>"",_TECH_Cascade_Engine!$E8<_TECH_Dependency_Map!$B$30),MIN((0.8*_TECH_Cascade_Engine!$B8+(1-0.8)*_TECH_Cascade_Engine!$C8),_TECH_Dependency_Map!$B$31),(0.8*_TECH_Cascade_Engine!$B8+(1-0.8)*_TECH_Cascade_Engine!$C8))) | F56: =IF(_TECH_Cascade_Engine!$B8="","",IF(AND(_TECH_Cascade_Engine!$E8<>"",_TECH_Cascade_Engine!$E8<_TECH_Dependency_Map!$B$30),MIN((0.95*_TECH_Cascade_Engine!$B8+(1-0.95)*_TECH_Cascade_Engine!$C8),_TECH_Dependency_Map!$B$31),(0.95*_TECH_Cascade_Engine!$B8+(1-0.95)*_TECH_Cascade_Engine!$C8)))
A57: =_TECH_Cascade_Engine!A9 -> Finance Procurement | B57: =IF(_TECH_Cascade_Engine!$B9="","",IF(AND(_TECH_Cascade_Engine!$E9<>"",_TECH_Cascade_Engine!$E9<_TECH_Dependency_Map!$B$30),MIN((0.4*_TECH_Cascade_Engine!$B9+(1-0.4)*_TECH_Cascade_Engine!$C9),_TECH_Dependency_Map!$B$31),(0.4*_TECH_Cascade_Engine!$B9+(1-0.4)*_TECH_Cascade_Engine!$C9))) | C57: =IF(_TECH_Cascade_Engine!$B9="","",IF(AND(_TECH_Cascade_Engine!$E9<>"",_TECH_Cascade_Engine!$E9<_TECH_Dependency_Map!$B$30),MIN((0.55*_TECH_Cascade_Engine!$B9+(1-0.55)*_TECH_Cascade_Engine!$C9),_TECH_Dependency_Map!$B$31),(0.55*_TECH_Cascade_Engine!$B9+(1-0.55)*_TECH_Cascade_Engine!$C9))) | D57: =IF(_TECH_Cascade_Engine!$B9="","",IF(AND(_TECH_Cascade_Engine!$E9<>"",_TECH_Cascade_Engine!$E9<_TECH_Dependency_Map!$B$30),MIN((0.65*_TECH_Cascade_Engine!$B9+(1-0.65)*_TECH_Cascade_Engine!$C9),_TECH_Dependency_Map!$B$31),(0.65*_TECH_Cascade_Engine!$B9+(1-0.65)*_TECH_Cascade_Engine!$C9))) | E57: =IF(_TECH_Cascade_Engine!$B9="","",IF(AND(_TECH_Cascade_Engine!$E9<>"",_TECH_Cascade_Engine!$E9<_TECH_Dependency_Map!$B$30),MIN((0.8*_TECH_Cascade_Engine!$B9+(1-0.8)*_TECH_Cascade_Engine!$C9),_TECH_Dependency_Map!$B$31),(0.8*_TECH_Cascade_Engine!$B9+(1-0.8)*_TECH_Cascade_Engine!$C9))) | F57: =IF(_TECH_Cascade_Engine!$B9="","",IF(AND(_TECH_Cascade_Engine!$E9<>"",_TECH_Cascade_Engine!$E9<_TECH_Dependency_Map!$B$30),MIN((0.95*_TECH_Cascade_Engine!$B9+(1-0.95)*_TECH_Cascade_Engine!$C9),_TECH_Dependency_Map!$B$31),(0.95*_TECH_Cascade_Engine!$B9+(1-0.95)*_TECH_Cascade_Engine!$C9)))
A58: =_TECH_Cascade_Engine!A10 -> Legal Risk | B58: =IF(_TECH_Cascade_Engine!$B10="","",IF(AND(_TECH_Cascade_Engine!$E10<>"",_TECH_Cascade_Engine!$E10<_TECH_Dependency_Map!$B$30),MIN((0.4*_TECH_Cascade_Engine!$B10+(1-0.4)*_TECH_Cascade_Engine!$C10),_TECH_Dependency_Map!$B$31),(0.4*_TECH_Cascade_Engine!$B10+(1-0.4)*_TECH_Cascade_Engine!$C10))) | C58: =IF(_TECH_Cascade_Engine!$B10="","",IF(AND(_TECH_Cascade_Engine!$E10<>"",_TECH_Cascade_Engine!$E10<_TECH_Dependency_Map!$B$30),MIN((0.55*_TECH_Cascade_Engine!$B10+(1-0.55)*_TECH_Cascade_Engine!$C10),_TECH_Dependency_Map!$B$31),(0.55*_TECH_Cascade_Engine!$B10+(1-0.55)*_TECH_Cascade_Engine!$C10))) | D58: =IF(_TECH_Cascade_Engine!$B10="","",IF(AND(_TECH_Cascade_Engine!$E10<>"",_TECH_Cascade_Engine!$E10<_TECH_Dependency_Map!$B$30),MIN((0.65*_TECH_Cascade_Engine!$B10+(1-0.65)*_TECH_Cascade_Engine!$C10),_TECH_Dependency_Map!$B$31),(0.65*_TECH_Cascade_Engine!$B10+(1-0.65)*_TECH_Cascade_Engine!$C10))) | E58: =IF(_TECH_Cascade_Engine!$B10="","",IF(AND(_TECH_Cascade_Engine!$E10<>"",_TECH_Cascade_Engine!$E10<_TECH_Dependency_Map!$B$30),MIN((0.8*_TECH_Cascade_Engine!$B10+(1-0.8)*_TECH_Cascade_Engine!$C10),_TECH_Dependency_Map!$B$31),(0.8*_TECH_Cascade_Engine!$B10+(1-0.8)*_TECH_Cascade_Engine!$C10))) | F58: =IF(_TECH_Cascade_Engine!$B10="","",IF(AND(_TECH_Cascade_Engine!$E10<>"",_TECH_Cascade_Engine!$E10<_TECH_Dependency_Map!$B$30),MIN((0.95*_TECH_Cascade_Engine!$B10+(1-0.95)*_TECH_Cascade_Engine!$C10),_TECH_Dependency_Map!$B$31),(0.95*_TECH_Cascade_Engine!$B10+(1-0.95)*_TECH_Cascade_Engine!$C10)))
A59: =_TECH_Cascade_Engine!A11 -> Physical Safety | B59: =IF(_TECH_Cascade_Engine!$B11="","",IF(AND(_TECH_Cascade_Engine!$E11<>"",_TECH_Cascade_Engine!$E11<_TECH_Dependency_Map!$B$30),MIN((0.4*_TECH_Cascade_Engine!$B11+(1-0.4)*_TECH_Cascade_Engine!$C11),_TECH_Dependency_Map!$B$31),(0.4*_TECH_Cascade_Engine!$B11+(1-0.4)*_TECH_Cascade_Engine!$C11))) | C59: =IF(_TECH_Cascade_Engine!$B11="","",IF(AND(_TECH_Cascade_Engine!$E11<>"",_TECH_Cascade_Engine!$E11<_TECH_Dependency_Map!$B$30),MIN((0.55*_TECH_Cascade_Engine!$B11+(1-0.55)*_TECH_Cascade_Engine!$C11),_TECH_Dependency_Map!$B$31),(0.55*_TECH_Cascade_Engine!$B11+(1-0.55)*_TECH_Cascade_Engine!$C11))) | D59: =IF(_TECH_Cascade_Engine!$B11="","",IF(AND(_TECH_Cascade_Engine!$E11<>"",_TECH_Cascade_Engine!$E11<_TECH_Dependency_Map!$B$30),MIN((0.65*_TECH_Cascade_Engine!$B11+(1-0.65)*_TECH_Cascade_Engine!$C11),_TECH_Dependency_Map!$B$31),(0.65*_TECH_Cascade_Engine!$B11+(1-0.65)*_TECH_Cascade_Engine!$C11))) | E59: =IF(_TECH_Cascade_Engine!$B11="","",IF(AND(_TECH_Cascade_Engine!$E11<>"",_TECH_Cascade_Engine!$E11<_TECH_Dependency_Map!$B$30),MIN((0.8*_TECH_Cascade_Engine!$B11+(1-0.8)*_TECH_Cascade_Engine!$C11),_TECH_Dependency_Map!$B$31),(0.8*_TECH_Cascade_Engine!$B11+(1-0.8)*_TECH_Cascade_Engine!$C11))) | F59: =IF(_TECH_Cascade_Engine!$B11="","",IF(AND(_TECH_Cascade_Engine!$E11<>"",_TECH_Cascade_Engine!$E11<_TECH_Dependency_Map!$B$30),MIN((0.95*_TECH_Cascade_Engine!$B11+(1-0.95)*_TECH_Cascade_Engine!$C11),_TECH_Dependency_Map!$B$31),(0.95*_TECH_Cascade_Engine!$B11+(1-0.95)*_TECH_Cascade_Engine!$C11)))
A60: =_TECH_Cascade_Engine!A12 -> Delivery Ops | B60: =IF(_TECH_Cascade_Engine!$B12="","",IF(AND(_TECH_Cascade_Engine!$E12<>"",_TECH_Cascade_Engine!$E12<_TECH_Dependency_Map!$B$30),MIN((0.4*_TECH_Cascade_Engine!$B12+(1-0.4)*_TECH_Cascade_Engine!$C12),_TECH_Dependency_Map!$B$31),(0.4*_TECH_Cascade_Engine!$B12+(1-0.4)*_TECH_Cascade_Engine!$C12))) | C60: =IF(_TECH_Cascade_Engine!$B12="","",IF(AND(_TECH_Cascade_Engine!$E12<>"",_TECH_Cascade_Engine!$E12<_TECH_Dependency_Map!$B$30),MIN((0.55*_TECH_Cascade_Engine!$B12+(1-0.55)*_TECH_Cascade_Engine!$C12),_TECH_Dependency_Map!$B$31),(0.55*_TECH_Cascade_Engine!$B12+(1-0.55)*_TECH_Cascade_Engine!$C12))) | D60: =IF(_TECH_Cascade_Engine!$B12="","",IF(AND(_TECH_Cascade_Engine!$E12<>"",_TECH_Cascade_Engine!$E12<_TECH_Dependency_Map!$B$30),MIN((0.65*_TECH_Cascade_Engine!$B12+(1-0.65)*_TECH_Cascade_Engine!$C12),_TECH_Dependency_Map!$B$31),(0.65*_TECH_Cascade_Engine!$B12+(1-0.65)*_TECH_Cascade_Engine!$C12))) | E60: =IF(_TECH_Cascade_Engine!$B12="","",IF(AND(_TECH_Cascade_Engine!$E12<>"",_TECH_Cascade_Engine!$E12<_TECH_Dependency_Map!$B$30),MIN((0.8*_TECH_Cascade_Engine!$B12+(1-0.8)*_TECH_Cascade_Engine!$C12),_TECH_Dependency_Map!$B$31),(0.8*_TECH_Cascade_Engine!$B12+(1-0.8)*_TECH_Cascade_Engine!$C12))) | F60: =IF(_TECH_Cascade_Engine!$B12="","",IF(AND(_TECH_Cascade_Engine!$E12<>"",_TECH_Cascade_Engine!$E12<_TECH_Dependency_Map!$B$30),MIN((0.95*_TECH_Cascade_Engine!$B12+(1-0.95)*_TECH_Cascade_Engine!$C12),_TECH_Dependency_Map!$B$31),(0.95*_TECH_Cascade_Engine!$B12+(1-0.95)*_TECH_Cascade_Engine!$C12)))
A61: =_TECH_Cascade_Engine!A13 -> Supply Chain | B61: =IF(_TECH_Cascade_Engine!$B13="","",IF(AND(_TECH_Cascade_Engine!$E13<>"",_TECH_Cascade_Engine!$E13<_TECH_Dependency_Map!$B$30),MIN((0.4*_TECH_Cascade_Engine!$B13+(1-0.4)*_TECH_Cascade_Engine!$C13),_TECH_Dependency_Map!$B$31),(0.4*_TECH_Cascade_Engine!$B13+(1-0.4)*_TECH_Cascade_Engine!$C13))) | C61: =IF(_TECH_Cascade_Engine!$B13="","",IF(AND(_TECH_Cascade_Engine!$E13<>"",_TECH_Cascade_Engine!$E13<_TECH_Dependency_Map!$B$30),MIN((0.55*_TECH_Cascade_Engine!$B13+(1-0.55)*_TECH_Cascade_Engine!$C13),_TECH_Dependency_Map!$B$31),(0.55*_TECH_Cascade_Engine!$B13+(1-0.55)*_TECH_Cascade_Engine!$C13))) | D61: =IF(_TECH_Cascade_Engine!$B13="","",IF(AND(_TECH_Cascade_Engine!$E13<>"",_TECH_Cascade_Engine!$E13<_TECH_Dependency_Map!$B$30),MIN((0.65*_TECH_Cascade_Engine!$B13+(1-0.65)*_TECH_Cascade_Engine!$C13),_TECH_Dependency_Map!$B$31),(0.65*_TECH_Cascade_Engine!$B13+(1-0.65)*_TECH_Cascade_Engine!$C13))) | E61: =IF(_TECH_Cascade_Engine!$B13="","",IF(AND(_TECH_Cascade_Engine!$E13<>"",_TECH_Cascade_Engine!$E13<_TECH_Dependency_Map!$B$30),MIN((0.8*_TECH_Cascade_Engine!$B13+(1-0.8)*_TECH_Cascade_Engine!$C13),_TECH_Dependency_Map!$B$31),(0.8*_TECH_Cascade_Engine!$B13+(1-0.8)*_TECH_Cascade_Engine!$C13))) | F61: =IF(_TECH_Cascade_Engine!$B13="","",IF(AND(_TECH_Cascade_Engine!$E13<>"",_TECH_Cascade_Engine!$E13<_TECH_Dependency_Map!$B$30),MIN((0.95*_TECH_Cascade_Engine!$B13+(1-0.95)*_TECH_Cascade_Engine!$C13),_TECH_Dependency_Map!$B$31),(0.95*_TECH_Cascade_Engine!$B13+(1-0.95)*_TECH_Cascade_Engine!$C13)))
A62: =_TECH_Cascade_Engine!A14 -> Manufacturing MES | B62: =IF(_TECH_Cascade_Engine!$B14="","",IF(AND(_TECH_Cascade_Engine!$E14<>"",_TECH_Cascade_Engine!$E14<_TECH_Dependency_Map!$B$30),MIN((0.4*_TECH_Cascade_Engine!$B14+(1-0.4)*_TECH_Cascade_Engine!$C14),_TECH_Dependency_Map!$B$31),(0.4*_TECH_Cascade_Engine!$B14+(1-0.4)*_TECH_Cascade_Engine!$C14))) | C62: =IF(_TECH_Cascade_Engine!$B14="","",IF(AND(_TECH_Cascade_Engine!$E14<>"",_TECH_Cascade_Engine!$E14<_TECH_Dependency_Map!$B$30),MIN((0.55*_TECH_Cascade_Engine!$B14+(1-0.55)*_TECH_Cascade_Engine!$C14),_TECH_Dependency_Map!$B$31),(0.55*_TECH_Cascade_Engine!$B14+(1-0.55)*_TECH_Cascade_Engine!$C14))) | D62: =IF(_TECH_Cascade_Engine!$B14="","",IF(AND(_TECH_Cascade_Engine!$E14<>"",_TECH_Cascade_Engine!$E14<_TECH_Dependency_Map!$B$30),MIN((0.65*_TECH_Cascade_Engine!$B14+(1-0.65)*_TECH_Cascade_Engine!$C14),_TECH_Dependency_Map!$B$31),(0.65*_TECH_Cascade_Engine!$B14+(1-0.65)*_TECH_Cascade_Engine!$C14))) | E62: =IF(_TECH_Cascade_Engine!$B14="","",IF(AND(_TECH_Cascade_Engine!$E14<>"",_TECH_Cascade_Engine!$E14<_TECH_Dependency_Map!$B$30),MIN((0.8*_TECH_Cascade_Engine!$B14+(1-0.8)*_TECH_Cascade_Engine!$C14),_TECH_Dependency_Map!$B$31),(0.8*_TECH_Cascade_Engine!$B14+(1-0.8)*_TECH_Cascade_Engine!$C14))) | F62: =IF(_TECH_Cascade_Engine!$B14="","",IF(AND(_TECH_Cascade_Engine!$E14<>"",_TECH_Cascade_Engine!$E14<_TECH_Dependency_Map!$B$30),MIN((0.95*_TECH_Cascade_Engine!$B14+(1-0.95)*_TECH_Cascade_Engine!$C14),_TECH_Dependency_Map!$B$31),(0.95*_TECH_Cascade_Engine!$B14+(1-0.95)*_TECH_Cascade_Engine!$C14)))
A63: =_TECH_Cascade_Engine!A15 -> Sales CRM | B63: =IF(_TECH_Cascade_Engine!$B15="","",IF(AND(_TECH_Cascade_Engine!$E15<>"",_TECH_Cascade_Engine!$E15<_TECH_Dependency_Map!$B$30),MIN((0.4*_TECH_Cascade_Engine!$B15+(1-0.4)*_TECH_Cascade_Engine!$C15),_TECH_Dependency_Map!$B$31),(0.4*_TECH_Cascade_Engine!$B15+(1-0.4)*_TECH_Cascade_Engine!$C15))) | C63: =IF(_TECH_Cascade_Engine!$B15="","",IF(AND(_TECH_Cascade_Engine!$E15<>"",_TECH_Cascade_Engine!$E15<_TECH_Dependency_Map!$B$30),MIN((0.55*_TECH_Cascade_Engine!$B15+(1-0.55)*_TECH_Cascade_Engine!$C15),_TECH_Dependency_Map!$B$31),(0.55*_TECH_Cascade_Engine!$B15+(1-0.55)*_TECH_Cascade_Engine!$C15))) | D63: =IF(_TECH_Cascade_Engine!$B15="","",IF(AND(_TECH_Cascade_Engine!$E15<>"",_TECH_Cascade_Engine!$E15<_TECH_Dependency_Map!$B$30),MIN((0.65*_TECH_Cascade_Engine!$B15+(1-0.65)*_TECH_Cascade_Engine!$C15),_TECH_Dependency_Map!$B$31),(0.65*_TECH_Cascade_Engine!$B15+(1-0.65)*_TECH_Cascade_Engine!$C15))) | E63: =IF(_TECH_Cascade_Engine!$B15="","",IF(AND(_TECH_Cascade_Engine!$E15<>"",_TECH_Cascade_Engine!$E15<_TECH_Dependency_Map!$B$30),MIN((0.8*_TECH_Cascade_Engine!$B15+(1-0.8)*_TECH_Cascade_Engine!$C15),_TECH_Dependency_Map!$B$31),(0.8*_TECH_Cascade_Engine!$B15+(1-0.8)*_TECH_Cascade_Engine!$C15))) | F63: =IF(_TECH_Cascade_Engine!$B15="","",IF(AND(_TECH_Cascade_Engine!$E15<>"",_TECH_Cascade_Engine!$E15<_TECH_Dependency_Map!$B$30),MIN((0.95*_TECH_Cascade_Engine!$B15+(1-0.95)*_TECH_Cascade_Engine!$C15),_TECH_Dependency_Map!$B$31),(0.95*_TECH_Cascade_Engine!$B15+(1-0.95)*_TECH_Cascade_Engine!$C15)))
A64: =_TECH_Cascade_Engine!A16 -> Marketing Comms | B64: =IF(_TECH_Cascade_Engine!$B16="","",IF(AND(_TECH_Cascade_Engine!$E16<>"",_TECH_Cascade_Engine!$E16<_TECH_Dependency_Map!$B$30),MIN((0.4*_TECH_Cascade_Engine!$B16+(1-0.4)*_TECH_Cascade_Engine!$C16),_TECH_Dependency_Map!$B$31),(0.4*_TECH_Cascade_Engine!$B16+(1-0.4)*_TECH_Cascade_Engine!$C16))) | C64: =IF(_TECH_Cascade_Engine!$B16="","",IF(AND(_TECH_Cascade_Engine!$E16<>"",_TECH_Cascade_Engine!$E16<_TECH_Dependency_Map!$B$30),MIN((0.55*_TECH_Cascade_Engine!$B16+(1-0.55)*_TECH_Cascade_Engine!$C16),_TECH_Dependency_Map!$B$31),(0.55*_TECH_Cascade_Engine!$B16+(1-0.55)*_TECH_Cascade_Engine!$C16))) | D64: =IF(_TECH_Cascade_Engine!$B16="","",IF(AND(_TECH_Cascade_Engine!$E16<>"",_TECH_Cascade_Engine!$E16<_TECH_Dependency_Map!$B$30),MIN((0.65*_TECH_Cascade_Engine!$B16+(1-0.65)*_TECH_Cascade_Engine!$C16),_TECH_Dependency_Map!$B$31),(0.65*_TECH_Cascade_Engine!$B16+(1-0.65)*_TECH_Cascade_Engine!$C16))) | E64: =IF(_TECH_Cascade_Engine!$B16="","",IF(AND(_TECH_Cascade_Engine!$E16<>"",_TECH_Cascade_Engine!$E16<_TECH_Dependency_Map!$B$30),MIN((0.8*_TECH_Cascade_Engine!$B16+(1-0.8)*_TECH_Cascade_Engine!$C16),_TECH_Dependency_Map!$B$31),(0.8*_TECH_Cascade_Engine!$B16+(1-0.8)*_TECH_Cascade_Engine!$C16))) | F64: =IF(_TECH_Cascade_Engine!$B16="","",IF(AND(_TECH_Cascade_Engine!$E16<>"",_TECH_Cascade_Engine!$E16<_TECH_Dependency_Map!$B$30),MIN((0.95*_TECH_Cascade_Engine!$B16+(1-0.95)*_TECH_Cascade_Engine!$C16),_TECH_Dependency_Map!$B$31),(0.95*_TECH_Cascade_Engine!$B16+(1-0.95)*_TECH_Cascade_Engine!$C16)))
... A69: =_TECH_Cascade_Engine!A21 -> Quality Portfolio | B69: =IF(_TECH_Cascade_Engine!$B21="","",IF(AND(_TECH_Cascade_Engine!$E21<>"",_TECH_Cascade_Engine!$E21<_TECH_Dependency_Map!$B$30),MIN((0.4*_TECH_Cascade_Engine!$B21+(1-0.4)*_TECH_Cascade_Engine!$C21),_TECH_Dependency_Map!$B$31),(0.4*_TECH_Cascade_Engine!$B21+(1-0.4)*_TECH_Cascade_Engine!$C21))) | C69: =IF(_TECH_Cascade_Engine!$B21="","",IF(AND(_TECH_Cascade_Engine!$E21<>"",_TECH_Cascade_Engine!$E21<_TECH_Dependency_Map!$B$30),MIN((0.55*_TECH_Cascade_Engine!$B21+(1-0.55)*_TECH_Cascade_Engine!$C21),_TECH_Dependency_Map!$B$31),(0.55*_TECH_Cascade_Engine!$B21+(1-0.55)*_TECH_Cascade_Engine!$C21))) | D69: =IF(_TECH_Cascade_Engine!$B21="","",IF(AND(_TECH_Cascade_Engine!$E21<>"",_TECH_Cascade_Engine!$E21<_TECH_Dependency_Map!$B$30),MIN((0.65*_TECH_Cascade_Engine!$B21+(1-0.65)*_TECH_Cascade_Engine!$C21),_TECH_Dependency_Map!$B$31),(0.65*_TECH_Cascade_Engine!$B21+(1-0.65)*_TECH_Cascade_Engine!$C21))) | E69: =IF(_TECH_Cascade_Engine!$B21="","",IF(AND(_TECH_Cascade_Engine!$E21<>"",_TECH_Cascade_Engine!$E21<_TECH_Dependency_Map!$B$30),MIN((0.8*_TECH_Cascade_Engine!$B21+(1-0.8)*_TECH_Cascade_Engine!$C21),_TECH_Dependency_Map!$B$31),(0.8*_TECH_Cascade_Engine!$B21+(1-0.8)*_TECH_Cascade_Engine!$C21))) | F69: =IF(_TECH_Cascade_Engine!$B21="","",IF(AND(_TECH_Cascade_Engine!$E21<>"",_TECH_Cascade_Engine!$E21<_TECH_Dependency_Map!$B$30),MIN((0.95*_TECH_Cascade_Engine!$B21+(1-0.95)*_TECH_Cascade_Engine!$C21),_TECH_Dependency_Map!$B$31),(0.95*_TECH_Cascade_Engine!$B21+(1-0.95)*_TECH_Cascade_Engine!$C21)))
A70: Org resilience | B70: =IFERROR(_TECH_Dependency_Map!$B$33*AVERAGE(B53:B69)+(1-_TECH_Dependency_Map!$B$33)*MIN(B53:B69),"") | C70: =IFERROR(_TECH_Dependency_Map!$B$33*AVERAGE(C53:C69)+(1-_TECH_Dependency_Map!$B$33)*MIN(C53:C69),"") | D70: =IFERROR(_TECH_Dependency_Map!$B$33*AVERAGE(D53:D69)+(1-_TECH_Dependency_Map!$B$33)*MIN(D53:D69),"") | E70: =IFERROR(_TECH_Dependency_Map!$B$33*AVERAGE(E53:E69)+(1-_TECH_Dependency_Map!$B$33)*MIN(E53:E69),"") | F70: =IFERROR(_TECH_Dependency_Map!$B$33*AVERAGE(F53:F69)+(1-_TECH_Dependency_Map!$B$33)*MIN(F53:F69),"")
A71: Current alpha = '_TECH_Dependency_Map'!$B$27 (edit in _TECH_Dependency_Map)
A73: Reading the stress test: if the 'Org peak' row in section 1 climbs steeply from severity 1 to 5 while base maturity is decent, severity is overpowering maturity — lower scen_factor_cap or gamma. If beta barely moves results, cascades are immaterial for this profile; if it dominates, recalibrate the matrix.

Sheet Scoring Guide
A1: Scoring Guide
A2: Use 0-5 scoring for each question. The model is designed to capture evidence, crisis impact, and improvement actions.
A4: Score | B4: Maturity label | C4: Criteria
A5: 0 | B5: Absent / unknown | C5: No documented process, owner, data, evidence, or reliable practice exists. High crisis exposure.
A6: 1 | B6: Ad hoc | C6: Activity exists informally, depends on individuals, and is not consistently documented, measured, or controlled.
A7: 2 | B7: Basic / partial | C7: Some process, document, or system exists, but coverage is incomplete, inconsistent, or not crisis-tested.
A8: 3 | B8: Defined | C8: Process is documented, owned, used in normal operations, and supported by basic metrics or evidence.
A9: 4 | B9: Managed / tested | C9: Process is measured, reviewed, integrated with related domains, and periodically tested against disruption scenarios.
A10: 5 | B10: Optimized / resilient | C10: Process is automated where practical, continuously improved, stress-tested, and demonstrably supports crisis resilience.
A11: N/A | B11: Not applicable | C11: Use only if the question is genuinely not applicable, not when evidence is missing.
A13: Weight | B13: Meaning | C13: Use
A14: 1 | B14: Low | C14: Useful context or low impact on crisis resilience.
A15: 2 | B15: Moderate | C15: Relevant to one domain but limited enterprise-wide impact.
A16: 3 | B16: Important | C16: Meaningful impact on operational continuity or decision quality.
A17: 4 | B17: High | C17: Strong impact on continuity, revenue, safety, legal, cyber, or supplier resilience.
A18: 5 | B18: Critical | C18: Failure may materially affect people safety, cash, operations, compliance, delivery, or survival.
A20: Risk level | B20: Score range | C20: Interpretation
A21: Critical | B21: 0-1 | C21: Absent or ad hoc capability. Immediate crisis-management exposure.
A22: High | B22: 2 | C22: Partial capability. Significant gaps likely during disruption.
A23: Medium | B23: 3 | C23: Defined capability. Usable but not yet strongly tested or optimized.
A24: Low | B24: 4 | C24: Managed and tested capability. Some improvements remain.
A25: Resilient | B25: 5 | C25: Strong, tested and continuously improved capability.
A27: Spider dashboard additions
A28: Common domain spider | B28: Uses Dashboard maturity 0-5 per domain. | C28: Shows which crisis domains are structurally weak.
A29: Subarea spider | B29: Uses each tab's Subdomain column and Score 0-5 / N/A. | C29: Shows weaknesses inside each assessment area.
A30: Digitalization | B30: Calculated from scores weighted by Digitalization relevance in column W. | C30: Measures implementation of cloud, systems, data, automation and digital tools.
A31: Resilience | B31: Calculated from scores weighted by Resilience relevance in column X. | C31: Measures ability to withstand and recover from crisis scenarios.
A32: Process Maturity | B32: Calculated from scores weighted by Process maturity relevance in column Y. | C32: Measures whether processes are owned, documented, measured and repeatable.
A33: Relevance weights | B33: 0 = not relevant; 5 = strongly relevant. | C33: Weights can be adjusted manually for sector-specific diagnostics.
A34: Important note | B34: Charts update after scores are entered and the workbook recalculates. | C34: Use Excel recalculation if charts do not immediately refresh.
A36: Recommendation engine and WSJF logic
A37: Recommendation Matrix | B37: Hidden/admin vocabulary | C37: Contains one row per questionnaire item and score-specific next-level recommendations for scores 0–5.
A38: Executive Recommendations | B38: Visible output | C38: Pulls all entered scores from domain tabs and produces concise recommendations, priority, complexity and WSJF ranking.
A39: Priority score | B39: 1–5 | C39: Calculated from maturity gap, question weight and resilience relevance.
A40: Complexity / job size | B40: 1–5 | C40: Estimated implementation difficulty. Higher values reduce WSJF.
A41: WSJF | B41: (Business value + time criticality + risk reduction + opportunity enablement) / job size | C41: Higher WSJF means a better candidate for earlier execution.
A42: How to use | B42: Filter Show = Yes | C42: Then sort by Rank ascending or WSJF descending. Score 5 items are marked Maintain.
A43: Note | B43: Formula-driven | C43: The executive sheet updates after scores are entered or changed in domain tabs.
A46: Risk Engine and Risk Summary
A47: Component | B47: Description
A48: Risk Library | B48: Hidden admin vocabulary. Each questionnaire item has score-specific risk statements, risk treatments and complexity values.
A49: Risk Summary | B49: Visible executive risk register. It pulls current scores from domain tabs and converts low maturity into active risks.
A50: Risk logic | B50: Lower maturity score means higher likelihood. Impact is calculated from question weight, resilience relevance and process maturity relevance.
A51: Risk score | B51: Likelihood x Impact, both on a 1-5 scale. Maximum risk score is 25.
A52: WSJF | B52: (Business value + Time criticality + Risk reduction + Opportunity enablement) / Complexity. Sort by WSJF descending or Rank ascending.
A53: Recommended use | B53: Filter Show = Yes, review Critical and High risks first, assign owners, due dates and risk treatment decisions.
A55: Crisis scenario logic and strategy recommendation engine
A56: Crisis Simulator | B56: Visible sheet where the assessor selects a crisis scenario and severity. Domain exposure is recalculated using hidden scenario-domain multipliers.
A57: _TECH_Crisis_Model | B57: Very hidden technical sheet with scenario, domain, base multiplier, severity-adjusted multiplier, rationale and mitigation theme.
A58: Risk Summary update | B58: Added scenario-adjusted risk score and scenario-adjusted WSJF so active risks can be interpreted under the selected crisis.
A59: Executive Recommendations update | B59: Added scenario-adjusted WSJF and crisis rationale, so recommended actions can be sorted under the selected crisis mode.
A60: Strategy Selection | B60: Visible strategy engine that scores strategies by crisis fit, domain gap fit, active risk fit and digitalization/resilience/process gaps.
A61: _TECH_Strategy_Library | B61: Very hidden technical sheet with strategy definitions, scenario multipliers, domain weights, owners, timelines and KPIs.
A62: Interpretation rule | B62: Do not treat the top strategy as an automatic decision. Use it as a decision-support output that should be validated by management and domain SMEs.
A65: Initiative library and roadmap engine
A66: Component | B66: Description
A67: _TECH_Initiative_Library | B67: Hidden technical library. Each initiative is mapped to a domain, subdomain, strategy, risk category, crisis scenario, questions, owner, dependencies and KPIs.
A68: Connection to Recommendation Matrix | B68: The initiative engine counts active recommendations from Executive Recommendations by domain and subdomain.
A69: Connection to Risk Library | B69: The initiative engine counts active risks from Risk Summary by domain and subdomain and uses them in the Risk Reduction component of WSJF.
A70: Connection to Strategy Selection | B70: Each initiative is mapped to one strategy. The current strategy rank and score influence Business Value, Time Criticality and Opportunity Enablement.
A71: Connection to Crisis Simulator | B71: The selected crisis scenario and severity drive crisis multipliers, which increase initiative urgency when a domain is exposed to the selected crisis.
A72: WSJF formula | B72: WSJF = (Business Value + Time Criticality + Risk Reduction + Opportunity Enablement) / Complexity.
A73: Roadmap wave | B73: Initiatives are ranked by WSJF and grouped into 0-90 days, 3-6 months, 6-12 months and 12+ months.
A76: Latest workbook scope update
A77: Sheet / item | B77: Purpose
A78: Company Profile | B78: Captures organization context, assessment boundaries, target scores and roadmap start date.
A79: Quality Control | B79: Checks missing or invalid scores, missing comments for critical/high risks, missing owners and missing linked recommendations.
A80: Gantt Roadmap | B80: Converts the initiative library into a time-based implementation view with roadmap waves and month-level bars.
A81: Standards per Question | B81: Maps each question to standards, frameworks, evidence, score criteria, crisis tags and metric relevance.
A82: Out of scope by design | B82: LLM export, LLM-generated narrative and financial modeling are intentionally excluded from this workbook version.
A85: Industry templates and improved scoring logic
A86: Industry template | B86: Selected in Company Profile. It adjusts domain weight, target maturity, criticality, initiative priority, strategy fit and red-line controls.
A87: Evidence confidence | B87: Question-level confidence factor. High = 1.00, Medium = 0.90, Low = 0.80, Not assessed = 0.65. Blank uses the default from Company Profile.
A88: Assessor confidence | B88: Separates verified findings from opinions. It uses the same confidence factors and also defaults from Company Profile if blank.
A89: Confidence-adjusted score | B89: Raw score multiplied by evidence and assessor confidence. This avoids over-rating weakly evidenced answers.
A90: Industry target maturity | B90: Expected maturity level for the selected industry. The same raw score can be acceptable in one industry and a serious gap in another.
A91: Red-line threshold | B91: Minimum viable maturity for the selected industry. Breaches are highlighted in Improved Scoring Model and Quality Control.
A92: Industry-adjusted ranking | B92: Strategy, recommendation, risk and initiative ranking now include industry multipliers while preserving the original formulas and base scores.
A94: Gantt and Heatmap Upgrade
A95: Gantt Roadmap now includes month-level capacity load, overload flags, decision-required flags, dependencies, KPIs, owner roles, status dropdown and a top-priority initiative timeline.
A96: Heatmaps tab adds domain-by-crisis exposure, domain-by-risk-category score, top initiative timeline and monthly capacity heatmaps.

Sheet Company Profile
A1: Company Profile and Assessment Context
A2: Use this sheet once per organization. It captures the context that influences crisis exposure, strategy relevance and the Gantt roadmap. LLM and financial modeling are intentionally out of scope for this workbook version.
A4: Profile field | B4: Value / input | C4: Guidance | D4: Used by | F4: How this sheet is used
A5: Organization name | C5: Legal or commercial name used in the assessment. | D5: Dashboard / executive summary | F5: 1. Define organization context and assessment boundaries. 2. Use Crisis Simulator for active scenario and severity. 3. Use Assessment date as the roadmap start date. 4. Use target scores to calibrate expected maturity level. 5. Keep LLM and financial analysis outside this workbook version.
A6: Assessment date | B6: 46179 | C6: Baseline date. Gantt roadmap starts from this date unless changed. | D6: Gantt Roadmap
A7: Assessment owner | C7: Person responsible for coordinating the assessment. | D7: Quality Control
A8: Executive sponsor | C8: Senior owner who accepts priorities and crisis roadmap. | D8: Roadmap governance
A9: Industry | B9: IT Services | C9: Primary industry or sector. | D9: Strategy logic
A10: Sub-industry / segment | C10: More specific segment, e.g. manufacturing, SaaS, retail, healthcare. | D10: Strategy logic
A11: Headquarters country | C11: Country where the main legal or management entity is located. | D11: Risk context
A12: Operating countries / regions | C12: List countries, regions and key cities where the company operates. | D12: Geographical exposure
A13: Ownership type | C13: Private, public, state-owned, family-owned, PE-backed, NGO or other. | D13: Governance context
A14: Legal entities | C14: Main legal entities and subsidiaries. | D14: Legal / continuity context
A15: Employee count | C15: Total employees and contractors. | D15: HR / continuity logic
A16: Revenue size band | C16: Annual revenue band. | D16: Financial context, not calculation
A17: Operating model | C17: Centralized, decentralized, hub-and-spoke, remote-first, multi-site, franchise, hybrid. | D17: Crisis exposure
A18: Business model | C18: B2B, B2C, B2B2C, marketplace, subscription, project-based, manufacturing, distribution. | D18: GTM / resilience logic
A19: Critical products / services | C19: Products or services that must continue during disruption. | D19: Business continuity
A20: ICP / key customer segments | C20: Ideal customer profiles and most important customer groups. | D20: GTM / revenue resilience
A21: Top markets by revenue | C21: Countries, regions or customer segments with highest revenue share. | D21: Revenue concentration
... A28: Cloud and infrastructure model | C28: On-premise, public cloud, private cloud, hybrid, multi-cloud, SaaS-first. | D28: IT / DR strategy
A29: Primary crisis scenario to test | B29: ='Crisis Simulator'!$B$4 -> War / security crisis | C29: Active scenario is selected in Crisis Simulator. | D29: Crisis Simulator
A30: Scenario severity 1-5 | B30: ='Crisis Simulator'!$B$5 -> 3 | C30: Active scenario severity is selected in Crisis Simulator. | D30: Crisis Simulator
A31: Target process maturity 0-5 | B31: 4 | C31: Target level for process maturity. | D31: Gap analysis
A32: Target digitalization 0-5 | B32: 4 | C32: Target level for implementation of digital technologies. | D32: Gap analysis
A33: Target resilience 0-5 | B33: 4 | C33: Target level for resilience against relevant risks. | D33: Gap analysis
A34: Assessment cadence | C34: Quarterly, semi-annual, annual, or crisis-triggered review. | D34: Governance
A35: Risk appetite statement | C35: Short statement explaining acceptable residual risk. | D35: Risk treatment
A36: Key assumptions / comments | C36: Context notes, limitations, excluded scope or special assessment assumptions. | D36: All outputs
A38: Industry Template and Improved Scoring Logic
A39: Selected industry template | B39: =B9 -> IT Services | C39: Used as lookup key for domain weights, targets, criticality and recommendations.
A40: Default evidence confidence | B40: Medium | C40: Used when question-level evidence confidence is blank.
A41: Default assessor confidence | B41: Medium | C41: Used when question-level assessor confidence is blank.
A42: Template domains | B42: =COUNTIF(_TECH_Industry_Templates!$A:$A,$B$9) -> 17 | C42: Should equal 17 for a valid industry template.
A43: Average target maturity | B43: =IFERROR(ROUND(AVERAGEIFS(_TECH_Industry_Templates!$D:$D,_TECH_Industry_Templates!$A:$A,$B$9),2),"") -> 3.54 | C43: Average expected maturity for selected industry.
A44: Average criticality multiplier | B44: =IFERROR(ROUND(AVERAGEIFS(_TECH_Industry_Templates!$E:$E,_TECH_Industry_Templates!$A:$A,$B$9),2),"") -> 1.05 | C44: Higher value means industry makes weaknesses more material.
A45: Critical systems | B45: =IFERROR(INDEX(_TECH_Industry_Templates!$H:$H,MATCH($B$9,_TECH_Industry_Templates!$A:$A,0)),"") -> CRM; HRMS; project/portfolio tools; time tracking; knowledge base; finance system; cloud collaboration; IAM; BI dashboards | C45: Typical systems that should be treated as critical for this industry.
A46: Red-line controls | B46: =IFERROR(INDEX(_TECH_Industry_Templates!$I:$I,MATCH($B$9,_TECH_Industry_Templates!$A:$A,0)),"") -> critical role backups; secure remote work; MFA; delivery continuity; project knowledge base; customer communication path | C46: Minimum controls that should not be missing even if average maturity looks acceptable.
A47: Preferred strategy logic | B47: =IFERROR(INDEX(_TECH_Industry_Templates!$L:$L,MATCH($B$9,_TECH_Industry_Templates!$A:$A,0)),"") -> Workforce Resilience Strategy; Digital Foundation Strategy; Business Continuity and Resilience Strategy | C47: Strategies that receive extra relevance for this industry.
A49: Extended Company Context Inputs (closed answers only)
A50: Revenue model | B50: Project-based | C50: Primary revenue model used by the company. | D50: Risk, strategy and initiative logic
A51: Secondary revenue model | B51: Hybrid | C51: Secondary or supporting monetization model. | D51: Revenue diversification logic
A52: Revenue recurrence | B52: Mixed recurring and project-based | C52: Revenue stability profile. | D52: Crisis impact and revenue risk
A53: Primary sales motion | B53: Direct enterprise sales | C53: Dominant sales motion. | D53: GTM and CRM strategy
A54: Customer concentration: top 1 client revenue share | B54: 10-25% | C54: Estimated revenue share of the largest customer. | D54: Customer concentration risk
A55: Customer concentration: top 5 clients revenue share | B55: 25-50% | C55: Estimated revenue share of top 5 customers. | D55: Customer concentration risk
A56: Customer concentration: top 10 clients revenue share | B56: 50-75% | C56: Estimated revenue share of top 10 customers. | D56: Revenue diversification risk
A57: Supplier concentration: top 1 supplier dependency | B57: 10-25% | C57: Estimated dependency on largest supplier/vendor/input. | D57: Supplier risk
A58: Supplier concentration: top 5 supplier dependency | B58: 25-50% | C58: Estimated dependency on top 5 suppliers/vendors/inputs. | D58: Supply chain risk
A59: Critical supplier substitutability | B59: Partial alternatives exist | C59: Availability of alternatives for critical suppliers. | D59: Supply chain resilience
A61: Business Criticality of Locations
A62: Location type | B62: Business criticality | C62: Disruption impact | D62: Continuity option | E62: Used by
A63: HQ | B63: High | C63: Major degradation | D63: Remote / distributed alternative | E63: Location and physical resilience logic
A64: Production site | B64: Not applicable | C64: No material impact | D64: Not applicable | E64: Location and physical resilience logic
A65: Warehouse | B65: Not applicable | C65: No material impact | D65: Not applicable | E65: Location and physical resilience logic
A66: Data center / core cloud region | B66: Critical | C66: Severe business interruption | D66: Fully redundant / alternative available | E66: Location and physical resilience logic
A67: Call center / customer support center | B67: Medium | C67: Moderate degradation | D67: Remote / distributed alternative | E67: Location and physical resilience logic
A68: R&D / engineering center | B68: High | C68: Major degradation | D68: Remote / distributed alternative | E68: Location and physical resilience logic
A69: Sales office | B69: Medium | C69: Moderate degradation | D69: Remote / distributed alternative | E69: Location and physical resilience logic
A70: Retail / service branch | B70: Not applicable | C70: No material impact | D70: Not applicable | E70: Location and physical resilience logic
A72: Workforce Distribution
A73: Countries with workforce | B73: 2-3 countries | C73: Workforce country footprint. | D73: Workforce/geographic concentration
A74: Largest country workforce share | B74: 50-75% | C74: Estimated share of workforce in largest country. | D74: Workforce concentration risk
A75: Largest city/location workforce share | B75: 25-50% | C75: Estimated share of workforce in largest city/site. | D75: Location concentration risk
A76: Remote work readiness | B76: Hybrid-ready for most roles | C76: Ability to continue work remotely. | D76: Pandemic/war/infrastructure resilience
A77: Cross-border mobility / relocation support | B77: Ad hoc relocation support | C77: Ability to relocate or support distributed workforce during crisis. | D77: Workforce continuity
A79: Critical Process List (select top processes)
A80: Critical process #1 | B80: Order-to-cash | C80: Select one of the most business-critical processes. | D80: Risk, continuity and roadmap logic
A81: Critical process #2 | B81: Customer support | C81: Select one of the most business-critical processes. | D81: Risk, continuity and roadmap logic
A82: Critical process #3 | B82: IT operations | C82: Select one of the most business-critical processes. | D82: Risk, continuity and roadmap logic
A83: Critical process #4 | B83: Data reporting and BI | C83: Select one of the most business-critical processes. | D83: Risk, continuity and roadmap logic
A84: Critical process #5 | B84: Finance closing | C84: Select one of the most business-critical processes. | D84: Risk, continuity and roadmap logic
A86: Critical Product / Service List (select top items)
A87: Critical product/service #1 | B87: Custom project delivery | C87: Select one of the most critical products or services. | D87: Revenue and continuity logic
A88: Critical product/service #2 | B88: Digital platform | C88: Select one of the most critical products or services. | D88: Revenue and continuity logic
A89: Critical product/service #3 | B89: Professional services | C89: Select one of the most critical products or services. | D89: Revenue and continuity logic
A90: Critical product/service #4 | B90: Data / AI service | C90: Select one of the most critical products or services. | D90: Revenue and continuity logic
A91: Critical product/service #5 | B91: Other / not applicable | C91: Select one of the most critical products or services. | D91: Revenue and continuity logic
A93: Crisis History
A94: Experienced crisis | B94: Impact level | C94: Guidance | D94: Used by
A95: Pandemic | B95: Medium impact | C95: Select a crisis the organization has already experienced and its observed impact. | D95: Calibration of scenario logic
A96: War / geopolitical escalation | B96: High impact | C96: Select a crisis the organization has already experienced and its observed impact. | D96: Calibration of scenario logic
A97: Cyberattack / ransomware | B97: Low impact | C97: Select a crisis the organization has already experienced and its observed impact. | D97: Calibration of scenario logic
A98: Supply chain disruption | B98: Medium impact | C98: Select a crisis the organization has already experienced and its observed impact. | D98: Calibration of scenario logic
A99: None experienced | B99: No impact | C99: Select a crisis the organization has already experienced and its observed impact. | D99: Calibration of scenario logic

Sheet Crisis Scenarios
A1: Crisis Scenarios Taxonomy
A2: Use this sheet to interpret questionnaire results by crisis type and to design stress tests.
A4: Crisis type | B4: Typical triggers | C4: Key impact dimensions | D4: Most affected domains | E4: Example evidence to collect
A5: War / security crisis | B5: Military activity, shelling, curfews, checkpoints, occupation risk, civil unrest | C5: People safety; site availability; logistics; workforce location; customer confidence | D5: Physical Safety; HR Workforce; Delivery Ops; Supply Chain; IT Cloud DR | E5: Site security plan; employee location map; evacuation plan; alternative delivery model
A6: Physical site loss | B6: Fire, flood, explosion, structural damage, lease loss, access restriction | C6: Safety; production; delivery; data center; office continuity | D6: Physical Safety; Manufacturing MES; Delivery Ops; IT Cloud DR | E6: Site BIA; insurance; alternate site plan; recovery sequence
A7: Cyberattack / ransomware | B7: Credential compromise, malware, ransomware, supplier breach, BEC | C7: Data loss; system outage; financial fraud; reputation; regulatory exposure | D7: Cyber Privacy; IT Cloud DR; Business Systems; Legal Risk; Marketing Comms | E7: IR plan; backup restore tests; MFA coverage; ransomware tabletop
A8: Cloud / SaaS outage | B8: Provider outage, region failure, account lockout, identity failure, DNS issue | C8: System downtime; data access; remote work; customer service | D8: IT Cloud DR; Business Systems; Data BI AI; Sales CRM | E8: Cloud architecture; RTO/RPO; SaaS backup; failover tests
A9: Supplier / logistics disruption | B9: Supplier insolvency, border closure, port congestion, sanctions, transport failure | C9: Inventory; production; delivery; customer commitments; cost | D9: Supply Chain; Manufacturing MES; Finance Procurement; Delivery Ops | E9: Supplier map; alternative suppliers; safety stock; route alternatives
A10: Energy / utilities outage | B10: Grid outage, fuel shortage, water failure, heating/cooling failure, telecom outage | C10: Site operations; production; IT; employee safety | D10: Physical Safety; Manufacturing MES; IT Cloud DR; Delivery Ops | E10: Generator tests; UPS capacity; fuel plan; utility dependency map
A11: Financial liquidity crisis | B11: Revenue decline, delayed receivables, currency shock, financing restriction | C11: Cash; payroll; supplier payments; investment cuts | D11: Finance Procurement; Strategy GTM; Sales CRM; Governance Crisis | E11: Cash-flow forecast; stress tests; liquidity buffer; payment priority list
A12: Demand shock | B12: Customer budget cuts, market collapse, competitor move, crisis-driven demand shift | C12: Revenue; pipeline; pricing; capacity; offering relevance | D12: Strategy GTM; Sales CRM; Marketing Comms; Finance Procurement | E12: Pipeline scenarios; ICP analysis; churn dashboard; pricing policy
A13: Pandemic / health crisis | B13: Infectious disease, mass absenteeism, travel restrictions, office closure | C13: Workforce availability; remote work; safety; customer service | D13: HR Workforce; Physical Safety; IT Cloud DR; Delivery Ops | E13: Remote work readiness; absence monitoring; health protocols; minimum staffing
A14: Regulatory / legal shock | B14: New law, sanctions, audit, license loss, data protection issue | C14: Compliance; contracts; market access; penalties; reputation | D14: Legal Risk; Data BI AI; Cyber Privacy; Finance Procurement | E14: Compliance register; contract register; RoPA; legal escalation plan
A15: Reputation crisis | B15: Public complaint, service failure, safety incident, data breach, misinformation | C15: Trust; sales; customer retention; regulatory scrutiny | D15: Marketing Comms; Sales CRM; Legal Risk; Cyber Privacy | E15: Crisis comms templates; media monitoring; customer notification rules
A16: Natural disaster / climate event | B16: Flood, storm, extreme heat/cold, earthquake, wildfire | C16: Site safety; logistics; utilities; employee availability | D16: Physical Safety; Supply Chain; HR Workforce; Delivery Ops | E16: Site risk assessment; emergency supplies; alternate routes; employee notification

Sheet Industry Template Summary
A1: Industry Template Summary
A2: Visible explanation of the selected industry template. The hidden template sheet remains editable for calibration.
A3: Selected industry | B3: ='Company Profile'!$B$9 -> IT Services
A5: Domain | B5: Domain weight | C5: Target maturity | D5: Criticality multiplier | E5: Minimum threshold | F5: Initiative multiplier | G5: Crisis exposure | H5: Critical systems | I5: Red-line controls | J5: Preferred strategies
A6: Company Geography | B6: =IFERROR(SUMIFS(_TECH_Industry_Templates!$C:$C,_TECH_Industry_Templates!$A:$A,'Company Profile'!$B$9,_TECH_Industry_Templates!$B:$B,$A6),"") -> 3 | C6: =IFERROR(SUMIFS(_TECH_Industry_Templates!$D:$D,_TECH_Industry_Templates!$A:$A,'Company Profile'!$B$9,_TECH_Industry_Templates!$B:$B,$A6),"") -> 3.5 | D6: =IFERROR(SUMIFS(_TECH_Industry_Templates!$E:$E,_TECH_Industry_Templates!$A:$A,'Company Profile'!$B$9,_TECH_Industry_Templates!$B:$B,$A6),"") -> 1 | E6: =IFERROR(SUMIFS(_TECH_Industry_Templates!$F:$F,_TECH_Industry_Templates!$A:$A,'Company Profile'!$B$9,_TECH_Industry_Templates!$B:$B,$A6),"") -> 2.5 | F6: =IFERROR(SUMIFS(_TECH_Industry_Templates!$J:$J,_TECH_Industry_Templates!$A:$A,'Company Profile'!$B$9,_TECH_Industry_Templates!$B:$B,$A6),"") -> 1 | G6: =IFERROR(INDEX(_TECH_Industry_Templates!$G:$G,MATCH(1,INDEX((_TECH_Industry_Templates!$A:$A='Company Profile'!$B$9)*(_TECH_Industry_Templates!$B:$B=$A6),0),0)),"") -> Low | H6: =IFERROR(INDEX(_TECH_Industry_Templates!$H:$H,MATCH(1,INDEX((_TECH_Industry_Templates!$A:$A='Company Profile'!$B$9)*(_TECH_Industry_Templates!$B:$B=$A6),0),0)),"") -> CRM; HRMS; project/portfolio tools; time tracking; knowledge base; finance system; cloud collaboration; IAM; BI dashboards | I6: =IFERROR(INDEX(_TECH_Industry_Templates!$I:$I,MATCH(1,INDEX((_TECH_Industry_Templates!$A:$A='Company Profile'!$B$9)*(_TECH_Industry_Templates!$B:$B=$A6),0),0)),"") -> critical role backups; secure remote work; MFA; delivery continuity; project knowledge base; customer communication path | J6: =IFERROR(INDEX(_TECH_Industry_Templates!$L:$L,MATCH(1,INDEX((_TECH_Industry_Templates!$A:$A='Company Profile'!$B$9)*(_TECH_Industry_Templates!$B:$B=$A6),0),0)),"") -> Workforce Resilience Strategy; Digital Foundation Strategy; Business Continuity and Resilience Strategy
A7: Strategy GTM | B7: =IFERROR(SUMIFS(_TECH_Industry_Templates!$C:$C,_TECH_Industry_Templates!$A:$A,'Company Profile'!$B$9,_TECH_Industry_Templates!$B:$B,$A7),"") -> 3 | C7: =IFERROR(SUMIFS(_TECH_Industry_Templates!$D:$D,_TECH_Industry_Templates!$A:$A,'Company Profile'!$B$9,_TECH_Industry_Templates!$B:$B,$A7),"") -> 3.5 | D7: =IFERROR(SUMIFS(_TECH_Industry_Templates!$E:$E,_TECH_Industry_Templates!$A:$A,'Company Profile'!$B$9,_TECH_Industry_Templates!$B:$B,$A7),"") -> 1 | E7: =IFERROR(SUMIFS(_TECH_Industry_Templates!$F:$F,_TECH_Industry_Templates!$A:$A,'Company Profile'!$B$9,_TECH_Industry_Templates!$B:$B,$A7),"") -> 2.5 | F7: =IFERROR(SUMIFS(_TECH_Industry_Templates!$J:$J,_TECH_Industry_Templates!$A:$A,'Company Profile'!$B$9,_TECH_Industry_Templates!$B:$B,$A7),"") -> 1 | G7: =IFERROR(INDEX(_TECH_Industry_Templates!$G:$G,MATCH(1,INDEX((_TECH_Industry_Templates!$A:$A='Company Profile'!$B$9)*(_TECH_Industry_Templates!$B:$B=$A7),0),0)),"") -> Low | H7: =IFERROR(INDEX(_TECH_Industry_Templates!$H:$H,MATCH(1,INDEX((_TECH_Industry_Templates!$A:$A='Company Profile'!$B$9)*(_TECH_Industry_Templates!$B:$B=$A7),0),0)),"") -> CRM; HRMS; project/portfolio tools; time tracking; knowledge base; finance system; cloud collaboration; IAM; BI dashboards | I7: =IFERROR(INDEX(_TECH_Industry_Templates!$I:$I,MATCH(1,INDEX((_TECH_Industry_Templates!$A:$A='Company Profile'!$B$9)*(_TECH_Industry_Templates!$B:$B=$A7),0),0)),"") -> critical role backups; secure remote work; MFA; delivery continuity; project knowledge base; customer communication path | J7: =IFERROR(INDEX(_TECH_Industry_Templates!$L:$L,MATCH(1,INDEX((_TECH_Industry_Templates!$A:$A='Company Profile'!$B$9)*(_TECH_Industry_Templates!$B:$B=$A7),0),0)),"") -> Workforce Resilience Strategy; Digital Foundation Strategy; Business Continuity and Resilience Strategy
A8: Governance Crisis | B8: =IFERROR(SUMIFS(_TECH_Industry_Templates!$C:$C,_TECH_Industry_Templates!$A:$A,'Company Profile'!$B$9,_TECH_Industry_Templates!$B:$B,$A8),"") -> 3 | C8: =IFERROR(SUMIFS(_TECH_Industry_Templates!$D:$D,_TECH_Industry_Templates!$A:$A,'Company Profile'!$B$9,_TECH_Industry_Templates!$B:$B,$A8),"") -> 4 | D8: =IFERROR(SUMIFS(_TECH_Industry_Templates!$E:$E,_TECH_Industry_Templates!$A:$A,'Company Profile'!$B$9,_TECH_Industry_Templates!$B:$B,$A8),"") -> 1.15 | E8: =IFERROR(SUMIFS(_TECH_Industry_Templates!$F:$F,_TECH_Industry_Templates!$A:$A,'Company Profile'!$B$9,_TECH_Industry_Templates!$B:$B,$A8),"") -> 3 | F8: =IFERROR(SUMIFS(_TECH_Industry_Templates!$J:$J,_TECH_Industry_Templates!$A:$A,'Company Profile'!$B$9,_TECH_Industry_Templates!$B:$B,$A8),"") -> 1.1 | G8: =IFERROR(INDEX(_TECH_Industry_Templates!$G:$G,MATCH(1,INDEX((_TECH_Industry_Templates!$A:$A='Company Profile'!$B$9)*(_TECH_Industry_Templates!$B:$B=$A8),0),0)),"") -> Medium | H8: =IFERROR(INDEX(_TECH_Industry_Templates!$H:$H,MATCH(1,INDEX((_TECH_Industry_Templates!$A:$A='Company Profile'!$B$9)*(_TECH_Industry_Templates!$B:$B=$A8),0),0)),"") -> CRM; HRMS; project/portfolio tools; time tracking; knowledge base; finance system; cloud collaboration; IAM; BI dashboards | I8: =IFERROR(INDEX(_TECH_Industry_Templates!$I:$I,MATCH(1,INDEX((_TECH_Industry_Templates!$A:$A='Company Profile'!$B$9)*(_TECH_Industry_Templates!$B:$B=$A8),0),0)),"") -> critical role backups; secure remote work; MFA; delivery continuity; project knowledge base; customer communication path | J8: =IFERROR(INDEX(_TECH_Industry_Templates!$L:$L,MATCH(1,INDEX((_TECH_Industry_Templates!$A:$A='Company Profile'!$B$9)*(_TECH_Industry_Templates!$B:$B=$A8),0),0)),"") -> Workforce Resilience Strategy; Digital Foundation Strategy; Business Continuity and Resilience Strategy
A9: HR Workforce | B9: =IFERROR(SUMIFS(_TECH_Industry_Templates!$C:$C,_TECH_Industry_Templates!$A:$A,'Company Profile'!$B$9,_TECH_Industry_Templates!$B:$B,$A9),"") -> 5 | C9: =IFERROR(SUMIFS(_TECH_Industry_Templates!$D:$D,_TECH_Industry_Templates!$A:$A,'Company Profile'!$B$9,_TECH_Industry_Templates!$B:$B,$A9),"") -> 4 | D9: =IFERROR(SUMIFS(_TECH_Industry_Templates!$E:$E,_TECH_Industry_Templates!$A:$A,'Company Profile'!$B$9,_TECH_Industry_Templates!$B:$B,$A9),"") -> 1.25 | E9: =IFERROR(SUMIFS(_TECH_Industry_Templates!$F:$F,_TECH_Industry_Templates!$A:$A,'Company Profile'!$B$9,_TECH_Industry_Templates!$B:$B,$A9),"") -> 3 | F9: =IFERROR(SUMIFS(_TECH_Industry_Templates!$J:$J,_TECH_Industry_Templates!$A:$A,'Company Profile'!$B$9,_TECH_Industry_Templates!$B:$B,$A9),"") -> 1.2 | G9: =IFERROR(INDEX(_TECH_Industry_Templates!$G:$G,MATCH(1,INDEX((_TECH_Industry_Templates!$A:$A='Company Profile'!$B$9)*(_TECH_Industry_Templates!$B:$B=$A9),0),0)),"") -> Medium | H9: =IFERROR(INDEX(_TECH_Industry_Templates!$H:$H,MATCH(1,INDEX((_TECH_Industry_Templates!$A:$A='Company Profile'!$B$9)*(_TECH_Industry_Templates!$B:$B=$A9),0),0)),"") -> CRM; HRMS; project/portfolio tools; time tracking; knowledge base; finance system; cloud collaboration; IAM; BI dashboards | I9: =IFERROR(INDEX(_TECH_Industry_Templates!$I:$I,MATCH(1,INDEX((_TECH_Industry_Templates!$A:$A='Company Profile'!$B$9)*(_TECH_Industry_Templates!$B:$B=$A9),0),0)),"") -> critical role backups; secure remote work; MFA; delivery continuity; project knowledge base; customer communication path | J9: =IFERROR(INDEX(_TECH_Industry_Templates!$L:$L,MATCH(1,INDEX((_TECH_Industry_Templates!$A:$A='Company Profile'!$B$9)*(_TECH_Industry_Templates!$B:$B=$A9),0),0)),"") -> Workforce Resilience Strategy; Digital Foundation Strategy; Business Continuity and Resilience Strategy
A10: Finance Procurement | B10: =IFERROR(SUMIFS(_TECH_Industry_Templates!$C:$C,_TECH_Industry_Templates!$A:$A,'Company Profile'!$B$9,_TECH_Industry_Templates!$B:$B,$A10),"") -> 3 | C10: =IFERROR(SUMIFS(_TECH_Industry_Templates!$D:$D,_TECH_Industry_Templates!$A:$A,'Company Profile'!$B$9,_TECH_Industry_Templates!$B:$B,$A10),"") -> 3.5 | D10: =IFERROR(SUMIFS(_TECH_Industry_Templates!$E:$E,_TECH_Industry_Templates!$A:$A,'Company Profile'!$B$9,_TECH_Industry_Templates!$B:$B,$A10),"") -> 1 | E10: =IFERROR(SUMIFS(_TECH_Industry_Templates!$F:$F,_TECH_Industry_Templates!$A:$A,'Company Profile'!$B$9,_TECH_Industry_Templates!$B:$B,$A10),"") -> 2.5 | F10: =IFERROR(SUMIFS(_TECH_Industry_Templates!$J:$J,_TECH_Industry_Templates!$A:$A,'Company Profile'!$B$9,_TECH_Industry_Templates!$B:$B,$A10),"") -> 1 | G10: =IFERROR(INDEX(_TECH_Industry_Templates!$G:$G,MATCH(1,INDEX((_TECH_Industry_Templates!$A:$A='Company Profile'!$B$9)*(_TECH_Industry_Templates!$B:$B=$A10),0),0)),"") -> Low | H10: =IFERROR(INDEX(_TECH_Industry_Templates!$H:$H,MATCH(1,INDEX((_TECH_Industry_Templates!$A:$A='Company Profile'!$B$9)*(_TECH_Industry_Templates!$B:$B=$A10),0),0)),"") -> CRM; HRMS; project/portfolio tools; time tracking; knowledge base; finance system; cloud collaboration; IAM; BI dashboards | I10: =IFERROR(INDEX(_TECH_Industry_Templates!$I:$I,MATCH(1,INDEX((_TECH_Industry_Templates!$A:$A='Company Profile'!$B$9)*(_TECH_Industry_Templates!$B:$B=$A10),0),0)),"") -> critical role backups; secure remote work; MFA; delivery continuity; project knowledge base; customer communication path | J10: =IFERROR(INDEX(_TECH_Industry_Templates!$L:$L,MATCH(1,INDEX((_TECH_Industry_Templates!$A:$A='Company Profile'!$B$9)*(_TECH_Industry_Templates!$B:$B=$A10),0),0)),"") -> Workforce Resilience Strategy; Digital Foundation Strategy; Business Continuity and Resilience Strategy
A11: Legal Risk | B11: =IFERROR(SUMIFS(_TECH_Industry_Templates!$C:$C,_TECH_Industry_Templates!$A:$A,'Company Profile'!$B$9,_TECH_Industry_Templates!$B:$B,$A11),"") -> 3 | C11: =IFERROR(SUMIFS(_TECH_Industry_Templates!$D:$D,_TECH_Industry_Templates!$A:$A,'Company Profile'!$B$9,_TECH_Industry_Templates!$B:$B,$A11),"") -> 3.5 | D11: =IFERROR(SUMIFS(_TECH_Industry_Templates!$E:$E,_TECH_Industry_Templates!$A:$A,'Company Profile'!$B$9,_TECH_Industry_Templates!$B:$B,$A11),"") -> 1 | E11: =IFERROR(SUMIFS(_TECH_Industry_Templates!$F:$F,_TECH_Industry_Templates!$A:$A,'Company Profile'!$B$9,_TECH_Industry_Templates!$B:$B,$A11),"") -> 2.5 | F11: =IFERROR(SUMIFS(_TECH_Industry_Templates!$J:$J,_TECH_Industry_Templates!$A:$A,'Company Profile'!$B$9,_TECH_Industry_Templates!$B:$B,$A11),"") -> 1 | G11: =IFERROR(INDEX(_TECH_Industry_Templates!$G:$G,MATCH(1,INDEX((_TECH_Industry_Templates!$A:$A='Company Profile'!$B$9)*(_TECH_Industry_Templates!$B:$B=$A11),0),0)),"") -> Low | H11: =IFERROR(INDEX(_TECH_Industry_Templates!$H:$H,MATCH(1,INDEX((_TECH_Industry_Templates!$A:$A='Company Profile'!$B$9)*(_TECH_Industry_Templates!$B:$B=$A11),0),0)),"") -> CRM; HRMS; project/portfolio tools; time tracking; knowledge base; finance system; cloud collaboration; IAM; BI dashboards | I11: =IFERROR(INDEX(_TECH_Industry_Templates!$I:$I,MATCH(1,INDEX((_TECH_Industry_Templates!$A:$A='Company Profile'!$B$9)*(_TECH_Industry_Templates!$B:$B=$A11),0),0)),"") -> critical role backups; secure remote work; MFA; delivery continuity; project knowledge base; customer communication path | J11: =IFERROR(INDEX(_TECH_Industry_Templates!$L:$L,MATCH(1,INDEX((_TECH_Industry_Templates!$A:$A='Company Profile'!$B$9)*(_TECH_Industry_Templates!$B:$B=$A11),0),0)),"") -> Workforce Resilience Strategy; Digital Foundation Strategy; Business Continuity and Resilience Strategy
A12: Physical Safety | B12: =IFERROR(SUMIFS(_TECH_Industry_Templates!$C:$C,_TECH_Industry_Templates!$A:$A,'Company Profile'!$B$9,_TECH_Industry_Templates!$B:$B,$A12),"") -> 2 | C12: =IFERROR(SUMIFS(_TECH_Industry_Templates!$D:$D,_TECH_Industry_Templates!$A:$A,'Company Profile'!$B$9,_TECH_Industry_Templates!$B:$B,$A12),"") -> 2.8 | D12: =IFERROR(SUMIFS(_TECH_Industry_Templates!$E:$E,_TECH_Industry_Templates!$A:$A,'Company Profile'!$B$9,_TECH_Industry_Templates!$B:$B,$A12),"") -> 0.9 | E12: =IFERROR(SUMIFS(_TECH_Industry_Templates!$F:$F,_TECH_Industry_Templates!$A:$A,'Company Profile'!$B$9,_TECH_Industry_Templates!$B:$B,$A12),"") -> 2 | F12: =IFERROR(SUMIFS(_TECH_Industry_Templates!$J:$J,_TECH_Industry_Templates!$A:$A,'Company Profile'!$B$9,_TECH_Industry_Templates!$B:$B,$A12),"") -> 0.9 | G12: =IFERROR(INDEX(_TECH_Industry_Templates!$G:$G,MATCH(1,INDEX((_TECH_Industry_Templates!$A:$A='Company Profile'!$B$9)*(_TECH_Industry_Templates!$B:$B=$A12),0),0)),"") -> Low | H12: =IFERROR(INDEX(_TECH_Industry_Templates!$H:$H,MATCH(1,INDEX((_TECH_Industry_Templates!$A:$A='Company Profile'!$B$9)*(_TECH_Industry_Templates!$B:$B=$A12),0),0)),"") -> CRM; HRMS; project/portfolio tools; time tracking; knowledge base; finance system; cloud collaboration; IAM; BI dashboards | I12: =IFERROR(INDEX(_TECH_Industry_Templates!$I:$I,MATCH(1,INDEX((_TECH_Industry_Templates!$A:$A='Company Profile'!$B$9)*(_TECH_Industry_Templates!$B:$B=$A12),0),0)),"") -> critical role backups; secure remote work; MFA; delivery continuity; project knowledge base; customer communication path | J12: =IFERROR(INDEX(_TECH_Industry_Templates!$L:$L,MATCH(1,INDEX((_TECH_Industry_Templates!$A:$A='Company Profile'!$B$9)*(_TECH_Industry_Templates!$B:$B=$A12),0),0)),"") -> Workforce Resilience Strategy; Digital Foundation Strategy; Business Continuity and Resilience Strategy
A13: Delivery Ops | B13: =IFERROR(SUMIFS(_TECH_Industry_Templates!$C:$C,_TECH_Industry_Templates!$A:$A,'Company Profile'!$B$9,_TECH_Industry_Templates!$B:$B,$A13),"") -> 5 | C13: =IFERROR(SUMIFS(_TECH_Industry_Templates!$D:$D,_TECH_Industry_Templates!$A:$A,'Company Profile'!$B$9,_TECH_Industry_Templates!$B:$B,$A13),"") -> 4 | D13: =IFERROR(SUMIFS(_TECH_Industry_Templates!$E:$E,_TECH_Industry_Templates!$A:$A,'Company Profile'!$B$9,_TECH_Industry_Templates!$B:$B,$A13),"") -> 1.25 | E13: =IFERROR(SUMIFS(_TECH_Industry_Templates!$F:$F,_TECH_Industry_Templates!$A:$A,'Company Profile'!$B$9,_TECH_Industry_Templates!$B:$B,$A13),"") -> 3 | F13: =IFERROR(SUMIFS(_TECH_Industry_Templates!$J:$J,_TECH_Industry_Templates!$A:$A,'Company Profile'!$B$9,_TECH_Industry_Templates!$B:$B,$A13),"") -> 1.2 | G13: =IFERROR(INDEX(_TECH_Industry_Templates!$G:$G,MATCH(1,INDEX((_TECH_Industry_Templates!$A:$A='Company Profile'!$B$9)*(_TECH_Industry_Templates!$B:$B=$A13),0),0)),"") -> Medium | H13: =IFERROR(INDEX(_TECH_Industry_Templates!$H:$H,MATCH(1,INDEX((_TECH_Industry_Templates!$A:$A='Company Profile'!$B$9)*(_TECH_Industry_Templates!$B:$B=$A13),0),0)),"") -> CRM; HRMS; project/portfolio tools; time tracking; knowledge base; finance system; cloud collaboration; IAM; BI dashboards | I13: =IFERROR(INDEX(_TECH_Industry_Templates!$I:$I,MATCH(1,INDEX((_TECH_Industry_Templates!$A:$A='Company Profile'!$B$9)*(_TECH_Industry_Templates!$B:$B=$A13),0),0)),"") -> critical role backups; secure remote work; MFA; delivery continuity; project knowledge base; customer communication path | J13: =IFERROR(INDEX(_TECH_Industry_Templates!$L:$L,MATCH(1,INDEX((_TECH_Industry_Templates!$A:$A='Company Profile'!$B$9)*(_TECH_Industry_Templates!$B:$B=$A13),0),0)),"") -> Workforce Resilience Strategy; Digital Foundation Strategy; Business Continuity and Resilience Strategy
A14: Supply Chain | B14: =IFERROR(SUMIFS(_TECH_Industry_Templates!$C:$C,_TECH_Industry_Templates!$A:$A,'Company Profile'!$B$9,_TECH_Industry_Templates!$B:$B,$A14),"") -> 3 | C14: =IFERROR(SUMIFS(_TECH_Industry_Templates!$D:$D,_TECH_Industry_Templates!$A:$A,'Company Profile'!$B$9,_TECH_Industry_Templates!$B:$B,$A14),"") -> 3.5 | D14: =IFERROR(SUMIFS(_TECH_Industry_Templates!$E:$E,_TECH_Industry_Templates!$A:$A,'Company Profile'!$B$9,_TECH_Industry_Templates!$B:$B,$A14),"") -> 1 | E14: =IFERROR(SUMIFS(_TECH_Industry_Templates!$F:$F,_TECH_Industry_Templates!$A:$A,'Company Profile'!$B$9,_TECH_Industry_Templates!$B:$B,$A14),"") -> 2.5 | F14: =IFERROR(SUMIFS(_TECH_Industry_Templates!$J:$J,_TECH_Industry_Templates!$A:$A,'Company Profile'!$B$9,_TECH_Industry_Templates!$B:$B,$A14),"") -> 1 | G14: =IFERROR(INDEX(_TECH_Industry_Templates!$G:$G,MATCH(1,INDEX((_TECH_Industry_Templates!$A:$A='Company Profile'!$B$9)*(_TECH_Industry_Templates!$B:$B=$A14),0),0)),"") -> Low | H14: =IFERROR(INDEX(_TECH_Industry_Templates!$H:$H,MATCH(1,INDEX((_TECH_Industry_Templates!$A:$A='Company Profile'!$B$9)*(_TECH_Industry_Templates!$B:$B=$A14),0),0)),"") -> CRM; HRMS; project/portfolio tools; time tracking; knowledge base; finance system; cloud collaboration; IAM; BI dashboards | I14: =IFERROR(INDEX(_TECH_Industry_Templates!$I:$I,MATCH(1,INDEX((_TECH_Industry_Templates!$A:$A='Company Profile'!$B$9)*(_TECH_Industry_Templates!$B:$B=$A14),0),0)),"") -> critical role backups; secure remote work; MFA; delivery continuity; project knowledge base; customer communication path | J14: =IFERROR(INDEX(_TECH_Industry_Templates!$L:$L,MATCH(1,INDEX((_TECH_Industry_Templates!$A:$A='Company Profile'!$B$9)*(_TECH_Industry_Templates!$B:$B=$A14),0),0)),"") -> Workforce Resilience Strategy; Digital Foundation Strategy; Business Continuity and Resilience Strategy
A15: Manufacturing MES | B15: =IFERROR(SUMIFS(_TECH_Industry_Templates!$C:$C,_TECH_Industry_Templates!$A:$A,'Company Profile'!$B$9,_TECH_Industry_Templates!$B:$B,$A15),"") -> 1 | C15: =IFERROR(SUMIFS(_TECH_Industry_Templates!$D:$D,_TECH_Industry_Templates!$A:$A,'Company Profile'!$B$9,_TECH_Industry_Templates!$B:$B,$A15),"") -> 1 | D15: =IFERROR(SUMIFS(_TECH_Industry_Templates!$E:$E,_TECH_Industry_Templates!$A:$A,'Company Profile'!$B$9,_TECH_Industry_Templates!$B:$B,$A15),"") -> 0.6 | E15: =IFERROR(SUMIFS(_TECH_Industry_Templates!$F:$F,_TECH_Industry_Templates!$A:$A,'Company Profile'!$B$9,_TECH_Industry_Templates!$B:$B,$A15),"") -> 0 | F15: =IFERROR(SUMIFS(_TECH_Industry_Templates!$J:$J,_TECH_Industry_Templates!$A:$A,'Company Profile'!$B$9,_TECH_Industry_Templates!$B:$B,$A15),"") -> 0.7 | G15: =IFERROR(INDEX(_TECH_Industry_Templates!$G:$G,MATCH(1,INDEX((_TECH_Industry_Templates!$A:$A='Company Profile'!$B$9)*(_TECH_Industry_Templates!$B:$B=$A15),0),0)),"") -> Low | H15: =IFERROR(INDEX(_TECH_Industry_Templates!$H:$H,MATCH(1,INDEX((_TECH_Industry_Templates!$A:$A='Company Profile'!$B$9)*(_TECH_Industry_Templates!$B:$B=$A15),0),0)),"") -> CRM; HRMS; project/portfolio tools; time tracking; knowledge base; finance system; cloud collaboration; IAM; BI dashboards | I15: =IFERROR(INDEX(_TECH_Industry_Templates!$I:$I,MATCH(1,INDEX((_TECH_Industry_Templates!$A:$A='Company Profile'!$B$9)*(_TECH_Industry_Templates!$B:$B=$A15),0),0)),"") -> critical role backups; secure remote work; MFA; delivery continuity; project knowledge base; customer communication path | J15: =IFERROR(INDEX(_TECH_Industry_Templates!$L:$L,MATCH(1,INDEX((_TECH_Industry_Templates!$A:$A='Company Profile'!$B$9)*(_TECH_Industry_Templates!$B:$B=$A15),0),0)),"") -> Workforce Resilience Strategy; Digital Foundation Strategy; Business Continuity and Resilience Strategy
A16: Sales CRM | B16: =IFERROR(SUMIFS(_TECH_Industry_Templates!$C:$C,_TECH_Industry_Templates!$A:$A,'Company Profile'!$B$9,_TECH_Industry_Templates!$B:$B,$A16),"") -> 4 | C16: =IFERROR(SUMIFS(_TECH_Industry_Templates!$D:$D,_TECH_Industry_Templates!$A:$A,'Company Profile'!$B$9,_TECH_Industry_Templates!$B:$B,$A16),"") -> 3.8 | D16: =IFERROR(SUMIFS(_TECH_Industry_Templates!$E:$E,_TECH_Industry_Templates!$A:$A,'Company Profile'!$B$9,_TECH_Industry_Templates!$B:$B,$A16),"") -> 1.1 | E16: =IFERROR(SUMIFS(_TECH_Industry_Templates!$F:$F,_TECH_Industry_Templates!$A:$A,'Company Profile'!$B$9,_TECH_Industry_Templates!$B:$B,$A16),"") -> 2.8 | F16: =IFERROR(SUMIFS(_TECH_Industry_Templates!$J:$J,_TECH_Industry_Templates!$A:$A,'Company Profile'!$B$9,_TECH_Industry_Templates!$B:$B,$A16),"") -> 1.1 | G16: =IFERROR(INDEX(_TECH_Industry_Templates!$G:$G,MATCH(1,INDEX((_TECH_Industry_Templates!$A:$A='Company Profile'!$B$9)*(_TECH_Industry_Templates!$B:$B=$A16),0),0)),"") -> Medium | H16: =IFERROR(INDEX(_TECH_Industry_Templates!$H:$H,MATCH(1,INDEX((_TECH_Industry_Templates!$A:$A='Company Profile'!$B$9)*(_TECH_Industry_Templates!$B:$B=$A16),0),0)),"") -> CRM; HRMS; project/portfolio tools; time tracking; knowledge base; finance system; cloud collaboration; IAM; BI dashboards | I16: =IFERROR(INDEX(_TECH_Industry_Templates!$I:$I,MATCH(1,INDEX((_TECH_Industry_Templates!$A:$A='Company Profile'!$B$9)*(_TECH_Industry_Templates!$B:$B=$A16),0),0)),"") -> critical role backups; secure remote work; MFA; delivery continuity; project knowledge base; customer communication path | J16: =IFERROR(INDEX(_TECH_Industry_Templates!$L:$L,MATCH(1,INDEX((_TECH_Industry_Templates!$A:$A='Company Profile'!$B$9)*(_TECH_Industry_Templates!$B:$B=$A16),0),0)),"") -> Workforce Resilience Strategy; Digital Foundation Strategy; Business Continuity and Resilience Strategy
A17: Marketing Comms | B17: =IFERROR(SUMIFS(_TECH_Industry_Templates!$C:$C,_TECH_Industry_Templates!$A:$A,'Company Profile'!$B$9,_TECH_Industry_Templates!$B:$B,$A17),"") -> 3 | C17: =IFERROR(SUMIFS(_TECH_Industry_Templates!$D:$D,_TECH_Industry_Templates!$A:$A,'Company Profile'!$B$9,_TECH_Industry_Templates!$B:$B,$A17),"") -> 3.5 | D17: =IFERROR(SUMIFS(_TECH_Industry_Templates!$E:$E,_TECH_Industry_Templates!$A:$A,'Company Profile'!$B$9,_TECH_Industry_Templates!$B:$B,$A17),"") -> 1 | E17: =IFERROR(SUMIFS(_TECH_Industry_Templates!$F:$F,_TECH_Industry_Templates!$A:$A,'Company Profile'!$B$9,_TECH_Industry_Templates!$B:$B,$A17),"") -> 2.5 | F17: =IFERROR(SUMIFS(_TECH_Industry_Templates!$J:$J,_TECH_Industry_Templates!$A:$A,'Company Profile'!$B$9,_TECH_Industry_Templates!$B:$B,$A17),"") -> 1 | G17: =IFERROR(INDEX(_TECH_Industry_Templates!$G:$G,MATCH(1,INDEX((_TECH_Industry_Templates!$A:$A='Company Profile'!$B$9)*(_TECH_Industry_Templates!$B:$B=$A17),0),0)),"") -> Low | H17: =IFERROR(INDEX(_TECH_Industry_Templates!$H:$H,MATCH(1,INDEX((_TECH_Industry_Templates!$A:$A='Company Profile'!$B$9)*(_TECH_Industry_Templates!$B:$B=$A17),0),0)),"") -> CRM; HRMS; project/portfolio tools; time tracking; knowledge base; finance system; cloud collaboration; IAM; BI dashboards | I17: =IFERROR(INDEX(_TECH_Industry_Templates!$I:$I,MATCH(1,INDEX((_TECH_Industry_Templates!$A:$A='Company Profile'!$B$9)*(_TECH_Industry_Templates!$B:$B=$A17),0),0)),"") -> critical role backups; secure remote work; MFA; delivery continuity; project knowledge base; customer communication path | J17: =IFERROR(INDEX(_TECH_Industry_Templates!$L:$L,MATCH(1,INDEX((_TECH_Industry_Templates!$A:$A='Company Profile'!$B$9)*(_TECH_Industry_Templates!$B:$B=$A17),0),0)),"") -> Workforce Resilience Strategy; Digital Foundation Strategy; Business Continuity and Resilience Strategy
... A22: Quality Portfolio | B22: =IFERROR(SUMIFS(_TECH_Industry_Templates!$C:$C,_TECH_Industry_Templates!$A:$A,'Company Profile'!$B$9,_TECH_Industry_Templates!$B:$B,$A22),"") -> 5 | C22: =IFERROR(SUMIFS(_TECH_Industry_Templates!$D:$D,_TECH_Industry_Templates!$A:$A,'Company Profile'!$B$9,_TECH_Industry_Templates!$B:$B,$A22),"") -> 4 | D22: =IFERROR(SUMIFS(_TECH_Industry_Templates!$E:$E,_TECH_Industry_Templates!$A:$A,'Company Profile'!$B$9,_TECH_Industry_Templates!$B:$B,$A22),"") -> 1.2 | E22: =IFERROR(SUMIFS(_TECH_Industry_Templates!$F:$F,_TECH_Industry_Templates!$A:$A,'Company Profile'!$B$9,_TECH_Industry_Templates!$B:$B,$A22),"") -> 3 | F22: =IFERROR(SUMIFS(_TECH_Industry_Templates!$J:$J,_TECH_Industry_Templates!$A:$A,'Company Profile'!$B$9,_TECH_Industry_Templates!$B:$B,$A22),"") -> 1.2 | G22: =IFERROR(INDEX(_TECH_Industry_Templates!$G:$G,MATCH(1,INDEX((_TECH_Industry_Templates!$A:$A='Company Profile'!$B$9)*(_TECH_Industry_Templates!$B:$B=$A22),0),0)),"") -> Medium | H22: =IFERROR(INDEX(_TECH_Industry_Templates!$H:$H,MATCH(1,INDEX((_TECH_Industry_Templates!$A:$A='Company Profile'!$B$9)*(_TECH_Industry_Templates!$B:$B=$A22),0),0)),"") -> CRM; HRMS; project/portfolio tools; time tracking; knowledge base; finance system; cloud collaboration; IAM; BI dashboards | I22: =IFERROR(INDEX(_TECH_Industry_Templates!$I:$I,MATCH(1,INDEX((_TECH_Industry_Templates!$A:$A='Company Profile'!$B$9)*(_TECH_Industry_Templates!$B:$B=$A22),0),0)),"") -> critical role backups; secure remote work; MFA; delivery continuity; project knowledge base; customer communication path | J22: =IFERROR(INDEX(_TECH_Industry_Templates!$L:$L,MATCH(1,INDEX((_TECH_Industry_Templates!$A:$A='Company Profile'!$B$9)*(_TECH_Industry_Templates!$B:$B=$A22),0),0)),"") -> Workforce Resilience Strategy; Digital Foundation Strategy; Business Continuity and Resilience Strategy

Sheet Crisis Simulator
A1: Crisis Simulator
A2: Select a crisis scenario and severity. The sheet converts current maturity gaps into scenario-adjusted exposure by domain, using the hidden crisis multiplier model.
A4: Selected crisis scenario | B4: War / security crisis | N4: Scenario Summary
A5: Severity 1-5 | B5: 3 | N5: Selected scenario | O5: =B4 -> War / security crisis
A6: Severity logic | B6: 1 = mild pressure; 3 = base case; 5 = severe crisis. Multipliers increase/decrease automatically. | N6: Severity | O6: =B5 -> 3
N7: Top exposed domain | O7: =IFERROR(INDEX($A$9:$A$25,MATCH(1,$L$9:$L$25,0)),"")
A8: Domain | B8: Current maturity 0-5 | C8: Gap to 5 | D8: Critical/High items | E8: Crisis multiplier | F8: Scenario-adjusted exposure | G8: Priority level | H8: Target maturity | I8: Gap to target | J8: Scenario rationale | K8: Mitigation emphasis | L8: Rank | N8: Critical/High domains | O8: =COUNTIF($G$9:$G$25,"Critical")+COUNTIF($G$9:$G$25,"High") -> 17
A9: =Dashboard!$A$5 -> Company Geography | B9: =Dashboard!$H$5 -> 0 | C9: =IF(B9="","",ROUND(5-B9,2)) -> 5 | D9: =Dashboard!$J$5+Dashboard!$K$5 -> 0 | E9: =IFERROR(SUMIFS(_TECH_Crisis_Model!$D$5:$D$191,_TECH_Crisis_Model!$A$5:$A$191,$B$4,_TECH_Crisis_Model!$B$5:$B$191,A9),1) -> 1.6 | F9: =IF(B9="","",ROUND((C9*E9)+(D9*0.25*E9),2)) -> 8 | G9: =IF(F9>=5,"Critical",IF(F9>=3.5,"High",IF(F9>=2,"Medium","Low"))) -> Critical | H9: =IF(G9="Critical",4.5,IF(G9="High",4,IF(G9="Medium",3.5,3))) -> 4.5 | I9: =MAX(0,ROUND(H9-B9,2)) -> 4.5 | J9: =IFERROR(INDEX(_TECH_Crisis_Model!$E$5:$E$191,MATCH($B$4&"|"&A9,_TECH_Crisis_Model!$I$5:$I$191,0)),"") -> Geographic concentration, legal entity exposure and site dependency can amplify crisis impact. | K9: =IFERROR(INDEX(_TECH_Crisis_Model!$G$5:$G$191,MATCH($B$4&"|"&A9,_TECH_Crisis_Model!$I$5:$I$191,0)),"") -> Map entities, locations, markets, revenue exposure and alternate operating options. | L9: =RANK.EQ(F9,$F$9:$F$25,0)+COUNTIF($F$9:F9,F9)-1 | N9: Average adjusted exposure | O9: =IFERROR(ROUND(AVERAGE($F$9:$F$25),2),"") -> 6.97
A10: =Dashboard!$A$6 -> Strategy GTM | B10: =Dashboard!$H$6 -> 0 | C10: =IF(B10="","",ROUND(5-B10,2)) -> 5 | D10: =Dashboard!$J$6+Dashboard!$K$6 -> 0 | E10: =IFERROR(SUMIFS(_TECH_Crisis_Model!$D$5:$D$191,_TECH_Crisis_Model!$A$5:$A$191,$B$4,_TECH_Crisis_Model!$B$5:$B$191,A10),1) -> 1 | F10: =IF(B10="","",ROUND((C10*E10)+(D10*0.25*E10),2)) -> 5 | G10: =IF(F10>=5,"Critical",IF(F10>=3.5,"High",IF(F10>=2,"Medium","Low"))) -> Critical | H10: =IF(G10="Critical",4.5,IF(G10="High",4,IF(G10="Medium",3.5,3))) -> 4.5 | I10: =MAX(0,ROUND(H10-B10,2)) -> 4.5 | J10: =IFERROR(INDEX(_TECH_Crisis_Model!$E$5:$E$191,MATCH($B$4&"|"&A10,_TECH_Crisis_Model!$I$5:$I$191,0)),"") -> Market positioning, ICP clarity and offer structure determine whether the company can adapt revenue during crisis. | K10: =IFERROR(INDEX(_TECH_Crisis_Model!$G$5:$G$191,MATCH($B$4&"|"&A10,_TECH_Crisis_Model!$I$5:$I$191,0)),"") -> Stress-test ICP, offering, pricing, channels and market focus under the selected crisis. | L10: =RANK.EQ(F10,$F$9:$F$25,0)+COUNTIF($F$9:F10,F10)-1 | N10: Primary strategy | O10: =IFERROR('Strategy Selection'!$B$6,"")
A11: =Dashboard!$A$7 -> Governance Crisis | B11: =Dashboard!$H$7 -> 0 | C11: =IF(B11="","",ROUND(5-B11,2)) -> 5 | D11: =Dashboard!$J$7+Dashboard!$K$7 -> 0 | E11: =IFERROR(SUMIFS(_TECH_Crisis_Model!$D$5:$D$191,_TECH_Crisis_Model!$A$5:$A$191,$B$4,_TECH_Crisis_Model!$B$5:$B$191,A11),1) -> 1.4 | F11: =IF(B11="","",ROUND((C11*E11)+(D11*0.25*E11),2)) -> 7 | G11: =IF(F11>=5,"Critical",IF(F11>=3.5,"High",IF(F11>=2,"Medium","Low"))) -> Critical | H11: =IF(G11="Critical",4.5,IF(G11="High",4,IF(G11="Medium",3.5,3))) -> 4.5 | I11: =MAX(0,ROUND(H11-B11,2)) -> 4.5 | J11: =IFERROR(INDEX(_TECH_Crisis_Model!$E$5:$E$191,MATCH($B$4&"|"&A11,_TECH_Crisis_Model!$I$5:$I$191,0)),"") -> Decision rights, escalation and crisis governance determine response speed under pressure. | K11: =IFERROR(INDEX(_TECH_Crisis_Model!$G$5:$G$191,MATCH($B$4&"|"&A11,_TECH_Crisis_Model!$I$5:$I$191,0)),"") -> Define crisis roles, escalation path, decision cadence and management war room routines. | L11: =RANK.EQ(F11,$F$9:$F$25,0)+COUNTIF($F$9:F11,F11)-1
A12: =Dashboard!$A$8 -> HR Workforce | B12: =Dashboard!$H$8 -> 0 | C12: =IF(B12="","",ROUND(5-B12,2)) -> 5 | D12: =Dashboard!$J$8+Dashboard!$K$8 -> 0 | E12: =IFERROR(SUMIFS(_TECH_Crisis_Model!$D$5:$D$191,_TECH_Crisis_Model!$A$5:$A$191,$B$4,_TECH_Crisis_Model!$B$5:$B$191,A12),1) -> 1.8 | F12: =IF(B12="","",ROUND((C12*E12)+(D12*0.25*E12),2)) -> 9 | G12: =IF(F12>=5,"Critical",IF(F12>=3.5,"High",IF(F12>=2,"Medium","Low"))) -> Critical | H12: =IF(G12="Critical",4.5,IF(G12="High",4,IF(G12="Medium",3.5,3))) -> 4.5 | I12: =MAX(0,ROUND(H12-B12,2)) -> 4.5 | J12: =IFERROR(INDEX(_TECH_Crisis_Model!$E$5:$E$191,MATCH($B$4&"|"&A12,_TECH_Crisis_Model!$I$5:$I$191,0)),"") -> Workforce availability, critical people and knowledge continuity determine operational capacity. | K12: =IFERROR(INDEX(_TECH_Crisis_Model!$G$5:$G$191,MATCH($B$4&"|"&A12,_TECH_Crisis_Model!$I$5:$I$191,0)),"") -> Create critical role backups, knowledge transfer, cross-training and workforce continuity plans. | L12: =RANK.EQ(F12,$F$9:$F$25,0)+COUNTIF($F$9:F12,F12)-1
A13: =Dashboard!$A$9 -> Finance Procurement | B13: =Dashboard!$H$9 -> 0 | C13: =IF(B13="","",ROUND(5-B13,2)) -> 5 | D13: =Dashboard!$J$9+Dashboard!$K$9 -> 0 | E13: =IFERROR(SUMIFS(_TECH_Crisis_Model!$D$5:$D$191,_TECH_Crisis_Model!$A$5:$A$191,$B$4,_TECH_Crisis_Model!$B$5:$B$191,A13),1) -> 1.3 | F13: =IF(B13="","",ROUND((C13*E13)+(D13*0.25*E13),2)) -> 6.5 | G13: =IF(F13>=5,"Critical",IF(F13>=3.5,"High",IF(F13>=2,"Medium","Low"))) -> Critical | H13: =IF(G13="Critical",4.5,IF(G13="High",4,IF(G13="Medium",3.5,3))) -> 4.5 | I13: =MAX(0,ROUND(H13-B13,2)) -> 4.5 | J13: =IFERROR(INDEX(_TECH_Crisis_Model!$E$5:$E$191,MATCH($B$4&"|"&A13,_TECH_Crisis_Model!$I$5:$I$191,0)),"") -> Cash control, supplier payments and procurement discipline determine financial survival and response options. | K13: =IFERROR(INDEX(_TECH_Crisis_Model!$G$5:$G$191,MATCH($B$4&"|"&A13,_TECH_Crisis_Model!$I$5:$I$191,0)),"") -> Build cash stress testing, payment prioritization, supplier risk review and procurement controls. | L13: =RANK.EQ(F13,$F$9:$F$25,0)+COUNTIF($F$9:F13,F13)-1
A14: =Dashboard!$A$10 -> Legal Risk | B14: =Dashboard!$H$10 -> 0 | C14: =IF(B14="","",ROUND(5-B14,2)) -> 5 | D14: =Dashboard!$J$10+Dashboard!$K$10 -> 0 | E14: =IFERROR(SUMIFS(_TECH_Crisis_Model!$D$5:$D$191,_TECH_Crisis_Model!$A$5:$A$191,$B$4,_TECH_Crisis_Model!$B$5:$B$191,A14),1) -> 1.4 | F14: =IF(B14="","",ROUND((C14*E14)+(D14*0.25*E14),2)) -> 7 | G14: =IF(F14>=5,"Critical",IF(F14>=3.5,"High",IF(F14>=2,"Medium","Low"))) -> Critical | H14: =IF(G14="Critical",4.5,IF(G14="High",4,IF(G14="Medium",3.5,3))) -> 4.5 | I14: =MAX(0,ROUND(H14-B14,2)) -> 4.5 | J14: =IFERROR(INDEX(_TECH_Crisis_Model!$E$5:$E$191,MATCH($B$4&"|"&A14,_TECH_Crisis_Model!$I$5:$I$191,0)),"") -> Contracts, obligations and compliance exposure can turn operational crisis into legal or regulatory failure. | K14: =IFERROR(INDEX(_TECH_Crisis_Model!$G$5:$G$191,MATCH($B$4&"|"&A14,_TECH_Crisis_Model!$I$5:$I$191,0)),"") -> Review critical contracts, compliance obligations, force majeure, data protection and legal continuity. | L14: =RANK.EQ(F14,$F$9:$F$25,0)+COUNTIF($F$9:F14,F14)-1
A15: =Dashboard!$A$11 -> Physical Safety | B15: =Dashboard!$H$11 -> 0 | C15: =IF(B15="","",ROUND(5-B15,2)) -> 5 | D15: =Dashboard!$J$11+Dashboard!$K$11 -> 0 | E15: =IFERROR(SUMIFS(_TECH_Crisis_Model!$D$5:$D$191,_TECH_Crisis_Model!$A$5:$A$191,$B$4,_TECH_Crisis_Model!$B$5:$B$191,A15),1) -> 2 | F15: =IF(B15="","",ROUND((C15*E15)+(D15*0.25*E15),2)) -> 10 | G15: =IF(F15>=5,"Critical",IF(F15>=3.5,"High",IF(F15>=2,"Medium","Low"))) -> Critical | H15: =IF(G15="Critical",4.5,IF(G15="High",4,IF(G15="Medium",3.5,3))) -> 4.5 | I15: =MAX(0,ROUND(H15-B15,2)) -> 4.5 | J15: =IFERROR(INDEX(_TECH_Crisis_Model!$E$5:$E$191,MATCH($B$4&"|"&A15,_TECH_Crisis_Model!$I$5:$I$191,0)),"") -> Employee safety, access control, evacuation and facilities resilience are direct crisis constraints. | K15: =IFERROR(INDEX(_TECH_Crisis_Model!$G$5:$G$191,MATCH($B$4&"|"&A15,_TECH_Crisis_Model!$I$5:$I$191,0)),"") -> Implement evacuation, access control, emergency response, site security and travel-risk procedures. | L15: =RANK.EQ(F15,$F$9:$F$25,0)+COUNTIF($F$9:F15,F15)-1
A16: =Dashboard!$A$12 -> Delivery Ops | B16: =Dashboard!$H$12 -> 0 | C16: =IF(B16="","",ROUND(5-B16,2)) -> 5 | D16: =Dashboard!$J$12+Dashboard!$K$12 -> 0 | E16: =IFERROR(SUMIFS(_TECH_Crisis_Model!$D$5:$D$191,_TECH_Crisis_Model!$A$5:$A$191,$B$4,_TECH_Crisis_Model!$B$5:$B$191,A16),1) -> 1.7 | F16: =IF(B16="","",ROUND((C16*E16)+(D16*0.25*E16),2)) -> 8.5 | G16: =IF(F16>=5,"Critical",IF(F16>=3.5,"High",IF(F16>=2,"Medium","Low"))) -> Critical | H16: =IF(G16="Critical",4.5,IF(G16="High",4,IF(G16="Medium",3.5,3))) -> 4.5 | I16: =MAX(0,ROUND(H16-B16,2)) -> 4.5 | J16: =IFERROR(INDEX(_TECH_Crisis_Model!$E$5:$E$191,MATCH($B$4&"|"&A16,_TECH_Crisis_Model!$I$5:$I$191,0)),"") -> Delivery capacity, SLA control and operational handover determine customer continuity. | K16: =IFERROR(INDEX(_TECH_Crisis_Model!$G$5:$G$191,MATCH($B$4&"|"&A16,_TECH_Crisis_Model!$I$5:$I$191,0)),"") -> Define alternative delivery models, capacity buffers, SLA triage and incident recovery procedures. | L16: =RANK.EQ(F16,$F$9:$F$25,0)+COUNTIF($F$9:F16,F16)-1
A17: =Dashboard!$A$13 -> Supply Chain | B17: =Dashboard!$H$13 -> 0 | C17: =IF(B17="","",ROUND(5-B17,2)) -> 5 | D17: =Dashboard!$J$13+Dashboard!$K$13 -> 0 | E17: =IFERROR(SUMIFS(_TECH_Crisis_Model!$D$5:$D$191,_TECH_Crisis_Model!$A$5:$A$191,$B$4,_TECH_Crisis_Model!$B$5:$B$191,A17),1) -> 1.7 | F17: =IF(B17="","",ROUND((C17*E17)+(D17*0.25*E17),2)) -> 8.5 | G17: =IF(F17>=5,"Critical",IF(F17>=3.5,"High",IF(F17>=2,"Medium","Low"))) -> Critical | H17: =IF(G17="Critical",4.5,IF(G17="High",4,IF(G17="Medium",3.5,3))) -> 4.5 | I17: =MAX(0,ROUND(H17-B17,2)) -> 4.5 | J17: =IFERROR(INDEX(_TECH_Crisis_Model!$E$5:$E$191,MATCH($B$4&"|"&A17,_TECH_Crisis_Model!$I$5:$I$191,0)),"") -> Supplier concentration, logistics and inventory visibility determine production and delivery continuity. | K17: =IFERROR(INDEX(_TECH_Crisis_Model!$G$5:$G$191,MATCH($B$4&"|"&A17,_TECH_Crisis_Model!$I$5:$I$191,0)),"") -> Diversify suppliers, define safety stock, alternate routes, supplier monitoring and substitution rules. | L17: =RANK.EQ(F17,$F$9:$F$25,0)+COUNTIF($F$9:F17,F17)-1
A18: =Dashboard!$A$14 -> Manufacturing MES | B18: =Dashboard!$H$14 -> 0 | C18: =IF(B18="","",ROUND(5-B18,2)) -> 5 | D18: =Dashboard!$J$14+Dashboard!$K$14 -> 0 | E18: =IFERROR(SUMIFS(_TECH_Crisis_Model!$D$5:$D$191,_TECH_Crisis_Model!$A$5:$A$191,$B$4,_TECH_Crisis_Model!$B$5:$B$191,A18),1) -> 1.4 | F18: =IF(B18="","",ROUND((C18*E18)+(D18*0.25*E18),2)) -> 7 | G18: =IF(F18>=5,"Critical",IF(F18>=3.5,"High",IF(F18>=2,"Medium","Low"))) -> Critical | H18: =IF(G18="Critical",4.5,IF(G18="High",4,IF(G18="Medium",3.5,3))) -> 4.5 | I18: =MAX(0,ROUND(H18-B18,2)) -> 4.5 | J18: =IFERROR(INDEX(_TECH_Crisis_Model!$E$5:$E$191,MATCH($B$4&"|"&A18,_TECH_Crisis_Model!$I$5:$I$191,0)),"") -> Production assets, MES, maintenance and utilities determine manufacturing recoverability. | K18: =IFERROR(INDEX(_TECH_Crisis_Model!$G$5:$G$191,MATCH($B$4&"|"&A18,_TECH_Crisis_Model!$I$5:$I$191,0)),"") -> Define production fallback, maintenance priorities, spare parts, MES continuity and utility backup. | L18: =RANK.EQ(F18,$F$9:$F$25,0)+COUNTIF($F$9:F18,F18)-1
A19: =Dashboard!$A$15 -> Sales CRM | B19: =Dashboard!$H$15 -> 0 | C19: =IF(B19="","",ROUND(5-B19,2)) -> 5 | D19: =Dashboard!$J$15+Dashboard!$K$15 -> 0 | E19: =IFERROR(SUMIFS(_TECH_Crisis_Model!$D$5:$D$191,_TECH_Crisis_Model!$A$5:$A$191,$B$4,_TECH_Crisis_Model!$B$5:$B$191,A19),1) -> 1 | F19: =IF(B19="","",ROUND((C19*E19)+(D19*0.25*E19),2)) -> 5 | G19: =IF(F19>=5,"Critical",IF(F19>=3.5,"High",IF(F19>=2,"Medium","Low"))) -> Critical | H19: =IF(G19="Critical",4.5,IF(G19="High",4,IF(G19="Medium",3.5,3))) -> 4.5 | I19: =MAX(0,ROUND(H19-B19,2)) -> 4.5 | J19: =IFERROR(INDEX(_TECH_Crisis_Model!$E$5:$E$191,MATCH($B$4&"|"&A19,_TECH_Crisis_Model!$I$5:$I$191,0)),"") -> CRM discipline, pipeline visibility and retention actions determine revenue protection. | K19: =IFERROR(INDEX(_TECH_Crisis_Model!$G$5:$G$191,MATCH($B$4&"|"&A19,_TECH_Crisis_Model!$I$5:$I$191,0)),"") -> Improve CRM hygiene, retention playbooks, pipeline scenarios and customer segmentation. | L19: =RANK.EQ(F19,$F$9:$F$25,0)+COUNTIF($F$9:F19,F19)-1
A20: =Dashboard!$A$16 -> Marketing Comms | B20: =Dashboard!$H$16 -> 0 | C20: =IF(B20="","",ROUND(5-B20,2)) -> 5 | D20: =Dashboard!$J$16+Dashboard!$K$16 -> 0 | E20: =IFERROR(SUMIFS(_TECH_Crisis_Model!$D$5:$D$191,_TECH_Crisis_Model!$A$5:$A$191,$B$4,_TECH_Crisis_Model!$B$5:$B$191,A20),1) -> 1.2 | F20: =IF(B20="","",ROUND((C20*E20)+(D20*0.25*E20),2)) -> 6 | G20: =IF(F20>=5,"Critical",IF(F20>=3.5,"High",IF(F20>=2,"Medium","Low"))) -> Critical | H20: =IF(G20="Critical",4.5,IF(G20="High",4,IF(G20="Medium",3.5,3))) -> 4.5 | I20: =MAX(0,ROUND(H20-B20,2)) -> 4.5 | J20: =IFERROR(INDEX(_TECH_Crisis_Model!$E$5:$E$191,MATCH($B$4&"|"&A20,_TECH_Crisis_Model!$I$5:$I$191,0)),"") -> Customer communication and reputation control determine trust during uncertainty. | K20: =IFERROR(INDEX(_TECH_Crisis_Model!$G$5:$G$191,MATCH($B$4&"|"&A20,_TECH_Crisis_Model!$I$5:$I$191,0)),"") -> Prepare crisis messages, customer notification templates, comms approval flow and brand monitoring. | L20: =RANK.EQ(F20,$F$9:$F$25,0)+COUNTIF($F$9:F20,F20)-1
A21: =Dashboard!$A$17 -> IT Cloud DR | B21: =Dashboard!$H$17 -> 0 | C21: =IF(B21="","",ROUND(5-B21,2)) -> 5 | D21: =Dashboard!$J$17+Dashboard!$K$17 -> 0 | E21: =IFERROR(SUMIFS(_TECH_Crisis_Model!$D$5:$D$191,_TECH_Crisis_Model!$A$5:$A$191,$B$4,_TECH_Crisis_Model!$B$5:$B$191,A21),1) -> 1.7 | F21: =IF(B21="","",ROUND((C21*E21)+(D21*0.25*E21),2)) -> 8.5 | G21: =IF(F21>=5,"Critical",IF(F21>=3.5,"High",IF(F21>=2,"Medium","Low"))) -> Critical | H21: =IF(G21="Critical",4.5,IF(G21="High",4,IF(G21="Medium",3.5,3))) -> 4.5 | I21: =MAX(0,ROUND(H21-B21,2)) -> 4.5 | J21: =IFERROR(INDEX(_TECH_Crisis_Model!$E$5:$E$191,MATCH($B$4&"|"&A21,_TECH_Crisis_Model!$I$5:$I$191,0)),"") -> Cloud, infrastructure, backups, RTO and RPO determine system recoverability. | K21: =IFERROR(INDEX(_TECH_Crisis_Model!$G$5:$G$191,MATCH($B$4&"|"&A21,_TECH_Crisis_Model!$I$5:$I$191,0)),"") -> Implement tested backups, DR runbooks, failover, cloud landing zones and RTO/RPO monitoring. | L21: =RANK.EQ(F21,$F$9:$F$25,0)+COUNTIF($F$9:F21,F21)-1
A22: =Dashboard!$A$18 -> Business Systems | B22: =Dashboard!$H$18 -> 0 | C22: =IF(B22="","",ROUND(5-B22,2)) -> 5 | D22: =Dashboard!$J$18+Dashboard!$K$18 -> 0 | E22: =IFERROR(SUMIFS(_TECH_Crisis_Model!$D$5:$D$191,_TECH_Crisis_Model!$A$5:$A$191,$B$4,_TECH_Crisis_Model!$B$5:$B$191,A22),1) -> 1 | F22: =IF(B22="","",ROUND((C22*E22)+(D22*0.25*E22),2)) -> 5 | G22: =IF(F22>=5,"Critical",IF(F22>=3.5,"High",IF(F22>=2,"Medium","Low"))) -> Critical | H22: =IF(G22="Critical",4.5,IF(G22="High",4,IF(G22="Medium",3.5,3))) -> 4.5 | I22: =MAX(0,ROUND(H22-B22,2)) -> 4.5 | J22: =IFERROR(INDEX(_TECH_Crisis_Model!$E$5:$E$191,MATCH($B$4&"|"&A22,_TECH_Crisis_Model!$I$5:$I$191,0)),"") -> ERP, CRM, HRMS, MES and SaaS continuity determine transaction and process continuity. | K22: =IFERROR(INDEX(_TECH_Crisis_Model!$G$5:$G$191,MATCH($B$4&"|"&A22,_TECH_Crisis_Model!$I$5:$I$191,0)),"") -> Document system dependencies, SaaS continuity, role access, data exports and manual fallback. | L22: =RANK.EQ(F22,$F$9:$F$25,0)+COUNTIF($F$9:F22,F22)-1
A23: =Dashboard!$A$19 -> Data BI AI | B23: =Dashboard!$H$19 -> 0 | C23: =IF(B23="","",ROUND(5-B23,2)) -> 5 | D23: =Dashboard!$J$19+Dashboard!$K$19 -> 0 | E23: =IFERROR(SUMIFS(_TECH_Crisis_Model!$D$5:$D$191,_TECH_Crisis_Model!$A$5:$A$191,$B$4,_TECH_Crisis_Model!$B$5:$B$191,A23),1) -> 1 | F23: =IF(B23="","",ROUND((C23*E23)+(D23*0.25*E23),2)) -> 5 | G23: =IF(F23>=5,"Critical",IF(F23>=3.5,"High",IF(F23>=2,"Medium","Low"))) -> Critical | H23: =IF(G23="Critical",4.5,IF(G23="High",4,IF(G23="Medium",3.5,3))) -> 4.5 | I23: =MAX(0,ROUND(H23-B23,2)) -> 4.5 | J23: =IFERROR(INDEX(_TECH_Crisis_Model!$E$5:$E$191,MATCH($B$4&"|"&A23,_TECH_Crisis_Model!$I$5:$I$191,0)),"") -> Data quality, BI and analytics determine decision visibility and forecasting under stress. | K23: =IFERROR(INDEX(_TECH_Crisis_Model!$G$5:$G$191,MATCH($B$4&"|"&A23,_TECH_Crisis_Model!$I$5:$I$191,0)),"") -> Assign data owners, improve data quality, dashboards, forecasting and AI governance. | L23: =RANK.EQ(F23,$F$9:$F$25,0)+COUNTIF($F$9:F23,F23)-1
A24: =Dashboard!$A$20 -> Cyber Privacy | B24: =Dashboard!$H$20 -> 0 | C24: =IF(B24="","",ROUND(5-B24,2)) -> 5 | D24: =Dashboard!$J$20+Dashboard!$K$20 -> 0 | E24: =IFERROR(SUMIFS(_TECH_Crisis_Model!$D$5:$D$191,_TECH_Crisis_Model!$A$5:$A$191,$B$4,_TECH_Crisis_Model!$B$5:$B$191,A24),1) -> 1.5 | F24: =IF(B24="","",ROUND((C24*E24)+(D24*0.25*E24),2)) -> 7.5 | G24: =IF(F24>=5,"Critical",IF(F24>=3.5,"High",IF(F24>=2,"Medium","Low"))) -> Critical | H24: =IF(G24="Critical",4.5,IF(G24="High",4,IF(G24="Medium",3.5,3))) -> 4.5 | I24: =MAX(0,ROUND(H24-B24,2)) -> 4.5 | J24: =IFERROR(INDEX(_TECH_Crisis_Model!$E$5:$E$191,MATCH($B$4&"|"&A24,_TECH_Crisis_Model!$I$5:$I$191,0)),"") -> Cybersecurity and privacy controls determine resistance to digital disruption and regulatory exposure. | K24: =IFERROR(INDEX(_TECH_Crisis_Model!$G$5:$G$191,MATCH($B$4&"|"&A24,_TECH_Crisis_Model!$I$5:$I$191,0)),"") -> Strengthen MFA, EDR, logging, IR playbooks, restore testing, privacy controls and awareness. | L24: =RANK.EQ(F24,$F$9:$F$25,0)+COUNTIF($F$9:F24,F24)-1
